Pos   Hex Data           Description or Code
------------------------------------------------------------------------
0000                     ** source chunk: JETSKIRACEDATA.LUA.LC
                         ** global header start **
0000  1B4C7561           header signature: "\27Lua"
0004  50                 version (major:minor hex digits)
0005  01                 endianness (1=little endian)
0006  04                 size of int (bytes)
0007  04                 size of size_t (bytes)
0008  04                 size of Instruction (bytes)
0009  06                 size of OP (bits)
000A  08                 size of A (bits)
000B  09                 size of B (bits)
000C  09                 size of C (bits)
000D  04                 size of number (bytes)
000E  3BAFEF4B           sample number (single)
                         * chunk platform unrecognized
                         ** global header end **
                         
0012                     ** function [0] definition (level 1)
                         ** start of function **
0012  08000000           string size (8)
0016  3D286E6F6E652900   "=(none)"
                         source name: =(none)
001E  00000000           line defined (0)
0022  00                 nups (0)
0023  00                 numparams (0)
0024  00                 is_vararg (0)
0025  02                 maxstacksize (2)
                         * lines:
0026  00000000           sizelineinfo (0)
                         [pc] (line)
                         * locals:
002A  00000000           sizelocvars (0)
                         * upvalues:
002E  00000000           sizeupvalues (0)
                         * constants:
0032  00000000           sizek (0)
                         * functions:
0036  01000000           sizep (1)
                         
003A                     ** function [0] definition (level 2)
                         ** start of function **
003A  00000000           string size (0)
                         source name: (none)
003E  01000000           line defined (1)
0042  00                 nups (0)
0043  00                 numparams (0)
0044  00                 is_vararg (0)
0045  26                 maxstacksize (38)
                         * lines:
0046  00000000           sizelineinfo (0)
                         [pc] (line)
                         * locals:
004A  00000000           sizelocvars (0)
                         * upvalues:
004E  00000000           sizeupvalues (0)
                         * constants:
0052  A8020000           sizek (680)
0056  04                 const type 4
0057  0D000000           string size (13)
005B  47616D654C6F6361+  "GameLoca"
0063  74696F6E00         "tion\0"
                         const [0]: "GameLocation"
0068  03                 const type 3
0069  00000000           const [1]: (0)
006D  04                 const type 4
006E  07000000           string size (7)
0072  52616365496400     "RaceId"
                         const [2]: "RaceId"
0079  03                 const type 3
007A  CE78D143           const [3]: (418.94378662109)
007E  03                 const type 3
007F  F2B03C42           const [4]: (47.172798156738)
0083  03                 const type 3
0084  F2B03CC2           const [5]: (-47.172798156738)
0088  03                 const type 3
0089  098ABF40           const [6]: (5.9855999946594)
008D  03                 const type 3
008E  00001041           const [7]: (9)
0092  03                 const type 3
0093  1CA4D043           const [8]: (417.28210449219)
0097  03                 const type 3
0098  5E6A4043           const [9]: (192.41549682617)
009C  03                 const type 3
009D  5E6A40C3           const [10]: (-192.41549682617)
00A1  03                 const type 3
00A2  F085C540           const [11]: (6.1725997924805)
00A6  03                 const type 3
00A7  8F1BCB43           const [12]: (406.21530151367)
00AB  03                 const type 3
00AC  747D9043           const [13]: (288.98010253906)
00B0  03                 const type 3
00B1  747D90C3           const [14]: (-288.98010253906)
00B5  03                 const type 3
00B6  3F35C640           const [15]: (6.1939997673035)
00BA  03                 const type 3
00BB  B4E9AE43           const [16]: (349.82580566406)
00BF  03                 const type 3
00C0  AAA2C243           const [17]: (389.27081298828)
00C4  03                 const type 3
00C5  AAA2C2C3           const [18]: (-389.27081298828)
00C9  03                 const type 3
00CA  0612CC40           const [19]: (6.3772001266479)
00CE  03                 const type 3
00CF  82BB8843           const [20]: (273.46490478516)
00D3  03                 const type 3
00D4  3F9EF143           const [21]: (483.23629760742)
00D8  03                 const type 3
00D9  3F9EF1C3           const [22]: (-483.23629760742)
00DD  03                 const type 3
00DE  2B87D440           const [23]: (6.6414999961853)
00E2  03                 const type 3
00E3  ADAA5543           const [24]: (213.66670227051)
00E7  03                 const type 3
00E8  78721044           const [25]: (577.78857421875)
00EC  03                 const type 3
00ED  787210C4           const [26]: (-577.78857421875)
00F1  03                 const type 3
00F2  9E5EC540           const [27]: (6.167799949646)
00F6  03                 const type 3
00F7  EEBA1943           const [28]: (153.7301940918)
00FB  03                 const type 3
00FC  126F1F44           const [29]: (637.73547363281)
0100  03                 const type 3
0101  126F1FC4           const [30]: (-637.73547363281)
0105  03                 const type 3
0106  431CC140           const [31]: (6.0346999168396)
010A  03                 const type 3
010B  7E4C7D42           const [32]: (63.324699401855)
010F  03                 const type 3
0110  BE432844           const [33]: (673.05847167969)
0114  03                 const type 3
0115  BE4328C4           const [34]: (-673.05847167969)
0119  03                 const type 3
011A  4ED1C340           const [35]: (6.1192998886108)
011E  03                 const type 3
011F  31080241           const [36]: (8.1269998550415)
0123  03                 const type 3
0124  310802C1           const [37]: (-8.1269998550415)
0128  03                 const type 3
0129  93DA2944           const [38]: (679.41522216797)
012D  03                 const type 3
012E  93DA29C4           const [39]: (-679.41522216797)
0132  03                 const type 3
0133  7E8CB340           const [40]: (5.6108999252319)
0137  03                 const type 3
0138  96E16F42           const [41]: (59.97029876709)
013C  03                 const type 3
013D  96E16FC2           const [42]: (-59.97029876709)
0141  03                 const type 3
0142  23EB2444           const [43]: (659.67401123047)
0146  03                 const type 3
0147  23EB24C4           const [44]: (-659.67401123047)
014B  03                 const type 3
014C  3D9B9D40           const [45]: (4.9251999855042)
0150  03                 const type 3
0151  700E9842           const [46]: (76.028198242188)
0155  03                 const type 3
0156  700E98C2           const [47]: (-76.028198242188)
015A  03                 const type 3
015B  D76A1344           const [48]: (589.66937255859)
015F  03                 const type 3
0160  D76A13C4           const [49]: (-589.66937255859)
0164  03                 const type 3
0165  FB3ACA40           const [50]: (6.3196997642517)
0169  03                 const type 3
016A  BC744D42           const [51]: (51.363998413086)
016E  03                 const type 3
016F  BC744DC2           const [52]: (-51.363998413086)
0173  03                 const type 3
0174  02740244           const [53]: (521.81262207031)
0178  03                 const type 3
0179  027402C4           const [54]: (-521.81262207031)
017D  03                 const type 3
017E  A857D040           const [55]: (6.5107002258301)
0182  03                 const type 3
0183  9EEFBD40           const [56]: (5.9355001449585)
0187  03                 const type 3
0188  9EEFBDC0           const [57]: (-5.9355001449585)
018C  03                 const type 3
018D  8F64D743           const [58]: (430.78561401367)
0191  03                 const type 3
0192  8F64D7C3           const [59]: (-430.78561401367)
0196  03                 const type 3
0197  3789DF40           const [60]: (6.9854998588562)
019B  03                 const type 3
019C  5839EE40           const [61]: (7.4444999694824)
01A0  03                 const type 3
01A1  5ED3A143           const [62]: (323.65130615234)
01A5  03                 const type 3
01A6  5ED3A1C3           const [63]: (-323.65130615234)
01AA  03                 const type 3
01AB  E2E9BF40           const [64]: (5.9973001480103)
01AF  03                 const type 3
01B0  48D07942           const [65]: (62.453399658203)
01B4  03                 const type 3
01B5  912D8743           const [66]: (270.35598754883)
01B9  03                 const type 3
01BA  912D87C3           const [67]: (-270.35598754883)
01BE  03                 const type 3
01BF  D95FC240           const [68]: (6.0742001533508)
01C3  03                 const type 3
01C4  43FD2743           const [69]: (167.98930358887)
01C8  03                 const type 3
01C9  EC614743           const [70]: (199.38250732422)
01CD  03                 const type 3
01CE  EC6147C3           const [71]: (-199.38250732422)
01D2  03                 const type 3
01D3  7368BF40           const [72]: (5.9815001487732)
01D7  03                 const type 3
01D8  2FAD5843           const [73]: (216.67649841309)
01DC  03                 const type 3
01DD  81E4EE42           const [74]: (119.44629669189)
01E1  03                 const type 3
01E2  81E4EEC2           const [75]: (-119.44629669189)
01E6  03                 const type 3
01E7  9FABC740           const [76]: (6.2396998405457)
01EB  03                 const type 3
01EC  20325343           const [77]: (211.19580078125)
01F0  03                 const type 3
01F1  52490540           const [78]: (2.0826001167297)
01F5  03                 const type 3
01F6  FE65C540           const [79]: (6.1687002182007)
01FA  03                 const type 3
01FB  46668743           const [80]: (270.79901123047)
01FF  03                 const type 3
0200  84CDC442           const [81]: (98.401397705078)
0204  03                 const type 3
0205  62A1CC40           const [82]: (6.394700050354)
0209  03                 const type 3
020A  0BA6B543           const [83]: (363.29721069336)
020E  03                 const type 3
020F  EBE26642           const [84]: (57.721599578857)
0213  03                 const type 3
0214  73D7C440           const [85]: (6.1512999534607)
0218  03                 const type 3
0219  0000803F           const [86]: (1)
021D  03                 const type 3
021E  D7529F42           const [87]: (79.661796569824)
0222  03                 const type 3
0223  D7529FC2           const [88]: (-79.661796569824)
0227  03                 const type 3
0228  B1179F43           const [89]: (318.18508911133)
022C  03                 const type 3
022D  B1179FC3           const [90]: (-318.18508911133)
0231  03                 const type 3
0232  A8C6BD40           const [91]: (5.9305000305176)
0236  03                 const type 3
0237  427E8542           const [92]: (66.746597290039)
023B  03                 const type 3
023C  427E85C2           const [93]: (-66.746597290039)
0240  03                 const type 3
0241  3E78C843           const [94]: (400.93939208984)
0245  03                 const type 3
0246  3E78C8C3           const [95]: (-400.93939208984)
024A  03                 const type 3
024B  705FCB40           const [96]: (6.3554000854492)
024F  03                 const type 3
0250  3BF08442           const [97]: (66.469200134277)
0254  03                 const type 3
0255  3BF084C2           const [98]: (-66.469200134277)
0259  03                 const type 3
025A  D76A0444           const [99]: (529.66937255859)
025E  03                 const type 3
025F  D76A04C4           const [100]: (-529.66937255859)
0263  03                 const type 3
0264  F46CB840           const [101]: (5.7632999420166)
0268  03                 const type 3
0269  A846AB42           const [102]: (85.638000488281)
026D  03                 const type 3
026E  A846ABC2           const [103]: (-85.638000488281)
0272  03                 const type 3
0273  38201744           const [104]: (604.50341796875)
0277  03                 const type 3
0278  382017C4           const [105]: (-604.50341796875)
027C  03                 const type 3
027D  08ACBC40           const [106]: (5.8959999084473)
0281  03                 const type 3
0282  3F975A42           const [107]: (54.647701263428)
0286  03                 const type 3
0287  3F975AC2           const [108]: (-54.647701263428)
028B  03                 const type 3
028C  EDD22544           const [109]: (663.29571533203)
0290  03                 const type 3
0291  EDD225C4           const [110]: (-663.29571533203)
0295  03                 const type 3
0296  014DBA40           const [111]: (5.8218998908997)
029A  03                 const type 3
029B  F5CAEA41           const [112]: (29.349100112915)
029F  03                 const type 3
02A0  C88F2944           const [113]: (678.24658203125)
02A4  03                 const type 3
02A5  C88F29C4           const [114]: (-678.24658203125)
02A9  03                 const type 3
02AA  8E06C640           const [115]: (6.1883001327515)
02AE  03                 const type 3
02AF  CCFFF842           const [116]: (124.49960327148)
02B3  03                 const type 3
02B4  D3582144           const [117]: (645.38787841797)
02B8  03                 const type 3
02B9  D35821C4           const [118]: (-645.38787841797)
02BD  03                 const type 3
02BE  8C4ABC40           const [119]: (5.8840999603271)
02C2  03                 const type 3
02C3  E9A84D43           const [120]: (205.65980529785)
02C7  03                 const type 3
02C8  664F1444           const [121]: (593.24060058594)
02CC  03                 const type 3
02CD  664F14C4           const [122]: (-593.24060058594)
02D1  03                 const type 3
02D2  0000C240           const [123]: (6.0625)
02D6  03                 const type 3
02D7  76B78643           const [124]: (269.43328857422)
02DB  03                 const type 3
02DC  FEDBF443           const [125]: (489.71868896484)
02E0  03                 const type 3
02E1  FEDBF4C3           const [126]: (-489.71868896484)
02E5  03                 const type 3
02E6  C217C240           const [127]: (6.0654001235962)
02EA  03                 const type 3
02EB  916DA743           const [128]: (334.85598754883)
02EF  03                 const type 3
02F0  52E8C543           const [129]: (395.81500244141)
02F4  03                 const type 3
02F5  52E8C5C3           const [130]: (-395.81500244141)
02F9  03                 const type 3
02FA  48E1CA40           const [131]: (6.3400001525879)
02FE  03                 const type 3
02FF  8E1EC943           const [132]: (402.23870849609)
0303  03                 const type 3
0304  78648D43           const [133]: (282.78491210938)
0308  03                 const type 3
0309  78648DC3           const [134]: (-282.78491210938)
030D  03                 const type 3
030E  7DD0BD40           const [135]: (5.9317002296448)
0312  03                 const type 3
0313  FF39D043           const [136]: (416.45309448242)
0317  03                 const type 3
0318  6FD01F43           const [137]: (159.81419372559)
031C  03                 const type 3
031D  6FD01FC3           const [138]: (-159.81419372559)
0321  03                 const type 3
0322  29CBCE40           const [139]: (6.462299823761)
0326  03                 const type 3
0327  C6F4CE43           const [140]: (413.91229248047)
032B  03                 const type 3
032C  BCD62142           const [141]: (40.459701538086)
0330  03                 const type 3
0331  BCD621C2           const [142]: (-40.459701538086)
0335  03                 const type 3
0336  4A0CD040           const [143]: (6.5015001296997)
033A  03                 const type 3
033B  66EEBF43           const [144]: (383.86248779297)
033F  03                 const type 3
0340  ACCB2342           const [145]: (40.94889831543)
0344  03                 const type 3
0345  5BD3BC40           const [146]: (5.9008002281189)
0349  03                 const type 3
034A  EF519243           const [147]: (292.64010620117)
034E  03                 const type 3
034F  05440143           const [148]: (129.26570129395)
0353  03                 const type 3
0354  6C09BF40           const [149]: (5.9699001312256)
0358  03                 const type 3
0359  25565143           const [150]: (209.3365020752)
035D  03                 const type 3
035E  C4F25743           const [151]: (215.94830322266)
0362  03                 const type 3
0363  D6C5BB40           const [152]: (5.8678998947144)
0367  03                 const type 3
0368  48505C43           const [153]: (220.31359863281)
036C  03                 const type 3
036D  11C69343           const [154]: (295.54739379883)
0371  03                 const type 3
0372  643BC140           const [155]: (6.0384998321533)
0376  03                 const type 3
0377  31886C43           const [156]: (236.53199768066)
037B  03                 const type 3
037C  CDC4BD43           const [157]: (379.53750610352)
0380  03                 const type 3
0381  FF21CB40           const [158]: (6.3478999137878)
0385  03                 const type 3
0386  9A8F8D43           const [159]: (283.12188720703)
038A  03                 const type 3
038B  D01DF043           const [160]: (480.23291015625)
038F  03                 const type 3
0390  5DDCC240           const [161]: (6.0893998146057)
0394  03                 const type 3
0395  3A628443           const [162]: (264.76739501953)
0399  03                 const type 3
039A  4CF60B44           const [163]: (559.84838867188)
039E  03                 const type 3
039F  3EE8CD40           const [164]: (6.4345998764038)
03A3  03                 const type 3
03A4  299B3843           const [165]: (184.60609436035)
03A8  03                 const type 3
03A9  33D31944           const [166]: (615.29998779297)
03AD  03                 const type 3
03AE  67D5C340           const [167]: (6.1198000907898)
03B2  03                 const type 3
03B3  DE33F442           const [168]: (122.10130310059)
03B7  03                 const type 3
03B8  08082444           const [169]: (656.12548828125)
03BC  03                 const type 3
03BD  2428D440           const [170]: (6.6298999786377)
03C1  03                 const type 3
03C2  12A5B441           const [171]: (22.580600738525)
03C6  03                 const type 3
03C7  03E12944           const [172]: (679.51580810547)
03CB  03                 const type 3
03CC  F241CF40           const [173]: (6.4767999649048)
03D0  03                 const type 3
03D1  280FAB42           const [174]: (85.529602050781)
03D5  03                 const type 3
03D6  280FABC2           const [175]: (-85.529602050781)
03DA  03                 const type 3
03DB  6DAE2544           const [176]: (662.72540283203)
03DF  03                 const type 3
03E0  9031C940           const [177]: (6.2873001098633)
03E4  03                 const type 3
03E5  E9B71C43           const [178]: (156.71839904785)
03E9  03                 const type 3
03EA  E9B71CC3           const [179]: (-156.71839904785)
03EE  03                 const type 3
03EF  776A2344           const [180]: (653.66351318359)
03F3  03                 const type 3
03F4  9A99C940           const [181]: (6.3000001907349)
03F8  03                 const type 3
03F9  39A57443           const [182]: (244.64540100098)
03FD  03                 const type 3
03FE  39A574C3           const [183]: (-244.64540100098)
0402  03                 const type 3
0403  ECFD1B44           const [184]: (623.96752929688)
0407  03                 const type 3
0408  29EDCB40           const [185]: (6.372700214386)
040C  03                 const type 3
040D  540A9143           const [186]: (290.08068847656)
0411  03                 const type 3
0412  540A91C3           const [187]: (-290.08068847656)
0416  03                 const type 3
0417  B4A80844           const [188]: (546.63598632813)
041B  03                 const type 3
041C  2F6EC540           const [189]: (6.1697001457214)
0420  03                 const type 3
0421  68939A43           const [190]: (309.15161132813)
0425  03                 const type 3
0426  68939AC3           const [191]: (-309.15161132813)
042A  03                 const type 3
042B  4926E343           const [192]: (454.2991027832)
042F  03                 const type 3
0430  BADACE40           const [193]: (6.4642000198364)
0434  03                 const type 3
0435  B5FE8B43           const [194]: (279.98989868164)
0439  03                 const type 3
043A  B5FE8BC3           const [195]: (-279.98989868164)
043E  03                 const type 3
043F  8CD1AE43           const [196]: (349.63708496094)
0443  03                 const type 3
0444  B22EC840           const [197]: (6.2557001113892)
0448  03                 const type 3
0449  DB9A6D43           const [198]: (237.6049041748)
044D  03                 const type 3
044E  DB9A6DC3           const [199]: (-237.6049041748)
0452  03                 const type 3
0453  D5A08543           const [200]: (267.25650024414)
0457  03                 const type 3
0458  AEB6C040           const [201]: (6.0222997665405)
045C  03                 const type 3
045D  AF644343           const [202]: (195.39329528809)
0461  03                 const type 3
0462  AF6443C3           const [203]: (-195.39329528809)
0466  03                 const type 3
0467  87664943           const [204]: (201.40049743652)
046B  03                 const type 3
046C  C9E5CB40           const [205]: (6.3717999458313)
0470  03                 const type 3
0471  BB671943           const [206]: (153.40519714355)
0475  03                 const type 3
0476  BB6719C3           const [207]: (-153.40519714355)
047A  03                 const type 3
047B  FA4DE342           const [208]: (113.65229797363)
047F  03                 const type 3
0480  68B3C040           const [209]: (6.021900177002)
0484  03                 const type 3
0485  421E0243           const [210]: (130.11819458008)
0489  03                 const type 3
048A  421E02C3           const [211]: (-130.11819458008)
048E  03                 const type 3
048F  F9A0A641           const [212]: (20.82859992981)
0493  03                 const type 3
0494  ED0DCA40           const [213]: (6.314199924469)
0498  03                 const type 3
0499  6005E642           const [214]: (115.01049804688)
049D  03                 const type 3
049E  6005E6C2           const [215]: (-115.01049804688)
04A2  03                 const type 3
04A3  32E69842           const [216]: (76.449600219727)
04A7  03                 const type 3
04A8  32E698C2           const [217]: (-76.449600219727)
04AC  03                 const type 3
04AD  560EC140           const [218]: (6.0329999923706)
04B1  03                 const type 3
04B2  C2F7C742           const [219]: (99.983901977539)
04B6  03                 const type 3
04B7  C2F7C7C2           const [220]: (-99.983901977539)
04BB  03                 const type 3
04BC  C07C3343           const [221]: (179.4873046875)
04C0  03                 const type 3
04C1  C07C33C3           const [222]: (-179.4873046875)
04C5  03                 const type 3
04C6  9790C940           const [223]: (6.2989001274109)
04CA  03                 const type 3
04CB  00000040           const [224]: (2)
04CF  03                 const type 3
04D0  779EF342           const [225]: (121.80950164795)
04D4  03                 const type 3
04D5  779EF3C2           const [226]: (-121.80950164795)
04D9  03                 const type 3
04DA  990AFE42           const [227]: (127.02069854736)
04DE  03                 const type 3
04DF  990AFEC2           const [228]: (-127.02069854736)
04E3  03                 const type 3
04E4  A245C840           const [229]: (6.2585000991821)
04E8  03                 const type 3
04E9  640D0843           const [230]: (136.05230712891)
04ED  03                 const type 3
04EE  640D08C3           const [231]: (-136.05230712891)
04F2  03                 const type 3
04F3  C898E441           const [232]: (28.574600219727)
04F7  03                 const type 3
04F8  C898E4C1           const [233]: (-28.574600219727)
04FC  03                 const type 3
04FD  CC7FC240           const [234]: (6.0781002044678)
0501  03                 const type 3
0502  0E9D0443           const [235]: (132.61349487305)
0506  03                 const type 3
0507  0E9D04C3           const [236]: (-132.61349487305)
050B  03                 const type 3
050C  997B0742           const [237]: (33.870700836182)
0510  03                 const type 3
0511  0456C840           const [238]: (6.2604999542236)
0515  03                 const type 3
0516  6D87F342           const [239]: (121.764503479)
051A  03                 const type 3
051B  6D87F3C2           const [240]: (-121.764503479)
051F  03                 const type 3
0520  C0AB1043           const [241]: (144.6708984375)
0524  03                 const type 3
0525  DE93BF40           const [242]: (5.9868001937866)
0529  03                 const type 3
052A  91BEDE42           const [243]: (111.37220001221)
052E  03                 const type 3
052F  91BEDEC2           const [244]: (-111.37220001221)
0533  03                 const type 3
0534  67445843           const [245]: (216.26719665527)
0538  03                 const type 3
0539  2B18CD40           const [246]: (6.4092001914978)
053D  03                 const type 3
053E  D7E3AA42           const [247]: (85.444999694824)
0542  03                 const type 3
0543  D7E3AAC2           const [248]: (-85.444999694824)
0547  03                 const type 3
0548  A3239943           const [249]: (306.27841186523)
054C  03                 const type 3
054D  4694C840           const [250]: (6.2680997848511)
0551  03                 const type 3
0552  789C723F           const [251]: (0.94770002365112)
0556  03                 const type 3
0557  2D81C243           const [252]: (389.00918579102)
055B  03                 const type 3
055C  3D0ACF40           const [253]: (6.4699997901917)
0560  03                 const type 3
0561  916DEA42           const [254]: (117.21399688721)
0565  03                 const type 3
0566  2A42C943           const [255]: (402.51690673828)
056A  03                 const type 3
056B  3108C040           const [256]: (6.0009999275208)
056F  03                 const type 3
0570  711C5543           const [257]: (213.11109924316)
0574  03                 const type 3
0575  5B63BD43           const [258]: (378.77621459961)
0579  03                 const type 3
057A  AE47C740           const [259]: (6.227499961853)
057E  03                 const type 3
057F  42AE5A43           const [260]: (218.68069458008)
0583  03                 const type 3
0584  F2789543           const [261]: (298.94488525391)
0588  03                 const type 3
0589  B30CBF40           const [262]: (5.9703001976013)
058D  03                 const type 3
058E  C3436A43           const [263]: (234.26469421387)
0592  03                 const type 3
0593  1F954043           const [264]: (192.58250427246)
0597  03                 const type 3
0598  6666C840           const [265]: (6.2624998092651)
059C  03                 const type 3
059D  F7EEBB43           const [266]: (375.8669128418)
05A1  03                 const type 3
05A2  C7293242           const [267]: (44.540798187256)
05A6  03                 const type 3
05A7  083DC740           const [268]: (6.2262001037598)
05AB  03                 const type 3
05AC  3C96CB43           const [269]: (407.17370605469)
05B0  03                 const type 3
05B1  36CDA140           const [270]: (5.056300163269)
05B5  03                 const type 3
05B6  36CDA1C0           const [271]: (-5.056300163269)
05BA  03                 const type 3
05BB  5B42CA40           const [272]: (6.3206000328064)
05BF  03                 const type 3
05C0  AC3BD343           const [273]: (422.46618652344)
05C4  03                 const type 3
05C5  01DD1643           const [274]: (150.86329650879)
05C9  03                 const type 3
05CA  01DD16C3           const [275]: (-150.86329650879)
05CE  03                 const type 3
05CF  8351C140           const [276]: (6.0412001609802)
05D3  03                 const type 3
05D4  225DD043           const [277]: (416.72760009766)
05D8  03                 const type 3
05D9  7F6B7F43           const [278]: (255.41990661621)
05DD  03                 const type 3
05DE  7F6B7FC3           const [279]: (-255.41990661621)
05E2  03                 const type 3
05E3  B37BD040           const [280]: (6.5151000022888)
05E7  03                 const type 3
05E8  947EAE43           const [281]: (348.98889160156)
05EC  03                 const type 3
05ED  E2B0C043           const [282]: (385.38189697266)
05F1  03                 const type 3
05F2  E2B0C0C3           const [283]: (-385.38189697266)
05F6  03                 const type 3
05F7  7D3FC540           const [284]: (6.1640000343323)
05FB  03                 const type 3
05FC  BC448743           const [285]: (270.53698730469)
0600  03                 const type 3
0601  A166F643           const [286]: (492.80178833008)
0605  03                 const type 3
0606  A166F6C3           const [287]: (-492.80178833008)
060A  03                 const type 3
060B  21B0C040           const [288]: (6.0215001106262)
060F  03                 const type 3
0610  D5284B43           const [289]: (203.15950012207)
0614  03                 const type 3
0615  71611444           const [290]: (593.52252197266)
0619  03                 const type 3
061A  716114C4           const [291]: (-593.52252197266)
061E  03                 const type 3
061F  1973CB40           const [292]: (6.3578000068665)
0623  03                 const type 3
0624  BA791443           const [293]: (148.47549438477)
0628  03                 const type 3
0629  227C1F44           const [294]: (637.93957519531)
062D  03                 const type 3
062E  227C1FC4           const [295]: (-637.93957519531)
0632  03                 const type 3
0633  64CCD340           const [296]: (6.6187000274658)
0637  03                 const type 3
0638  0A973942           const [297]: (46.397499084473)
063C  03                 const type 3
063D  CF432944           const [298]: (677.05950927734)
0641  03                 const type 3
0642  CF4329C4           const [299]: (-677.05950927734)
0646  03                 const type 3
0647  20D2BD40           const [300]: (5.9319000244141)
064B  03                 const type 3
064C  A57D0A42           const [301]: (34.622699737549)
0650  03                 const type 3
0651  A57D0AC2           const [302]: (-34.622699737549)
0655  03                 const type 3
0656  81E62744           const [303]: (671.60162353516)
065A  03                 const type 3
065B  81E627C4           const [304]: (-671.60162353516)
065F  03                 const type 3
0660  6F81C040           const [305]: (6.0157999992371)
0664  03                 const type 3
0665  299CAD42           const [306]: (86.805000305176)
0669  03                 const type 3
066A  299CADC2           const [307]: (-86.805000305176)
066E  03                 const type 3
066F  E06E1544           const [308]: (597.732421875)
0673  03                 const type 3
0674  E06E15C4           const [309]: (-597.732421875)
0678  03                 const type 3
0679  FF21CF40           const [310]: (6.4728999137878)
067D  03                 const type 3
067E  05C3AD42           const [311]: (86.880897521973)
0682  03                 const type 3
0683  05C3ADC2           const [312]: (-86.880897521973)
0687  03                 const type 3
0688  B995FC43           const [313]: (505.16970825195)
068C  03                 const type 3
068D  B995FCC3           const [314]: (-505.16970825195)
0691  03                 const type 3
0692  492EC940           const [315]: (6.2869000434875)
0696  03                 const type 3
0697  F5EAA742           const [316]: (83.95890045166)
069B  03                 const type 3
069C  F5EAA7C2           const [317]: (-83.95890045166)
06A0  03                 const type 3
06A1  1DC8B943           const [318]: (371.56338500977)
06A5  03                 const type 3
06A6  1DC8B9C3           const [319]: (-371.56338500977)
06AA  03                 const type 3
06AB  BDE3BC40           const [320]: (5.9028000831604)
06AF  03                 const type 3
06B0  3D2CBC42           const [321]: (94.086402893066)
06B4  03                 const type 3
06B5  3D2CBCC2           const [322]: (-94.086402893066)
06B9  03                 const type 3
06BA  C3336B43           const [323]: (235.20219421387)
06BE  03                 const type 3
06BF  C3336BC3           const [324]: (-235.20219421387)
06C3  03                 const type 3
06C4  0D71D640           const [325]: (6.7013001441956)
06C8  03                 const type 3
06C9  00004040           const [326]: (3)
06CD  03                 const type 3
06CE  A7392743           const [327]: (167.22520446777)
06D2  03                 const type 3
06D3  A73927C3           const [328]: (-167.22520446777)
06D7  03                 const type 3
06D8  0D719244           const [329]: (1171.5328369141)
06DC  03                 const type 3
06DD  17B7C740           const [330]: (6.2410998344421)
06E1  03                 const type 3
06E2  A6AAA042           const [331]: (80.333297729492)
06E6  03                 const type 3
06E7  A6AAA0C2           const [332]: (-80.333297729492)
06EB  03                 const type 3
06EC  04D49C44           const [333]: (1254.6254882813)
06F0  03                 const type 3
06F1  3867C240           const [334]: (6.0750999450684)
06F5  03                 const type 3
06F6  D41A1C42           const [335]: (39.02619934082)
06FA  03                 const type 3
06FB  413C9D44           const [336]: (1257.8829345703)
06FF  03                 const type 3
0700  64CCC740           const [337]: (6.2437000274658)
0704  03                 const type 3
0705  9683E042           const [338]: (112.25700378418)
0709  03                 const type 3
070A  C5B99644           const [339]: (1205.8052978516)
070E  03                 const type 3
070F  95D4C340           const [340]: (6.1196999549866)
0713  03                 const type 3
0714  C0CC2A43           const [341]: (170.7998046875)
0718  03                 const type 3
0719  58938A44           const [342]: (1108.6044921875)
071D  03                 const type 3
071E  92CBC740           const [343]: (6.2435998916626)
0722  03                 const type 3
0723  DDD44543           const [344]: (197.83149719238)
0727  03                 const type 3
0728  E3578044           const [345]: (1026.7464599609)
072C  03                 const type 3
072D  5F07C040           const [346]: (6.0008997917175)
0731  03                 const type 3
0732  D6150A43           const [347]: (138.08529663086)
0736  03                 const type 3
0737  71195744           const [348]: (860.39752197266)
073B  03                 const type 3
073C  6ABCC640           const [349]: (6.2104997634888)
0740  03                 const type 3
0741  B5A68042           const [350]: (64.32559967041)
0745  03                 const type 3
0746  7D624844           const [351]: (801.53887939453)
074A  03                 const type 3
074B  DFE0C940           const [352]: (6.3087000846863)
074F  03                 const type 3
0750  4547523F           const [353]: (0.82139998674393)
0754  03                 const type 3
0755  D5154B44           const [354]: (812.34112548828)
0759  03                 const type 3
075A  6C09C940           const [355]: (6.2824001312256)
075E  03                 const type 3
075F  72F9F842           const [356]: (124.48719787598)
0763  03                 const type 3
0764  72F9F8C2           const [357]: (-124.48719787598)
0768  03                 const type 3
0769  5E6E5744           const [358]: (861.72448730469)
076D  03                 const type 3
076E  83C0CA40           const [359]: (6.3359999656677)
0772  03                 const type 3
0773  E6FF3743           const [360]: (183.99960327148)
0777  03                 const type 3
0778  E6FF37C3           const [361]: (-183.99960327148)
077C  03                 const type 3
077D  C0206944           const [362]: (932.51171875)
0781  03                 const type 3
0782  4ED1C940           const [363]: (6.3067998886108)
0786  03                 const type 3
0787  0DA14843           const [364]: (200.62910461426)
078B  03                 const type 3
078C  0DA148C3           const [365]: (-200.62910461426)
0790  03                 const type 3
0791  731E8144           const [366]: (1032.9515380859)
0795  03                 const type 3
0796  5AF5C340           const [367]: (6.1237001419067)
079A  03                 const type 3
079B  00008040           const [368]: (4)
079F  03                 const type 3
07A0  BA2B5642           const [369]: (53.542701721191)
07A4  03                 const type 3
07A5  22B62844           const [370]: (674.84582519531)
07A9  03                 const type 3
07AA  0C02C940           const [371]: (6.2814998626709)
07AE  03                 const type 3
07AF  1A80C142           const [372]: (96.750198364258)
07B3  03                 const type 3
07B4  1A80C1C2           const [373]: (-96.750198364258)
07B8  03                 const type 3
07B9  38432444           const [374]: (657.05029296875)
07BD  03                 const type 3
07BE  091BC040           const [375]: (6.0033001899719)
07C2  03                 const type 3
07C3  10493543           const [376]: (181.28540039063)
07C7  03                 const type 3
07C8  104935C3           const [377]: (-181.28540039063)
07CC  03                 const type 3
07CD  DACC2144           const [378]: (647.20080566406)
07D1  03                 const type 3
07D2  BBB8C140           const [379]: (6.0538001060486)
07D6  03                 const type 3
07D7  D2207D43           const [380]: (253.1282043457)
07DB  03                 const type 3
07DC  D2207DC3           const [381]: (-253.1282043457)
07E0  03                 const type 3
07E1  740A1844           const [382]: (608.16333007813)
07E5  03                 const type 3
07E6  158CC240           const [383]: (6.0795998573303)
07EA  03                 const type 3
07EB  00599743           const [384]: (302.6953125)
07EF  03                 const type 3
07F0  005997C3           const [385]: (-302.6953125)
07F4  03                 const type 3
07F5  31210044           const [386]: (512.51861572266)
07F9  03                 const type 3
07FA  AA82C540           const [387]: (6.1722002029419)
07FE  03                 const type 3
07FF  DA8B7343           const [388]: (243.54629516602)
0803  03                 const type 3
0804  DA8B73C3           const [389]: (-243.54629516602)
0808  03                 const type 3
0809  563DCE43           const [390]: (412.47918701172)
080D  03                 const type 3
080E  F1F4C040           const [391]: (6.0299000740051)
0812  03                 const type 3
0813  FDF70F43           const [392]: (143.96870422363)
0817  03                 const type 3
0818  FDF70FC3           const [393]: (-143.96870422363)
081C  03                 const type 3
081D  5D76BC43           const [394]: (376.92471313477)
0821  03                 const type 3
0822  0681C740           const [395]: (6.2344999313354)
0826  03                 const type 3
0827  12652C42           const [396]: (43.098701477051)
082B  03                 const type 3
082C  12652CC2           const [397]: (-43.098701477051)
0830  03                 const type 3
0831  8340C043           const [398]: (384.50399780273)
0835  03                 const type 3
0836  E926C540           const [399]: (6.1609997749329)
083A  03                 const type 3
083B  E9A88642           const [400]: (67.329902648926)
083F  03                 const type 3
0840  8A6FC943           const [401]: (402.87139892578)
0844  03                 const type 3
0845  62A1D440           const [402]: (6.644700050354)
0849  03                 const type 3
084A  59873843           const [403]: (184.52870178223)
084E  03                 const type 3
084F  86E9C343           const [404]: (391.82440185547)
0853  03                 const type 3
0854  8C4AC440           const [405]: (6.1340999603271)
0858  03                 const type 3
0859  1C338C43           const [406]: (280.39929199219)
085D  03                 const type 3
085E  49DDED43           const [407]: (475.7287902832)
0862  03                 const type 3
0863  FCA9C940           const [408]: (6.3020000457764)
0867  03                 const type 3
0868  A8DD8843           const [409]: (273.73168945313)
086C  03                 const type 3
086D  5D9A0944           const [410]: (550.41192626953)
0871  03                 const type 3
0872  FCA9C340           const [411]: (6.1145000457764)
0876  03                 const type 3
0877  A7A84843           const [412]: (200.65879821777)
087B  03                 const type 3
087C  DED31744           const [413]: (607.31042480469)
0880  03                 const type 3
0881  C66DC840           const [414]: (6.2634000778198)
0885  03                 const type 3
0886  4BF9FD42           const [415]: (126.98690032959)
088A  03                 const type 3
088B  A2702344           const [416]: (653.75988769531)
088F  03                 const type 3
0890  BCC40543           const [417]: (133.76849365234)
0894  03                 const type 3
0895  BCC405C3           const [418]: (-133.76849365234)
0899  03                 const type 3
089A  C3E41C42           const [419]: (39.223400115967)
089E  03                 const type 3
089F  3BDFC340           const [420]: (6.1209998130798)
08A3  03                 const type 3
08A4  98ECFE42           const [421]: (127.46209716797)
08A8  03                 const type 3
08A9  98ECFEC2           const [422]: (-127.46209716797)
08AD  03                 const type 3
08AE  26134E42           const [423]: (51.518699645996)
08B2  03                 const type 3
08B3  26134EC2           const [424]: (-51.518699645996)
08B7  03                 const type 3
08B8  F163C640           const [425]: (6.1996998786926)
08BC  03                 const type 3
08BD  C5FE7C42           const [426]: (63.248798370361)
08C1  03                 const type 3
08C2  C5FE7CC2           const [427]: (-63.248798370361)
08C6  03                 const type 3
08C7  52891B43           const [428]: (155.5364074707)
08CB  03                 const type 3
08CC  52891BC3           const [429]: (-155.5364074707)
08D0  03                 const type 3
08D1  6519C640           const [430]: (6.1905999183655)
08D5  03                 const type 3
08D6  E7FD3643           const [431]: (182.99180603027)
08DA  03                 const type 3
08DB  36EB2943           const [432]: (169.91879272461)
08DF  03                 const type 3
08E0  36EB29C3           const [433]: (-169.91879272461)
08E4  03                 const type 3
08E5  295CC140           const [434]: (6.0425000190735)
08E9  03                 const type 3
08EA  60E55443           const [435]: (212.89599609375)
08EE  03                 const type 3
08EF  6980AD42           const [436]: (86.750801086426)
08F3  03                 const type 3
08F4  6980ADC2           const [437]: (-86.750801086426)
08F8  03                 const type 3
08F9  87A7C140           const [438]: (6.0517001152039)
08FD  03                 const type 3
08FE  3AF25843           const [439]: (216.94619750977)
0902  03                 const type 3
0903  70DF9241           const [440]: (18.359100341797)
0907  03                 const type 3
0908  F1F4C840           const [441]: (6.2799000740051)
090C  03                 const type 3
090D  36CD7943           const [442]: (249.80160522461)
0911  03                 const type 3
0912  86F8F642           const [443]: (123.48539733887)
0916  03                 const type 3
0917  E6AEC140           const [444]: (6.0525999069214)
091B  03                 const type 3
091C  2DC34943           const [445]: (201.76240539551)
0920  03                 const type 3
0921  09696F43           const [446]: (239.4102935791)
0925  03                 const type 3
0926  9EEFCB40           const [447]: (6.3730001449585)
092A  03                 const type 3
092B  92DB6643           const [448]: (230.8576965332)
092F  03                 const type 3
0930  B392A343           const [449]: (327.14608764648)
0934  03                 const type 3
0935  07F0C440           const [450]: (6.1543002128601)
0939  03                 const type 3
093A  DE632443           const [451]: (164.39010620117)
093E  03                 const type 3
093F  B565C143           const [452]: (386.79458618164)
0943  03                 const type 3
0944  4F1EC240           const [453]: (6.0661997795105)
0948  03                 const type 3
0949  5DBE7342           const [454]: (60.935901641846)
094D  03                 const type 3
094E  6D77C943           const [455]: (402.93301391602)
0952  03                 const type 3
0953  0534C340           const [456]: (6.1001000404358)
0957  03                 const type 3
0958  27A07540           const [457]: (3.8378999233246)
095C  03                 const type 3
095D  27A075C0           const [458]: (-3.8378999233246)
0961  03                 const type 3
0962  129CC043           const [459]: (385.21929931641)
0966  03                 const type 3
0967  3CBDC840           const [460]: (6.273099899292)
096B  03                 const type 3
096C  865A6742           const [461]: (57.838401794434)
0970  03                 const type 3
0971  865A67C2           const [462]: (-57.838401794434)
0975  03                 const type 3
0976  C72BAC43           const [463]: (344.34201049805)
097A  03                 const type 3
097B  E6AEC340           const [464]: (6.1150999069214)
097F  03                 const type 3
0980  F2F0B742           const [465]: (91.970596313477)
0984  03                 const type 3
0985  F2F0B7C2           const [466]: (-91.970596313477)
0989  03                 const type 3
098A  D9568B43           const [467]: (278.67849731445)
098E  03                 const type 3
098F  8F53CA40           const [468]: (6.3227000236511)
0993  03                 const type 3
0994  BD63EC42           const [469]: (118.19480133057)
0998  03                 const type 3
0999  BD63ECC2           const [470]: (-118.19480133057)
099D  03                 const type 3
099E  353E2243           const [471]: (162.24299621582)
09A2  03                 const type 3
09A3  4F40C540           const [472]: (6.1641001701355)
09A7  03                 const type 3
09A8  E05E0643           const [473]: (134.37060546875)
09AC  03                 const type 3
09AD  E05E06C3           const [474]: (-134.37060546875)
09B1  03                 const type 3
09B2  58C94743           const [475]: (199.78649902344)
09B6  03                 const type 3
09B7  58C947C3           const [476]: (-199.78649902344)
09BB  03                 const type 3
09BC  3D9BD140           const [477]: (6.5501999855042)
09C0  03                 const type 3
09C1  D6261543           const [478]: (149.15170288086)
09C5  03                 const type 3
09C6  D62615C3           const [479]: (-149.15170288086)
09CA  03                 const type 3
09CB  46B6DF40           const [480]: (6.9910001754761)
09CF  03                 const type 3
09D0  787AC940           const [481]: (6.296199798584)
09D4  03                 const type 3
09D5  8A0F2543           const [482]: (165.06069946289)
09D9  03                 const type 3
09DA  8A0F25C3           const [483]: (-165.06069946289)
09DE  03                 const type 3
09DF  4D050843           const [484]: (136.02070617676)
09E3  03                 const type 3
09E4  40A4C940           const [485]: (6.3013000488281)
09E8  03                 const type 3
09E9  B4885F43           const [486]: (223.53399658203)
09ED  03                 const type 3
09EE  B4885FC3           const [487]: (-223.53399658203)
09F2  03                 const type 3
09F3  76F09443           const [488]: (297.87860107422)
09F7  03                 const type 3
09F8  E86AD340           const [489]: (6.6068000793457)
09FC  03                 const type 3
09FD  2B478E43           const [490]: (284.55599975586)
0A01  03                 const type 3
0A02  2B478EC3           const [491]: (-284.55599975586)
0A06  03                 const type 3
0A07  725ACF43           const [492]: (414.70660400391)
0A0B  03                 const type 3
0A0C  FB3AC840           const [493]: (6.2571997642517)
0A10  03                 const type 3
0A11  E0259643           const [494]: (300.2958984375)
0A15  03                 const type 3
0A16  E02596C3           const [495]: (-300.2958984375)
0A1A  03                 const type 3
0A1B  6626FF43           const [496]: (510.29998779297)
0A1F  03                 const type 3
0A20  933AC340           const [497]: (6.1009001731873)
0A24  03                 const type 3
0A25  E32E8043           const [498]: (256.36630249023)
0A29  03                 const type 3
0A2A  E32E80C3           const [499]: (-256.36630249023)
0A2E  03                 const type 3
0A2F  05591544           const [500]: (597.39093017578)
0A33  03                 const type 3
0A34  8FC2BB40           const [501]: (5.8674998283386)
0A38  03                 const type 3
0A39  640B3443           const [502]: (180.04449462891)
0A3D  03                 const type 3
0A3E  640B34C3           const [503]: (-180.04449462891)
0A42  03                 const type 3
0A43  C8DC2244           const [504]: (651.44970703125)
0A47  03                 const type 3
0A48  696FCE40           const [505]: (6.4510998725891)
0A4C  03                 const type 3
0A4D  B34C4F42           const [506]: (51.824901580811)
0A51  03                 const type 3
0A52  B34C4FC2           const [507]: (-51.824901580811)
0A56  03                 const type 3
0A57  02722A44           const [508]: (681.78137207031)
0A5B  03                 const type 3
0A5C  A245CC40           const [509]: (6.3835000991821)
0A60  03                 const type 3
0A61  A8356D42           const [510]: (59.302398681641)
0A65  03                 const type 3
0A66  B1E42944           const [511]: (679.57330322266)
0A6A  03                 const type 3
0A6B  D34DC640           const [512]: (6.1970000267029)
0A6F  03                 const type 3
0A70  E3B61543           const [513]: (149.71440124512)
0A74  03                 const type 3
0A75  D48F1F44           const [514]: (638.24731445313)
0A79  03                 const type 3
0A7A  6F81CE40           const [515]: (6.4532999992371)
0A7E  03                 const type 3
0A7F  40237243           const [516]: (242.1376953125)
0A83  03                 const type 3
0A84  01A51344           const [517]: (590.57818603516)
0A88  03                 const type 3
0A89  4E62C640           const [518]: (6.1995000839233)
0A8D  03                 const type 3
0A8E  9B159243           const [519]: (292.16879272461)
0A92  03                 const type 3
0A93  B54D0244           const [520]: (521.21417236328)
0A97  03                 const type 3
0A98  9643D540           const [521]: (6.6645002365112)
0A9C  03                 const type 3
0A9D  72997E43           const [522]: (254.59939575195)
0AA1  03                 const type 3
0AA2  50BDDC43           const [523]: (441.47900390625)
0AA6  03                 const type 3
0AA7  7671BB40           const [524]: (5.8576002120972)
0AAB  03                 const type 3
0AAC  5F296943           const [525]: (233.16160583496)
0AB0  03                 const type 3
0AB1  AA50AB43           const [526]: (342.63018798828)
0AB5  03                 const type 3
0AB6  0612C640           const [527]: (6.1897001266479)
0ABA  03                 const type 3
0ABB  82135F43           const [528]: (223.07620239258)
0ABF  03                 const type 3
0AC0  D3FE9243           const [529]: (293.99081420898)
0AC4  03                 const type 3
0AC5  7E8CC940           const [530]: (6.2983999252319)
0AC9  03                 const type 3
0ACA  227C6D43           const [531]: (237.48489379883)
0ACE  03                 const type 3
0ACF  1BAE3E43           const [532]: (190.6800994873)
0AD3  03                 const type 3
0AD4  16FBC340           const [533]: (6.124400138855)
0AD8  03                 const type 3
0AD9  8349B943           const [534]: (370.57431030273)
0ADD  03                 const type 3
0ADE  2AFA4E42           const [535]: (51.744300842285)
0AE2  03                 const type 3
0AE3  CA32C840           const [536]: (6.256199836731)
0AE7  03                 const type 3
0AE8  48D8D043           const [537]: (417.68969726563)
0AEC  03                 const type 3
0AED  E9266B42           const [538]: (58.787998199463)
0AF1  03                 const type 3
0AF2  E9266BC2           const [539]: (-58.787998199463)
0AF6  03                 const type 3
0AF7  C729C840           const [540]: (6.255099773407)
0AFB  03                 const type 3
0AFC  4BB1D143           const [541]: (419.38510131836)
0B00  03                 const type 3
0B01  5A454143           const [542]: (193.27090454102)
0B05  03                 const type 3
0B06  5A4541C3           const [543]: (-193.27090454102)
0B0A  03                 const type 3
0B0B  3277C540           const [544]: (6.1708002090454)
0B0F  03                 const type 3
0B10  7609CA43           const [545]: (404.07391357422)
0B14  03                 const type 3
0B15  30CA9A43           const [546]: (309.57958984375)
0B19  03                 const type 3
0B1A  30CA9AC3           const [547]: (-309.57958984375)
0B1E  03                 const type 3
0B1F  E10BC540           const [548]: (6.1577000617981)
0B23  03                 const type 3
0B24  5414A143           const [549]: (322.15881347656)
0B28  03                 const type 3
0B29  DC58CF43           const [550]: (414.69421386719)
0B2D  03                 const type 3
0B2E  DC58CFC3           const [551]: (-414.69421386719)
0B32  03                 const type 3
0B33  2AA9CD40           const [552]: (6.4268999099731)
0B37  03                 const type 3
0B38  5A6C8943           const [553]: (274.84649658203)
0B3C  03                 const type 3
0B3D  0B24F143           const [554]: (482.28158569336)
0B41  03                 const type 3
0B42  0B24F1C3           const [555]: (-482.28158569336)
0B46  03                 const type 3
0B47  FBCBCE40           const [556]: (6.4623999595642)
0B4B  03                 const type 3
0B4C  B1015243           const [557]: (210.00660705566)
0B50  03                 const type 3
0B51  4F721244           const [558]: (585.78607177734)
0B55  03                 const type 3
0B56  4F7212C4           const [559]: (-585.78607177734)
0B5A  03                 const type 3
0B5B  F2B0CE40           const [560]: (6.4590997695923)
0B5F  03                 const type 3
0B60  1EF61A43           const [561]: (154.96139526367)
0B64  03                 const type 3
0B65  47321F44           const [562]: (636.78558349609)
0B69  03                 const type 3
0B6A  47321FC4           const [563]: (-636.78558349609)
0B6E  03                 const type 3
0B6F  2BF6C940           const [564]: (6.3112998008728)
0B73  03                 const type 3
0B74  EAD56E42           const [565]: (59.70890045166)
0B78  03                 const type 3
0B79  C81F2844           const [566]: (672.49658203125)
0B7D  03                 const type 3
0B7E  C81F28C4           const [567]: (-672.49658203125)
0B82  03                 const type 3
0B83  6076C740           const [568]: (6.2332000732422)
0B87  03                 const type 3
0B88  1294C141           const [569]: (24.197299957275)
0B8C  03                 const type 3
0B8D  1294C1C1           const [570]: (-24.197299957275)
0B91  03                 const type 3
0B92  C5482A44           const [571]: (681.13702392578)
0B96  03                 const type 3
0B97  C5482AC4           const [572]: (-681.13702392578)
0B9B  03                 const type 3
0B9C  92CBC340           const [573]: (6.1185998916626)
0BA0  03                 const type 3
0BA1  D0D59C42           const [574]: (78.417602539063)
0BA5  03                 const type 3
0BA6  D0D59CC2           const [575]: (-78.417602539063)
0BAA  03                 const type 3
0BAB  56AE1744           const [576]: (606.72399902344)
0BAF  03                 const type 3
0BB0  56AE17C4           const [577]: (-606.72399902344)
0BB4  03                 const type 3
0BB5  D191BC40           const [578]: (5.8927998542786)
0BB9  03                 const type 3
0BBA  F54A9E42           const [579]: (79.14640045166)
0BBE  03                 const type 3
0BBF  F54A9EC2           const [580]: (-79.14640045166)
0BC3  03                 const type 3
0BC4  336CFD43           const [581]: (506.84530639648)
0BC8  03                 const type 3
0BC9  336CFDC3           const [582]: (-506.84530639648)
0BCD  03                 const type 3
0BCE  BF0EBC40           const [583]: (5.8768000602722)
0BD2  03                 const type 3
0BD3  F114AB42           const [584]: (85.540901184082)
0BD7  03                 const type 3
0BD8  F114ABC2           const [585]: (-85.540901184082)
0BDC  03                 const type 3
0BDD  C860C143           const [586]: (386.75610351563)
0BE1  03                 const type 3
0BE2  C860C1C3           const [587]: (-386.75610351563)
0BE6  03                 const type 3
0BE7  60E5CA40           const [588]: (6.3404998779297)
0BEB  03                 const type 3
0BEC  ECEFE042           const [589]: (112.46859741211)
0BF0  03                 const type 3
0BF1  ECEFE0C2           const [590]: (-112.46859741211)
0BF5  03                 const type 3
0BF6  636E8B43           const [591]: (278.86239624023)
0BFA  03                 const type 3
0BFB  636E8BC3           const [592]: (-278.86239624023)
0BFF  03                 const type 3
0C00  083DC540           const [593]: (6.1637001037598)
0C04  03                 const type 3
0C05  0000A040           const [594]: (5)
0C09  03                 const type 3
0C0A  6251B743           const [595]: (366.63580322266)
0C0E  03                 const type 3
0C0F  6251B7C3           const [596]: (-366.63580322266)
0C13  03                 const type 3
0C14  AAF13A43           const [597]: (186.94400024414)
0C18  03                 const type 3
0C19  AAF13AC3           const [598]: (-186.94400024414)
0C1D  03                 const type 3
0C1E  3108C840           const [599]: (6.2509999275208)
0C22  03                 const type 3
0C23  832FFD43           const [600]: (506.37118530273)
0C27  03                 const type 3
0C28  832FFDC3           const [601]: (-506.37118530273)
0C2C  03                 const type 3
0C2D  89313943           const [602]: (185.1934967041)
0C31  03                 const type 3
0C32  893139C3           const [603]: (-185.1934967041)
0C36  03                 const type 3
0C37  4772BF40           const [604]: (5.9826998710632)
0C3B  03                 const type 3
0C3C  E3451A44           const [605]: (617.09197998047)
0C40  03                 const type 3
0C41  E3451AC4           const [606]: (-617.09197998047)
0C45  03                 const type 3
0C46  20513A43           const [607]: (186.31689453125)
0C4A  03                 const type 3
0C4B  20513AC3           const [608]: (-186.31689453125)
0C4F  03                 const type 3
0C50  3333C740           const [609]: (6.2249999046326)
0C54  03                 const type 3
0C55  A44F2F44           const [610]: (701.24438476563)
0C59  03                 const type 3
0C5A  A44F2FC4           const [611]: (-701.24438476563)
0C5E  03                 const type 3
0C5F  AE689443           const [612]: (296.81781005859)
0C63  03                 const type 3
0C64  AE6894C3           const [613]: (-296.81781005859)
0C68  03                 const type 3
0C69  79E9C240           const [614]: (6.0910000801086)
0C6D  03                 const type 3
0C6E  C5F23844           const [615]: (739.79327392578)
0C72  03                 const type 3
0C73  C5F238C4           const [616]: (-739.79327392578)
0C77  03                 const type 3
0C78  45C7C943           const [617]: (403.55679321289)
0C7C  03                 const type 3
0C7D  45C7C9C3           const [618]: (-403.55679321289)
0C81  03                 const type 3
0C82  A5BDBB40           const [619]: (5.8668999671936)
0C86  03                 const type 3
0C87  76A73A44           const [620]: (746.61657714844)
0C8B  03                 const type 3
0C8C  76A73AC4           const [621]: (-746.61657714844)
0C90  03                 const type 3
0C91  304AFC43           const [622]: (504.57958984375)
0C95  03                 const type 3
0C96  304AFCC3           const [623]: (-504.57958984375)
0C9A  03                 const type 3
0C9B  C139C340           const [624]: (6.100800037384)
0C9F  03                 const type 3
0CA0  BA8F2C44           const [625]: (690.24572753906)
0CA4  03                 const type 3
0CA5  BA8F2CC4           const [626]: (-690.24572753906)
0CA9  03                 const type 3
0CAA  5A141144           const [627]: (580.31799316406)
0CAE  03                 const type 3
0CAF  5A1411C4           const [628]: (-580.31799316406)
0CB3  03                 const type 3
0CB4  DAACC240           const [629]: (6.0836000442505)
0CB8  03                 const type 3
0CB9  88571544           const [630]: (597.36767578125)
0CBD  03                 const type 3
0CBE  885715C4           const [631]: (-597.36767578125)
0CC2  03                 const type 3
0CC3  06CE1E44           const [632]: (635.21911621094)
0CC7  03                 const type 3
0CC8  06CE1EC4           const [633]: (-635.21911621094)
0CCC  03                 const type 3
0CCD  5EBABB40           const [634]: (5.8664999008179)
0CD1  03                 const type 3
0CD2  60F5FB43           const [635]: (503.9169921875)
0CD6  03                 const type 3
0CD7  60F5FBC3           const [636]: (-503.9169921875)
0CDB  03                 const type 3
0CDC  F7D82644           const [637]: (667.39007568359)
0CE0  03                 const type 3
0CE1  F7D826C4           const [638]: (-667.39007568359)
0CE5  03                 const type 3
0CE6  1214CB40           const [639]: (6.3461999893188)
0CEA  03                 const type 3
0CEB  6CB0BB43           const [640]: (375.37829589844)
0CEF  03                 const type 3
0CF0  6CB0BBC3           const [641]: (-375.37829589844)
0CF4  03                 const type 3
0CF5  AB162844           const [642]: (672.35418701172)
0CF9  03                 const type 3
0CFA  AB1628C4           const [643]: (-672.35418701172)
0CFE  03                 const type 3
0CFF  CF66CB40           const [644]: (6.3562998771667)
0D03  03                 const type 3
0D04  27208743           const [645]: (270.25119018555)
0D08  03                 const type 3
0D09  272087C3           const [646]: (-270.25119018555)
0D0D  03                 const type 3
0D0E  81842644           const [647]: (666.07037353516)
0D12  03                 const type 3
0D13  818426C4           const [648]: (-666.07037353516)
0D17  03                 const type 3
0D18  4BEABE40           const [649]: (5.9661002159119)
0D1C  03                 const type 3
0D1D  778E4343           const [650]: (195.5565032959)
0D21  03                 const type 3
0D22  778E43C3           const [651]: (-195.5565032959)
0D26  03                 const type 3
0D27  59071D44           const [652]: (628.11480712891)
0D2B  03                 const type 3
0D2C  59071DC4           const [653]: (-628.11480712891)
0D30  03                 const type 3
0D31  295CCB40           const [654]: (6.3550000190735)
0D35  03                 const type 3
0D36  53551243           const [655]: (146.33329772949)
0D3A  03                 const type 3
0D3B  535512C3           const [656]: (-146.33329772949)
0D3F  03                 const type 3
0D40  39960644           const [657]: (538.34722900391)
0D44  03                 const type 3
0D45  399606C4           const [658]: (-538.34722900391)
0D49  03                 const type 3
0D4A  DF4FCB40           const [659]: (6.3534998893738)
0D4E  03                 const type 3
0D4F  294D0743           const [660]: (135.30140686035)
0D53  03                 const type 3
0D54  294D07C3           const [661]: (-135.30140686035)
0D58  03                 const type 3
0D59  E42CD243           const [662]: (420.35070800781)
0D5D  03                 const type 3
0D5E  E42CD2C3           const [663]: (-420.35070800781)
0D62  03                 const type 3
0D63  0BB5C640           const [664]: (6.2095999717712)
0D67  03                 const type 3
0D68  1F542E43           const [665]: (174.32859802246)
0D6C  03                 const type 3
0D6D  1F542EC3           const [666]: (-174.32859802246)
0D71  03                 const type 3
0D72  74649B43           const [667]: (310.78479003906)
0D76  03                 const type 3
0D77  74649BC3           const [668]: (-310.78479003906)
0D7B  03                 const type 3
0D7C  4D84C340           const [669]: (6.1098999977112)
0D80  03                 const type 3
0D81  3B517F43           const [670]: (255.31730651855)
0D85  03                 const type 3
0D86  3B517FC3           const [671]: (-255.31730651855)
0D8A  03                 const type 3
0D8B  BB176343           const [672]: (227.09269714355)
0D8F  03                 const type 3
0D90  BB1763C3           const [673]: (-227.09269714355)
0D94  03                 const type 3
0D95  A779BD40           const [674]: (5.9211001396179)
0D99  03                 const type 3
0D9A  0000C040           const [675]: (6)
0D9E  03                 const type 3
0D9F  0000E040           const [676]: (7)
0DA3  03                 const type 3
0DA4  00000041           const [677]: (8)
0DA8  03                 const type 3
0DA9  00002041           const [678]: (10)
0DAD  03                 const type 3
0DAE  00003041           const [679]: (11)
                         * functions:
0DB2  00000000           sizep (0)
                         * code:
0DB6  C3050000           sizecode (1475)
0DBA  0A000000           [0001] newtable   0   0   0    ; array=0, hash=0
0DBE  05000001           [0002] getglobal  1   0        ; GameLocation
0DC2  99800001           [0003] call       1   1   2  
0DC6  D5BE0000           [0004] eq         0   1   251  ; 0, to [6] if true
0DCA  14A68000           [0005] jmp        665          ; to [671]
0DCE  85000001           [0006] getglobal  1   2        ; RaceId
0DD2  99800001           [0007] call       1   1   2  
0DD6  D5BE0000           [0008] eq         0   1   251  ; 0, to [10] if true
0DDA  D4288000           [0009] jmp        164          ; to [174]
0DDE  0A800A01           [0010] newtable   1   21  0    ; array=20, hash=0
0DE2  0A000102           [0011] newtable   2   2   0    ; array=2, hash=0
0DE6  0A800103           [0012] newtable   3   3   0    ; array=3, hash=0
0DEA  C1000004           [0013] loadk      4   3        ; 418.94378662109
0DEE  41010005           [0014] loadk      5   5        ; -47.172798156738
0DF2  81010006           [0015] loadk      6   6        ; 5.9855999946594
0DF6  9F000003           [0016] setlist    3   2        ; index 1 to 3
0DFA  C1010004           [0017] loadk      4   7        ; 9
0DFE  5F000002           [0018] setlist    2   1        ; index 1 to 2
0E02  0A000103           [0019] newtable   3   2   0    ; array=2, hash=0
0E06  0A800104           [0020] newtable   4   3   0    ; array=3, hash=0
0E0A  01020005           [0021] loadk      5   8        ; 417.28210449219
0E0E  81020006           [0022] loadk      6   10       ; -192.41549682617
0E12  C1020007           [0023] loadk      7   11       ; 6.1725997924805
0E16  9F000004           [0024] setlist    4   2        ; index 1 to 3
0E1A  C1010005           [0025] loadk      5   7        ; 9
0E1E  5F000003           [0026] setlist    3   1        ; index 1 to 2
0E22  0A000104           [0027] newtable   4   2   0    ; array=2, hash=0
0E26  0A800105           [0028] newtable   5   3   0    ; array=3, hash=0
0E2A  01030006           [0029] loadk      6   12       ; 406.21530151367
0E2E  81030007           [0030] loadk      7   14       ; -288.98010253906
0E32  C1030008           [0031] loadk      8   15       ; 6.1939997673035
0E36  9F000005           [0032] setlist    5   2        ; index 1 to 3
0E3A  C1010006           [0033] loadk      6   7        ; 9
0E3E  5F000004           [0034] setlist    4   1        ; index 1 to 2
0E42  0A000105           [0035] newtable   5   2   0    ; array=2, hash=0
0E46  0A800106           [0036] newtable   6   3   0    ; array=3, hash=0
0E4A  01040007           [0037] loadk      7   16       ; 349.82580566406
0E4E  81040008           [0038] loadk      8   18       ; -389.27081298828
0E52  C1040009           [0039] loadk      9   19       ; 6.3772001266479
0E56  9F000006           [0040] setlist    6   2        ; index 1 to 3
0E5A  C1010007           [0041] loadk      7   7        ; 9
0E5E  5F000005           [0042] setlist    5   1        ; index 1 to 2
0E62  0A000106           [0043] newtable   6   2   0    ; array=2, hash=0
0E66  0A800107           [0044] newtable   7   3   0    ; array=3, hash=0
0E6A  01050008           [0045] loadk      8   20       ; 273.46490478516
0E6E  81050009           [0046] loadk      9   22       ; -483.23629760742
0E72  C105000A           [0047] loadk      10  23       ; 6.6414999961853
0E76  9F000007           [0048] setlist    7   2        ; index 1 to 3
0E7A  C1010008           [0049] loadk      8   7        ; 9
0E7E  5F000006           [0050] setlist    6   1        ; index 1 to 2
0E82  0A000107           [0051] newtable   7   2   0    ; array=2, hash=0
0E86  0A800108           [0052] newtable   8   3   0    ; array=3, hash=0
0E8A  01060009           [0053] loadk      9   24       ; 213.66670227051
0E8E  8106000A           [0054] loadk      10  26       ; -577.78857421875
0E92  C106000B           [0055] loadk      11  27       ; 6.167799949646
0E96  9F000008           [0056] setlist    8   2        ; index 1 to 3
0E9A  C1010009           [0057] loadk      9   7        ; 9
0E9E  5F000007           [0058] setlist    7   1        ; index 1 to 2
0EA2  0A000108           [0059] newtable   8   2   0    ; array=2, hash=0
0EA6  0A800109           [0060] newtable   9   3   0    ; array=3, hash=0
0EAA  0107000A           [0061] loadk      10  28       ; 153.7301940918
0EAE  8107000B           [0062] loadk      11  30       ; -637.73547363281
0EB2  C107000C           [0063] loadk      12  31       ; 6.0346999168396
0EB6  9F000009           [0064] setlist    9   2        ; index 1 to 3
0EBA  C101000A           [0065] loadk      10  7        ; 9
0EBE  5F000008           [0066] setlist    8   1        ; index 1 to 2
0EC2  0A000109           [0067] newtable   9   2   0    ; array=2, hash=0
0EC6  0A80010A           [0068] newtable   10  3   0    ; array=3, hash=0
0ECA  0108000B           [0069] loadk      11  32       ; 63.324699401855
0ECE  8108000C           [0070] loadk      12  34       ; -673.05847167969
0ED2  C108000D           [0071] loadk      13  35       ; 6.1192998886108
0ED6  9F00000A           [0072] setlist    10  2        ; index 1 to 3
0EDA  C101000B           [0073] loadk      11  7        ; 9
0EDE  5F000009           [0074] setlist    9   1        ; index 1 to 2
0EE2  0A00010A           [0075] newtable   10  2   0    ; array=2, hash=0
0EE6  0A80010B           [0076] newtable   11  3   0    ; array=3, hash=0
0EEA  4109000C           [0077] loadk      12  37       ; -8.1269998550415
0EEE  C109000D           [0078] loadk      13  39       ; -679.41522216797
0EF2  010A000E           [0079] loadk      14  40       ; 5.6108999252319
0EF6  9F00000B           [0080] setlist    11  2        ; index 1 to 3
0EFA  C101000C           [0081] loadk      12  7        ; 9
0EFE  5F00000A           [0082] setlist    10  1        ; index 1 to 2
0F02  0A00010B           [0083] newtable   11  2   0    ; array=2, hash=0
0F06  0A80010C           [0084] newtable   12  3   0    ; array=3, hash=0
0F0A  810A000D           [0085] loadk      13  42       ; -59.97029876709
0F0E  010B000E           [0086] loadk      14  44       ; -659.67401123047
0F12  410B000F           [0087] loadk      15  45       ; 4.9251999855042
0F16  9F00000C           [0088] setlist    12  2        ; index 1 to 3
0F1A  C101000D           [0089] loadk      13  7        ; 9
0F1E  5F00000B           [0090] setlist    11  1        ; index 1 to 2
0F22  0A00010C           [0091] newtable   12  2   0    ; array=2, hash=0
0F26  0A80010D           [0092] newtable   13  3   0    ; array=3, hash=0
0F2A  C10B000E           [0093] loadk      14  47       ; -76.028198242188
0F2E  410C000F           [0094] loadk      15  49       ; -589.66937255859
0F32  810C0010           [0095] loadk      16  50       ; 6.3196997642517
0F36  9F00000D           [0096] setlist    13  2        ; index 1 to 3
0F3A  C101000E           [0097] loadk      14  7        ; 9
0F3E  5F00000C           [0098] setlist    12  1        ; index 1 to 2
0F42  0A00010D           [0099] newtable   13  2   0    ; array=2, hash=0
0F46  0A80010E           [0100] newtable   14  3   0    ; array=3, hash=0
0F4A  010D000F           [0101] loadk      15  52       ; -51.363998413086
0F4E  810D0010           [0102] loadk      16  54       ; -521.81262207031
0F52  C10D0011           [0103] loadk      17  55       ; 6.5107002258301
0F56  9F00000E           [0104] setlist    14  2        ; index 1 to 3
0F5A  C101000F           [0105] loadk      15  7        ; 9
0F5E  5F00000D           [0106] setlist    13  1        ; index 1 to 2
0F62  0A00010E           [0107] newtable   14  2   0    ; array=2, hash=0
0F66  0A80010F           [0108] newtable   15  3   0    ; array=3, hash=0
0F6A  410E0010           [0109] loadk      16  57       ; -5.9355001449585
0F6E  C10E0011           [0110] loadk      17  59       ; -430.78561401367
0F72  010F0012           [0111] loadk      18  60       ; 6.9854998588562
0F76  9F00000F           [0112] setlist    15  2        ; index 1 to 3
0F7A  C1010010           [0113] loadk      16  7        ; 9
0F7E  5F00000E           [0114] setlist    14  1        ; index 1 to 2
0F82  0A00010F           [0115] newtable   15  2   0    ; array=2, hash=0
0F86  0A800110           [0116] newtable   16  3   0    ; array=3, hash=0
0F8A  410F0011           [0117] loadk      17  61       ; 7.4444999694824
0F8E  C10F0012           [0118] loadk      18  63       ; -323.65130615234
0F92  01100013           [0119] loadk      19  64       ; 5.9973001480103
0F96  9F000010           [0120] setlist    16  2        ; index 1 to 3
0F9A  C1010011           [0121] loadk      17  7        ; 9
0F9E  5F00000F           [0122] setlist    15  1        ; index 1 to 2
0FA2  0A000110           [0123] newtable   16  2   0    ; array=2, hash=0
0FA6  0A800111           [0124] newtable   17  3   0    ; array=3, hash=0
0FAA  41100012           [0125] loadk      18  65       ; 62.453399658203
0FAE  C1100013           [0126] loadk      19  67       ; -270.35598754883
0FB2  01110014           [0127] loadk      20  68       ; 6.0742001533508
0FB6  9F000011           [0128] setlist    17  2        ; index 1 to 3
0FBA  C1010012           [0129] loadk      18  7        ; 9
0FBE  5F000010           [0130] setlist    16  1        ; index 1 to 2
0FC2  0A000111           [0131] newtable   17  2   0    ; array=2, hash=0
0FC6  0A800112           [0132] newtable   18  3   0    ; array=3, hash=0
0FCA  41110013           [0133] loadk      19  69       ; 167.98930358887
0FCE  C1110014           [0134] loadk      20  71       ; -199.38250732422
0FD2  01120015           [0135] loadk      21  72       ; 5.9815001487732
0FD6  9F000012           [0136] setlist    18  2        ; index 1 to 3
0FDA  C1010013           [0137] loadk      19  7        ; 9
0FDE  5F000011           [0138] setlist    17  1        ; index 1 to 2
0FE2  0A000112           [0139] newtable   18  2   0    ; array=2, hash=0
0FE6  0A800113           [0140] newtable   19  3   0    ; array=3, hash=0
0FEA  41120014           [0141] loadk      20  73       ; 216.67649841309
0FEE  C1120015           [0142] loadk      21  75       ; -119.44629669189
0FF2  01130016           [0143] loadk      22  76       ; 6.2396998405457
0FF6  9F000013           [0144] setlist    19  2        ; index 1 to 3
0FFA  C1010014           [0145] loadk      20  7        ; 9
0FFE  5F000012           [0146] setlist    18  1        ; index 1 to 2
1002  0A000113           [0147] newtable   19  2   0    ; array=2, hash=0
1006  0A800114           [0148] newtable   20  3   0    ; array=3, hash=0
100A  41130015           [0149] loadk      21  77       ; 211.19580078125
100E  81130016           [0150] loadk      22  78       ; 2.0826001167297
1012  C1130017           [0151] loadk      23  79       ; 6.1687002182007
1016  9F000014           [0152] setlist    20  2        ; index 1 to 3
101A  C1010015           [0153] loadk      21  7        ; 9
101E  5F000013           [0154] setlist    19  1        ; index 1 to 2
1022  0A000114           [0155] newtable   20  2   0    ; array=2, hash=0
1026  0A800115           [0156] newtable   21  3   0    ; array=3, hash=0
102A  01140016           [0157] loadk      22  80       ; 270.79901123047
102E  41140017           [0158] loadk      23  81       ; 98.401397705078
1032  81140018           [0159] loadk      24  82       ; 6.394700050354
1036  9F000015           [0160] setlist    21  2        ; index 1 to 3
103A  C1010016           [0161] loadk      22  7        ; 9
103E  5F000014           [0162] setlist    20  1        ; index 1 to 2
1042  0A000115           [0163] newtable   21  2   0    ; array=2, hash=0
1046  0A800116           [0164] newtable   22  3   0    ; array=3, hash=0
104A  C1140017           [0165] loadk      23  83       ; 363.29721069336
104E  01150018           [0166] loadk      24  84       ; 57.721599578857
1052  41150019           [0167] loadk      25  85       ; 6.1512999534607
1056  9F000016           [0168] setlist    22  2        ; index 1 to 3
105A  C1010017           [0169] loadk      23  7        ; 9
105E  5F000015           [0170] setlist    21  1        ; index 1 to 2
1062  DF040001           [0171] setlist    1   19       ; index 1 to 20
1066  00800000           [0172] move       0   1      
106A  D4448100           [0173] jmp        1300         ; to [1474]
106E  85000001           [0174] getglobal  1   2        ; RaceId
1072  99800001           [0175] call       1   1   2  
1076  15D40000           [0176] eq         0   1   336  ; 1, to [178] if true
107A  14478000           [0177] jmp        285          ; to [463]
107E  0A800E01           [0178] newtable   1   29  0    ; array=40, hash=0
1082  0A000102           [0179] newtable   2   2   0    ; array=2, hash=0
1086  0A800103           [0180] newtable   3   3   0    ; array=3, hash=0
108A  01160004           [0181] loadk      4   88       ; -79.661796569824
108E  81160005           [0182] loadk      5   90       ; -318.18508911133
1092  C1160006           [0183] loadk      6   91       ; 5.9305000305176
1096  9F000003           [0184] setlist    3   2        ; index 1 to 3
109A  C1010004           [0185] loadk      4   7        ; 9
109E  5F000002           [0186] setlist    2   1        ; index 1 to 2
10A2  0A000103           [0187] newtable   3   2   0    ; array=2, hash=0
10A6  0A800104           [0188] newtable   4   3   0    ; array=3, hash=0
10AA  41170005           [0189] loadk      5   93       ; -66.746597290039
10AE  C1170006           [0190] loadk      6   95       ; -400.93939208984
10B2  01180007           [0191] loadk      7   96       ; 6.3554000854492
10B6  9F000004           [0192] setlist    4   2        ; index 1 to 3
10BA  C1010005           [0193] loadk      5   7        ; 9
10BE  5F000003           [0194] setlist    3   1        ; index 1 to 2
10C2  0A000104           [0195] newtable   4   2   0    ; array=2, hash=0
10C6  0A800105           [0196] newtable   5   3   0    ; array=3, hash=0
10CA  81180006           [0197] loadk      6   98       ; -66.469200134277
10CE  01190007           [0198] loadk      7   100      ; -529.66937255859
10D2  41190008           [0199] loadk      8   101      ; 5.7632999420166
10D6  9F000005           [0200] setlist    5   2        ; index 1 to 3
10DA  C1010006           [0201] loadk      6   7        ; 9
10DE  5F000004           [0202] setlist    4   1        ; index 1 to 2
10E2  0A000105           [0203] newtable   5   2   0    ; array=2, hash=0
10E6  0A800106           [0204] newtable   6   3   0    ; array=3, hash=0
10EA  C1190007           [0205] loadk      7   103      ; -85.638000488281
10EE  411A0008           [0206] loadk      8   105      ; -604.50341796875
10F2  811A0009           [0207] loadk      9   106      ; 5.8959999084473
10F6  9F000006           [0208] setlist    6   2        ; index 1 to 3
10FA  C1010007           [0209] loadk      7   7        ; 9
10FE  5F000005           [0210] setlist    5   1        ; index 1 to 2
1102  0A000106           [0211] newtable   6   2   0    ; array=2, hash=0
1106  0A800107           [0212] newtable   7   3   0    ; array=3, hash=0
110A  011B0008           [0213] loadk      8   108      ; -54.647701263428
110E  811B0009           [0214] loadk      9   110      ; -663.29571533203
1112  C11B000A           [0215] loadk      10  111      ; 5.8218998908997
1116  9F000007           [0216] setlist    7   2        ; index 1 to 3
111A  C1010008           [0217] loadk      8   7        ; 9
111E  5F000006           [0218] setlist    6   1        ; index 1 to 2
1122  0A000107           [0219] newtable   7   2   0    ; array=2, hash=0
1126  0A800108           [0220] newtable   8   3   0    ; array=3, hash=0
112A  011C0009           [0221] loadk      9   112      ; 29.349100112915
112E  811C000A           [0222] loadk      10  114      ; -678.24658203125
1132  C11C000B           [0223] loadk      11  115      ; 6.1883001327515
1136  9F000008           [0224] setlist    8   2        ; index 1 to 3
113A  C1010009           [0225] loadk      9   7        ; 9
113E  5F000007           [0226] setlist    7   1        ; index 1 to 2
1142  0A000108           [0227] newtable   8   2   0    ; array=2, hash=0
1146  0A800109           [0228] newtable   9   3   0    ; array=3, hash=0
114A  011D000A           [0229] loadk      10  116      ; 124.49960327148
114E  811D000B           [0230] loadk      11  118      ; -645.38787841797
1152  C11D000C           [0231] loadk      12  119      ; 5.8840999603271
1156  9F000009           [0232] setlist    9   2        ; index 1 to 3
115A  C101000A           [0233] loadk      10  7        ; 9
115E  5F000008           [0234] setlist    8   1        ; index 1 to 2
1162  0A000109           [0235] newtable   9   2   0    ; array=2, hash=0
1166  0A80010A           [0236] newtable   10  3   0    ; array=3, hash=0
116A  011E000B           [0237] loadk      11  120      ; 205.65980529785
116E  811E000C           [0238] loadk      12  122      ; -593.24060058594
1172  C11E000D           [0239] loadk      13  123      ; 6.0625
1176  9F00000A           [0240] setlist    10  2        ; index 1 to 3
117A  C101000B           [0241] loadk      11  7        ; 9
117E  5F000009           [0242] setlist    9   1        ; index 1 to 2
1182  0A00010A           [0243] newtable   10  2   0    ; array=2, hash=0
1186  0A80010B           [0244] newtable   11  3   0    ; array=3, hash=0
118A  011F000C           [0245] loadk      12  124      ; 269.43328857422
118E  811F000D           [0246] loadk      13  126      ; -489.71868896484
1192  C11F000E           [0247] loadk      14  127      ; 6.0654001235962
1196  9F00000B           [0248] setlist    11  2        ; index 1 to 3
119A  C101000C           [0249] loadk      12  7        ; 9
119E  5F00000A           [0250] setlist    10  1        ; index 1 to 2
11A2  0A00010B           [0251] newtable   11  2   0    ; array=2, hash=0
11A6  0A80010C           [0252] newtable   12  3   0    ; array=3, hash=0
11AA  0120000D           [0253] loadk      13  128      ; 334.85598754883
11AE  8120000E           [0254] loadk      14  130      ; -395.81500244141
11B2  C120000F           [0255] loadk      15  131      ; 6.3400001525879
11B6  9F00000C           [0256] setlist    12  2        ; index 1 to 3
11BA  C101000D           [0257] loadk      13  7        ; 9
11BE  5F00000B           [0258] setlist    11  1        ; index 1 to 2
11C2  0A00010C           [0259] newtable   12  2   0    ; array=2, hash=0
11C6  0A80010D           [0260] newtable   13  3   0    ; array=3, hash=0
11CA  0121000E           [0261] loadk      14  132      ; 402.23870849609
11CE  8121000F           [0262] loadk      15  134      ; -282.78491210938
11D2  C1210010           [0263] loadk      16  135      ; 5.9317002296448
11D6  9F00000D           [0264] setlist    13  2        ; index 1 to 3
11DA  C101000E           [0265] loadk      14  7        ; 9
11DE  5F00000C           [0266] setlist    12  1        ; index 1 to 2
11E2  0A00010D           [0267] newtable   13  2   0    ; array=2, hash=0
11E6  0A80010E           [0268] newtable   14  3   0    ; array=3, hash=0
11EA  0122000F           [0269] loadk      15  136      ; 416.45309448242
11EE  81220010           [0270] loadk      16  138      ; -159.81419372559
11F2  C1220011           [0271] loadk      17  139      ; 6.462299823761
11F6  9F00000E           [0272] setlist    14  2        ; index 1 to 3
11FA  C101000F           [0273] loadk      15  7        ; 9
11FE  5F00000D           [0274] setlist    13  1        ; index 1 to 2
1202  0A00010E           [0275] newtable   14  2   0    ; array=2, hash=0
1206  0A80010F           [0276] newtable   15  3   0    ; array=3, hash=0
120A  01230010           [0277] loadk      16  140      ; 413.91229248047
120E  81230011           [0278] loadk      17  142      ; -40.459701538086
1212  C1230012           [0279] loadk      18  143      ; 6.5015001296997
1216  9F00000F           [0280] setlist    15  2        ; index 1 to 3
121A  C1010010           [0281] loadk      16  7        ; 9
121E  5F00000E           [0282] setlist    14  1        ; index 1 to 2
1222  0A00010F           [0283] newtable   15  2   0    ; array=2, hash=0
1226  0A800110           [0284] newtable   16  3   0    ; array=3, hash=0
122A  01240011           [0285] loadk      17  144      ; 383.86248779297
122E  41240012           [0286] loadk      18  145      ; 40.94889831543
1232  81240013           [0287] loadk      19  146      ; 5.9008002281189
1236  9F000010           [0288] setlist    16  2        ; index 1 to 3
123A  C1010011           [0289] loadk      17  7        ; 9
123E  5F00000F           [0290] setlist    15  1        ; index 1 to 2
1242  0A000110           [0291] newtable   16  2   0    ; array=2, hash=0
1246  0A800111           [0292] newtable   17  3   0    ; array=3, hash=0
124A  C1240012           [0293] loadk      18  147      ; 292.64010620117
124E  01250013           [0294] loadk      19  148      ; 129.26570129395
1252  41250014           [0295] loadk      20  149      ; 5.9699001312256
1256  9F000011           [0296] setlist    17  2        ; index 1 to 3
125A  C1010012           [0297] loadk      18  7        ; 9
125E  5F000010           [0298] setlist    16  1        ; index 1 to 2
1262  0A000111           [0299] newtable   17  2   0    ; array=2, hash=0
1266  0A800112           [0300] newtable   18  3   0    ; array=3, hash=0
126A  81250013           [0301] loadk      19  150      ; 209.3365020752
126E  C1250014           [0302] loadk      20  151      ; 215.94830322266
1272  01260015           [0303] loadk      21  152      ; 5.8678998947144
1276  9F000012           [0304] setlist    18  2        ; index 1 to 3
127A  C1010013           [0305] loadk      19  7        ; 9
127E  5F000011           [0306] setlist    17  1        ; index 1 to 2
1282  0A000112           [0307] newtable   18  2   0    ; array=2, hash=0
1286  0A800113           [0308] newtable   19  3   0    ; array=3, hash=0
128A  41260014           [0309] loadk      20  153      ; 220.31359863281
128E  81260015           [0310] loadk      21  154      ; 295.54739379883
1292  C1260016           [0311] loadk      22  155      ; 6.0384998321533
1296  9F000013           [0312] setlist    19  2        ; index 1 to 3
129A  C1010014           [0313] loadk      20  7        ; 9
129E  5F000012           [0314] setlist    18  1        ; index 1 to 2
12A2  0A000113           [0315] newtable   19  2   0    ; array=2, hash=0
12A6  0A800114           [0316] newtable   20  3   0    ; array=3, hash=0
12AA  01270015           [0317] loadk      21  156      ; 236.53199768066
12AE  41270016           [0318] loadk      22  157      ; 379.53750610352
12B2  81270017           [0319] loadk      23  158      ; 6.3478999137878
12B6  9F000014           [0320] setlist    20  2        ; index 1 to 3
12BA  C1010015           [0321] loadk      21  7        ; 9
12BE  5F000013           [0322] setlist    19  1        ; index 1 to 2
12C2  0A000114           [0323] newtable   20  2   0    ; array=2, hash=0
12C6  0A800115           [0324] newtable   21  3   0    ; array=3, hash=0
12CA  C1270016           [0325] loadk      22  159      ; 283.12188720703
12CE  01280017           [0326] loadk      23  160      ; 480.23291015625
12D2  41280018           [0327] loadk      24  161      ; 6.0893998146057
12D6  9F000015           [0328] setlist    21  2        ; index 1 to 3
12DA  C1010016           [0329] loadk      22  7        ; 9
12DE  5F000014           [0330] setlist    20  1        ; index 1 to 2
12E2  0A000115           [0331] newtable   21  2   0    ; array=2, hash=0
12E6  0A800116           [0332] newtable   22  3   0    ; array=3, hash=0
12EA  81280017           [0333] loadk      23  162      ; 264.76739501953
12EE  C1280018           [0334] loadk      24  163      ; 559.84838867188
12F2  01290019           [0335] loadk      25  164      ; 6.4345998764038
12F6  9F000016           [0336] setlist    22  2        ; index 1 to 3
12FA  C1010017           [0337] loadk      23  7        ; 9
12FE  5F000015           [0338] setlist    21  1        ; index 1 to 2
1302  0A000116           [0339] newtable   22  2   0    ; array=2, hash=0
1306  0A800117           [0340] newtable   23  3   0    ; array=3, hash=0
130A  41290018           [0341] loadk      24  165      ; 184.60609436035
130E  81290019           [0342] loadk      25  166      ; 615.29998779297
1312  C129001A           [0343] loadk      26  167      ; 6.1198000907898
1316  9F000017           [0344] setlist    23  2        ; index 1 to 3
131A  C1010018           [0345] loadk      24  7        ; 9
131E  5F000016           [0346] setlist    22  1        ; index 1 to 2
1322  0A000117           [0347] newtable   23  2   0    ; array=2, hash=0
1326  0A800118           [0348] newtable   24  3   0    ; array=3, hash=0
132A  012A0019           [0349] loadk      25  168      ; 122.10130310059
132E  412A001A           [0350] loadk      26  169      ; 656.12548828125
1332  812A001B           [0351] loadk      27  170      ; 6.6298999786377
1336  9F000018           [0352] setlist    24  2        ; index 1 to 3
133A  C1010019           [0353] loadk      25  7        ; 9
133E  5F000017           [0354] setlist    23  1        ; index 1 to 2
1342  0A000118           [0355] newtable   24  2   0    ; array=2, hash=0
1346  0A800119           [0356] newtable   25  3   0    ; array=3, hash=0
134A  C12A001A           [0357] loadk      26  171      ; 22.580600738525
134E  012B001B           [0358] loadk      27  172      ; 679.51580810547
1352  412B001C           [0359] loadk      28  173      ; 6.4767999649048
1356  9F000019           [0360] setlist    25  2        ; index 1 to 3
135A  C101001A           [0361] loadk      26  7        ; 9
135E  5F000018           [0362] setlist    24  1        ; index 1 to 2
1362  0A000119           [0363] newtable   25  2   0    ; array=2, hash=0
1366  0A80011A           [0364] newtable   26  3   0    ; array=3, hash=0
136A  C12B001B           [0365] loadk      27  175      ; -85.529602050781
136E  012C001C           [0366] loadk      28  176      ; 662.72540283203
1372  412C001D           [0367] loadk      29  177      ; 6.2873001098633
1376  9F00001A           [0368] setlist    26  2        ; index 1 to 3
137A  C101001B           [0369] loadk      27  7        ; 9
137E  5F000019           [0370] setlist    25  1        ; index 1 to 2
1382  0A00011A           [0371] newtable   26  2   0    ; array=2, hash=0
1386  0A80011B           [0372] newtable   27  3   0    ; array=3, hash=0
138A  C12C001C           [0373] loadk      28  179      ; -156.71839904785
138E  012D001D           [0374] loadk      29  180      ; 653.66351318359
1392  412D001E           [0375] loadk      30  181      ; 6.3000001907349
1396  9F00001B           [0376] setlist    27  2        ; index 1 to 3
139A  C101001C           [0377] loadk      28  7        ; 9
139E  5F00001A           [0378] setlist    26  1        ; index 1 to 2
13A2  0A00011B           [0379] newtable   27  2   0    ; array=2, hash=0
13A6  0A80011C           [0380] newtable   28  3   0    ; array=3, hash=0
13AA  C12D001D           [0381] loadk      29  183      ; -244.64540100098
13AE  012E001E           [0382] loadk      30  184      ; 623.96752929688
13B2  412E001F           [0383] loadk      31  185      ; 6.372700214386
13B6  9F00001C           [0384] setlist    28  2        ; index 1 to 3
13BA  C101001D           [0385] loadk      29  7        ; 9
13BE  5F00001B           [0386] setlist    27  1        ; index 1 to 2
13C2  0A00011C           [0387] newtable   28  2   0    ; array=2, hash=0
13C6  0A80011D           [0388] newtable   29  3   0    ; array=3, hash=0
13CA  C12E001E           [0389] loadk      30  187      ; -290.08068847656
13CE  012F001F           [0390] loadk      31  188      ; 546.63598632813
13D2  412F0020           [0391] loadk      32  189      ; 6.1697001457214
13D6  9F00001D           [0392] setlist    29  2        ; index 1 to 3
13DA  C101001E           [0393] loadk      30  7        ; 9
13DE  5F00001C           [0394] setlist    28  1        ; index 1 to 2
13E2  0A00011D           [0395] newtable   29  2   0    ; array=2, hash=0
13E6  0A80011E           [0396] newtable   30  3   0    ; array=3, hash=0
13EA  C12F001F           [0397] loadk      31  191      ; -309.15161132813
13EE  01300020           [0398] loadk      32  192      ; 454.2991027832
13F2  41300021           [0399] loadk      33  193      ; 6.4642000198364
13F6  9F00001E           [0400] setlist    30  2        ; index 1 to 3
13FA  C101001F           [0401] loadk      31  7        ; 9
13FE  5F00001D           [0402] setlist    29  1        ; index 1 to 2
1402  0A00011E           [0403] newtable   30  2   0    ; array=2, hash=0
1406  0A80011F           [0404] newtable   31  3   0    ; array=3, hash=0
140A  C1300020           [0405] loadk      32  195      ; -279.98989868164
140E  01310021           [0406] loadk      33  196      ; 349.63708496094
1412  41310022           [0407] loadk      34  197      ; 6.2557001113892
1416  9F00001F           [0408] setlist    31  2        ; index 1 to 3
141A  C1010020           [0409] loadk      32  7        ; 9
141E  5F00001E           [0410] setlist    30  1        ; index 1 to 2
1422  0A00011F           [0411] newtable   31  2   0    ; array=2, hash=0
1426  0A800120           [0412] newtable   32  3   0    ; array=3, hash=0
142A  C1310021           [0413] loadk      33  199      ; -237.6049041748
142E  01320022           [0414] loadk      34  200      ; 267.25650024414
1432  41320023           [0415] loadk      35  201      ; 6.0222997665405
1436  9F000020           [0416] setlist    32  2        ; index 1 to 3
143A  C1010021           [0417] loadk      33  7        ; 9
143E  5F00001F           [0418] setlist    31  1        ; index 1 to 2
1442  0A000120           [0419] newtable   32  2   0    ; array=2, hash=0
1446  0A800121           [0420] newtable   33  3   0    ; array=3, hash=0
144A  C1320022           [0421] loadk      34  203      ; -195.39329528809
144E  01330023           [0422] loadk      35  204      ; 201.40049743652
1452  41330024           [0423] loadk      36  205      ; 6.3717999458313
1456  9F000021           [0424] setlist    33  2        ; index 1 to 3
145A  C1010022           [0425] loadk      34  7        ; 9
145E  5F000020           [0426] setlist    32  1        ; index 1 to 2
1462  0A000121           [0427] newtable   33  2   0    ; array=2, hash=0
1466  0A800122           [0428] newtable   34  3   0    ; array=3, hash=0
146A  C1330023           [0429] loadk      35  207      ; -153.40519714355
146E  01340024           [0430] loadk      36  208      ; 113.65229797363
1472  41340025           [0431] loadk      37  209      ; 6.021900177002
1476  9F000022           [0432] setlist    34  2        ; index 1 to 3
147A  C1010023           [0433] loadk      35  7        ; 9
147E  5F000021           [0434] setlist    33  1        ; index 1 to 2
1482  DF070001           [0435] setlist    1   31       ; index 1 to 32
1486  0A000102           [0436] newtable   2   2   0    ; array=2, hash=0
148A  0A800103           [0437] newtable   3   3   0    ; array=3, hash=0
148E  C1340004           [0438] loadk      4   211      ; -130.11819458008
1492  01350005           [0439] loadk      5   212      ; 20.82859992981
1496  41350006           [0440] loadk      6   213      ; 6.314199924469
149A  9F000003           [0441] setlist    3   2        ; index 1 to 3
149E  C1010004           [0442] loadk      4   7        ; 9
14A2  5F000002           [0443] setlist    2   1        ; index 1 to 2
14A6  0A000103           [0444] newtable   3   2   0    ; array=2, hash=0
14AA  0A800104           [0445] newtable   4   3   0    ; array=3, hash=0
14AE  C1350005           [0446] loadk      5   215      ; -115.01049804688
14B2  41360006           [0447] loadk      6   217      ; -76.449600219727
14B6  81360007           [0448] loadk      7   218      ; 6.0329999923706
14BA  9F000004           [0449] setlist    4   2        ; index 1 to 3
14BE  C1010005           [0450] loadk      5   7        ; 9
14C2  5F000003           [0451] setlist    3   1        ; index 1 to 2
14C6  0A000104           [0452] newtable   4   2   0    ; array=2, hash=0
14CA  0A800105           [0453] newtable   5   3   0    ; array=3, hash=0
14CE  01370006           [0454] loadk      6   220      ; -99.983901977539
14D2  81370007           [0455] loadk      7   222      ; -179.4873046875
14D6  C1370008           [0456] loadk      8   223      ; 6.2989001274109
14DA  9F000005           [0457] setlist    5   2        ; index 1 to 3
14DE  C1010006           [0458] loadk      6   7        ; 9
14E2  5F000004           [0459] setlist    4   1        ; index 1 to 2
14E6  9F080001           [0460] setlist    1   34       ; index 33 to 35
14EA  00800000           [0461] move       0   1      
14EE  94FC8000           [0462] jmp        1011         ; to [1474]
14F2  85000001           [0463] getglobal  1   2        ; RaceId
14F6  99800001           [0464] call       1   1   2  
14FA  95F60000           [0465] eq         0   1   474  ; 2, to [467] if true
14FE  94FB8000           [0466] jmp        1007         ; to [1474]
1502  0A800B01           [0467] newtable   1   23  0    ; array=28, hash=0
1506  0A000102           [0468] newtable   2   2   0    ; array=2, hash=0
150A  0A800103           [0469] newtable   3   3   0    ; array=3, hash=0
150E  81380004           [0470] loadk      4   226      ; -121.80950164795
1512  01390005           [0471] loadk      5   228      ; -127.02069854736
1516  41390006           [0472] loadk      6   229      ; 6.2585000991821
151A  9F000003           [0473] setlist    3   2        ; index 1 to 3
151E  C1010004           [0474] loadk      4   7        ; 9
1522  5F000002           [0475] setlist    2   1        ; index 1 to 2
1526  0A000103           [0476] newtable   3   2   0    ; array=2, hash=0
152A  0A800104           [0477] newtable   4   3   0    ; array=3, hash=0
152E  C1390005           [0478] loadk      5   231      ; -136.05230712891
1532  413A0006           [0479] loadk      6   233      ; -28.574600219727
1536  813A0007           [0480] loadk      7   234      ; 6.0781002044678
153A  9F000004           [0481] setlist    4   2        ; index 1 to 3
153E  C1010005           [0482] loadk      5   7        ; 9
1542  5F000003           [0483] setlist    3   1        ; index 1 to 2
1546  0A000104           [0484] newtable   4   2   0    ; array=2, hash=0
154A  0A800105           [0485] newtable   5   3   0    ; array=3, hash=0
154E  013B0006           [0486] loadk      6   236      ; -132.61349487305
1552  413B0007           [0487] loadk      7   237      ; 33.870700836182
1556  813B0008           [0488] loadk      8   238      ; 6.2604999542236
155A  9F000005           [0489] setlist    5   2        ; index 1 to 3
155E  C1010006           [0490] loadk      6   7        ; 9
1562  5F000004           [0491] setlist    4   1        ; index 1 to 2
1566  0A000105           [0492] newtable   5   2   0    ; array=2, hash=0
156A  0A800106           [0493] newtable   6   3   0    ; array=3, hash=0
156E  013C0007           [0494] loadk      7   240      ; -121.764503479
1572  413C0008           [0495] loadk      8   241      ; 144.6708984375
1576  813C0009           [0496] loadk      9   242      ; 5.9868001937866
157A  9F000006           [0497] setlist    6   2        ; index 1 to 3
157E  C1010007           [0498] loadk      7   7        ; 9
1582  5F000005           [0499] setlist    5   1        ; index 1 to 2
1586  0A000106           [0500] newtable   6   2   0    ; array=2, hash=0
158A  0A800107           [0501] newtable   7   3   0    ; array=3, hash=0
158E  013D0008           [0502] loadk      8   244      ; -111.37220001221
1592  413D0009           [0503] loadk      9   245      ; 216.26719665527
1596  813D000A           [0504] loadk      10  246      ; 6.4092001914978
159A  9F000007           [0505] setlist    7   2        ; index 1 to 3
159E  C1010008           [0506] loadk      8   7        ; 9
15A2  5F000006           [0507] setlist    6   1        ; index 1 to 2
15A6  0A000107           [0508] newtable   7   2   0    ; array=2, hash=0
15AA  0A800108           [0509] newtable   8   3   0    ; array=3, hash=0
15AE  013E0009           [0510] loadk      9   248      ; -85.444999694824
15B2  413E000A           [0511] loadk      10  249      ; 306.27841186523
15B6  813E000B           [0512] loadk      11  250      ; 6.2680997848511
15BA  9F000008           [0513] setlist    8   2        ; index 1 to 3
15BE  C1010009           [0514] loadk      9   7        ; 9
15C2  5F000007           [0515] setlist    7   1        ; index 1 to 2
15C6  0A000108           [0516] newtable   8   2   0    ; array=2, hash=0
15CA  0A800109           [0517] newtable   9   3   0    ; array=3, hash=0
15CE  C13E000A           [0518] loadk      10  251      ; 0.94770002365112
15D2  013F000B           [0519] loadk      11  252      ; 389.00918579102
15D6  413F000C           [0520] loadk      12  253      ; 6.4699997901917
15DA  9F000009           [0521] setlist    9   2        ; index 1 to 3
15DE  C101000A           [0522] loadk      10  7        ; 9
15E2  5F000008           [0523] setlist    8   1        ; index 1 to 2
15E6  0A000109           [0524] newtable   9   2   0    ; array=2, hash=0
15EA  0A80010A           [0525] newtable   10  3   0    ; array=3, hash=0
15EE  813F000B           [0526] loadk      11  254      ; 117.21399688721
15F2  C13F000C           [0527] loadk      12  255      ; 402.51690673828
15F6  0140000D           [0528] loadk      13  256      ; 6.0009999275208
15FA  9F00000A           [0529] setlist    10  2        ; index 1 to 3
15FE  C101000B           [0530] loadk      11  7        ; 9
1602  5F000009           [0531] setlist    9   1        ; index 1 to 2
1606  0A00010A           [0532] newtable   10  2   0    ; array=2, hash=0
160A  0A80010B           [0533] newtable   11  3   0    ; array=3, hash=0
160E  4140000C           [0534] loadk      12  257      ; 213.11109924316
1612  8140000D           [0535] loadk      13  258      ; 378.77621459961
1616  C140000E           [0536] loadk      14  259      ; 6.227499961853
161A  9F00000B           [0537] setlist    11  2        ; index 1 to 3
161E  C101000C           [0538] loadk      12  7        ; 9
1622  5F00000A           [0539] setlist    10  1        ; index 1 to 2
1626  0A00010B           [0540] newtable   11  2   0    ; array=2, hash=0
162A  0A80010C           [0541] newtable   12  3   0    ; array=3, hash=0
162E  0141000D           [0542] loadk      13  260      ; 218.68069458008
1632  4141000E           [0543] loadk      14  261      ; 298.94488525391
1636  8141000F           [0544] loadk      15  262      ; 5.9703001976013
163A  9F00000C           [0545] setlist    12  2        ; index 1 to 3
163E  C101000D           [0546] loadk      13  7        ; 9
1642  5F00000B           [0547] setlist    11  1        ; index 1 to 2
1646  0A00010C           [0548] newtable   12  2   0    ; array=2, hash=0
164A  0A80010D           [0549] newtable   13  3   0    ; array=3, hash=0
164E  C141000E           [0550] loadk      14  263      ; 234.26469421387
1652  0142000F           [0551] loadk      15  264      ; 192.58250427246
1656  41420010           [0552] loadk      16  265      ; 6.2624998092651
165A  9F00000D           [0553] setlist    13  2        ; index 1 to 3
165E  C101000E           [0554] loadk      14  7        ; 9
1662  5F00000C           [0555] setlist    12  1        ; index 1 to 2
1666  0A00010D           [0556] newtable   13  2   0    ; array=2, hash=0
166A  0A80010E           [0557] newtable   14  3   0    ; array=3, hash=0
166E  8142000F           [0558] loadk      15  266      ; 375.8669128418
1672  C1420010           [0559] loadk      16  267      ; 44.540798187256
1676  01430011           [0560] loadk      17  268      ; 6.2262001037598
167A  9F00000E           [0561] setlist    14  2        ; index 1 to 3
167E  C101000F           [0562] loadk      15  7        ; 9
1682  5F00000D           [0563] setlist    13  1        ; index 1 to 2
1686  0A00010E           [0564] newtable   14  2   0    ; array=2, hash=0
168A  0A80010F           [0565] newtable   15  3   0    ; array=3, hash=0
168E  41430010           [0566] loadk      16  269      ; 407.17370605469
1692  C1430011           [0567] loadk      17  271      ; -5.056300163269
1696  01440012           [0568] loadk      18  272      ; 6.3206000328064
169A  9F00000F           [0569] setlist    15  2        ; index 1 to 3
169E  C1010010           [0570] loadk      16  7        ; 9
16A2  5F00000E           [0571] setlist    14  1        ; index 1 to 2
16A6  0A00010F           [0572] newtable   15  2   0    ; array=2, hash=0
16AA  0A800110           [0573] newtable   16  3   0    ; array=3, hash=0
16AE  41440011           [0574] loadk      17  273      ; 422.46618652344
16B2  C1440012           [0575] loadk      18  275      ; -150.86329650879
16B6  01450013           [0576] loadk      19  276      ; 6.0412001609802
16BA  9F000010           [0577] setlist    16  2        ; index 1 to 3
16BE  C1010011           [0578] loadk      17  7        ; 9
16C2  5F00000F           [0579] setlist    15  1        ; index 1 to 2
16C6  0A000110           [0580] newtable   16  2   0    ; array=2, hash=0
16CA  0A800111           [0581] newtable   17  3   0    ; array=3, hash=0
16CE  41450012           [0582] loadk      18  277      ; 416.72760009766
16D2  C1450013           [0583] loadk      19  279      ; -255.41990661621
16D6  01460014           [0584] loadk      20  280      ; 6.5151000022888
16DA  9F000011           [0585] setlist    17  2        ; index 1 to 3
16DE  C1010012           [0586] loadk      18  7        ; 9
16E2  5F000010           [0587] setlist    16  1        ; index 1 to 2
16E6  0A000111           [0588] newtable   17  2   0    ; array=2, hash=0
16EA  0A800112           [0589] newtable   18  3   0    ; array=3, hash=0
16EE  41460013           [0590] loadk      19  281      ; 348.98889160156
16F2  C1460014           [0591] loadk      20  283      ; -385.38189697266
16F6  01470015           [0592] loadk      21  284      ; 6.1640000343323
16FA  9F000012           [0593] setlist    18  2        ; index 1 to 3
16FE  C1010013           [0594] loadk      19  7        ; 9
1702  5F000011           [0595] setlist    17  1        ; index 1 to 2
1706  0A000112           [0596] newtable   18  2   0    ; array=2, hash=0
170A  0A800113           [0597] newtable   19  3   0    ; array=3, hash=0
170E  41470014           [0598] loadk      20  285      ; 270.53698730469
1712  C1470015           [0599] loadk      21  287      ; -492.80178833008
1716  01480016           [0600] loadk      22  288      ; 6.0215001106262
171A  9F000013           [0601] setlist    19  2        ; index 1 to 3
171E  C1010014           [0602] loadk      20  7        ; 9
1722  5F000012           [0603] setlist    18  1        ; index 1 to 2
1726  0A000113           [0604] newtable   19  2   0    ; array=2, hash=0
172A  0A800114           [0605] newtable   20  3   0    ; array=3, hash=0
172E  41480015           [0606] loadk      21  289      ; 203.15950012207
1732  C1480016           [0607] loadk      22  291      ; -593.52252197266
1736  01490017           [0608] loadk      23  292      ; 6.3578000068665
173A  9F000014           [0609] setlist    20  2        ; index 1 to 3
173E  C1010015           [0610] loadk      21  7        ; 9
1742  5F000013           [0611] setlist    19  1        ; index 1 to 2
1746  0A000114           [0612] newtable   20  2   0    ; array=2, hash=0
174A  0A800115           [0613] newtable   21  3   0    ; array=3, hash=0
174E  41490016           [0614] loadk      22  293      ; 148.47549438477
1752  C1490017           [0615] loadk      23  295      ; -637.93957519531
1756  014A0018           [0616] loadk      24  296      ; 6.6187000274658
175A  9F000015           [0617] setlist    21  2        ; index 1 to 3
175E  C1010016           [0618] loadk      22  7        ; 9
1762  5F000014           [0619] setlist    20  1        ; index 1 to 2
1766  0A000115           [0620] newtable   21  2   0    ; array=2, hash=0
176A  0A800116           [0621] newtable   22  3   0    ; array=3, hash=0
176E  414A0017           [0622] loadk      23  297      ; 46.397499084473
1772  C14A0018           [0623] loadk      24  299      ; -677.05950927734
1776  014B0019           [0624] loadk      25  300      ; 5.9319000244141
177A  9F000016           [0625] setlist    22  2        ; index 1 to 3
177E  C1010017           [0626] loadk      23  7        ; 9
1782  5F000015           [0627] setlist    21  1        ; index 1 to 2
1786  0A000116           [0628] newtable   22  2   0    ; array=2, hash=0
178A  0A800117           [0629] newtable   23  3   0    ; array=3, hash=0
178E  814B0018           [0630] loadk      24  302      ; -34.622699737549
1792  014C0019           [0631] loadk      25  304      ; -671.60162353516
1796  414C001A           [0632] loadk      26  305      ; 6.0157999992371
179A  9F000017           [0633] setlist    23  2        ; index 1 to 3
179E  C1010018           [0634] loadk      24  7        ; 9
17A2  5F000016           [0635] setlist    22  1        ; index 1 to 2
17A6  0A000117           [0636] newtable   23  2   0    ; array=2, hash=0
17AA  0A800118           [0637] newtable   24  3   0    ; array=3, hash=0
17AE  C14C0019           [0638] loadk      25  307      ; -86.805000305176
17B2  414D001A           [0639] loadk      26  309      ; -597.732421875
17B6  814D001B           [0640] loadk      27  310      ; 6.4728999137878
17BA  9F000018           [0641] setlist    24  2        ; index 1 to 3
17BE  C1010019           [0642] loadk      25  7        ; 9
17C2  5F000017           [0643] setlist    23  1        ; index 1 to 2
17C6  0A000118           [0644] newtable   24  2   0    ; array=2, hash=0
17CA  0A800119           [0645] newtable   25  3   0    ; array=3, hash=0
17CE  014E001A           [0646] loadk      26  312      ; -86.880897521973
17D2  814E001B           [0647] loadk      27  314      ; -505.16970825195
17D6  C14E001C           [0648] loadk      28  315      ; 6.2869000434875
17DA  9F000019           [0649] setlist    25  2        ; index 1 to 3
17DE  C101001A           [0650] loadk      26  7        ; 9
17E2  5F000018           [0651] setlist    24  1        ; index 1 to 2
17E6  0A000119           [0652] newtable   25  2   0    ; array=2, hash=0
17EA  0A80011A           [0653] newtable   26  3   0    ; array=3, hash=0
17EE  414F001B           [0654] loadk      27  317      ; -83.95890045166
17F2  C14F001C           [0655] loadk      28  319      ; -371.56338500977
17F6  0150001D           [0656] loadk      29  320      ; 5.9028000831604
17FA  9F00001A           [0657] setlist    26  2        ; index 1 to 3
17FE  C101001B           [0658] loadk      27  7        ; 9
1802  5F000019           [0659] setlist    25  1        ; index 1 to 2
1806  0A00011A           [0660] newtable   26  2   0    ; array=2, hash=0
180A  0A80011B           [0661] newtable   27  3   0    ; array=3, hash=0
180E  8150001C           [0662] loadk      28  322      ; -94.086402893066
1812  0151001D           [0663] loadk      29  324      ; -235.20219421387
1816  4151001E           [0664] loadk      30  325      ; 6.7013001441956
181A  9F00001B           [0665] setlist    27  2        ; index 1 to 3
181E  C101001C           [0666] loadk      28  7        ; 9
1822  5F00001A           [0667] setlist    26  1        ; index 1 to 2
1826  1F060001           [0668] setlist    1   24       ; index 1 to 25
182A  00800000           [0669] move       0   1      
182E  94C88000           [0670] jmp        803          ; to [1474]
1832  05000001           [0671] getglobal  1   0        ; GameLocation
1836  99800001           [0672] call       1   1   2  
183A  15D40000           [0673] eq         0   1   336  ; 1, to [675] if true
183E  14008000           [0674] jmp        1            ; to [676]
1842  54C78000           [0675] jmp        798          ; to [1474]
1846  05000001           [0676] getglobal  1   0        ; GameLocation
184A  99800001           [0677] call       1   1   2  
184E  95F60000           [0678] eq         0   1   474  ; 2, to [680] if true
1852  14008000           [0679] jmp        1            ; to [681]
1856  14C68000           [0680] jmp        793          ; to [1474]
185A  05000001           [0681] getglobal  1   0        ; GameLocation
185E  99800001           [0682] call       1   1   2  
1862  81510002           [0683] loadk      2   326      ; 3
1866  95800000           [0684] eq         0   1   2    ; to [686] if true
186A  D4198000           [0685] jmp        104          ; to [790]
186E  85000001           [0686] getglobal  1   2        ; RaceId
1872  99800001           [0687] call       1   1   2  
1876  D5BE0000           [0688] eq         0   1   251  ; 0, to [690] if true
187A  D4C38000           [0689] jmp        784          ; to [1474]
187E  0A000701           [0690] newtable   1   14  0    ; array=12, hash=0
1882  0A000102           [0691] newtable   2   2   0    ; array=2, hash=0
1886  0A800103           [0692] newtable   3   3   0    ; array=3, hash=0
188A  01520004           [0693] loadk      4   328      ; -167.22520446777
188E  41520005           [0694] loadk      5   329      ; 1171.5328369141
1892  81520006           [0695] loadk      6   330      ; 6.2410998344421
1896  9F000003           [0696] setlist    3   2        ; index 1 to 3
189A  C1010004           [0697] loadk      4   7        ; 9
189E  5F000002           [0698] setlist    2   1        ; index 1 to 2
18A2  0A000103           [0699] newtable   3   2   0    ; array=2, hash=0
18A6  0A800104           [0700] newtable   4   3   0    ; array=3, hash=0
18AA  01530005           [0701] loadk      5   332      ; -80.333297729492
18AE  41530006           [0702] loadk      6   333      ; 1254.6254882813
18B2  81530007           [0703] loadk      7   334      ; 6.0750999450684
18B6  9F000004           [0704] setlist    4   2        ; index 1 to 3
18BA  C1010005           [0705] loadk      5   7        ; 9
18BE  5F000003           [0706] setlist    3   1        ; index 1 to 2
18C2  0A000104           [0707] newtable   4   2   0    ; array=2, hash=0
18C6  0A800105           [0708] newtable   5   3   0    ; array=3, hash=0
18CA  C1530006           [0709] loadk      6   335      ; 39.02619934082
18CE  01540007           [0710] loadk      7   336      ; 1257.8829345703
18D2  41540008           [0711] loadk      8   337      ; 6.2437000274658
18D6  9F000005           [0712] setlist    5   2        ; index 1 to 3
18DA  C1010006           [0713] loadk      6   7        ; 9
18DE  5F000004           [0714] setlist    4   1        ; index 1 to 2
18E2  0A000105           [0715] newtable   5   2   0    ; array=2, hash=0
18E6  0A800106           [0716] newtable   6   3   0    ; array=3, hash=0
18EA  81540007           [0717] loadk      7   338      ; 112.25700378418
18EE  C1540008           [0718] loadk      8   339      ; 1205.8052978516
18F2  01550009           [0719] loadk      9   340      ; 6.1196999549866
18F6  9F000006           [0720] setlist    6   2        ; index 1 to 3
18FA  C1010007           [0721] loadk      7   7        ; 9
18FE  5F000005           [0722] setlist    5   1        ; index 1 to 2
1902  0A000106           [0723] newtable   6   2   0    ; array=2, hash=0
1906  0A800107           [0724] newtable   7   3   0    ; array=3, hash=0
190A  41550008           [0725] loadk      8   341      ; 170.7998046875
190E  81550009           [0726] loadk      9   342      ; 1108.6044921875
1912  C155000A           [0727] loadk      10  343      ; 6.2435998916626
1916  9F000007           [0728] setlist    7   2        ; index 1 to 3
191A  C1010008           [0729] loadk      8   7        ; 9
191E  5F000006           [0730] setlist    6   1        ; index 1 to 2
1922  0A000107           [0731] newtable   7   2   0    ; array=2, hash=0
1926  0A800108           [0732] newtable   8   3   0    ; array=3, hash=0
192A  01560009           [0733] loadk      9   344      ; 197.83149719238
192E  4156000A           [0734] loadk      10  345      ; 1026.7464599609
1932  8156000B           [0735] loadk      11  346      ; 6.0008997917175
1936  9F000008           [0736] setlist    8   2        ; index 1 to 3
193A  C1010009           [0737] loadk      9   7        ; 9
193E  5F000007           [0738] setlist    7   1        ; index 1 to 2
1942  0A000108           [0739] newtable   8   2   0    ; array=2, hash=0
1946  0A800109           [0740] newtable   9   3   0    ; array=3, hash=0
194A  C156000A           [0741] loadk      10  347      ; 138.08529663086
194E  0157000B           [0742] loadk      11  348      ; 860.39752197266
1952  4157000C           [0743] loadk      12  349      ; 6.2104997634888
1956  9F000009           [0744] setlist    9   2        ; index 1 to 3
195A  C101000A           [0745] loadk      10  7        ; 9
195E  5F000008           [0746] setlist    8   1        ; index 1 to 2
1962  0A000109           [0747] newtable   9   2   0    ; array=2, hash=0
1966  0A80010A           [0748] newtable   10  3   0    ; array=3, hash=0
196A  8157000B           [0749] loadk      11  350      ; 64.32559967041
196E  C157000C           [0750] loadk      12  351      ; 801.53887939453
1972  0158000D           [0751] loadk      13  352      ; 6.3087000846863
1976  9F00000A           [0752] setlist    10  2        ; index 1 to 3
197A  C101000B           [0753] loadk      11  7        ; 9
197E  5F000009           [0754] setlist    9   1        ; index 1 to 2
1982  0A00010A           [0755] newtable   10  2   0    ; array=2, hash=0
1986  0A80010B           [0756] newtable   11  3   0    ; array=3, hash=0
198A  4158000C           [0757] loadk      12  353      ; 0.82139998674393
198E  8158000D           [0758] loadk      13  354      ; 812.34112548828
1992  C158000E           [0759] loadk      14  355      ; 6.2824001312256
1996  9F00000B           [0760] setlist    11  2        ; index 1 to 3
199A  C101000C           [0761] loadk      12  7        ; 9
199E  5F00000A           [0762] setlist    10  1        ; index 1 to 2
19A2  0A00010B           [0763] newtable   11  2   0    ; array=2, hash=0
19A6  0A80010C           [0764] newtable   12  3   0    ; array=3, hash=0
19AA  4159000D           [0765] loadk      13  357      ; -124.48719787598
19AE  8159000E           [0766] loadk      14  358      ; 861.72448730469
19B2  C159000F           [0767] loadk      15  359      ; 6.3359999656677
19B6  9F00000C           [0768] setlist    12  2        ; index 1 to 3
19BA  C101000D           [0769] loadk      13  7        ; 9
19BE  5F00000B           [0770] setlist    11  1        ; index 1 to 2
19C2  0A00010C           [0771] newtable   12  2   0    ; array=2, hash=0
19C6  0A80010D           [0772] newtable   13  3   0    ; array=3, hash=0
19CA  415A000E           [0773] loadk      14  361      ; -183.99960327148
19CE  815A000F           [0774] loadk      15  362      ; 932.51171875
19D2  C15A0010           [0775] loadk      16  363      ; 6.3067998886108
19D6  9F00000D           [0776] setlist    13  2        ; index 1 to 3
19DA  C101000E           [0777] loadk      14  7        ; 9
19DE  5F00000C           [0778] setlist    12  1        ; index 1 to 2
19E2  0A00010D           [0779] newtable   13  2   0    ; array=2, hash=0
19E6  0A80010E           [0780] newtable   14  3   0    ; array=3, hash=0
19EA  415B000F           [0781] loadk      15  365      ; -200.62910461426
19EE  815B0010           [0782] loadk      16  366      ; 1032.9515380859
19F2  C15B0011           [0783] loadk      17  367      ; 6.1237001419067
19F6  9F00000E           [0784] setlist    14  2        ; index 1 to 3
19FA  C101000F           [0785] loadk      15  7        ; 9
19FE  5F00000D           [0786] setlist    13  1        ; index 1 to 2
1A02  DF020001           [0787] setlist    1   11       ; index 1 to 12
1A06  00800000           [0788] move       0   1      
1A0A  D4AA8000           [0789] jmp        684          ; to [1474]
1A0E  05000001           [0790] getglobal  1   0        ; GameLocation
1A12  99800001           [0791] call       1   1   2  
1A16  015C0002           [0792] loadk      2   368      ; 4
1A1A  95800000           [0793] eq         0   1   2    ; to [795] if true
1A1E  D47D8000           [0794] jmp        504          ; to [1299]
1A22  85000001           [0795] getglobal  1   2        ; RaceId
1A26  99800001           [0796] call       1   1   2  
1A2A  D5BE0000           [0797] eq         0   1   251  ; 0, to [799] if true
1A2E  D41C8000           [0798] jmp        116          ; to [915]
1A32  0A800701           [0799] newtable   1   15  0    ; array=14, hash=0
1A36  0A000102           [0800] newtable   2   2   0    ; array=2, hash=0
1A3A  0A800103           [0801] newtable   3   3   0    ; array=3, hash=0
1A3E  415C0004           [0802] loadk      4   369      ; 53.542701721191
1A42  815C0005           [0803] loadk      5   370      ; 674.84582519531
1A46  C15C0006           [0804] loadk      6   371      ; 6.2814998626709
1A4A  9F000003           [0805] setlist    3   2        ; index 1 to 3
1A4E  C1010004           [0806] loadk      4   7        ; 9
1A52  5F000002           [0807] setlist    2   1        ; index 1 to 2
1A56  0A000103           [0808] newtable   3   2   0    ; array=2, hash=0
1A5A  0A800104           [0809] newtable   4   3   0    ; array=3, hash=0
1A5E  415D0005           [0810] loadk      5   373      ; -96.750198364258
1A62  815D0006           [0811] loadk      6   374      ; 657.05029296875
1A66  C15D0007           [0812] loadk      7   375      ; 6.0033001899719
1A6A  9F000004           [0813] setlist    4   2        ; index 1 to 3
1A6E  C1010005           [0814] loadk      5   7        ; 9
1A72  5F000003           [0815] setlist    3   1        ; index 1 to 2
1A76  0A000104           [0816] newtable   4   2   0    ; array=2, hash=0
1A7A  0A800105           [0817] newtable   5   3   0    ; array=3, hash=0
1A7E  415E0006           [0818] loadk      6   377      ; -181.28540039063
1A82  815E0007           [0819] loadk      7   378      ; 647.20080566406
1A86  C15E0008           [0820] loadk      8   379      ; 6.0538001060486
1A8A  9F000005           [0821] setlist    5   2        ; index 1 to 3
1A8E  C1010006           [0822] loadk      6   7        ; 9
1A92  5F000004           [0823] setlist    4   1        ; index 1 to 2
1A96  0A000105           [0824] newtable   5   2   0    ; array=2, hash=0
1A9A  0A800106           [0825] newtable   6   3   0    ; array=3, hash=0
1A9E  415F0007           [0826] loadk      7   381      ; -253.1282043457
1AA2  815F0008           [0827] loadk      8   382      ; 608.16333007813
1AA6  C15F0009           [0828] loadk      9   383      ; 6.0795998573303
1AAA  9F000006           [0829] setlist    6   2        ; index 1 to 3
1AAE  C1010007           [0830] loadk      7   7        ; 9
1AB2  5F000005           [0831] setlist    5   1        ; index 1 to 2
1AB6  0A000106           [0832] newtable   6   2   0    ; array=2, hash=0
1ABA  0A800107           [0833] newtable   7   3   0    ; array=3, hash=0
1ABE  41600008           [0834] loadk      8   385      ; -302.6953125
1AC2  81600009           [0835] loadk      9   386      ; 512.51861572266
1AC6  C160000A           [0836] loadk      10  387      ; 6.1722002029419
1ACA  9F000007           [0837] setlist    7   2        ; index 1 to 3
1ACE  C1010008           [0838] loadk      8   7        ; 9
1AD2  5F000006           [0839] setlist    6   1        ; index 1 to 2
1AD6  0A000107           [0840] newtable   7   2   0    ; array=2, hash=0
1ADA  0A800108           [0841] newtable   8   3   0    ; array=3, hash=0
1ADE  41610009           [0842] loadk      9   389      ; -243.54629516602
1AE2  8161000A           [0843] loadk      10  390      ; 412.47918701172
1AE6  C161000B           [0844] loadk      11  391      ; 6.0299000740051
1AEA  9F000008           [0845] setlist    8   2        ; index 1 to 3
1AEE  C1010009           [0846] loadk      9   7        ; 9
1AF2  5F000007           [0847] setlist    7   1        ; index 1 to 2
1AF6  0A000108           [0848] newtable   8   2   0    ; array=2, hash=0
1AFA  0A800109           [0849] newtable   9   3   0    ; array=3, hash=0
1AFE  4162000A           [0850] loadk      10  393      ; -143.96870422363
1B02  8162000B           [0851] loadk      11  394      ; 376.92471313477
1B06  C162000C           [0852] loadk      12  395      ; 6.2344999313354
1B0A  9F000009           [0853] setlist    9   2        ; index 1 to 3
1B0E  C101000A           [0854] loadk      10  7        ; 9
1B12  5F000008           [0855] setlist    8   1        ; index 1 to 2
1B16  0A000109           [0856] newtable   9   2   0    ; array=2, hash=0
1B1A  0A80010A           [0857] newtable   10  3   0    ; array=3, hash=0
1B1E  4163000B           [0858] loadk      11  397      ; -43.098701477051
1B22  8163000C           [0859] loadk      12  398      ; 384.50399780273
1B26  C163000D           [0860] loadk      13  399      ; 6.1609997749329
1B2A  9F00000A           [0861] setlist    10  2        ; index 1 to 3
1B2E  C101000B           [0862] loadk      11  7        ; 9
1B32  5F000009           [0863] setlist    9   1        ; index 1 to 2
1B36  0A00010A           [0864] newtable   10  2   0    ; array=2, hash=0
1B3A  0A80010B           [0865] newtable   11  3   0    ; array=3, hash=0
1B3E  0164000C           [0866] loadk      12  400      ; 67.329902648926
1B42  4164000D           [0867] loadk      13  401      ; 402.87139892578
1B46  8164000E           [0868] loadk      14  402      ; 6.644700050354
1B4A  9F00000B           [0869] setlist    11  2        ; index 1 to 3
1B4E  C101000C           [0870] loadk      12  7        ; 9
1B52  5F00000A           [0871] setlist    10  1        ; index 1 to 2
1B56  0A00010B           [0872] newtable   11  2   0    ; array=2, hash=0
1B5A  0A80010C           [0873] newtable   12  3   0    ; array=3, hash=0
1B5E  C164000D           [0874] loadk      13  403      ; 184.52870178223
1B62  0165000E           [0875] loadk      14  404      ; 391.82440185547
1B66  4165000F           [0876] loadk      15  405      ; 6.1340999603271
1B6A  9F00000C           [0877] setlist    12  2        ; index 1 to 3
1B6E  C101000D           [0878] loadk      13  7        ; 9
1B72  5F00000B           [0879] setlist    11  1        ; index 1 to 2
1B76  0A00010C           [0880] newtable   12  2   0    ; array=2, hash=0
1B7A  0A80010D           [0881] newtable   13  3   0    ; array=3, hash=0
1B7E  8165000E           [0882] loadk      14  406      ; 280.39929199219
1B82  C165000F           [0883] loadk      15  407      ; 475.7287902832
1B86  01660010           [0884] loadk      16  408      ; 6.3020000457764
1B8A  9F00000D           [0885] setlist    13  2        ; index 1 to 3
1B8E  C101000E           [0886] loadk      14  7        ; 9
1B92  5F00000C           [0887] setlist    12  1        ; index 1 to 2
1B96  0A00010D           [0888] newtable   13  2   0    ; array=2, hash=0
1B9A  0A80010E           [0889] newtable   14  3   0    ; array=3, hash=0
1B9E  4166000F           [0890] loadk      15  409      ; 273.73168945313
1BA2  81660010           [0891] loadk      16  410      ; 550.41192626953
1BA6  C1660011           [0892] loadk      17  411      ; 6.1145000457764
1BAA  9F00000E           [0893] setlist    14  2        ; index 1 to 3
1BAE  C101000F           [0894] loadk      15  7        ; 9
1BB2  5F00000D           [0895] setlist    13  1        ; index 1 to 2
1BB6  0A00010E           [0896] newtable   14  2   0    ; array=2, hash=0
1BBA  0A80010F           [0897] newtable   15  3   0    ; array=3, hash=0
1BBE  01670010           [0898] loadk      16  412      ; 200.65879821777
1BC2  41670011           [0899] loadk      17  413      ; 607.31042480469
1BC6  81670012           [0900] loadk      18  414      ; 6.2634000778198
1BCA  9F00000F           [0901] setlist    15  2        ; index 1 to 3
1BCE  C1010010           [0902] loadk      16  7        ; 9
1BD2  5F00000E           [0903] setlist    14  1        ; index 1 to 2
1BD6  0A00010F           [0904] newtable   15  2   0    ; array=2, hash=0
1BDA  0A800110           [0905] newtable   16  3   0    ; array=3, hash=0
1BDE  C1670011           [0906] loadk      17  415      ; 126.98690032959
1BE2  01680012           [0907] loadk      18  416      ; 653.75988769531
1BE6  412B0013           [0908] loadk      19  173      ; 6.4767999649048
1BEA  9F000010           [0909] setlist    16  2        ; index 1 to 3
1BEE  C1010011           [0910] loadk      17  7        ; 9
1BF2  5F00000F           [0911] setlist    15  1        ; index 1 to 2
1BF6  5F030001           [0912] setlist    1   13       ; index 1 to 14
1BFA  00800000           [0913] move       0   1      
1BFE  948B8000           [0914] jmp        559          ; to [1474]
1C02  85000001           [0915] getglobal  1   2        ; RaceId
1C06  99800001           [0916] call       1   1   2  
1C0A  15D40000           [0917] eq         0   1   336  ; 1, to [919] if true
1C0E  D41E8000           [0918] jmp        124          ; to [1043]
1C12  0A000A01           [0919] newtable   1   20  0    ; array=16, hash=0
1C16  0A000102           [0920] newtable   2   2   0    ; array=2, hash=0
1C1A  0A800103           [0921] newtable   3   3   0    ; array=3, hash=0
1C1E  81680004           [0922] loadk      4   418      ; -133.76849365234
1C22  C1680005           [0923] loadk      5   419      ; 39.223400115967
1C26  01690006           [0924] loadk      6   420      ; 6.1209998130798
1C2A  9F000003           [0925] setlist    3   2        ; index 1 to 3
1C2E  C1010004           [0926] loadk      4   7        ; 9
1C32  5F000002           [0927] setlist    2   1        ; index 1 to 2
1C36  0A000103           [0928] newtable   3   2   0    ; array=2, hash=0
1C3A  0A800104           [0929] newtable   4   3   0    ; array=3, hash=0
1C3E  81690005           [0930] loadk      5   422      ; -127.46209716797
1C42  016A0006           [0931] loadk      6   424      ; -51.518699645996
1C46  416A0007           [0932] loadk      7   425      ; 6.1996998786926
1C4A  9F000004           [0933] setlist    4   2        ; index 1 to 3
1C4E  C1010005           [0934] loadk      5   7        ; 9
1C52  5F000003           [0935] setlist    3   1        ; index 1 to 2
1C56  0A000104           [0936] newtable   4   2   0    ; array=2, hash=0
1C5A  0A800105           [0937] newtable   5   3   0    ; array=3, hash=0
1C5E  C16A0006           [0938] loadk      6   427      ; -63.248798370361
1C62  416B0007           [0939] loadk      7   429      ; -155.5364074707
1C66  816B0008           [0940] loadk      8   430      ; 6.1905999183655
1C6A  9F000005           [0941] setlist    5   2        ; index 1 to 3
1C6E  C1010006           [0942] loadk      6   7        ; 9
1C72  5F000004           [0943] setlist    4   1        ; index 1 to 2
1C76  0A000105           [0944] newtable   5   2   0    ; array=2, hash=0
1C7A  0A800106           [0945] newtable   6   3   0    ; array=3, hash=0
1C7E  C16B0007           [0946] loadk      7   431      ; 182.99180603027
1C82  416C0008           [0947] loadk      8   433      ; -169.91879272461
1C86  816C0009           [0948] loadk      9   434      ; 6.0425000190735
1C8A  9F000006           [0949] setlist    6   2        ; index 1 to 3
1C8E  C1010007           [0950] loadk      7   7        ; 9
1C92  5F000005           [0951] setlist    5   1        ; index 1 to 2
1C96  0A000106           [0952] newtable   6   2   0    ; array=2, hash=0
1C9A  0A800107           [0953] newtable   7   3   0    ; array=3, hash=0
1C9E  C16C0008           [0954] loadk      8   435      ; 212.89599609375
1CA2  416D0009           [0955] loadk      9   437      ; -86.750801086426
1CA6  816D000A           [0956] loadk      10  438      ; 6.0517001152039
1CAA  9F000007           [0957] setlist    7   2        ; index 1 to 3
1CAE  C1010008           [0958] loadk      8   7        ; 9
1CB2  5F000006           [0959] setlist    6   1        ; index 1 to 2
1CB6  0A000107           [0960] newtable   7   2   0    ; array=2, hash=0
1CBA  0A800108           [0961] newtable   8   3   0    ; array=3, hash=0
1CBE  C16D0009           [0962] loadk      9   439      ; 216.94619750977
1CC2  016E000A           [0963] loadk      10  440      ; 18.359100341797
1CC6  416E000B           [0964] loadk      11  441      ; 6.2799000740051
1CCA  9F000008           [0965] setlist    8   2        ; index 1 to 3
1CCE  C1010009           [0966] loadk      9   7        ; 9
1CD2  5F000007           [0967] setlist    7   1        ; index 1 to 2
1CD6  0A000108           [0968] newtable   8   2   0    ; array=2, hash=0
1CDA  0A800109           [0969] newtable   9   3   0    ; array=3, hash=0
1CDE  816E000A           [0970] loadk      10  442      ; 249.80160522461
1CE2  C16E000B           [0971] loadk      11  443      ; 123.48539733887
1CE6  016F000C           [0972] loadk      12  444      ; 6.0525999069214
1CEA  9F000009           [0973] setlist    9   2        ; index 1 to 3
1CEE  C101000A           [0974] loadk      10  7        ; 9
1CF2  5F000008           [0975] setlist    8   1        ; index 1 to 2
1CF6  0A000109           [0976] newtable   9   2   0    ; array=2, hash=0
1CFA  0A80010A           [0977] newtable   10  3   0    ; array=3, hash=0
1CFE  416F000B           [0978] loadk      11  445      ; 201.76240539551
1D02  816F000C           [0979] loadk      12  446      ; 239.4102935791
1D06  C16F000D           [0980] loadk      13  447      ; 6.3730001449585
1D0A  9F00000A           [0981] setlist    10  2        ; index 1 to 3
1D0E  C101000B           [0982] loadk      11  7        ; 9
1D12  5F000009           [0983] setlist    9   1        ; index 1 to 2
1D16  0A00010A           [0984] newtable   10  2   0    ; array=2, hash=0
1D1A  0A80010B           [0985] newtable   11  3   0    ; array=3, hash=0
1D1E  0170000C           [0986] loadk      12  448      ; 230.8576965332
1D22  4170000D           [0987] loadk      13  449      ; 327.14608764648
1D26  8170000E           [0988] loadk      14  450      ; 6.1543002128601
1D2A  9F00000B           [0989] setlist    11  2        ; index 1 to 3
1D2E  C101000C           [0990] loadk      12  7        ; 9
1D32  5F00000A           [0991] setlist    10  1        ; index 1 to 2
1D36  0A00010B           [0992] newtable   11  2   0    ; array=2, hash=0
1D3A  0A80010C           [0993] newtable   12  3   0    ; array=3, hash=0
1D3E  C170000D           [0994] loadk      13  451      ; 164.39010620117
1D42  0171000E           [0995] loadk      14  452      ; 386.79458618164
1D46  4171000F           [0996] loadk      15  453      ; 6.0661997795105
1D4A  9F00000C           [0997] setlist    12  2        ; index 1 to 3
1D4E  C101000D           [0998] loadk      13  7        ; 9
1D52  5F00000B           [0999] setlist    11  1        ; index 1 to 2
1D56  0A00010C           [1000] newtable   12  2   0    ; array=2, hash=0
1D5A  0A80010D           [1001] newtable   13  3   0    ; array=3, hash=0
1D5E  8171000E           [1002] loadk      14  454      ; 60.935901641846
1D62  C171000F           [1003] loadk      15  455      ; 402.93301391602
1D66  01720010           [1004] loadk      16  456      ; 6.1001000404358
1D6A  9F00000D           [1005] setlist    13  2        ; index 1 to 3
1D6E  C101000E           [1006] loadk      14  7        ; 9
1D72  5F00000C           [1007] setlist    12  1        ; index 1 to 2
1D76  0A00010D           [1008] newtable   13  2   0    ; array=2, hash=0
1D7A  0A80010E           [1009] newtable   14  3   0    ; array=3, hash=0
1D7E  8172000F           [1010] loadk      15  458      ; -3.8378999233246
1D82  C1720010           [1011] loadk      16  459      ; 385.21929931641
1D86  01730011           [1012] loadk      17  460      ; 6.273099899292
1D8A  9F00000E           [1013] setlist    14  2        ; index 1 to 3
1D8E  C101000F           [1014] loadk      15  7        ; 9
1D92  5F00000D           [1015] setlist    13  1        ; index 1 to 2
1D96  0A00010E           [1016] newtable   14  2   0    ; array=2, hash=0
1D9A  0A80010F           [1017] newtable   15  3   0    ; array=3, hash=0
1D9E  81730010           [1018] loadk      16  462      ; -57.838401794434
1DA2  C1730011           [1019] loadk      17  463      ; 344.34201049805
1DA6  01740012           [1020] loadk      18  464      ; 6.1150999069214
1DAA  9F00000F           [1021] setlist    15  2        ; index 1 to 3
1DAE  C1010010           [1022] loadk      16  7        ; 9
1DB2  5F00000E           [1023] setlist    14  1        ; index 1 to 2
1DB6  0A00010F           [1024] newtable   15  2   0    ; array=2, hash=0
1DBA  0A800110           [1025] newtable   16  3   0    ; array=3, hash=0
1DBE  81740011           [1026] loadk      17  466      ; -91.970596313477
1DC2  C1740012           [1027] loadk      18  467      ; 278.67849731445
1DC6  01750013           [1028] loadk      19  468      ; 6.3227000236511
1DCA  9F000010           [1029] setlist    16  2        ; index 1 to 3
1DCE  C1010011           [1030] loadk      17  7        ; 9
1DD2  5F00000F           [1031] setlist    15  1        ; index 1 to 2
1DD6  0A000110           [1032] newtable   16  2   0    ; array=2, hash=0
1DDA  0A800111           [1033] newtable   17  3   0    ; array=3, hash=0
1DDE  81750012           [1034] loadk      18  470      ; -118.19480133057
1DE2  C1750013           [1035] loadk      19  471      ; 162.24299621582
1DE6  01760014           [1036] loadk      20  472      ; 6.1641001701355
1DEA  9F000011           [1037] setlist    17  2        ; index 1 to 3
1DEE  C1010012           [1038] loadk      18  7        ; 9
1DF2  5F000010           [1039] setlist    16  1        ; index 1 to 2
1DF6  9F030001           [1040] setlist    1   14       ; index 1 to 15
1DFA  00800000           [1041] move       0   1      
1DFE  946B8000           [1042] jmp        431          ; to [1474]
1E02  85000001           [1043] getglobal  1   2        ; RaceId
1E06  99800001           [1044] call       1   1   2  
1E0A  95F60000           [1045] eq         0   1   474  ; 2, to [1047] if true
1E0E  946A8000           [1046] jmp        427          ; to [1474]
1E12  0A000E01           [1047] newtable   1   28  0    ; array=32, hash=0
1E16  0A000102           [1048] newtable   2   2   0    ; array=2, hash=0
1E1A  0A800103           [1049] newtable   3   3   0    ; array=3, hash=0
1E1E  81760004           [1050] loadk      4   474      ; -134.37060546875
1E22  01770005           [1051] loadk      5   476      ; -199.78649902344
1E26  41770006           [1052] loadk      6   477      ; 6.5501999855042
1E2A  9F000003           [1053] setlist    3   2        ; index 1 to 3
1E2E  C1010004           [1054] loadk      4   7        ; 9
1E32  5F000002           [1055] setlist    2   1        ; index 1 to 2
1E36  0A000103           [1056] newtable   3   2   0    ; array=2, hash=0
1E3A  0A800104           [1057] newtable   4   3   0    ; array=3, hash=0
1E3E  C1770005           [1058] loadk      5   479      ; -149.15170288086
1E42  01780006           [1059] loadk      6   480      ; 6.9910001754761
1E46  41780007           [1060] loadk      7   481      ; 6.296199798584
1E4A  9F000004           [1061] setlist    4   2        ; index 1 to 3
1E4E  C1010005           [1062] loadk      5   7        ; 9
1E52  5F000003           [1063] setlist    3   1        ; index 1 to 2
1E56  0A000104           [1064] newtable   4   2   0    ; array=2, hash=0
1E5A  0A800105           [1065] newtable   5   3   0    ; array=3, hash=0
1E5E  C1780006           [1066] loadk      6   483      ; -165.06069946289
1E62  01790007           [1067] loadk      7   484      ; 136.02070617676
1E66  41790008           [1068] loadk      8   485      ; 6.3013000488281
1E6A  9F000005           [1069] setlist    5   2        ; index 1 to 3
1E6E  C1010006           [1070] loadk      6   7        ; 9
1E72  5F000004           [1071] setlist    4   1        ; index 1 to 2
1E76  0A000105           [1072] newtable   5   2   0    ; array=2, hash=0
1E7A  0A800106           [1073] newtable   6   3   0    ; array=3, hash=0
1E7E  C1790007           [1074] loadk      7   487      ; -223.53399658203
1E82  017A0008           [1075] loadk      8   488      ; 297.87860107422
1E86  417A0009           [1076] loadk      9   489      ; 6.6068000793457
1E8A  9F000006           [1077] setlist    6   2        ; index 1 to 3
1E8E  C1010007           [1078] loadk      7   7        ; 9
1E92  5F000005           [1079] setlist    5   1        ; index 1 to 2
1E96  0A000106           [1080] newtable   6   2   0    ; array=2, hash=0
1E9A  0A800107           [1081] newtable   7   3   0    ; array=3, hash=0
1E9E  C17A0008           [1082] loadk      8   491      ; -284.55599975586
1EA2  017B0009           [1083] loadk      9   492      ; 414.70660400391
1EA6  417B000A           [1084] loadk      10  493      ; 6.2571997642517
1EAA  9F000007           [1085] setlist    7   2        ; index 1 to 3
1EAE  C1010008           [1086] loadk      8   7        ; 9
1EB2  5F000006           [1087] setlist    6   1        ; index 1 to 2
1EB6  0A000107           [1088] newtable   7   2   0    ; array=2, hash=0
1EBA  0A800108           [1089] newtable   8   3   0    ; array=3, hash=0
1EBE  C17B0009           [1090] loadk      9   495      ; -300.2958984375
1EC2  017C000A           [1091] loadk      10  496      ; 510.29998779297
1EC6  417C000B           [1092] loadk      11  497      ; 6.1009001731873
1ECA  9F000008           [1093] setlist    8   2        ; index 1 to 3
1ECE  C1010009           [1094] loadk      9   7        ; 9
1ED2  5F000007           [1095] setlist    7   1        ; index 1 to 2
1ED6  0A000108           [1096] newtable   8   2   0    ; array=2, hash=0
1EDA  0A800109           [1097] newtable   9   3   0    ; array=3, hash=0
1EDE  C17C000A           [1098] loadk      10  499      ; -256.36630249023
1EE2  017D000B           [1099] loadk      11  500      ; 597.39093017578
1EE6  417D000C           [1100] loadk      12  501      ; 5.8674998283386
1EEA  9F000009           [1101] setlist    9   2        ; index 1 to 3
1EEE  C101000A           [1102] loadk      10  7        ; 9
1EF2  5F000008           [1103] setlist    8   1        ; index 1 to 2
1EF6  0A000109           [1104] newtable   9   2   0    ; array=2, hash=0
1EFA  0A80010A           [1105] newtable   10  3   0    ; array=3, hash=0
1EFE  C17D000B           [1106] loadk      11  503      ; -180.04449462891
1F02  017E000C           [1107] loadk      12  504      ; 651.44970703125
1F06  417E000D           [1108] loadk      13  505      ; 6.4510998725891
1F0A  9F00000A           [1109] setlist    10  2        ; index 1 to 3
1F0E  C101000B           [1110] loadk      11  7        ; 9
1F12  5F000009           [1111] setlist    9   1        ; index 1 to 2
1F16  0A00010A           [1112] newtable   10  2   0    ; array=2, hash=0
1F1A  0A80010B           [1113] newtable   11  3   0    ; array=3, hash=0
1F1E  C17E000C           [1114] loadk      12  507      ; -51.824901580811
1F22  017F000D           [1115] loadk      13  508      ; 681.78137207031
1F26  417F000E           [1116] loadk      14  509      ; 6.3835000991821
1F2A  9F00000B           [1117] setlist    11  2        ; index 1 to 3
1F2E  C101000C           [1118] loadk      12  7        ; 9
1F32  5F00000A           [1119] setlist    10  1        ; index 1 to 2
1F36  0A00010B           [1120] newtable   11  2   0    ; array=2, hash=0
1F3A  0A80010C           [1121] newtable   12  3   0    ; array=3, hash=0
1F3E  817F000D           [1122] loadk      13  510      ; 59.302398681641
1F42  C17F000E           [1123] loadk      14  511      ; 679.57330322266
1F46  0180000F           [1124] loadk      15  512      ; 6.1970000267029
1F4A  9F00000C           [1125] setlist    12  2        ; index 1 to 3
1F4E  C101000D           [1126] loadk      13  7        ; 9
1F52  5F00000B           [1127] setlist    11  1        ; index 1 to 2
1F56  0A00010C           [1128] newtable   12  2   0    ; array=2, hash=0
1F5A  0A80010D           [1129] newtable   13  3   0    ; array=3, hash=0
1F5E  4180000E           [1130] loadk      14  513      ; 149.71440124512
1F62  8180000F           [1131] loadk      15  514      ; 638.24731445313
1F66  C1800010           [1132] loadk      16  515      ; 6.4532999992371
1F6A  9F00000D           [1133] setlist    13  2        ; index 1 to 3
1F6E  C101000E           [1134] loadk      14  7        ; 9
1F72  5F00000C           [1135] setlist    12  1        ; index 1 to 2
1F76  0A00010D           [1136] newtable   13  2   0    ; array=2, hash=0
1F7A  0A80010E           [1137] newtable   14  3   0    ; array=3, hash=0
1F7E  0181000F           [1138] loadk      15  516      ; 242.1376953125
1F82  41810010           [1139] loadk      16  517      ; 590.57818603516
1F86  81810011           [1140] loadk      17  518      ; 6.1995000839233
1F8A  9F00000E           [1141] setlist    14  2        ; index 1 to 3
1F8E  C101000F           [1142] loadk      15  7        ; 9
1F92  5F00000D           [1143] setlist    13  1        ; index 1 to 2
1F96  0A00010E           [1144] newtable   14  2   0    ; array=2, hash=0
1F9A  0A80010F           [1145] newtable   15  3   0    ; array=3, hash=0
1F9E  C1810010           [1146] loadk      16  519      ; 292.16879272461
1FA2  01820011           [1147] loadk      17  520      ; 521.21417236328
1FA6  41820012           [1148] loadk      18  521      ; 6.6645002365112
1FAA  9F00000F           [1149] setlist    15  2        ; index 1 to 3
1FAE  C1010010           [1150] loadk      16  7        ; 9
1FB2  5F00000E           [1151] setlist    14  1        ; index 1 to 2
1FB6  0A00010F           [1152] newtable   15  2   0    ; array=2, hash=0
1FBA  0A800110           [1153] newtable   16  3   0    ; array=3, hash=0
1FBE  81820011           [1154] loadk      17  522      ; 254.59939575195
1FC2  C1820012           [1155] loadk      18  523      ; 441.47900390625
1FC6  01830013           [1156] loadk      19  524      ; 5.8576002120972
1FCA  9F000010           [1157] setlist    16  2        ; index 1 to 3
1FCE  C1010011           [1158] loadk      17  7        ; 9
1FD2  5F00000F           [1159] setlist    15  1        ; index 1 to 2
1FD6  0A000110           [1160] newtable   16  2   0    ; array=2, hash=0
1FDA  0A800111           [1161] newtable   17  3   0    ; array=3, hash=0
1FDE  41830012           [1162] loadk      18  525      ; 233.16160583496
1FE2  81830013           [1163] loadk      19  526      ; 342.63018798828
1FE6  C1830014           [1164] loadk      20  527      ; 6.1897001266479
1FEA  9F000011           [1165] setlist    17  2        ; index 1 to 3
1FEE  C1010012           [1166] loadk      18  7        ; 9
1FF2  5F000010           [1167] setlist    16  1        ; index 1 to 2
1FF6  0A000111           [1168] newtable   17  2   0    ; array=2, hash=0
1FFA  0A800112           [1169] newtable   18  3   0    ; array=3, hash=0
1FFE  01840013           [1170] loadk      19  528      ; 223.07620239258
2002  41840014           [1171] loadk      20  529      ; 293.99081420898
2006  81840015           [1172] loadk      21  530      ; 6.2983999252319
200A  9F000012           [1173] setlist    18  2        ; index 1 to 3
200E  C1010013           [1174] loadk      19  7        ; 9
2012  5F000011           [1175] setlist    17  1        ; index 1 to 2
2016  0A000112           [1176] newtable   18  2   0    ; array=2, hash=0
201A  0A800113           [1177] newtable   19  3   0    ; array=3, hash=0
201E  C1840014           [1178] loadk      20  531      ; 237.48489379883
2022  01850015           [1179] loadk      21  532      ; 190.6800994873
2026  41850016           [1180] loadk      22  533      ; 6.124400138855
202A  9F000013           [1181] setlist    19  2        ; index 1 to 3
202E  C1010014           [1182] loadk      20  7        ; 9
2032  5F000012           [1183] setlist    18  1        ; index 1 to 2
2036  0A000113           [1184] newtable   19  2   0    ; array=2, hash=0
203A  0A800114           [1185] newtable   20  3   0    ; array=3, hash=0
203E  81850015           [1186] loadk      21  534      ; 370.57431030273
2042  C1850016           [1187] loadk      22  535      ; 51.744300842285
2046  01860017           [1188] loadk      23  536      ; 6.256199836731
204A  9F000014           [1189] setlist    20  2        ; index 1 to 3
204E  C1010015           [1190] loadk      21  7        ; 9
2052  5F000013           [1191] setlist    19  1        ; index 1 to 2
2056  0A000114           [1192] newtable   20  2   0    ; array=2, hash=0
205A  0A800115           [1193] newtable   21  3   0    ; array=3, hash=0
205E  41860016           [1194] loadk      22  537      ; 417.68969726563
2062  C1860017           [1195] loadk      23  539      ; -58.787998199463
2066  01870018           [1196] loadk      24  540      ; 6.255099773407
206A  9F000015           [1197] setlist    21  2        ; index 1 to 3
206E  C1010016           [1198] loadk      22  7        ; 9
2072  5F000014           [1199] setlist    20  1        ; index 1 to 2
2076  0A000115           [1200] newtable   21  2   0    ; array=2, hash=0
207A  0A800116           [1201] newtable   22  3   0    ; array=3, hash=0
207E  41870017           [1202] loadk      23  541      ; 419.38510131836
2082  C1870018           [1203] loadk      24  543      ; -193.27090454102
2086  01880019           [1204] loadk      25  544      ; 6.1708002090454
208A  9F000016           [1205] setlist    22  2        ; index 1 to 3
208E  C1010017           [1206] loadk      23  7        ; 9
2092  5F000015           [1207] setlist    21  1        ; index 1 to 2
2096  0A000116           [1208] newtable   22  2   0    ; array=2, hash=0
209A  0A800117           [1209] newtable   23  3   0    ; array=3, hash=0
209E  41880018           [1210] loadk      24  545      ; 404.07391357422
20A2  C1880019           [1211] loadk      25  547      ; -309.57958984375
20A6  0189001A           [1212] loadk      26  548      ; 6.1577000617981
20AA  9F000017           [1213] setlist    23  2        ; index 1 to 3
20AE  C1010018           [1214] loadk      24  7        ; 9
20B2  5F000016           [1215] setlist    22  1        ; index 1 to 2
20B6  0A000117           [1216] newtable   23  2   0    ; array=2, hash=0
20BA  0A800118           [1217] newtable   24  3   0    ; array=3, hash=0
20BE  41890019           [1218] loadk      25  549      ; 322.15881347656
20C2  C189001A           [1219] loadk      26  551      ; -414.69421386719
20C6  018A001B           [1220] loadk      27  552      ; 6.4268999099731
20CA  9F000018           [1221] setlist    24  2        ; index 1 to 3
20CE  C1010019           [1222] loadk      25  7        ; 9
20D2  5F000017           [1223] setlist    23  1        ; index 1 to 2
20D6  0A000118           [1224] newtable   24  2   0    ; array=2, hash=0
20DA  0A800119           [1225] newtable   25  3   0    ; array=3, hash=0
20DE  418A001A           [1226] loadk      26  553      ; 274.84649658203
20E2  C18A001B           [1227] loadk      27  555      ; -482.28158569336
20E6  018B001C           [1228] loadk      28  556      ; 6.4623999595642
20EA  9F000019           [1229] setlist    25  2        ; index 1 to 3
20EE  C101001A           [1230] loadk      26  7        ; 9
20F2  5F000018           [1231] setlist    24  1        ; index 1 to 2
20F6  0A000119           [1232] newtable   25  2   0    ; array=2, hash=0
20FA  0A80011A           [1233] newtable   26  3   0    ; array=3, hash=0
20FE  418B001B           [1234] loadk      27  557      ; 210.00660705566
2102  C18B001C           [1235] loadk      28  559      ; -585.78607177734
2106  018C001D           [1236] loadk      29  560      ; 6.4590997695923
210A  9F00001A           [1237] setlist    26  2        ; index 1 to 3
210E  C101001B           [1238] loadk      27  7        ; 9
2112  5F000019           [1239] setlist    25  1        ; index 1 to 2
2116  0A00011A           [1240] newtable   26  2   0    ; array=2, hash=0
211A  0A80011B           [1241] newtable   27  3   0    ; array=3, hash=0
211E  418C001C           [1242] loadk      28  561      ; 154.96139526367
2122  C18C001D           [1243] loadk      29  563      ; -636.78558349609
2126  018D001E           [1244] loadk      30  564      ; 6.3112998008728
212A  9F00001B           [1245] setlist    27  2        ; index 1 to 3
212E  C101001C           [1246] loadk      28  7        ; 9
2132  5F00001A           [1247] setlist    26  1        ; index 1 to 2
2136  0A00011B           [1248] newtable   27  2   0    ; array=2, hash=0
213A  0A80011C           [1249] newtable   28  3   0    ; array=3, hash=0
213E  418D001D           [1250] loadk      29  565      ; 59.70890045166
2142  C18D001E           [1251] loadk      30  567      ; -672.49658203125
2146  018E001F           [1252] loadk      31  568      ; 6.2332000732422
214A  9F00001C           [1253] setlist    28  2        ; index 1 to 3
214E  C101001D           [1254] loadk      29  7        ; 9
2152  5F00001B           [1255] setlist    27  1        ; index 1 to 2
2156  0A00011C           [1256] newtable   28  2   0    ; array=2, hash=0
215A  0A80011D           [1257] newtable   29  3   0    ; array=3, hash=0
215E  818E001E           [1258] loadk      30  570      ; -24.197299957275
2162  018F001F           [1259] loadk      31  572      ; -681.13702392578
2166  418F0020           [1260] loadk      32  573      ; 6.1185998916626
216A  9F00001D           [1261] setlist    29  2        ; index 1 to 3
216E  C101001E           [1262] loadk      30  7        ; 9
2172  5F00001C           [1263] setlist    28  1        ; index 1 to 2
2176  0A00011D           [1264] newtable   29  2   0    ; array=2, hash=0
217A  0A80011E           [1265] newtable   30  3   0    ; array=3, hash=0
217E  C18F001F           [1266] loadk      31  575      ; -78.417602539063
2182  41900020           [1267] loadk      32  577      ; -606.72399902344
2186  81900021           [1268] loadk      33  578      ; 5.8927998542786
218A  9F00001E           [1269] setlist    30  2        ; index 1 to 3
218E  C101001F           [1270] loadk      31  7        ; 9
2192  5F00001D           [1271] setlist    29  1        ; index 1 to 2
2196  0A00011E           [1272] newtable   30  2   0    ; array=2, hash=0
219A  0A80011F           [1273] newtable   31  3   0    ; array=3, hash=0
219E  01910020           [1274] loadk      32  580      ; -79.14640045166
21A2  81910021           [1275] loadk      33  582      ; -506.84530639648
21A6  C1910022           [1276] loadk      34  583      ; 5.8768000602722
21AA  9F00001F           [1277] setlist    31  2        ; index 1 to 3
21AE  C1010020           [1278] loadk      32  7        ; 9
21B2  5F00001E           [1279] setlist    30  1        ; index 1 to 2
21B6  0A00011F           [1280] newtable   31  2   0    ; array=2, hash=0
21BA  0A800120           [1281] newtable   32  3   0    ; array=3, hash=0
21BE  41920021           [1282] loadk      33  585      ; -85.540901184082
21C2  C1920022           [1283] loadk      34  587      ; -386.75610351563
21C6  01930023           [1284] loadk      35  588      ; 6.3404998779297
21CA  9F000020           [1285] setlist    32  2        ; index 1 to 3
21CE  C1010021           [1286] loadk      33  7        ; 9
21D2  5F00001F           [1287] setlist    31  1        ; index 1 to 2
21D6  0A000120           [1288] newtable   32  2   0    ; array=2, hash=0
21DA  0A800121           [1289] newtable   33  3   0    ; array=3, hash=0
21DE  81930022           [1290] loadk      34  590      ; -112.46859741211
21E2  01940023           [1291] loadk      35  592      ; -278.86239624023
21E6  41940024           [1292] loadk      36  593      ; 6.1637001037598
21EA  9F000021           [1293] setlist    33  2        ; index 1 to 3
21EE  C1010022           [1294] loadk      34  7        ; 9
21F2  5F000020           [1295] setlist    32  1        ; index 1 to 2
21F6  9F070001           [1296] setlist    1   30       ; index 1 to 31
21FA  00800000           [1297] move       0   1      
21FE  942B8000           [1298] jmp        175          ; to [1474]
2202  05000001           [1299] getglobal  1   0        ; GameLocation
2206  99800001           [1300] call       1   1   2  
220A  81940002           [1301] loadk      2   594      ; 5
220E  95800000           [1302] eq         0   1   2    ; to [1304] if true
2212  D4218000           [1303] jmp        136          ; to [1440]
2216  85000001           [1304] getglobal  1   2        ; RaceId
221A  99800001           [1305] call       1   1   2  
221E  D5BE0000           [1306] eq         0   1   251  ; 0, to [1308] if true
2222  54298000           [1307] jmp        166          ; to [1474]
2226  0A000A01           [1308] newtable   1   20  0    ; array=16, hash=0
222A  0A000102           [1309] newtable   2   2   0    ; array=2, hash=0
222E  0A800103           [1310] newtable   3   3   0    ; array=3, hash=0
2232  01950004           [1311] loadk      4   596      ; -366.63580322266
2236  81950005           [1312] loadk      5   598      ; -186.94400024414
223A  C1950006           [1313] loadk      6   599      ; 6.2509999275208
223E  9F000003           [1314] setlist    3   2        ; index 1 to 3
2242  C1010004           [1315] loadk      4   7        ; 9
2246  5F000002           [1316] setlist    2   1        ; index 1 to 2
224A  0A000103           [1317] newtable   3   2   0    ; array=2, hash=0
224E  0A800104           [1318] newtable   4   3   0    ; array=3, hash=0
2252  41960005           [1319] loadk      5   601      ; -506.37118530273
2256  C1960006           [1320] loadk      6   603      ; -185.1934967041
225A  01970007           [1321] loadk      7   604      ; 5.9826998710632
225E  9F000004           [1322] setlist    4   2        ; index 1 to 3
2262  C1010005           [1323] loadk      5   7        ; 9
2266  5F000003           [1324] setlist    3   1        ; index 1 to 2
226A  0A000104           [1325] newtable   4   2   0    ; array=2, hash=0
226E  0A800105           [1326] newtable   5   3   0    ; array=3, hash=0
2272  81970006           [1327] loadk      6   606      ; -617.09197998047
2276  01980007           [1328] loadk      7   608      ; -186.31689453125
227A  41980008           [1329] loadk      8   609      ; 6.2249999046326
227E  9F000005           [1330] setlist    5   2        ; index 1 to 3
2282  C1010006           [1331] loadk      6   7        ; 9
2286  5F000004           [1332] setlist    4   1        ; index 1 to 2
228A  0A000105           [1333] newtable   5   2   0    ; array=2, hash=0
228E  0A800106           [1334] newtable   6   3   0    ; array=3, hash=0
2292  C1980007           [1335] loadk      7   611      ; -701.24438476563
2296  41990008           [1336] loadk      8   613      ; -296.81781005859
229A  81990009           [1337] loadk      9   614      ; 6.0910000801086
229E  9F000006           [1338] setlist    6   2        ; index 1 to 3
22A2  C1010007           [1339] loadk      7   7        ; 9
22A6  5F000005           [1340] setlist    5   1        ; index 1 to 2
22AA  0A000106           [1341] newtable   6   2   0    ; array=2, hash=0
22AE  0A800107           [1342] newtable   7   3   0    ; array=3, hash=0
22B2  019A0008           [1343] loadk      8   616      ; -739.79327392578
22B6  819A0009           [1344] loadk      9   618      ; -403.55679321289
22BA  C19A000A           [1345] loadk      10  619      ; 5.8668999671936
22BE  9F000007           [1346] setlist    7   2        ; index 1 to 3
22C2  C1010008           [1347] loadk      8   7        ; 9
22C6  5F000006           [1348] setlist    6   1        ; index 1 to 2
22CA  0A000107           [1349] newtable   7   2   0    ; array=2, hash=0
22CE  0A800108           [1350] newtable   8   3   0    ; array=3, hash=0
22D2  419B0009           [1351] loadk      9   621      ; -746.61657714844
22D6  C19B000A           [1352] loadk      10  623      ; -504.57958984375
22DA  019C000B           [1353] loadk      11  624      ; 6.100800037384
22DE  9F000008           [1354] setlist    8   2        ; index 1 to 3
22E2  C1010009           [1355] loadk      9   7        ; 9
22E6  5F000007           [1356] setlist    7   1        ; index 1 to 2
22EA  0A000108           [1357] newtable   8   2   0    ; array=2, hash=0
22EE  0A800109           [1358] newtable   9   3   0    ; array=3, hash=0
22F2  819C000A           [1359] loadk      10  626      ; -690.24572753906
22F6  019D000B           [1360] loadk      11  628      ; -580.31799316406
22FA  419D000C           [1361] loadk      12  629      ; 6.0836000442505
22FE  9F000009           [1362] setlist    9   2        ; index 1 to 3
2302  C101000A           [1363] loadk      10  7        ; 9
2306  5F000008           [1364] setlist    8   1        ; index 1 to 2
230A  0A000109           [1365] newtable   9   2   0    ; array=2, hash=0
230E  0A80010A           [1366] newtable   10  3   0    ; array=3, hash=0
2312  C19D000B           [1367] loadk      11  631      ; -597.36767578125
2316  419E000C           [1368] loadk      12  633      ; -635.21911621094
231A  819E000D           [1369] loadk      13  634      ; 5.8664999008179
231E  9F00000A           [1370] setlist    10  2        ; index 1 to 3
2322  C101000B           [1371] loadk      11  7        ; 9
2326  5F000009           [1372] setlist    9   1        ; index 1 to 2
232A  0A00010A           [1373] newtable   10  2   0    ; array=2, hash=0
232E  0A80010B           [1374] newtable   11  3   0    ; array=3, hash=0
2332  019F000C           [1375] loadk      12  636      ; -503.9169921875
2336  819F000D           [1376] loadk      13  638      ; -667.39007568359
233A  C19F000E           [1377] loadk      14  639      ; 6.3461999893188
233E  9F00000B           [1378] setlist    11  2        ; index 1 to 3
2342  C101000C           [1379] loadk      12  7        ; 9
2346  5F00000A           [1380] setlist    10  1        ; index 1 to 2
234A  0A00010B           [1381] newtable   11  2   0    ; array=2, hash=0
234E  0A80010C           [1382] newtable   12  3   0    ; array=3, hash=0
2352  41A0000D           [1383] loadk      13  641      ; -375.37829589844
2356  C1A0000E           [1384] loadk      14  643      ; -672.35418701172
235A  01A1000F           [1385] loadk      15  644      ; 6.3562998771667
235E  9F00000C           [1386] setlist    12  2        ; index 1 to 3
2362  C101000D           [1387] loadk      13  7        ; 9
2366  5F00000B           [1388] setlist    11  1        ; index 1 to 2
236A  0A00010C           [1389] newtable   12  2   0    ; array=2, hash=0
236E  0A80010D           [1390] newtable   13  3   0    ; array=3, hash=0
2372  81A1000E           [1391] loadk      14  646      ; -270.25119018555
2376  01A2000F           [1392] loadk      15  648      ; -666.07037353516
237A  41A20010           [1393] loadk      16  649      ; 5.9661002159119
237E  9F00000D           [1394] setlist    13  2        ; index 1 to 3
2382  C101000E           [1395] loadk      14  7        ; 9
2386  5F00000C           [1396] setlist    12  1        ; index 1 to 2
238A  0A00010D           [1397] newtable   13  2   0    ; array=2, hash=0
238E  0A80010E           [1398] newtable   14  3   0    ; array=3, hash=0
2392  C1A2000F           [1399] loadk      15  651      ; -195.5565032959
2396  41A30010           [1400] loadk      16  653      ; -628.11480712891
239A  81A30011           [1401] loadk      17  654      ; 6.3550000190735
239E  9F00000E           [1402] setlist    14  2        ; index 1 to 3
23A2  C101000F           [1403] loadk      15  7        ; 9
23A6  5F00000D           [1404] setlist    13  1        ; index 1 to 2
23AA  0A00010E           [1405] newtable   14  2   0    ; array=2, hash=0
23AE  0A80010F           [1406] newtable   15  3   0    ; array=3, hash=0
23B2  01A40010           [1407] loadk      16  656      ; -146.33329772949
23B6  81A40011           [1408] loadk      17  658      ; -538.34722900391
23BA  C1A40012           [1409] loadk      18  659      ; 6.3534998893738
23BE  9F00000F           [1410] setlist    15  2        ; index 1 to 3
23C2  C1010010           [1411] loadk      16  7        ; 9
23C6  5F00000E           [1412] setlist    14  1        ; index 1 to 2
23CA  0A00010F           [1413] newtable   15  2   0    ; array=2, hash=0
23CE  0A800110           [1414] newtable   16  3   0    ; array=3, hash=0
23D2  41A50011           [1415] loadk      17  661      ; -135.30140686035
23D6  C1A50012           [1416] loadk      18  663      ; -420.35070800781
23DA  01A60013           [1417] loadk      19  664      ; 6.2095999717712
23DE  9F000010           [1418] setlist    16  2        ; index 1 to 3
23E2  C1010011           [1419] loadk      17  7        ; 9
23E6  5F00000F           [1420] setlist    15  1        ; index 1 to 2
23EA  0A000110           [1421] newtable   16  2   0    ; array=2, hash=0
23EE  0A800111           [1422] newtable   17  3   0    ; array=3, hash=0
23F2  81A60012           [1423] loadk      18  666      ; -174.32859802246
23F6  01A70013           [1424] loadk      19  668      ; -310.78479003906
23FA  41A70014           [1425] loadk      20  669      ; 6.1098999977112
23FE  9F000011           [1426] setlist    17  2        ; index 1 to 3
2402  C1010012           [1427] loadk      18  7        ; 9
2406  5F000010           [1428] setlist    16  1        ; index 1 to 2
240A  0A000111           [1429] newtable   17  2   0    ; array=2, hash=0
240E  0A800112           [1430] newtable   18  3   0    ; array=3, hash=0
2412  C1A70013           [1431] loadk      19  671      ; -255.31730651855
2416  41A80014           [1432] loadk      20  673      ; -227.09269714355
241A  81A80015           [1433] loadk      21  674      ; 5.9211001396179
241E  9F000012           [1434] setlist    18  2        ; index 1 to 3
2422  C1010013           [1435] loadk      19  7        ; 9
2426  5F000011           [1436] setlist    17  1        ; index 1 to 2
242A  DF030001           [1437] setlist    1   15       ; index 1 to 16
242E  00800000           [1438] move       0   1      
2432  54088000           [1439] jmp        34           ; to [1474]
2436  05000001           [1440] getglobal  1   0        ; GameLocation
243A  99800001           [1441] call       1   1   2  
243E  C1A80002           [1442] loadk      2   675      ; 6
2442  95800000           [1443] eq         0   1   2    ; to [1445] if true
2446  14008000           [1444] jmp        1            ; to [1446]
244A  D4068000           [1445] jmp        28           ; to [1474]
244E  05000001           [1446] getglobal  1   0        ; GameLocation
2452  99800001           [1447] call       1   1   2  
2456  01A90002           [1448] loadk      2   676      ; 7
245A  95800000           [1449] eq         0   1   2    ; to [1451] if true
245E  14008000           [1450] jmp        1            ; to [1452]
2462  54058000           [1451] jmp        22           ; to [1474]
2466  05000001           [1452] getglobal  1   0        ; GameLocation
246A  99800001           [1453] call       1   1   2  
246E  41A90002           [1454] loadk      2   677      ; 8
2472  95800000           [1455] eq         0   1   2    ; to [1457] if true
2476  14008000           [1456] jmp        1            ; to [1458]
247A  D4038000           [1457] jmp        16           ; to [1474]
247E  05000001           [1458] getglobal  1   0        ; GameLocation
2482  99800001           [1459] call       1   1   2  
2486  55C00000           [1460] eq         0   1   257  ; 9, to [1462] if true
248A  14008000           [1461] jmp        1            ; to [1463]
248E  94028000           [1462] jmp        11           ; to [1474]
2492  05000001           [1463] getglobal  1   0        ; GameLocation
2496  99800001           [1464] call       1   1   2  
249A  81A90002           [1465] loadk      2   678      ; 10
249E  95800000           [1466] eq         0   1   2    ; to [1468] if true
24A2  14008000           [1467] jmp        1            ; to [1469]
24A6  14018000           [1468] jmp        5            ; to [1474]
24AA  05000001           [1469] getglobal  1   0        ; GameLocation
24AE  99800001           [1470] call       1   1   2  
24B2  C1A90002           [1471] loadk      2   679      ; 11
24B6  95800000           [1472] eq         0   1   2    ; to [1474] if true
24BA  D4FF7F00           [1473] jmp        0            ; to [1474]
24BE  1B000100           [1474] return     0   2      
24C2  1B800000           [1475] return     0   1      
                         ** end of function **

                         * code:
24C6  03000000           sizecode (3)
24CA  22000000           [1] closure    0   0        ; 0 upvalues
24CE  1B000100           [2] return     0   2      
24D2  1B800000           [3] return     0   1      
                         ** end of function **

24D6                     ** end of chunk **
