Pos   Hex Data           Description or Code
------------------------------------------------------------------------
0000                     ** source chunk: MULTIRACEPICKUPDATA.LUA.LC
                         ** global header start **
0000  1B4C7561           header signature: "\27Lua"
0004  50                 version (major:minor hex digits)
0005  01                 endianness (1=little endian)
0006  04                 size of int (bytes)
0007  04                 size of size_t (bytes)
0008  04                 size of Instruction (bytes)
0009  06                 size of OP (bits)
000A  08                 size of A (bits)
000B  09                 size of B (bits)
000C  09                 size of C (bits)
000D  04                 size of number (bytes)
000E  3BAFEF4B           sample number (single)
                         * chunk platform unrecognized
                         ** global header end **
                         
0012                     ** function [0] definition (level 1)
                         ** start of function **
0012  08000000           string size (8)
0016  3D286E6F6E652900   "=(none)"
                         source name: =(none)
001E  00000000           line defined (0)
0022  00                 nups (0)
0023  00                 numparams (0)
0024  00                 is_vararg (0)
0025  02                 maxstacksize (2)
                         * lines:
0026  00000000           sizelineinfo (0)
                         [pc] (line)
                         * locals:
002A  00000000           sizelocvars (0)
                         * upvalues:
002E  00000000           sizeupvalues (0)
                         * constants:
0032  00000000           sizek (0)
                         * functions:
0036  01000000           sizep (1)
                         
003A                     ** function [0] definition (level 2)
                         ** start of function **
003A  00000000           string size (0)
                         source name: (none)
003E  05000000           line defined (5)
0042  00                 nups (0)
0043  00                 numparams (0)
0044  00                 is_vararg (0)
0045  14                 maxstacksize (20)
                         * lines:
0046  00000000           sizelineinfo (0)
                         [pc] (line)
                         * locals:
004A  00000000           sizelocvars (0)
                         * upvalues:
004E  00000000           sizeupvalues (0)
                         * constants:
0052  75010000           sizek (373)
0056  04                 const type 4
0057  0D000000           string size (13)
005B  47616D654C6F6361+  "GameLoca"
0063  74696F6E00         "tion\0"
                         const [0]: "GameLocation"
0068  03                 const type 3
0069  00000000           const [1]: (0)
006D  04                 const type 4
006E  07000000           string size (7)
0072  52616365496400     "RaceId"
                         const [2]: "RaceId"
0079  04                 const type 4
007A  07000000           string size (7)
007E  7069636B757000     "pickup"
                         const [3]: "pickup"
0085  04                 const type 4
0086  09000000           string size (9)
008A  72616365676F6F64+  "racegood"
0092  00                 "\0"
                         const [4]: "racegood"
0093  03                 const type 3
0094  C1B8FA43           const [5]: (501.44338989258)
0098  03                 const type 3
0099  26F82044           const [6]: (643.87731933594)
009D  03                 const type 3
009E  A54E3141           const [7]: (11.081700325012)
00A2  03                 const type 3
00A3  0000F041           const [8]: (30)
00A7  03                 const type 3
00A8  CACA1144           const [9]: (583.16857910156)
00AC  03                 const type 3
00AD  E71F5744           const [10]: (860.49847412109)
00B1  03                 const type 3
00B2  BC749741           const [11]: (18.931999206543)
00B6  04                 const type 4
00B7  08000000           string size (8)
00BB  7261636562616400   "racebad"
                         const [12]: "racebad"
00C3  03                 const type 3
00C4  C557F343           const [13]: (486.68569946289)
00C8  03                 const type 3
00C9  22C58B44           const [14]: (1118.1604003906)
00CD  03                 const type 3
00CE  37098441           const [15]: (16.504499435425)
00D2  03                 const type 3
00D3  A720A343           const [16]: (326.25509643555)
00D7  03                 const type 3
00D8  AED86D44           const [17]: (951.38562011719)
00DC  03                 const type 3
00DD  4A0C3141           const [18]: (11.065500259399)
00E1  03                 const type 3
00E2  3AF37843           const [19]: (248.95010375977)
00E6  03                 const type 3
00E7  C1484344           const [20]: (781.13677978516)
00EB  03                 const type 3
00EC  0F0B2F41           const [21]: (10.94019985199)
00F0  03                 const type 3
00F1  3B67B543           const [22]: (362.80648803711)
00F5  03                 const type 3
00F6  9F49A044           const [23]: (1282.3006591797)
00FA  03                 const type 3
00FB  C57E8941           const [24]: (17.186899185181)
00FF  03                 const type 3
0100  927C3843           const [25]: (184.4866027832)
0104  03                 const type 3
0105  46C42B44           const [26]: (687.06677246094)
0109  03                 const type 3
010A  79E92D41           const [27]: (10.869500160217)
010E  03                 const type 3
010F  0000803F           const [28]: (1)
0113  03                 const type 3
0114  E5A1FA43           const [29]: (501.26480102539)
0118  03                 const type 3
0119  8F42F541           const [30]: (30.657499313354)
011D  03                 const type 3
011E  C58F2841           const [31]: (10.535099983215)
0122  03                 const type 3
0123  9514F043           const [32]: (480.16079711914)
0127  03                 const type 3
0128  4DF45E43           const [33]: (222.95429992676)
012C  03                 const type 3
012D  4DF45EC3           const [34]: (-222.95429992676)
0131  03                 const type 3
0132  2AA93C41           const [35]: (11.791299819946)
0136  03                 const type 3
0137  7F099443           const [36]: (296.07418823242)
013B  03                 const type 3
013C  00B1E543           const [37]: (459.3828125)
0140  03                 const type 3
0141  00B1E5C3           const [38]: (-459.3828125)
0145  03                 const type 3
0146  9D807E41           const [39]: (15.906399726868)
014A  03                 const type 3
014B  1215BE43           const [40]: (380.16461181641)
014F  03                 const type 3
0150  EFB88041           const [41]: (16.090299606323)
0154  03                 const type 3
0155  A7E85641           const [42]: (13.431799888611)
0159  03                 const type 3
015A  9534C743           const [43]: (398.41079711914)
015E  03                 const type 3
015F  2A292F43           const [44]: (175.16079711914)
0163  03                 const type 3
0164  6EA32841           const [45]: (10.53989982605)
0168  03                 const type 3
0169  40BBE843           const [46]: (465.462890625)
016D  03                 const type 3
016E  28EFED43           const [47]: (475.86840820313)
0172  03                 const type 3
0173  C5FE3441           const [48]: (11.31219959259)
0177  03                 const type 3
0178  72492F43           const [49]: (175.28689575195)
017C  03                 const type 3
017D  E6FF2944           const [50]: (679.99841308594)
0181  03                 const type 3
0182  08AC2841           const [51]: (10.541999816895)
0186  03                 const type 3
0187  4ABCDA43           const [52]: (437.47100830078)
018B  03                 const type 3
018C  E7334044           const [53]: (768.81097412109)
0190  03                 const type 3
0191  33332F41           const [54]: (10.949999809265)
0195  03                 const type 3
0196  9B290744           const [55]: (540.65008544922)
019A  03                 const type 3
019B  69740D44           const [56]: (565.81890869141)
019F  03                 const type 3
01A0  E09C2841           const [57]: (10.538299560547)
01A4  03                 const type 3
01A5  6E340F41           const [58]: (8.9503002166748)
01A9  03                 const type 3
01AA  6E340FC1           const [59]: (-8.9503002166748)
01AE  03                 const type 3
01AF  5DED8044           const [60]: (1031.4176025391)
01B3  03                 const type 3
01B4  5DED80C4           const [61]: (-1031.4176025391)
01B8  03                 const type 3
01B9  25751D41           const [62]: (9.8410997390747)
01BD  03                 const type 3
01BE  1127BA42           const [63]: (93.076301574707)
01C2  03                 const type 3
01C3  8C475244           const [64]: (841.11791992188)
01C7  03                 const type 3
01C8  8C4752C4           const [65]: (-841.11791992188)
01CC  03                 const type 3
01CD  3B701D41           const [66]: (9.8399000167847)
01D1  03                 const type 3
01D2  ACAB2D43           const [67]: (173.67059326172)
01D6  03                 const type 3
01D7  098D1C44           const [68]: (626.20367431641)
01DB  03                 const type 3
01DC  098D1CC4           const [69]: (-626.20367431641)
01E0  03                 const type 3
01E1  19F39041           const [70]: (18.118700027466)
01E5  03                 const type 3
01E6  102A9143           const [71]: (290.32861328125)
01EA  03                 const type 3
01EB  5E4BE543           const [72]: (458.58880615234)
01EF  03                 const type 3
01F0  5E4BE5C3           const [73]: (-458.58880615234)
01F4  03                 const type 3
01F5  83517F41           const [74]: (15.95740032196)
01F9  03                 const type 3
01FA  FB9AFA43           const [75]: (501.21078491211)
01FE  03                 const type 3
01FF  14EEF443           const [76]: (489.85998535156)
0203  03                 const type 3
0204  14EEF4C3           const [77]: (-489.85998535156)
0208  03                 const type 3
0209  C9E52641           const [78]: (10.431099891663)
020D  03                 const type 3
020E  3FB57F43           const [79]: (255.70799255371)
0212  03                 const type 3
0213  7F4B1544           const [80]: (597.17962646484)
0217  03                 const type 3
0218  7F4B15C4           const [81]: (-597.17962646484)
021C  03                 const type 3
021D  F1631641           const [82]: (9.3993997573853)
0221  03                 const type 3
0222  EBC3C143           const [83]: (387.53060913086)
0226  03                 const type 3
0227  01DEA541           const [84]: (20.733400344849)
022B  03                 const type 3
022C  C74B6A41           const [85]: (14.643500328064)
0230  03                 const type 3
0231  7EC5C843           const [86]: (401.54290771484)
0235  03                 const type 3
0236  787B6F43           const [87]: (239.48229980469)
023A  03                 const type 3
023B  24282541           const [88]: (10.322299957275)
023F  03                 const type 3
0240  561DFC43           const [89]: (504.22918701172)
0244  03                 const type 3
0245  D97FB842           const [90]: (92.249702453613)
0249  03                 const type 3
024A  D97FB8C2           const [91]: (-92.249702453613)
024E  03                 const type 3
024F  645D1C41           const [92]: (9.7728004455566)
0253  03                 const type 3
0254  AD29DC43           const [93]: (440.32559204102)
0258  03                 const type 3
0259  F5F9BF43           const [94]: (383.95278930664)
025D  03                 const type 3
025E  F5F9BFC3           const [95]: (-383.95278930664)
0262  03                 const type 3
0263  AB3E2041           const [96]: (10.015299797058)
0267  03                 const type 3
0268  56CF4643           const [97]: (198.80990600586)
026C  03                 const type 3
026D  AE043244           const [98]: (712.07312011719)
0271  03                 const type 3
0272  AE0432C4           const [99]: (-712.07312011719)
0276  03                 const type 3
0277  C66D1D41           const [100]: (9.8393001556396)
027B  03                 const type 3
027C  844E3643           const [101]: (182.30670166016)
0280  03                 const type 3
0281  309BDF43           const [102]: (447.21240234375)
0285  03                 const type 3
0286  309BDFC3           const [103]: (-447.21240234375)
028A  03                 const type 3
028B  34802641           const [104]: (10.406299591064)
028F  03                 const type 3
0290  00000040           const [105]: (2)
0294  03                 const type 3
0295  E02D0542           const [106]: (33.294799804688)
0299  03                 const type 3
029A  E02D05C2           const [107]: (-33.294799804688)
029E  03                 const type 3
029F  9BF69344           const [108]: (1183.7064208984)
02A3  03                 const type 3
02A4  9BF693C4           const [109]: (-1183.7064208984)
02A8  03                 const type 3
02A9  87162541           const [110]: (10.317999839783)
02AD  03                 const type 3
02AE  F2B28642           const [111]: (67.349502563477)
02B2  03                 const type 3
02B3  F2B286C2           const [112]: (-67.349502563477)
02B7  03                 const type 3
02B8  DBB28744           const [113]: (1085.5892333984)
02BC  03                 const type 3
02BD  DBB287C4           const [114]: (-1085.5892333984)
02C1  03                 const type 3
02C2  9D112541           const [115]: (10.316800117493)
02C6  03                 const type 3
02C7  0C733F43           const [116]: (191.44940185547)
02CB  03                 const type 3
02CC  0C733FC3           const [117]: (-191.44940185547)
02D0  03                 const type 3
02D1  F1578A44           const [118]: (1106.7481689453)
02D5  03                 const type 3
02D6  F1578AC4           const [119]: (-1106.7481689453)
02DA  03                 const type 3
02DB  D6562741           const [120]: (10.458700180054)
02DF  03                 const type 3
02E0  6B7A2343           const [121]: (163.47819519043)
02E4  03                 const type 3
02E5  6B7A23C3           const [122]: (-163.47819519043)
02E9  03                 const type 3
02EA  B7A6B544           const [123]: (1453.2098388672)
02EE  03                 const type 3
02EF  B7A6B5C4           const [124]: (-1453.2098388672)
02F3  03                 const type 3
02F4  6D562741           const [125]: (10.45860004425)
02F8  03                 const type 3
02F9  17376D42           const [126]: (59.303798675537)
02FD  03                 const type 3
02FE  17376DC2           const [127]: (-59.303798675537)
0302  03                 const type 3
0303  A001C444           const [128]: (1568.05078125)
0307  03                 const type 3
0308  A001C4C4           const [129]: (-1568.05078125)
030C  03                 const type 3
030D  18952441           const [130]: (10.286399841309)
0311  03                 const type 3
0312  0000C040           const [131]: (6)
0316  03                 const type 3
0317  7E114C44           const [132]: (816.27331542969)
031B  03                 const type 3
031C  7E114CC4           const [133]: (-816.27331542969)
0320  03                 const type 3
0321  A5943C44           const [134]: (754.32257080078)
0325  03                 const type 3
0326  E0BE2E41           const [135]: (10.921600341797)
032A  03                 const type 3
032B  69105A44           const [136]: (872.25640869141)
032F  03                 const type 3
0330  69105AC4           const [137]: (-872.25640869141)
0334  03                 const type 3
0335  98026B44           const [138]: (940.04052734375)
0339  03                 const type 3
033A  EF994A44           const [139]: (810.40521240234)
033E  03                 const type 3
033F  EF994AC4           const [140]: (-810.40521240234)
0343  03                 const type 3
0344  2DD19344           const [141]: (1182.5367431641)
0348  03                 const type 3
0349  6F812E41           const [142]: (10.906599998474)
034D  03                 const type 3
034E  636F2C44           const [143]: (689.74041748047)
0352  03                 const type 3
0353  636F2CC4           const [144]: (-689.74041748047)
0357  03                 const type 3
0358  E9867D44           const [145]: (1014.1079711914)
035C  03                 const type 3
035D  33C43541           const [146]: (11.36040019989)
0361  03                 const type 3
0362  381C2644           const [147]: (664.44091796875)
0366  03                 const type 3
0367  381C26C4           const [148]: (-664.44091796875)
036B  03                 const type 3
036C  E64F6044           const [149]: (897.24841308594)
0370  03                 const type 3
0371  DA1B3441           const [150]: (11.256799697876)
0375  03                 const type 3
0376  92A72644           const [151]: (666.61828613281)
037A  03                 const type 3
037B  92A726C4           const [152]: (-666.61828613281)
037F  03                 const type 3
0380  A53E2F44           const [153]: (700.97882080078)
0384  03                 const type 3
0385  B7623141           const [154]: (11.08660030365)
0389  03                 const type 3
038A  32F12844           const [155]: (675.76867675781)
038E  03                 const type 3
038F  32F128C4           const [156]: (-675.76867675781)
0393  03                 const type 3
0394  0ED91344           const [157]: (591.39147949219)
0398  03                 const type 3
0399  88633141           const [158]: (11.086799621582)
039D  03                 const type 3
039E  82CA2C44           const [159]: (691.16418457031)
03A2  03                 const type 3
03A3  82CA2CC4           const [160]: (-691.16418457031)
03A7  03                 const type 3
03A8  1B9DCF43           const [161]: (415.22738647461)
03AC  03                 const type 3
03AD  BB273141           const [162]: (11.072199821472)
03B1  03                 const type 3
03B2  AA4E4D44           const [163]: (821.22912597656)
03B6  03                 const type 3
03B7  AA4E4DC4           const [164]: (-821.22912597656)
03BB  03                 const type 3
03BC  5E4B7F43           const [165]: (255.29440307617)
03C0  03                 const type 3
03C1  5DDC1B41           const [166]: (9.7412996292114)
03C5  03                 const type 3
03C6  65CD3744           const [167]: (735.20928955078)
03CA  03                 const type 3
03CB  65CD37C4           const [168]: (-735.20928955078)
03CF  03                 const type 3
03D0  8D309843           const [169]: (304.37930297852)
03D4  03                 const type 3
03D5  25063241           const [170]: (11.1265001297)
03D9  03                 const type 3
03DA  3B512444           const [171]: (657.26922607422)
03DE  03                 const type 3
03DF  3B5124C4           const [172]: (-657.26922607422)
03E3  03                 const type 3
03E4  C3450444           const [173]: (529.09002685547)
03E8  03                 const type 3
03E9  B0033141           const [174]: (11.063400268555)
03ED  03                 const type 3
03EE  A8421144           const [175]: (581.04150390625)
03F2  03                 const type 3
03F3  A84211C4           const [176]: (-581.04150390625)
03F7  03                 const type 3
03F8  76712444           const [177]: (657.77282714844)
03FC  03                 const type 3
03FD  65193141           const [178]: (11.068699836731)
0401  03                 const type 3
0402  0000E040           const [179]: (7)
0406  03                 const type 3
0407  7BD68044           const [180]: (1030.7025146484)
040B  03                 const type 3
040C  7BD680C4           const [181]: (-1030.7025146484)
0410  03                 const type 3
0411  97BF2942           const [182]: (42.437099456787)
0415  03                 const type 3
0416  97BF29C2           const [183]: (-42.437099456787)
041A  03                 const type 3
041B  FBCB2D41           const [184]: (10.862299919128)
041F  03                 const type 3
0420  D78F9344           const [185]: (1180.4949951172)
0424  03                 const type 3
0425  D78F93C4           const [186]: (-1180.4949951172)
0429  03                 const type 3
042A  68A27443           const [187]: (244.63439941406)
042E  03                 const type 3
042F  68A274C3           const [188]: (-244.63439941406)
0433  03                 const type 3
0434  81953041           const [189]: (11.036499977112)
0438  03                 const type 3
0439  AE579444           const [190]: (1186.7399902344)
043D  03                 const type 3
043E  AE5794C4           const [191]: (-1186.7399902344)
0442  03                 const type 3
0443  CFEFF243           const [192]: (485.87350463867)
0447  03                 const type 3
0448  CFEFF2C3           const [193]: (-485.87350463867)
044C  03                 const type 3
044D  83C02641           const [194]: (10.421999931335)
0451  03                 const type 3
0452  7D018944           const [195]: (1096.0465087891)
0456  03                 const type 3
0457  7D0189C4           const [196]: (-1096.0465087891)
045B  03                 const type 3
045C  7317DD43           const [197]: (442.18319702148)
0460  03                 const type 3
0461  7317DDC3           const [198]: (-442.18319702148)
0465  03                 const type 3
0466  DE712441           const [199]: (10.277799606323)
046A  03                 const type 3
046B  9AA37E44           const [200]: (1018.5562744141)
046F  03                 const type 3
0470  9AA37EC4           const [201]: (-1018.5562744141)
0474  03                 const type 3
0475  41F29543           const [202]: (299.89260864258)
0479  03                 const type 3
047A  41F295C3           const [203]: (-299.89260864258)
047E  03                 const type 3
047F  55C12641           const [204]: (10.422200202942)
0483  03                 const type 3
0484  0D539444           const [205]: (1186.5953369141)
0488  03                 const type 3
0489  0D5394C4           const [206]: (-1186.5953369141)
048D  03                 const type 3
048E  3BF71D44           const [207]: (631.86297607422)
0492  03                 const type 3
0493  3BF71DC4           const [208]: (-631.86297607422)
0497  03                 const type 3
0498  9EEF2F41           const [209]: (10.996000289917)
049C  03                 const type 3
049D  01968B44           const [210]: (1116.6876220703)
04A1  03                 const type 3
04A2  01968BC4           const [211]: (-1116.6876220703)
04A6  03                 const type 3
04A7  25D91344           const [212]: (591.39288330078)
04AB  03                 const type 3
04AC  25D913C4           const [213]: (-591.39288330078)
04B0  03                 const type 3
04B1  7FD92F41           const [214]: (10.990599632263)
04B5  03                 const type 3
04B6  D10C8944           const [215]: (1096.4005126953)
04BA  03                 const type 3
04BB  D10C89C4           const [216]: (-1096.4005126953)
04BF  03                 const type 3
04C0  C8EFDC43           const [217]: (441.87329101563)
04C4  03                 const type 3
04C5  C8EFDCC3           const [218]: (-441.87329101563)
04C9  03                 const type 3
04CA  F9A02241           const [219]: (10.164299964905)
04CE  03                 const type 3
04CF  7D607E44           const [220]: (1017.5076293945)
04D3  03                 const type 3
04D4  7D607EC4           const [221]: (-1017.5076293945)
04D8  03                 const type 3
04D9  23CB9543           const [222]: (299.58700561523)
04DD  03                 const type 3
04DE  23CB95C3           const [223]: (-299.58700561523)
04E2  03                 const type 3
04E3  07F02441           const [224]: (10.30860042572)
04E7  03                 const type 3
04E8  47368244           const [225]: (1041.6961669922)
04EC  03                 const type 3
04ED  473682C4           const [226]: (-1041.6961669922)
04F1  03                 const type 3
04F2  F34F0143           const [227]: (129.31230163574)
04F6  03                 const type 3
04F7  F34F01C3           const [228]: (-129.31230163574)
04FB  03                 const type 3
04FC  E71D2C41           const [229]: (10.757300376892)
0500  03                 const type 3
0501  4F2D8644           const [230]: (1073.4158935547)
0505  03                 const type 3
0506  4F2D86C4           const [231]: (-1073.4158935547)
050A  03                 const type 3
050B  56DF3942           const [232]: (46.468101501465)
050F  03                 const type 3
0510  D8812C41           const [233]: (10.781700134277)
0514  03                 const type 3
0515  65E67C44           const [234]: (1011.5999145508)
0519  03                 const type 3
051A  65E67CC4           const [235]: (-1011.5999145508)
051E  03                 const type 3
051F  AED85E43           const [236]: (222.8464050293)
0523  03                 const type 3
0524  B7622C41           const [237]: (10.77410030365)
0528  03                 const type 3
0529  B4406444           const [238]: (913.01098632813)
052D  03                 const type 3
052E  B44064C4           const [239]: (-913.01098632813)
0532  03                 const type 3
0533  05539C43           const [240]: (312.64859008789)
0537  03                 const type 3
0538  73682C41           const [241]: (10.775500297546)
053C  03                 const type 3
053D  5D0D3444           const [242]: (720.20880126953)
0541  03                 const type 3
0542  5D0D34C4           const [243]: (-720.20880126953)
0546  03                 const type 3
0547  B4796B43           const [244]: (235.47540283203)
054B  03                 const type 3
054C  CC7F2941           const [245]: (10.593700408936)
0550  03                 const type 3
0551  183D6844           const [246]: (928.95458984375)
0555  03                 const type 3
0556  183D68C4           const [247]: (-928.95458984375)
055A  03                 const type 3
055B  D48A1543           const [248]: (149.54229736328)
055F  03                 const type 3
0560  81040C41           const [249]: (8.7510995864868)
0564  03                 const type 3
0565  4C4F6944           const [250]: (933.23901367188)
0569  03                 const type 3
056A  4C4F69C4           const [251]: (-933.23901367188)
056E  03                 const type 3
056F  30FB3942           const [252]: (46.495300292969)
0573  03                 const type 3
0574  30FB39C2           const [253]: (-46.495300292969)
0578  03                 const type 3
0579  A7E8C240           const [254]: (6.0908999443054)
057D  03                 const type 3
057E  79A55B44           const [255]: (878.58551025391)
0582  03                 const type 3
0583  79A55BC4           const [256]: (-878.58551025391)
0587  03                 const type 3
0588  5CB09443           const [257]: (297.37780761719)
058C  03                 const type 3
058D  5CB094C3           const [258]: (-297.37780761719)
0591  03                 const type 3
0592  23DB2A41           const [259]: (10.678500175476)
0596  03                 const type 3
0597  96BA5244           const [260]: (842.91540527344)
059B  03                 const type 3
059C  96BA52C4           const [261]: (-842.91540527344)
05A0  03                 const type 3
05A1  1E47FF43           const [262]: (510.55560302734)
05A5  03                 const type 3
05A6  1E47FFC3           const [263]: (-510.55560302734)
05AA  03                 const type 3
05AB  E10B2741           const [264]: (10.440400123596)
05AF  03                 const type 3
05B0  00000041           const [265]: (8)
05B4  03                 const type 3
05B5  118A4E44           const [266]: (826.15728759766)
05B9  03                 const type 3
05BA  118A4EC4           const [267]: (-826.15728759766)
05BE  03                 const type 3
05BF  BDED8244           const [268]: (1047.4293212891)
05C3  03                 const type 3
05C4  BDED82C4           const [269]: (-1047.4293212891)
05C8  03                 const type 3
05C9  C2172941           const [270]: (10.568300247192)
05CD  03                 const type 3
05CE  5FA13D44           const [271]: (758.52142333984)
05D2  03                 const type 3
05D3  5FA13DC4           const [272]: (-758.52142333984)
05D7  03                 const type 3
05D8  164FA744           const [273]: (1338.4714355469)
05DC  03                 const type 3
05DD  164FA7C4           const [274]: (-1338.4714355469)
05E1  03                 const type 3
05E2  8CB93341           const [275]: (11.232799530029)
05E6  03                 const type 3
05E7  7A4F6D44           const [276]: (949.24182128906)
05EB  03                 const type 3
05EC  7A4F6DC4           const [277]: (-949.24182128906)
05F0  03                 const type 3
05F1  A979AE44           const [278]: (1395.8018798828)
05F5  03                 const type 3
05F6  A979AEC4           const [279]: (-1395.8018798828)
05FA  03                 const type 3
05FB  984C3641           const [280]: (11.393699645996)
05FF  03                 const type 3
0600  7A536644           const [281]: (921.30432128906)
0604  03                 const type 3
0605  7A5366C4           const [282]: (-921.30432128906)
0609  03                 const type 3
060A  CFE78144           const [283]: (1039.2440185547)
060E  03                 const type 3
060F  CFE781C4           const [284]: (-1039.2440185547)
0613  03                 const type 3
0614  D7346541           const [285]: (14.325400352478)
0618  03                 const type 3
0619  F0488744           const [286]: (1082.279296875)
061D  03                 const type 3
061E  F04887C4           const [287]: (-1082.279296875)
0622  03                 const type 3
0623  97C45344           const [288]: (847.07171630859)
0627  03                 const type 3
0628  97C453C4           const [289]: (-847.07171630859)
062C  03                 const type 3
062D  158C3941           const [290]: (11.596699714661)
0631  03                 const type 3
0632  A0A17E44           const [291]: (1018.525390625)
0636  03                 const type 3
0637  A0A17EC4           const [292]: (-1018.525390625)
063B  03                 const type 3
063C  5C672844           const [293]: (673.61499023438)
0640  03                 const type 3
0641  5C6728C4           const [294]: (-673.61499023438)
0645  03                 const type 3
0646  E3363441           const [295]: (11.26340007782)
064A  03                 const type 3
064B  CEE05644           const [296]: (859.51257324219)
064F  03                 const type 3
0650  CEE056C4           const [297]: (-859.51257324219)
0654  03                 const type 3
0655  83B82844           const [298]: (674.88299560547)
0659  03                 const type 3
065A  83B828C4           const [299]: (-674.88299560547)
065E  03                 const type 3
065F  371A2E41           const [300]: (10.881400108337)
0663  03                 const type 3
0664  00001041           const [301]: (9)
0668  03                 const type 3
0669  4D215C44           const [302]: (880.52032470703)
066D  03                 const type 3
066E  4D215CC4           const [303]: (-880.52032470703)
0672  03                 const type 3
0673  47848544           const [304]: (1068.1336669922)
0677  03                 const type 3
0678  478485C4           const [305]: (-1068.1336669922)
067C  03                 const type 3
067D  D7346141           const [306]: (14.075400352478)
0681  03                 const type 3
0682  56E76E44           const [307]: (955.61462402344)
0686  03                 const type 3
0687  56E76EC4           const [308]: (-955.61462402344)
068B  03                 const type 3
068C  85B6A444           const [309]: (1317.7037353516)
0690  03                 const type 3
0691  85B6A4C4           const [310]: (-1317.7037353516)
0695  03                 const type 3
0696  F6973741           const [311]: (11.474599838257)
069A  03                 const type 3
069B  F8C25044           const [312]: (835.04638671875)
069F  03                 const type 3
06A0  F8C250C4           const [313]: (-835.04638671875)
06A4  03                 const type 3
06A5  1137B844           const [314]: (1473.7208251953)
06A9  03                 const type 3
06AA  1137B8C4           const [315]: (-1473.7208251953)
06AE  03                 const type 3
06AF  C58F3541           const [316]: (11.347599983215)
06B3  03                 const type 3
06B4  4F6B2D44           const [317]: (693.67669677734)
06B8  03                 const type 3
06B9  4F6B2DC4           const [318]: (-693.67669677734)
06BD  03                 const type 3
06BE  1EFDB344           const [319]: (1439.9099121094)
06C2  03                 const type 3
06C3  1EFDB3C4           const [320]: (-1439.9099121094)
06C7  03                 const type 3
06C8  9A992841           const [321]: (10.53750038147)
06CC  03                 const type 3
06CD  00002041           const [322]: (10)
06D1  03                 const type 3
06D2  F5FADC44           const [323]: (1767.8424072266)
06D6  03                 const type 3
06D7  F5FADCC4           const [324]: (-1767.8424072266)
06DB  03                 const type 3
06DC  6A454444           const [325]: (785.08459472656)
06E0  03                 const type 3
06E1  6A4544C4           const [326]: (-785.08459472656)
06E5  03                 const type 3
06E6  F241ED40           const [327]: (7.4142999649048)
06EA  03                 const type 3
06EB  B8A5E444           const [328]: (1829.1787109375)
06EF  03                 const type 3
06F0  B8A5E4C4           const [329]: (-1829.1787109375)
06F4  03                 const type 3
06F5  9FF70044           const [330]: (515.86907958984)
06F9  03                 const type 3
06FA  9FF700C4           const [331]: (-515.86907958984)
06FE  03                 const type 3
06FF  C58F6441           const [332]: (14.285099983215)
0703  03                 const type 3
0704  E42CD744           const [333]: (1721.4028320313)
0708  03                 const type 3
0709  E42CD7C4           const [334]: (-1721.4028320313)
070D  03                 const type 3
070E  6D979C43           const [335]: (313.18301391602)
0712  03                 const type 3
0713  6D979CC3           const [336]: (-313.18301391602)
0717  03                 const type 3
0718  643B6541           const [337]: (14.326999664307)
071C  03                 const type 3
071D  02B8A844           const [338]: (1349.7502441406)
0721  03                 const type 3
0722  02B8A8C4           const [339]: (-1349.7502441406)
0726  03                 const type 3
0727  B8D6E843           const [340]: (465.67749023438)
072B  03                 const type 3
072C  B8D6E8C3           const [341]: (-465.67749023438)
0730  03                 const type 3
0731  09F9EC40           const [342]: (7.4053997993469)
0735  03                 const type 3
0736  A9FA9C44           const [343]: (1255.8331298828)
073A  03                 const type 3
073B  A9FA9CC4           const [344]: (-1255.8331298828)
073F  03                 const type 3
0740  BD522B44           const [345]: (685.29278564453)
0744  03                 const type 3
0745  BD522BC4           const [346]: (-685.29278564453)
0749  03                 const type 3
074A  C4426541           const [347]: (14.328800201416)
074E  03                 const type 3
074F  D196B644           const [348]: (1460.7130126953)
0753  03                 const type 3
0754  D196B6C4           const [349]: (-1460.7130126953)
0758  03                 const type 3
0759  748E9E43           const [350]: (317.11291503906)
075D  03                 const type 3
075E  748E9EC3           const [351]: (-317.11291503906)
0762  03                 const type 3
0763  CD3B6541           const [352]: (14.32709980011)
0767  03                 const type 3
0768  3123C544           const [353]: (1577.0997314453)
076C  03                 const type 3
076D  3123C5C4           const [354]: (-1577.0997314453)
0771  03                 const type 3
0772  B4380C44           const [355]: (560.88598632813)
0776  03                 const type 3
0777  B4380CC4           const [356]: (-560.88598632813)
077B  03                 const type 3
077C  3D0AED40           const [357]: (7.4074997901917)
0780  03                 const type 3
0781  7D12BF44           const [358]: (1528.5777587891)
0785  03                 const type 3
0786  7D12BFC4           const [359]: (-1528.5777587891)
078A  03                 const type 3
078B  4F981C44           const [360]: (626.37982177734)
078F  03                 const type 3
0790  4F981CC4           const [361]: (-626.37982177734)
0794  03                 const type 3
0795  96436541           const [362]: (14.329000473022)
0799  03                 const type 3
079A  942BDC44           const [363]: (1761.3618164063)
079E  03                 const type 3
079F  942BDCC4           const [364]: (-1761.3618164063)
07A3  03                 const type 3
07A4  096E4444           const [365]: (785.71929931641)
07A8  03                 const type 3
07A9  096E44C4           const [366]: (-785.71929931641)
07AD  03                 const type 3
07AE  984CED40           const [367]: (7.415599822998)
07B2  03                 const type 3
07B3  77A5E444           const [368]: (1829.1707763672)
07B7  03                 const type 3
07B8  77A5E4C4           const [369]: (-1829.1707763672)
07BC  03                 const type 3
07BD  53760F44           const [370]: (573.84881591797)
07C1  03                 const type 3
07C2  53760FC4           const [371]: (-573.84881591797)
07C6  03                 const type 3
07C7  C05BFE40           const [372]: (7.9486999511719)
                         * functions:
07CB  00000000           sizep (0)
                         * code:
07CF  CD030000           sizecode (973)
07D3  0A000000           [001] newtable   0   0   0    ; array=0, hash=0
07D7  05000001           [002] getglobal  1   0        ; GameLocation
07DB  99800001           [003] call       1   1   2  
07DF  D5BE0000           [004] eq         0   1   251  ; 0, to [6] if true
07E3  D42B8000           [005] jmp        176          ; to [182]
07E7  85000001           [006] getglobal  1   2        ; RaceId
07EB  99800001           [007] call       1   1   2  
07EF  D5BE0000           [008] eq         0   1   251  ; 0, to [10] if true
07F3  54128000           [009] jmp        74           ; to [84]
07F7  0A800301           [010] newtable   1   7   0    ; array=7, hash=0
07FB  0A800102           [011] newtable   2   3   0    ; array=3, hash=0
07FF  C5000003           [012] getglobal  3   3        ; pickup
0803  86BF0103           [013] gettable   3   3   254  ; "racegood"
0807  0A800104           [014] newtable   4   3   0    ; array=3, hash=0
080B  41010005           [015] loadk      5   5        ; 501.44338989258
080F  81010006           [016] loadk      6   6        ; 643.87731933594
0813  C1010007           [017] loadk      7   7        ; 11.081700325012
0817  9F000004           [018] setlist    4   2        ; index 1 to 3
081B  01020005           [019] loadk      5   8        ; 30
081F  9F000002           [020] setlist    2   2        ; index 1 to 3
0823  0A800103           [021] newtable   3   3   0    ; array=3, hash=0
0827  C5000004           [022] getglobal  4   3        ; pickup
082B  863F0204           [023] gettable   4   4   254  ; "racegood"
082F  0A800105           [024] newtable   5   3   0    ; array=3, hash=0
0833  41020006           [025] loadk      6   9        ; 583.16857910156
0837  81020007           [026] loadk      7   10       ; 860.49847412109
083B  C1020008           [027] loadk      8   11       ; 18.931999206543
083F  9F000005           [028] setlist    5   2        ; index 1 to 3
0843  01020006           [029] loadk      6   8        ; 30
0847  9F000003           [030] setlist    3   2        ; index 1 to 3
084B  0A800104           [031] newtable   4   3   0    ; array=3, hash=0
084F  C5000005           [032] getglobal  5   3        ; pickup
0853  86C10205           [033] gettable   5   5   262  ; "racebad"
0857  0A800106           [034] newtable   6   3   0    ; array=3, hash=0
085B  41030007           [035] loadk      7   13       ; 486.68569946289
085F  81030008           [036] loadk      8   14       ; 1118.1604003906
0863  C1030009           [037] loadk      9   15       ; 16.504499435425
0867  9F000006           [038] setlist    6   2        ; index 1 to 3
086B  01020007           [039] loadk      7   8        ; 30
086F  9F000004           [040] setlist    4   2        ; index 1 to 3
0873  0A800105           [041] newtable   5   3   0    ; array=3, hash=0
0877  C5000006           [042] getglobal  6   3        ; pickup
087B  86410306           [043] gettable   6   6   262  ; "racebad"
087F  0A800107           [044] newtable   7   3   0    ; array=3, hash=0
0883  01040008           [045] loadk      8   16       ; 326.25509643555
0887  41040009           [046] loadk      9   17       ; 951.38562011719
088B  8104000A           [047] loadk      10  18       ; 11.065500259399
088F  9F000007           [048] setlist    7   2        ; index 1 to 3
0893  01020008           [049] loadk      8   8        ; 30
0897  9F000005           [050] setlist    5   2        ; index 1 to 3
089B  0A800106           [051] newtable   6   3   0    ; array=3, hash=0
089F  C5000007           [052] getglobal  7   3        ; pickup
08A3  86BF0307           [053] gettable   7   7   254  ; "racegood"
08A7  0A800108           [054] newtable   8   3   0    ; array=3, hash=0
08AB  C1040009           [055] loadk      9   19       ; 248.95010375977
08AF  0105000A           [056] loadk      10  20       ; 781.13677978516
08B3  4105000B           [057] loadk      11  21       ; 10.94019985199
08B7  9F000008           [058] setlist    8   2        ; index 1 to 3
08BB  01020009           [059] loadk      9   8        ; 30
08BF  9F000006           [060] setlist    6   2        ; index 1 to 3
08C3  0A800107           [061] newtable   7   3   0    ; array=3, hash=0
08C7  C5000008           [062] getglobal  8   3        ; pickup
08CB  863F0408           [063] gettable   8   8   254  ; "racegood"
08CF  0A800109           [064] newtable   9   3   0    ; array=3, hash=0
08D3  8105000A           [065] loadk      10  22       ; 362.80648803711
08D7  C105000B           [066] loadk      11  23       ; 1282.3006591797
08DB  0106000C           [067] loadk      12  24       ; 17.186899185181
08DF  9F000009           [068] setlist    9   2        ; index 1 to 3
08E3  0102000A           [069] loadk      10  8        ; 30
08E7  9F000007           [070] setlist    7   2        ; index 1 to 3
08EB  0A800108           [071] newtable   8   3   0    ; array=3, hash=0
08EF  C5000009           [072] getglobal  9   3        ; pickup
08F3  86C10409           [073] gettable   9   9   262  ; "racebad"
08F7  0A80010A           [074] newtable   10  3   0    ; array=3, hash=0
08FB  4106000B           [075] loadk      11  25       ; 184.4866027832
08FF  8106000C           [076] loadk      12  26       ; 687.06677246094
0903  C106000D           [077] loadk      13  27       ; 10.869500160217
0907  9F00000A           [078] setlist    10  2        ; index 1 to 3
090B  0102000B           [079] loadk      11  8        ; 30
090F  9F000008           [080] setlist    8   2        ; index 1 to 3
0913  9F010001           [081] setlist    1   6        ; index 1 to 7
0917  00800000           [082] move       0   1      
091B  D4DD8000           [083] jmp        888          ; to [972]
091F  85000001           [084] getglobal  1   2        ; RaceId
0923  99800001           [085] call       1   1   2  
0927  95C50000           [086] eq         0   1   278  ; 1, to [88] if true
092B  D4DC8000           [087] jmp        884          ; to [972]
092F  0A800601           [088] newtable   1   13  0    ; array=10, hash=0
0933  0A800102           [089] newtable   2   3   0    ; array=3, hash=0
0937  C5000003           [090] getglobal  3   3        ; pickup
093B  86BF0103           [091] gettable   3   3   254  ; "racegood"
093F  0A800104           [092] newtable   4   3   0    ; array=3, hash=0
0943  41070005           [093] loadk      5   29       ; 501.26480102539
0947  81070006           [094] loadk      6   30       ; 30.657499313354
094B  C1070007           [095] loadk      7   31       ; 10.535099983215
094F  9F000004           [096] setlist    4   2        ; index 1 to 3
0953  01020005           [097] loadk      5   8        ; 30
0957  9F000002           [098] setlist    2   2        ; index 1 to 3
095B  0A800103           [099] newtable   3   3   0    ; array=3, hash=0
095F  C5000004           [100] getglobal  4   3        ; pickup
0963  86410204           [101] gettable   4   4   262  ; "racebad"
0967  0A800105           [102] newtable   5   3   0    ; array=3, hash=0
096B  01080006           [103] loadk      6   32       ; 480.16079711914
096F  81080007           [104] loadk      7   34       ; -222.95429992676
0973  C1080008           [105] loadk      8   35       ; 11.791299819946
0977  9F000005           [106] setlist    5   2        ; index 1 to 3
097B  01020006           [107] loadk      6   8        ; 30
097F  9F000003           [108] setlist    3   2        ; index 1 to 3
0983  0A800104           [109] newtable   4   3   0    ; array=3, hash=0
0987  C5000005           [110] getglobal  5   3        ; pickup
098B  86BF0205           [111] gettable   5   5   254  ; "racegood"
098F  0A800106           [112] newtable   6   3   0    ; array=3, hash=0
0993  01090007           [113] loadk      7   36       ; 296.07418823242
0997  81090008           [114] loadk      8   38       ; -459.3828125
099B  C1090009           [115] loadk      9   39       ; 15.906399726868
099F  9F000006           [116] setlist    6   2        ; index 1 to 3
09A3  01020007           [117] loadk      7   8        ; 30
09A7  9F000004           [118] setlist    4   2        ; index 1 to 3
09AB  0A800105           [119] newtable   5   3   0    ; array=3, hash=0
09AF  C5000006           [120] getglobal  6   3        ; pickup
09B3  86410306           [121] gettable   6   6   262  ; "racebad"
09B7  0A800107           [122] newtable   7   3   0    ; array=3, hash=0
09BB  010A0008           [123] loadk      8   40       ; 380.16461181641
09BF  410A0009           [124] loadk      9   41       ; 16.090299606323
09C3  810A000A           [125] loadk      10  42       ; 13.431799888611
09C7  9F000007           [126] setlist    7   2        ; index 1 to 3
09CB  01020008           [127] loadk      8   8        ; 30
09CF  9F000005           [128] setlist    5   2        ; index 1 to 3
09D3  0A800106           [129] newtable   6   3   0    ; array=3, hash=0
09D7  C5000007           [130] getglobal  7   3        ; pickup
09DB  86BF0307           [131] gettable   7   7   254  ; "racegood"
09DF  0A800108           [132] newtable   8   3   0    ; array=3, hash=0
09E3  C10A0009           [133] loadk      9   43       ; 398.41079711914
09E7  010B000A           [134] loadk      10  44       ; 175.16079711914
09EB  410B000B           [135] loadk      11  45       ; 10.53989982605
09EF  9F000008           [136] setlist    8   2        ; index 1 to 3
09F3  01020009           [137] loadk      9   8        ; 30
09F7  9F000006           [138] setlist    6   2        ; index 1 to 3
09FB  0A800107           [139] newtable   7   3   0    ; array=3, hash=0
09FF  C5000008           [140] getglobal  8   3        ; pickup
0A03  86410408           [141] gettable   8   8   262  ; "racebad"
0A07  0A800109           [142] newtable   9   3   0    ; array=3, hash=0
0A0B  810B000A           [143] loadk      10  46       ; 465.462890625
0A0F  C10B000B           [144] loadk      11  47       ; 475.86840820313
0A13  010C000C           [145] loadk      12  48       ; 11.31219959259
0A17  9F000009           [146] setlist    9   2        ; index 1 to 3
0A1B  0102000A           [147] loadk      10  8        ; 30
0A1F  9F000007           [148] setlist    7   2        ; index 1 to 3
0A23  0A800108           [149] newtable   8   3   0    ; array=3, hash=0
0A27  C5000009           [150] getglobal  9   3        ; pickup
0A2B  86BF0409           [151] gettable   9   9   254  ; "racegood"
0A2F  0A80010A           [152] newtable   10  3   0    ; array=3, hash=0
0A33  410C000B           [153] loadk      11  49       ; 175.28689575195
0A37  810C000C           [154] loadk      12  50       ; 679.99841308594
0A3B  C10C000D           [155] loadk      13  51       ; 10.541999816895
0A3F  9F00000A           [156] setlist    10  2        ; index 1 to 3
0A43  0102000B           [157] loadk      11  8        ; 30
0A47  9F000008           [158] setlist    8   2        ; index 1 to 3
0A4B  0A800109           [159] newtable   9   3   0    ; array=3, hash=0
0A4F  C500000A           [160] getglobal  10  3        ; pickup
0A53  8641050A           [161] gettable   10  10  262  ; "racebad"
0A57  0A80010B           [162] newtable   11  3   0    ; array=3, hash=0
0A5B  010D000C           [163] loadk      12  52       ; 437.47100830078
0A5F  410D000D           [164] loadk      13  53       ; 768.81097412109
0A63  810D000E           [165] loadk      14  54       ; 10.949999809265
0A67  9F00000B           [166] setlist    11  2        ; index 1 to 3
0A6B  0102000C           [167] loadk      12  8        ; 30
0A6F  9F000009           [168] setlist    9   2        ; index 1 to 3
0A73  0A80010A           [169] newtable   10  3   0    ; array=3, hash=0
0A77  C500000B           [170] getglobal  11  3        ; pickup
0A7B  86BF050B           [171] gettable   11  11  254  ; "racegood"
0A7F  0A80010C           [172] newtable   12  3   0    ; array=3, hash=0
0A83  C10D000D           [173] loadk      13  55       ; 540.65008544922
0A87  010E000E           [174] loadk      14  56       ; 565.81890869141
0A8B  410E000F           [175] loadk      15  57       ; 10.538299560547
0A8F  9F00000C           [176] setlist    12  2        ; index 1 to 3
0A93  0102000D           [177] loadk      13  8        ; 30
0A97  9F00000A           [178] setlist    10  2        ; index 1 to 3
0A9B  1F020001           [179] setlist    1   8        ; index 1 to 9
0A9F  00800000           [180] move       0   1      
0AA3  54C58000           [181] jmp        790          ; to [972]
0AA7  05000001           [182] getglobal  1   0        ; GameLocation
0AAB  99800001           [183] call       1   1   2  
0AAF  95C50000           [184] eq         0   1   278  ; 1, to [186] if true
0AB3  D4218000           [185] jmp        136          ; to [322]
0AB7  85000001           [186] getglobal  1   2        ; RaceId
0ABB  99800001           [187] call       1   1   2  
0ABF  D5BE0000           [188] eq         0   1   251  ; 0, to [190] if true
0AC3  D40F8000           [189] jmp        64           ; to [254]
0AC7  0A000301           [190] newtable   1   6   0    ; array=6, hash=0
0ACB  0A800102           [191] newtable   2   3   0    ; array=3, hash=0
0ACF  C5000003           [192] getglobal  3   3        ; pickup
0AD3  86C10103           [193] gettable   3   3   262  ; "racebad"
0AD7  0A800104           [194] newtable   4   3   0    ; array=3, hash=0
0ADB  C10E0005           [195] loadk      5   59       ; -8.9503002166748
0ADF  410F0006           [196] loadk      6   61       ; -1031.4176025391
0AE3  810F0007           [197] loadk      7   62       ; 9.8410997390747
0AE7  9F000004           [198] setlist    4   2        ; index 1 to 3
0AEB  01020005           [199] loadk      5   8        ; 30
0AEF  9F000002           [200] setlist    2   2        ; index 1 to 3
0AF3  0A800103           [201] newtable   3   3   0    ; array=3, hash=0
0AF7  C5000004           [202] getglobal  4   3        ; pickup
0AFB  863F0204           [203] gettable   4   4   254  ; "racegood"
0AFF  0A800105           [204] newtable   5   3   0    ; array=3, hash=0
0B03  C10F0006           [205] loadk      6   63       ; 93.076301574707
0B07  41100007           [206] loadk      7   65       ; -841.11791992188
0B0B  81100008           [207] loadk      8   66       ; 9.8399000167847
0B0F  9F000005           [208] setlist    5   2        ; index 1 to 3
0B13  01020006           [209] loadk      6   8        ; 30
0B17  9F000003           [210] setlist    3   2        ; index 1 to 3
0B1B  0A800104           [211] newtable   4   3   0    ; array=3, hash=0
0B1F  C5000005           [212] getglobal  5   3        ; pickup
0B23  86C10205           [213] gettable   5   5   262  ; "racebad"
0B27  0A800106           [214] newtable   6   3   0    ; array=3, hash=0
0B2B  C1100007           [215] loadk      7   67       ; 173.67059326172
0B2F  41110008           [216] loadk      8   69       ; -626.20367431641
0B33  81110009           [217] loadk      9   70       ; 18.118700027466
0B37  9F000006           [218] setlist    6   2        ; index 1 to 3
0B3B  01020007           [219] loadk      7   8        ; 30
0B3F  9F000004           [220] setlist    4   2        ; index 1 to 3
0B43  0A800105           [221] newtable   5   3   0    ; array=3, hash=0
0B47  C5000006           [222] getglobal  6   3        ; pickup
0B4B  863F0306           [223] gettable   6   6   254  ; "racegood"
0B4F  0A800107           [224] newtable   7   3   0    ; array=3, hash=0
0B53  C1110008           [225] loadk      8   71       ; 290.32861328125
0B57  41120009           [226] loadk      9   73       ; -458.58880615234
0B5B  8112000A           [227] loadk      10  74       ; 15.95740032196
0B5F  9F000007           [228] setlist    7   2        ; index 1 to 3
0B63  01020008           [229] loadk      8   8        ; 30
0B67  9F000005           [230] setlist    5   2        ; index 1 to 3
0B6B  0A800106           [231] newtable   6   3   0    ; array=3, hash=0
0B6F  C5000007           [232] getglobal  7   3        ; pickup
0B73  86C10307           [233] gettable   7   7   262  ; "racebad"
0B77  0A800108           [234] newtable   8   3   0    ; array=3, hash=0
0B7B  C1120009           [235] loadk      9   75       ; 501.21078491211
0B7F  4113000A           [236] loadk      10  77       ; -489.85998535156
0B83  8113000B           [237] loadk      11  78       ; 10.431099891663
0B87  9F000008           [238] setlist    8   2        ; index 1 to 3
0B8B  01020009           [239] loadk      9   8        ; 30
0B8F  9F000006           [240] setlist    6   2        ; index 1 to 3
0B93  0A800107           [241] newtable   7   3   0    ; array=3, hash=0
0B97  C5000008           [242] getglobal  8   3        ; pickup
0B9B  863F0408           [243] gettable   8   8   254  ; "racegood"
0B9F  0A800109           [244] newtable   9   3   0    ; array=3, hash=0
0BA3  C113000A           [245] loadk      10  79       ; 255.70799255371
0BA7  4114000B           [246] loadk      11  81       ; -597.17962646484
0BAB  8114000C           [247] loadk      12  82       ; 9.3993997573853
0BAF  9F000009           [248] setlist    9   2        ; index 1 to 3
0BB3  0102000A           [249] loadk      10  8        ; 30
0BB7  9F000007           [250] setlist    7   2        ; index 1 to 3
0BBB  5F010001           [251] setlist    1   5        ; index 1 to 6
0BBF  00800000           [252] move       0   1      
0BC3  54B38000           [253] jmp        718          ; to [972]
0BC7  85000001           [254] getglobal  1   2        ; RaceId
0BCB  99800001           [255] call       1   1   2  
0BCF  95C50000           [256] eq         0   1   278  ; 1, to [258] if true
0BD3  54B28000           [257] jmp        714          ; to [972]
0BD7  0A000301           [258] newtable   1   6   0    ; array=6, hash=0
0BDB  0A800102           [259] newtable   2   3   0    ; array=3, hash=0
0BDF  C5000003           [260] getglobal  3   3        ; pickup
0BE3  86BF0103           [261] gettable   3   3   254  ; "racegood"
0BE7  0A800104           [262] newtable   4   3   0    ; array=3, hash=0
0BEB  C1140005           [263] loadk      5   83       ; 387.53060913086
0BEF  01150006           [264] loadk      6   84       ; 20.733400344849
0BF3  41150007           [265] loadk      7   85       ; 14.643500328064
0BF7  9F000004           [266] setlist    4   2        ; index 1 to 3
0BFB  01020005           [267] loadk      5   8        ; 30
0BFF  9F000002           [268] setlist    2   2        ; index 1 to 3
0C03  0A800103           [269] newtable   3   3   0    ; array=3, hash=0
0C07  C5000004           [270] getglobal  4   3        ; pickup
0C0B  86410204           [271] gettable   4   4   262  ; "racebad"
0C0F  0A800105           [272] newtable   5   3   0    ; array=3, hash=0
0C13  81150006           [273] loadk      6   86       ; 401.54290771484
0C17  C1150007           [274] loadk      7   87       ; 239.48229980469
0C1B  01160008           [275] loadk      8   88       ; 10.322299957275
0C1F  9F000005           [276] setlist    5   2        ; index 1 to 3
0C23  01020006           [277] loadk      6   8        ; 30
0C27  9F000003           [278] setlist    3   2        ; index 1 to 3
0C2B  0A800104           [279] newtable   4   3   0    ; array=3, hash=0
0C2F  C5000005           [280] getglobal  5   3        ; pickup
0C33  86BF0205           [281] gettable   5   5   254  ; "racegood"
0C37  0A800106           [282] newtable   6   3   0    ; array=3, hash=0
0C3B  41160007           [283] loadk      7   89       ; 504.22918701172
0C3F  C1160008           [284] loadk      8   91       ; -92.249702453613
0C43  01170009           [285] loadk      9   92       ; 9.7728004455566
0C47  9F000006           [286] setlist    6   2        ; index 1 to 3
0C4B  01020007           [287] loadk      7   8        ; 30
0C4F  9F000004           [288] setlist    4   2        ; index 1 to 3
0C53  0A800105           [289] newtable   5   3   0    ; array=3, hash=0
0C57  C5000006           [290] getglobal  6   3        ; pickup
0C5B  863F0306           [291] gettable   6   6   254  ; "racegood"
0C5F  0A800107           [292] newtable   7   3   0    ; array=3, hash=0
0C63  41170008           [293] loadk      8   93       ; 440.32559204102
0C67  C1170009           [294] loadk      9   95       ; -383.95278930664
0C6B  0118000A           [295] loadk      10  96       ; 10.015299797058
0C6F  9F000007           [296] setlist    7   2        ; index 1 to 3
0C73  01020008           [297] loadk      8   8        ; 30
0C77  9F000005           [298] setlist    5   2        ; index 1 to 3
0C7B  0A800106           [299] newtable   6   3   0    ; array=3, hash=0
0C7F  C5000007           [300] getglobal  7   3        ; pickup
0C83  86C10307           [301] gettable   7   7   262  ; "racebad"
0C87  0A800108           [302] newtable   8   3   0    ; array=3, hash=0
0C8B  41180009           [303] loadk      9   97       ; 198.80990600586
0C8F  C118000A           [304] loadk      10  99       ; -712.07312011719
0C93  0119000B           [305] loadk      11  100      ; 9.8393001556396
0C97  9F000008           [306] setlist    8   2        ; index 1 to 3
0C9B  01020009           [307] loadk      9   8        ; 30
0C9F  9F000006           [308] setlist    6   2        ; index 1 to 3
0CA3  0A800107           [309] newtable   7   3   0    ; array=3, hash=0
0CA7  C5000008           [310] getglobal  8   3        ; pickup
0CAB  863F0408           [311] gettable   8   8   254  ; "racegood"
0CAF  0A800109           [312] newtable   9   3   0    ; array=3, hash=0
0CB3  4119000A           [313] loadk      10  101      ; 182.30670166016
0CB7  C119000B           [314] loadk      11  103      ; -447.21240234375
0CBB  011A000C           [315] loadk      12  104      ; 10.406299591064
0CBF  9F000009           [316] setlist    9   2        ; index 1 to 3
0CC3  0102000A           [317] loadk      10  8        ; 30
0CC7  9F000007           [318] setlist    7   2        ; index 1 to 3
0CCB  5F010001           [319] setlist    1   5        ; index 1 to 6
0CCF  00800000           [320] move       0   1      
0CD3  54A28000           [321] jmp        650          ; to [972]
0CD7  05000001           [322] getglobal  1   0        ; GameLocation
0CDB  99800001           [323] call       1   1   2  
0CDF  D5D80000           [324] eq         0   1   355  ; 2, to [326] if true
0CE3  540E8000           [325] jmp        58           ; to [384]
0CE7  85000001           [326] getglobal  1   2        ; RaceId
0CEB  99800001           [327] call       1   1   2  
0CEF  D5BE0000           [328] eq         0   1   251  ; 0, to [330] if true
0CF3  54A08000           [329] jmp        642          ; to [972]
0CF7  0A800201           [330] newtable   1   5   0    ; array=5, hash=0
0CFB  0A800102           [331] newtable   2   3   0    ; array=3, hash=0
0CFF  C5000003           [332] getglobal  3   3        ; pickup
0D03  86BF0103           [333] gettable   3   3   254  ; "racegood"
0D07  0A800104           [334] newtable   4   3   0    ; array=3, hash=0
0D0B  C11A0005           [335] loadk      5   107      ; -33.294799804688
0D0F  411B0006           [336] loadk      6   109      ; -1183.7064208984
0D13  811B0007           [337] loadk      7   110      ; 10.317999839783
0D17  9F000004           [338] setlist    4   2        ; index 1 to 3
0D1B  01020005           [339] loadk      5   8        ; 30
0D1F  9F000002           [340] setlist    2   2        ; index 1 to 3
0D23  0A800103           [341] newtable   3   3   0    ; array=3, hash=0
0D27  C5000004           [342] getglobal  4   3        ; pickup
0D2B  86410204           [343] gettable   4   4   262  ; "racebad"
0D2F  0A800105           [344] newtable   5   3   0    ; array=3, hash=0
0D33  011C0006           [345] loadk      6   112      ; -67.349502563477
0D37  811C0007           [346] loadk      7   114      ; -1085.5892333984
0D3B  C11C0008           [347] loadk      8   115      ; 10.316800117493
0D3F  9F000005           [348] setlist    5   2        ; index 1 to 3
0D43  01020006           [349] loadk      6   8        ; 30
0D47  9F000003           [350] setlist    3   2        ; index 1 to 3
0D4B  0A800104           [351] newtable   4   3   0    ; array=3, hash=0
0D4F  C5000005           [352] getglobal  5   3        ; pickup
0D53  86BF0205           [353] gettable   5   5   254  ; "racegood"
0D57  0A800106           [354] newtable   6   3   0    ; array=3, hash=0
0D5B  411D0007           [355] loadk      7   117      ; -191.44940185547
0D5F  C11D0008           [356] loadk      8   119      ; -1106.7481689453
0D63  011E0009           [357] loadk      9   120      ; 10.458700180054
0D67  9F000006           [358] setlist    6   2        ; index 1 to 3
0D6B  01020007           [359] loadk      7   8        ; 30
0D6F  9F000004           [360] setlist    4   2        ; index 1 to 3
0D73  0A800105           [361] newtable   5   3   0    ; array=3, hash=0
0D77  C5000006           [362] getglobal  6   3        ; pickup
0D7B  86410306           [363] gettable   6   6   262  ; "racebad"
0D7F  0A800107           [364] newtable   7   3   0    ; array=3, hash=0
0D83  811E0008           [365] loadk      8   122      ; -163.47819519043
0D87  011F0009           [366] loadk      9   124      ; -1453.2098388672
0D8B  411F000A           [367] loadk      10  125      ; 10.45860004425
0D8F  9F000007           [368] setlist    7   2        ; index 1 to 3
0D93  01020008           [369] loadk      8   8        ; 30
0D97  9F000005           [370] setlist    5   2        ; index 1 to 3
0D9B  0A800106           [371] newtable   6   3   0    ; array=3, hash=0
0D9F  C5000007           [372] getglobal  7   3        ; pickup
0DA3  86BF0307           [373] gettable   7   7   254  ; "racegood"
0DA7  0A800108           [374] newtable   8   3   0    ; array=3, hash=0
0DAB  C11F0009           [375] loadk      9   127      ; -59.303798675537
0DAF  4120000A           [376] loadk      10  129      ; -1568.05078125
0DB3  8120000B           [377] loadk      11  130      ; 10.286399841309
0DB7  9F000008           [378] setlist    8   2        ; index 1 to 3
0DBB  01020009           [379] loadk      9   8        ; 30
0DBF  9F000006           [380] setlist    6   2        ; index 1 to 3
0DC3  1F010001           [381] setlist    1   4        ; index 1 to 5
0DC7  00800000           [382] move       0   1      
0DCB  D4928000           [383] jmp        588          ; to [972]
0DCF  05000001           [384] getglobal  1   0        ; GameLocation
0DD3  99800001           [385] call       1   1   2  
0DD7  55DF0000           [386] eq         0   1   381  ; 6, to [388] if true
0DDB  D41F8000           [387] jmp        128          ; to [516]
0DDF  85000001           [388] getglobal  1   2        ; RaceId
0DE3  99800001           [389] call       1   1   2  
0DE7  D5BE0000           [390] eq         0   1   251  ; 0, to [392] if true
0DEB  D4908000           [391] jmp        580          ; to [972]
0DEF  0A000701           [392] newtable   1   14  0    ; array=12, hash=0
0DF3  0A800102           [393] newtable   2   3   0    ; array=3, hash=0
0DF7  C5000003           [394] getglobal  3   3        ; pickup
0DFB  86BF0103           [395] gettable   3   3   254  ; "racegood"
0DFF  0A800104           [396] newtable   4   3   0    ; array=3, hash=0
0E03  41210005           [397] loadk      5   133      ; -816.27331542969
0E07  81210006           [398] loadk      6   134      ; 754.32257080078
0E0B  C1210007           [399] loadk      7   135      ; 10.921600341797
0E0F  9F000004           [400] setlist    4   2        ; index 1 to 3
0E13  01020005           [401] loadk      5   8        ; 30
0E17  9F000002           [402] setlist    2   2        ; index 1 to 3
0E1B  0A800103           [403] newtable   3   3   0    ; array=3, hash=0
0E1F  C5000004           [404] getglobal  4   3        ; pickup
0E23  86410204           [405] gettable   4   4   262  ; "racebad"
0E27  0A800105           [406] newtable   5   3   0    ; array=3, hash=0
0E2B  41220006           [407] loadk      6   137      ; -872.25640869141
0E2F  81220007           [408] loadk      7   138      ; 940.04052734375
0E33  C1210008           [409] loadk      8   135      ; 10.921600341797
0E37  9F000005           [410] setlist    5   2        ; index 1 to 3
0E3B  01020006           [411] loadk      6   8        ; 30
0E3F  9F000003           [412] setlist    3   2        ; index 1 to 3
0E43  0A800104           [413] newtable   4   3   0    ; array=3, hash=0
0E47  C5000005           [414] getglobal  5   3        ; pickup
0E4B  86BF0205           [415] gettable   5   5   254  ; "racegood"
0E4F  0A800106           [416] newtable   6   3   0    ; array=3, hash=0
0E53  01230007           [417] loadk      7   140      ; -810.40521240234
0E57  41230008           [418] loadk      8   141      ; 1182.5367431641
0E5B  81230009           [419] loadk      9   142      ; 10.906599998474
0E5F  9F000006           [420] setlist    6   2        ; index 1 to 3
0E63  01020007           [421] loadk      7   8        ; 30
0E67  9F000004           [422] setlist    4   2        ; index 1 to 3
0E6B  0A800105           [423] newtable   5   3   0    ; array=3, hash=0
0E6F  C5000006           [424] getglobal  6   3        ; pickup
0E73  86410306           [425] gettable   6   6   262  ; "racebad"
0E77  0A800107           [426] newtable   7   3   0    ; array=3, hash=0
0E7B  01240008           [427] loadk      8   144      ; -689.74041748047
0E7F  41240009           [428] loadk      9   145      ; 1014.1079711914
0E83  8124000A           [429] loadk      10  146      ; 11.36040019989
0E87  9F000007           [430] setlist    7   2        ; index 1 to 3
0E8B  01020008           [431] loadk      8   8        ; 30
0E8F  9F000005           [432] setlist    5   2        ; index 1 to 3
0E93  0A800106           [433] newtable   6   3   0    ; array=3, hash=0
0E97  C5000007           [434] getglobal  7   3        ; pickup
0E9B  86BF0307           [435] gettable   7   7   254  ; "racegood"
0E9F  0A800108           [436] newtable   8   3   0    ; array=3, hash=0
0EA3  01250009           [437] loadk      9   148      ; -664.44091796875
0EA7  4125000A           [438] loadk      10  149      ; 897.24841308594
0EAB  8125000B           [439] loadk      11  150      ; 11.256799697876
0EAF  9F000008           [440] setlist    8   2        ; index 1 to 3
0EB3  01020009           [441] loadk      9   8        ; 30
0EB7  9F000006           [442] setlist    6   2        ; index 1 to 3
0EBB  0A800107           [443] newtable   7   3   0    ; array=3, hash=0
0EBF  C5000008           [444] getglobal  8   3        ; pickup
0EC3  86410408           [445] gettable   8   8   262  ; "racebad"
0EC7  0A800109           [446] newtable   9   3   0    ; array=3, hash=0
0ECB  0126000A           [447] loadk      10  152      ; -666.61828613281
0ECF  4126000B           [448] loadk      11  153      ; 700.97882080078
0ED3  8126000C           [449] loadk      12  154      ; 11.08660030365
0ED7  9F000009           [450] setlist    9   2        ; index 1 to 3
0EDB  0102000A           [451] loadk      10  8        ; 30
0EDF  9F000007           [452] setlist    7   2        ; index 1 to 3
0EE3  0A800108           [453] newtable   8   3   0    ; array=3, hash=0
0EE7  C5000009           [454] getglobal  9   3        ; pickup
0EEB  86BF0409           [455] gettable   9   9   254  ; "racegood"
0EEF  0A80010A           [456] newtable   10  3   0    ; array=3, hash=0
0EF3  0127000B           [457] loadk      11  156      ; -675.76867675781
0EF7  4127000C           [458] loadk      12  157      ; 591.39147949219
0EFB  8127000D           [459] loadk      13  158      ; 11.086799621582
0EFF  9F00000A           [460] setlist    10  2        ; index 1 to 3
0F03  0102000B           [461] loadk      11  8        ; 30
0F07  9F000008           [462] setlist    8   2        ; index 1 to 3
0F0B  0A800109           [463] newtable   9   3   0    ; array=3, hash=0
0F0F  C500000A           [464] getglobal  10  3        ; pickup
0F13  863F050A           [465] gettable   10  10  254  ; "racegood"
0F17  0A80010B           [466] newtable   11  3   0    ; array=3, hash=0
0F1B  0128000C           [467] loadk      12  160      ; -691.16418457031
0F1F  4128000D           [468] loadk      13  161      ; 415.22738647461
0F23  8128000E           [469] loadk      14  162      ; 11.072199821472
0F27  9F00000B           [470] setlist    11  2        ; index 1 to 3
0F2B  0102000C           [471] loadk      12  8        ; 30
0F2F  9F000009           [472] setlist    9   2        ; index 1 to 3
0F33  0A80010A           [473] newtable   10  3   0    ; array=3, hash=0
0F37  C500000B           [474] getglobal  11  3        ; pickup
0F3B  86C1050B           [475] gettable   11  11  262  ; "racebad"
0F3F  0A80010C           [476] newtable   12  3   0    ; array=3, hash=0
0F43  0129000D           [477] loadk      13  164      ; -821.22912597656
0F47  4129000E           [478] loadk      14  165      ; 255.29440307617
0F4B  8129000F           [479] loadk      15  166      ; 9.7412996292114
0F4F  9F00000C           [480] setlist    12  2        ; index 1 to 3
0F53  0102000D           [481] loadk      13  8        ; 30
0F57  9F00000A           [482] setlist    10  2        ; index 1 to 3
0F5B  0A80010B           [483] newtable   11  3   0    ; array=3, hash=0
0F5F  C500000C           [484] getglobal  12  3        ; pickup
0F63  863F060C           [485] gettable   12  12  254  ; "racegood"
0F67  0A80010D           [486] newtable   13  3   0    ; array=3, hash=0
0F6B  012A000E           [487] loadk      14  168      ; -735.20928955078
0F6F  412A000F           [488] loadk      15  169      ; 304.37930297852
0F73  812A0010           [489] loadk      16  170      ; 11.1265001297
0F77  9F00000D           [490] setlist    13  2        ; index 1 to 3
0F7B  0102000E           [491] loadk      14  8        ; 30
0F7F  9F00000B           [492] setlist    11  2        ; index 1 to 3
0F83  0A80010C           [493] newtable   12  3   0    ; array=3, hash=0
0F87  C500000D           [494] getglobal  13  3        ; pickup
0F8B  86C1060D           [495] gettable   13  13  262  ; "racebad"
0F8F  0A80010E           [496] newtable   14  3   0    ; array=3, hash=0
0F93  012B000F           [497] loadk      15  172      ; -657.26922607422
0F97  412B0010           [498] loadk      16  173      ; 529.09002685547
0F9B  812B0011           [499] loadk      17  174      ; 11.063400268555
0F9F  9F00000E           [500] setlist    14  2        ; index 1 to 3
0FA3  0102000F           [501] loadk      15  8        ; 30
0FA7  9F00000C           [502] setlist    12  2        ; index 1 to 3
0FAB  0A80010D           [503] newtable   13  3   0    ; array=3, hash=0
0FAF  C500000E           [504] getglobal  14  3        ; pickup
0FB3  863F070E           [505] gettable   14  14  254  ; "racegood"
0FB7  0A80010F           [506] newtable   15  3   0    ; array=3, hash=0
0FBB  012C0010           [507] loadk      16  176      ; -581.04150390625
0FBF  412C0011           [508] loadk      17  177      ; 657.77282714844
0FC3  812C0012           [509] loadk      18  178      ; 11.068699836731
0FC7  9F00000F           [510] setlist    15  2        ; index 1 to 3
0FCB  01020010           [511] loadk      16  8        ; 30
0FCF  9F00000D           [512] setlist    13  2        ; index 1 to 3
0FD3  DF020001           [513] setlist    1   11       ; index 1 to 12
0FD7  00800000           [514] move       0   1      
0FDB  D4718000           [515] jmp        456          ; to [972]
0FDF  05000001           [516] getglobal  1   0        ; GameLocation
0FE3  99800001           [517] call       1   1   2  
0FE7  55EB0000           [518] eq         0   1   429  ; 7, to [520] if true
0FEB  D4308000           [519] jmp        196          ; to [716]
0FEF  85000001           [520] getglobal  1   2        ; RaceId
0FF3  99800001           [521] call       1   1   2  
0FF7  D5BE0000           [522] eq         0   1   251  ; 0, to [524] if true
0FFB  540D8000           [523] jmp        54           ; to [578]
0FFF  0A800201           [524] newtable   1   5   0    ; array=5, hash=0
1003  0A800102           [525] newtable   2   3   0    ; array=3, hash=0
1007  C5000003           [526] getglobal  3   3        ; pickup
100B  86BF0103           [527] gettable   3   3   254  ; "racegood"
100F  0A800104           [528] newtable   4   3   0    ; array=3, hash=0
1013  412D0005           [529] loadk      5   181      ; -1030.7025146484
1017  C12D0006           [530] loadk      6   183      ; -42.437099456787
101B  012E0007           [531] loadk      7   184      ; 10.862299919128
101F  9F000004           [532] setlist    4   2        ; index 1 to 3
1023  01020005           [533] loadk      5   8        ; 30
1027  9F000002           [534] setlist    2   2        ; index 1 to 3
102B  0A800103           [535] newtable   3   3   0    ; array=3, hash=0
102F  C5000004           [536] getglobal  4   3        ; pickup
1033  86410204           [537] gettable   4   4   262  ; "racebad"
1037  0A800105           [538] newtable   5   3   0    ; array=3, hash=0
103B  812E0006           [539] loadk      6   186      ; -1180.4949951172
103F  012F0007           [540] loadk      7   188      ; -244.63439941406
1043  412F0008           [541] loadk      8   189      ; 11.036499977112
1047  9F000005           [542] setlist    5   2        ; index 1 to 3
104B  01020006           [543] loadk      6   8        ; 30
104F  9F000003           [544] setlist    3   2        ; index 1 to 3
1053  0A800104           [545] newtable   4   3   0    ; array=3, hash=0
1057  C5000005           [546] getglobal  5   3        ; pickup
105B  86BF0205           [547] gettable   5   5   254  ; "racegood"
105F  0A800106           [548] newtable   6   3   0    ; array=3, hash=0
1063  C12F0007           [549] loadk      7   191      ; -1186.7399902344
1067  41300008           [550] loadk      8   193      ; -485.87350463867
106B  81300009           [551] loadk      9   194      ; 10.421999931335
106F  9F000006           [552] setlist    6   2        ; index 1 to 3
1073  01020007           [553] loadk      7   8        ; 30
1077  9F000004           [554] setlist    4   2        ; index 1 to 3
107B  0A800105           [555] newtable   5   3   0    ; array=3, hash=0
107F  C5000006           [556] getglobal  6   3        ; pickup
1083  86410306           [557] gettable   6   6   262  ; "racebad"
1087  0A800107           [558] newtable   7   3   0    ; array=3, hash=0
108B  01310008           [559] loadk      8   196      ; -1096.0465087891
108F  81310009           [560] loadk      9   198      ; -442.18319702148
1093  C131000A           [561] loadk      10  199      ; 10.277799606323
1097  9F000007           [562] setlist    7   2        ; index 1 to 3
109B  01020008           [563] loadk      8   8        ; 30
109F  9F000005           [564] setlist    5   2        ; index 1 to 3
10A3  0A800106           [565] newtable   6   3   0    ; array=3, hash=0
10A7  C5000007           [566] getglobal  7   3        ; pickup
10AB  86BF0307           [567] gettable   7   7   254  ; "racegood"
10AF  0A800108           [568] newtable   8   3   0    ; array=3, hash=0
10B3  41320009           [569] loadk      9   201      ; -1018.5562744141
10B7  C132000A           [570] loadk      10  203      ; -299.89260864258
10BB  0133000B           [571] loadk      11  204      ; 10.422200202942
10BF  9F000008           [572] setlist    8   2        ; index 1 to 3
10C3  01020009           [573] loadk      9   8        ; 30
10C7  9F000006           [574] setlist    6   2        ; index 1 to 3
10CB  1F010001           [575] setlist    1   4        ; index 1 to 5
10CF  00800000           [576] move       0   1      
10D3  54628000           [577] jmp        394          ; to [972]
10D7  85000001           [578] getglobal  1   2        ; RaceId
10DB  99800001           [579] call       1   1   2  
10DF  95C50000           [580] eq         0   1   278  ; 1, to [582] if true
10E3  54618000           [581] jmp        390          ; to [972]
10E7  0A800701           [582] newtable   1   15  0    ; array=14, hash=0
10EB  0A800102           [583] newtable   2   3   0    ; array=3, hash=0
10EF  C5000003           [584] getglobal  3   3        ; pickup
10F3  86BF0103           [585] gettable   3   3   254  ; "racegood"
10F7  0A800104           [586] newtable   4   3   0    ; array=3, hash=0
10FB  81330005           [587] loadk      5   206      ; -1186.5953369141
10FF  01340006           [588] loadk      6   208      ; -631.86297607422
1103  41340007           [589] loadk      7   209      ; 10.996000289917
1107  9F000004           [590] setlist    4   2        ; index 1 to 3
110B  01020005           [591] loadk      5   8        ; 30
110F  9F000002           [592] setlist    2   2        ; index 1 to 3
1113  0A800103           [593] newtable   3   3   0    ; array=3, hash=0
1117  C5000004           [594] getglobal  4   3        ; pickup
111B  86410204           [595] gettable   4   4   262  ; "racebad"
111F  0A800105           [596] newtable   5   3   0    ; array=3, hash=0
1123  C1340006           [597] loadk      6   211      ; -1116.6876220703
1127  41350007           [598] loadk      7   213      ; -591.39288330078
112B  81350008           [599] loadk      8   214      ; 10.990599632263
112F  9F000005           [600] setlist    5   2        ; index 1 to 3
1133  01020006           [601] loadk      6   8        ; 30
1137  9F000003           [602] setlist    3   2        ; index 1 to 3
113B  0A800104           [603] newtable   4   3   0    ; array=3, hash=0
113F  C5000005           [604] getglobal  5   3        ; pickup
1143  86BF0205           [605] gettable   5   5   254  ; "racegood"
1147  0A800106           [606] newtable   6   3   0    ; array=3, hash=0
114B  01360007           [607] loadk      7   216      ; -1096.4005126953
114F  81360008           [608] loadk      8   218      ; -441.87329101563
1153  C1360009           [609] loadk      9   219      ; 10.164299964905
1157  9F000006           [610] setlist    6   2        ; index 1 to 3
115B  01020007           [611] loadk      7   8        ; 30
115F  9F000004           [612] setlist    4   2        ; index 1 to 3
1163  0A800105           [613] newtable   5   3   0    ; array=3, hash=0
1167  C5000006           [614] getglobal  6   3        ; pickup
116B  86410306           [615] gettable   6   6   262  ; "racebad"
116F  0A800107           [616] newtable   7   3   0    ; array=3, hash=0
1173  41370008           [617] loadk      8   221      ; -1017.5076293945
1177  C1370009           [618] loadk      9   223      ; -299.58700561523
117B  0138000A           [619] loadk      10  224      ; 10.30860042572
117F  9F000007           [620] setlist    7   2        ; index 1 to 3
1183  01020008           [621] loadk      8   8        ; 30
1187  9F000005           [622] setlist    5   2        ; index 1 to 3
118B  0A800106           [623] newtable   6   3   0    ; array=3, hash=0
118F  C5000007           [624] getglobal  7   3        ; pickup
1193  86BF0307           [625] gettable   7   7   254  ; "racegood"
1197  0A800108           [626] newtable   8   3   0    ; array=3, hash=0
119B  81380009           [627] loadk      9   226      ; -1041.6961669922
119F  0139000A           [628] loadk      10  228      ; -129.31230163574
11A3  4139000B           [629] loadk      11  229      ; 10.757300376892
11A7  9F000008           [630] setlist    8   2        ; index 1 to 3
11AB  01020009           [631] loadk      9   8        ; 30
11AF  9F000006           [632] setlist    6   2        ; index 1 to 3
11B3  0A800107           [633] newtable   7   3   0    ; array=3, hash=0
11B7  C5000008           [634] getglobal  8   3        ; pickup
11BB  86410408           [635] gettable   8   8   262  ; "racebad"
11BF  0A800109           [636] newtable   9   3   0    ; array=3, hash=0
11C3  C139000A           [637] loadk      10  231      ; -1073.4158935547
11C7  013A000B           [638] loadk      11  232      ; 46.468101501465
11CB  413A000C           [639] loadk      12  233      ; 10.781700134277
11CF  9F000009           [640] setlist    9   2        ; index 1 to 3
11D3  0102000A           [641] loadk      10  8        ; 30
11D7  9F000007           [642] setlist    7   2        ; index 1 to 3
11DB  0A800108           [643] newtable   8   3   0    ; array=3, hash=0
11DF  C5000009           [644] getglobal  9   3        ; pickup
11E3  86BF0409           [645] gettable   9   9   254  ; "racegood"
11E7  0A80010A           [646] newtable   10  3   0    ; array=3, hash=0
11EB  C13A000B           [647] loadk      11  235      ; -1011.5999145508
11EF  013B000C           [648] loadk      12  236      ; 222.8464050293
11F3  413B000D           [649] loadk      13  237      ; 10.77410030365
11F7  9F00000A           [650] setlist    10  2        ; index 1 to 3
11FB  0102000B           [651] loadk      11  8        ; 30
11FF  9F000008           [652] setlist    8   2        ; index 1 to 3
1203  0A800109           [653] newtable   9   3   0    ; array=3, hash=0
1207  C500000A           [654] getglobal  10  3        ; pickup
120B  8641050A           [655] gettable   10  10  262  ; "racebad"
120F  0A80010B           [656] newtable   11  3   0    ; array=3, hash=0
1213  C13B000C           [657] loadk      12  239      ; -913.01098632813
1217  013C000D           [658] loadk      13  240      ; 312.64859008789
121B  413C000E           [659] loadk      14  241      ; 10.775500297546
121F  9F00000B           [660] setlist    11  2        ; index 1 to 3
1223  0102000C           [661] loadk      12  8        ; 30
1227  9F000009           [662] setlist    9   2        ; index 1 to 3
122B  0A80010A           [663] newtable   10  3   0    ; array=3, hash=0
122F  C500000B           [664] getglobal  11  3        ; pickup
1233  86BF050B           [665] gettable   11  11  254  ; "racegood"
1237  0A80010C           [666] newtable   12  3   0    ; array=3, hash=0
123B  C13C000D           [667] loadk      13  243      ; -720.20880126953
123F  013D000E           [668] loadk      14  244      ; 235.47540283203
1243  413D000F           [669] loadk      15  245      ; 10.593700408936
1247  9F00000C           [670] setlist    12  2        ; index 1 to 3
124B  0102000D           [671] loadk      13  8        ; 30
124F  9F00000A           [672] setlist    10  2        ; index 1 to 3
1253  0A80010B           [673] newtable   11  3   0    ; array=3, hash=0
1257  C500000C           [674] getglobal  12  3        ; pickup
125B  8641060C           [675] gettable   12  12  262  ; "racebad"
125F  0A80010D           [676] newtable   13  3   0    ; array=3, hash=0
1263  C13D000E           [677] loadk      14  247      ; -928.95458984375
1267  013E000F           [678] loadk      15  248      ; 149.54229736328
126B  413E0010           [679] loadk      16  249      ; 8.7510995864868
126F  9F00000D           [680] setlist    13  2        ; index 1 to 3
1273  0102000E           [681] loadk      14  8        ; 30
1277  9F00000B           [682] setlist    11  2        ; index 1 to 3
127B  0A80010C           [683] newtable   12  3   0    ; array=3, hash=0
127F  C500000D           [684] getglobal  13  3        ; pickup
1283  86BF060D           [685] gettable   13  13  254  ; "racegood"
1287  0A80010E           [686] newtable   14  3   0    ; array=3, hash=0
128B  C13E000F           [687] loadk      15  251      ; -933.23901367188
128F  413F0010           [688] loadk      16  253      ; -46.495300292969
1293  813F0011           [689] loadk      17  254      ; 6.0908999443054
1297  9F00000E           [690] setlist    14  2        ; index 1 to 3
129B  0102000F           [691] loadk      15  8        ; 30
129F  9F00000C           [692] setlist    12  2        ; index 1 to 3
12A3  0A80010D           [693] newtable   13  3   0    ; array=3, hash=0
12A7  C500000E           [694] getglobal  14  3        ; pickup
12AB  8641070E           [695] gettable   14  14  262  ; "racebad"
12AF  0A80010F           [696] newtable   15  3   0    ; array=3, hash=0
12B3  01400010           [697] loadk      16  256      ; -878.58551025391
12B7  81400011           [698] loadk      17  258      ; -297.37780761719
12BB  C1400012           [699] loadk      18  259      ; 10.678500175476
12BF  9F00000F           [700] setlist    15  2        ; index 1 to 3
12C3  01020010           [701] loadk      16  8        ; 30
12C7  9F00000D           [702] setlist    13  2        ; index 1 to 3
12CB  0A80010E           [703] newtable   14  3   0    ; array=3, hash=0
12CF  C500000F           [704] getglobal  15  3        ; pickup
12D3  86BF070F           [705] gettable   15  15  254  ; "racegood"
12D7  0A800110           [706] newtable   16  3   0    ; array=3, hash=0
12DB  41410011           [707] loadk      17  261      ; -842.91540527344
12DF  C1410012           [708] loadk      18  263      ; -510.55560302734
12E3  01420013           [709] loadk      19  264      ; 10.440400123596
12E7  9F000010           [710] setlist    16  2        ; index 1 to 3
12EB  01020011           [711] loadk      17  8        ; 30
12EF  9F00000E           [712] setlist    14  2        ; index 1 to 3
12F3  1F030001           [713] setlist    1   12       ; index 1 to 13
12F7  00800000           [714] move       0   1      
12FB  D43F8000           [715] jmp        256          ; to [972]
12FF  05000001           [716] getglobal  1   0        ; GameLocation
1303  99800001           [717] call       1   1   2  
1307  41420002           [718] loadk      2   265      ; 8
130B  95800000           [719] eq         0   1   2    ; to [721] if true
130F  54138000           [720] jmp        78           ; to [799]
1313  85000001           [721] getglobal  1   2        ; RaceId
1317  99800001           [722] call       1   1   2  
131B  D5BE0000           [723] eq         0   1   251  ; 0, to [725] if true
131F  943D8000           [724] jmp        247          ; to [972]
1323  0A800301           [725] newtable   1   7   0    ; array=7, hash=0
1327  0A800102           [726] newtable   2   3   0    ; array=3, hash=0
132B  C5000003           [727] getglobal  3   3        ; pickup
132F  86BF0103           [728] gettable   3   3   254  ; "racegood"
1333  0A800104           [729] newtable   4   3   0    ; array=3, hash=0
1337  C1420005           [730] loadk      5   267      ; -826.15728759766
133B  41430006           [731] loadk      6   269      ; -1047.4293212891
133F  81430007           [732] loadk      7   270      ; 10.568300247192
1343  9F000004           [733] setlist    4   2        ; index 1 to 3
1347  01020005           [734] loadk      5   8        ; 30
134B  9F000002           [735] setlist    2   2        ; index 1 to 3
134F  0A800103           [736] newtable   3   3   0    ; array=3, hash=0
1353  C5000004           [737] getglobal  4   3        ; pickup
1357  86410204           [738] gettable   4   4   262  ; "racebad"
135B  0A800105           [739] newtable   5   3   0    ; array=3, hash=0
135F  01440006           [740] loadk      6   272      ; -758.52142333984
1363  81440007           [741] loadk      7   274      ; -1338.4714355469
1367  C1440008           [742] loadk      8   275      ; 11.232799530029
136B  9F000005           [743] setlist    5   2        ; index 1 to 3
136F  01020006           [744] loadk      6   8        ; 30
1373  9F000003           [745] setlist    3   2        ; index 1 to 3
1377  0A800104           [746] newtable   4   3   0    ; array=3, hash=0
137B  C5000005           [747] getglobal  5   3        ; pickup
137F  86BF0205           [748] gettable   5   5   254  ; "racegood"
1383  0A800106           [749] newtable   6   3   0    ; array=3, hash=0
1387  41450007           [750] loadk      7   277      ; -949.24182128906
138B  C1450008           [751] loadk      8   279      ; -1395.8018798828
138F  01460009           [752] loadk      9   280      ; 11.393699645996
1393  9F000006           [753] setlist    6   2        ; index 1 to 3
1397  01020007           [754] loadk      7   8        ; 30
139B  9F000004           [755] setlist    4   2        ; index 1 to 3
139F  0A800105           [756] newtable   5   3   0    ; array=3, hash=0
13A3  C5000006           [757] getglobal  6   3        ; pickup
13A7  86410306           [758] gettable   6   6   262  ; "racebad"
13AB  0A800107           [759] newtable   7   3   0    ; array=3, hash=0
13AF  81460008           [760] loadk      8   282      ; -921.30432128906
13B3  01470009           [761] loadk      9   284      ; -1039.2440185547
13B7  4147000A           [762] loadk      10  285      ; 14.325400352478
13BB  9F000007           [763] setlist    7   2        ; index 1 to 3
13BF  01020008           [764] loadk      8   8        ; 30
13C3  9F000005           [765] setlist    5   2        ; index 1 to 3
13C7  0A800106           [766] newtable   6   3   0    ; array=3, hash=0
13CB  C5000007           [767] getglobal  7   3        ; pickup
13CF  86BF0307           [768] gettable   7   7   254  ; "racegood"
13D3  0A800108           [769] newtable   8   3   0    ; array=3, hash=0
13D7  C1470009           [770] loadk      9   287      ; -1082.279296875
13DB  4148000A           [771] loadk      10  289      ; -847.07171630859
13DF  8148000B           [772] loadk      11  290      ; 11.596699714661
13E3  9F000008           [773] setlist    8   2        ; index 1 to 3
13E7  01020009           [774] loadk      9   8        ; 30
13EB  9F000006           [775] setlist    6   2        ; index 1 to 3
13EF  0A800107           [776] newtable   7   3   0    ; array=3, hash=0
13F3  C5000008           [777] getglobal  8   3        ; pickup
13F7  86410408           [778] gettable   8   8   262  ; "racebad"
13FB  0A800109           [779] newtable   9   3   0    ; array=3, hash=0
13FF  0149000A           [780] loadk      10  292      ; -1018.525390625
1403  8149000B           [781] loadk      11  294      ; -673.61499023438
1407  C149000C           [782] loadk      12  295      ; 11.26340007782
140B  9F000009           [783] setlist    9   2        ; index 1 to 3
140F  0102000A           [784] loadk      10  8        ; 30
1413  9F000007           [785] setlist    7   2        ; index 1 to 3
1417  0A800108           [786] newtable   8   3   0    ; array=3, hash=0
141B  C5000009           [787] getglobal  9   3        ; pickup
141F  86BF0409           [788] gettable   9   9   254  ; "racegood"
1423  0A80010A           [789] newtable   10  3   0    ; array=3, hash=0
1427  414A000B           [790] loadk      11  297      ; -859.51257324219
142B  C14A000C           [791] loadk      12  299      ; -674.88299560547
142F  014B000D           [792] loadk      13  300      ; 10.881400108337
1433  9F00000A           [793] setlist    10  2        ; index 1 to 3
1437  0102000B           [794] loadk      11  8        ; 30
143B  9F000008           [795] setlist    8   2        ; index 1 to 3
143F  9F010001           [796] setlist    1   6        ; index 1 to 7
1443  00800000           [797] move       0   1      
1447  142B8000           [798] jmp        173          ; to [972]
144B  05000001           [799] getglobal  1   0        ; GameLocation
144F  99800001           [800] call       1   1   2  
1453  414B0002           [801] loadk      2   301      ; 9
1457  95800000           [802] eq         0   1   2    ; to [804] if true
145B  D40B8000           [803] jmp        48           ; to [852]
145F  85000001           [804] getglobal  1   2        ; RaceId
1463  99800001           [805] call       1   1   2  
1467  D5BE0000           [806] eq         0   1   251  ; 0, to [808] if true
146B  D4288000           [807] jmp        164          ; to [972]
146F  0A000201           [808] newtable   1   4   0    ; array=4, hash=0
1473  0A800102           [809] newtable   2   3   0    ; array=3, hash=0
1477  C5000003           [810] getglobal  3   3        ; pickup
147B  86BF0103           [811] gettable   3   3   254  ; "racegood"
147F  0A800104           [812] newtable   4   3   0    ; array=3, hash=0
1483  C14B0005           [813] loadk      5   303      ; -880.52032470703
1487  414C0006           [814] loadk      6   305      ; -1068.1336669922
148B  814C0007           [815] loadk      7   306      ; 14.075400352478
148F  9F000004           [816] setlist    4   2        ; index 1 to 3
1493  01020005           [817] loadk      5   8        ; 30
1497  9F000002           [818] setlist    2   2        ; index 1 to 3
149B  0A800103           [819] newtable   3   3   0    ; array=3, hash=0
149F  C5000004           [820] getglobal  4   3        ; pickup
14A3  86410204           [821] gettable   4   4   262  ; "racebad"
14A7  0A800105           [822] newtable   5   3   0    ; array=3, hash=0
14AB  014D0006           [823] loadk      6   308      ; -955.61462402344
14AF  814D0007           [824] loadk      7   310      ; -1317.7037353516
14B3  C14D0008           [825] loadk      8   311      ; 11.474599838257
14B7  9F000005           [826] setlist    5   2        ; index 1 to 3
14BB  01020006           [827] loadk      6   8        ; 30
14BF  9F000003           [828] setlist    3   2        ; index 1 to 3
14C3  0A800104           [829] newtable   4   3   0    ; array=3, hash=0
14C7  C5000005           [830] getglobal  5   3        ; pickup
14CB  86BF0205           [831] gettable   5   5   254  ; "racegood"
14CF  0A800106           [832] newtable   6   3   0    ; array=3, hash=0
14D3  414E0007           [833] loadk      7   313      ; -835.04638671875
14D7  C14E0008           [834] loadk      8   315      ; -1473.7208251953
14DB  014F0009           [835] loadk      9   316      ; 11.347599983215
14DF  9F000006           [836] setlist    6   2        ; index 1 to 3
14E3  01020007           [837] loadk      7   8        ; 30
14E7  9F000004           [838] setlist    4   2        ; index 1 to 3
14EB  0A800105           [839] newtable   5   3   0    ; array=3, hash=0
14EF  C5000006           [840] getglobal  6   3        ; pickup
14F3  86410306           [841] gettable   6   6   262  ; "racebad"
14F7  0A800107           [842] newtable   7   3   0    ; array=3, hash=0
14FB  814F0008           [843] loadk      8   318      ; -693.67669677734
14FF  01500009           [844] loadk      9   320      ; -1439.9099121094
1503  4150000A           [845] loadk      10  321      ; 10.53750038147
1507  9F000007           [846] setlist    7   2        ; index 1 to 3
150B  01020008           [847] loadk      8   8        ; 30
150F  9F000005           [848] setlist    5   2        ; index 1 to 3
1513  DF000001           [849] setlist    1   3        ; index 1 to 4
1517  00800000           [850] move       0   1      
151B  D41D8000           [851] jmp        120          ; to [972]
151F  05000001           [852] getglobal  1   0        ; GameLocation
1523  99800001           [853] call       1   1   2  
1527  81500002           [854] loadk      2   322      ; 10
152B  95800000           [855] eq         0   1   2    ; to [857] if true
152F  941C8000           [856] jmp        115          ; to [972]
1533  85000001           [857] getglobal  1   2        ; RaceId
1537  99800001           [858] call       1   1   2  
153B  D5BE0000           [859] eq         0   1   251  ; 0, to [861] if true
153F  540D8000           [860] jmp        54           ; to [915]
1543  0A800201           [861] newtable   1   5   0    ; array=5, hash=0
1547  0A800102           [862] newtable   2   3   0    ; array=3, hash=0
154B  C5000003           [863] getglobal  3   3        ; pickup
154F  86BF0103           [864] gettable   3   3   254  ; "racegood"
1553  0A800104           [865] newtable   4   3   0    ; array=3, hash=0
1557  01510005           [866] loadk      5   324      ; -1767.8424072266
155B  81510006           [867] loadk      6   326      ; -785.08459472656
155F  C1510007           [868] loadk      7   327      ; 7.4142999649048
1563  9F000004           [869] setlist    4   2        ; index 1 to 3
1567  01020005           [870] loadk      5   8        ; 30
156B  9F000002           [871] setlist    2   2        ; index 1 to 3
156F  0A800103           [872] newtable   3   3   0    ; array=3, hash=0
1573  C5000004           [873] getglobal  4   3        ; pickup
1577  86410204           [874] gettable   4   4   262  ; "racebad"
157B  0A800105           [875] newtable   5   3   0    ; array=3, hash=0
157F  41520006           [876] loadk      6   329      ; -1829.1787109375
1583  C1520007           [877] loadk      7   331      ; -515.86907958984
1587  01530008           [878] loadk      8   332      ; 14.285099983215
158B  9F000005           [879] setlist    5   2        ; index 1 to 3
158F  01020006           [880] loadk      6   8        ; 30
1593  9F000003           [881] setlist    3   2        ; index 1 to 3
1597  0A800104           [882] newtable   4   3   0    ; array=3, hash=0
159B  C5000005           [883] getglobal  5   3        ; pickup
159F  86BF0205           [884] gettable   5   5   254  ; "racegood"
15A3  0A800106           [885] newtable   6   3   0    ; array=3, hash=0
15A7  81530007           [886] loadk      7   334      ; -1721.4028320313
15AB  01540008           [887] loadk      8   336      ; -313.18301391602
15AF  41540009           [888] loadk      9   337      ; 14.326999664307
15B3  9F000006           [889] setlist    6   2        ; index 1 to 3
15B7  01020007           [890] loadk      7   8        ; 30
15BB  9F000004           [891] setlist    4   2        ; index 1 to 3
15BF  0A800105           [892] newtable   5   3   0    ; array=3, hash=0
15C3  C5000006           [893] getglobal  6   3        ; pickup
15C7  86410306           [894] gettable   6   6   262  ; "racebad"
15CB  0A800107           [895] newtable   7   3   0    ; array=3, hash=0
15CF  C1540008           [896] loadk      8   339      ; -1349.7502441406
15D3  41550009           [897] loadk      9   341      ; -465.67749023438
15D7  8155000A           [898] loadk      10  342      ; 7.4053997993469
15DB  9F000007           [899] setlist    7   2        ; index 1 to 3
15DF  01020008           [900] loadk      8   8        ; 30
15E3  9F000005           [901] setlist    5   2        ; index 1 to 3
15E7  0A800106           [902] newtable   6   3   0    ; array=3, hash=0
15EB  C5000007           [903] getglobal  7   3        ; pickup
15EF  86BF0307           [904] gettable   7   7   254  ; "racegood"
15F3  0A800108           [905] newtable   8   3   0    ; array=3, hash=0
15F7  01560009           [906] loadk      9   344      ; -1255.8331298828
15FB  8156000A           [907] loadk      10  346      ; -685.29278564453
15FF  C156000B           [908] loadk      11  347      ; 14.328800201416
1603  9F000008           [909] setlist    8   2        ; index 1 to 3
1607  01020009           [910] loadk      9   8        ; 30
160B  9F000006           [911] setlist    6   2        ; index 1 to 3
160F  1F010001           [912] setlist    1   4        ; index 1 to 5
1613  00800000           [913] move       0   1      
1617  140E8000           [914] jmp        57           ; to [972]
161B  85000001           [915] getglobal  1   2        ; RaceId
161F  99800001           [916] call       1   1   2  
1623  95C50000           [917] eq         0   1   278  ; 1, to [919] if true
1627  140D8000           [918] jmp        53           ; to [972]
162B  0A800201           [919] newtable   1   5   0    ; array=5, hash=0
162F  0A800102           [920] newtable   2   3   0    ; array=3, hash=0
1633  C5000003           [921] getglobal  3   3        ; pickup
1637  86BF0103           [922] gettable   3   3   254  ; "racegood"
163B  0A800104           [923] newtable   4   3   0    ; array=3, hash=0
163F  41570005           [924] loadk      5   349      ; -1460.7130126953
1643  C1570006           [925] loadk      6   351      ; -317.11291503906
1647  01580007           [926] loadk      7   352      ; 14.32709980011
164B  9F000004           [927] setlist    4   2        ; index 1 to 3
164F  01020005           [928] loadk      5   8        ; 30
1653  9F000002           [929] setlist    2   2        ; index 1 to 3
1657  0A800103           [930] newtable   3   3   0    ; array=3, hash=0
165B  C5000004           [931] getglobal  4   3        ; pickup
165F  86410204           [932] gettable   4   4   262  ; "racebad"
1663  0A800105           [933] newtable   5   3   0    ; array=3, hash=0
1667  81580006           [934] loadk      6   354      ; -1577.0997314453
166B  01590007           [935] loadk      7   356      ; -560.88598632813
166F  41590008           [936] loadk      8   357      ; 7.4074997901917
1673  9F000005           [937] setlist    5   2        ; index 1 to 3
1677  01020006           [938] loadk      6   8        ; 30
167B  9F000003           [939] setlist    3   2        ; index 1 to 3
167F  0A800104           [940] newtable   4   3   0    ; array=3, hash=0
1683  C5000005           [941] getglobal  5   3        ; pickup
1687  86BF0205           [942] gettable   5   5   254  ; "racegood"
168B  0A800106           [943] newtable   6   3   0    ; array=3, hash=0
168F  C1590007           [944] loadk      7   359      ; -1528.5777587891
1693  415A0008           [945] loadk      8   361      ; -626.37982177734
1697  815A0009           [946] loadk      9   362      ; 14.329000473022
169B  9F000006           [947] setlist    6   2        ; index 1 to 3
169F  01020007           [948] loadk      7   8        ; 30
16A3  9F000004           [949] setlist    4   2        ; index 1 to 3
16A7  0A800105           [950] newtable   5   3   0    ; array=3, hash=0
16AB  C5000006           [951] getglobal  6   3        ; pickup
16AF  86410306           [952] gettable   6   6   262  ; "racebad"
16B3  0A800107           [953] newtable   7   3   0    ; array=3, hash=0
16B7  015B0008           [954] loadk      8   364      ; -1761.3618164063
16BB  815B0009           [955] loadk      9   366      ; -785.71929931641
16BF  C15B000A           [956] loadk      10  367      ; 7.415599822998
16C3  9F000007           [957] setlist    7   2        ; index 1 to 3
16C7  01020008           [958] loadk      8   8        ; 30
16CB  9F000005           [959] setlist    5   2        ; index 1 to 3
16CF  0A800106           [960] newtable   6   3   0    ; array=3, hash=0
16D3  C5000007           [961] getglobal  7   3        ; pickup
16D7  86BF0307           [962] gettable   7   7   254  ; "racegood"
16DB  0A800108           [963] newtable   8   3   0    ; array=3, hash=0
16DF  415C0009           [964] loadk      9   369      ; -1829.1707763672
16E3  C15C000A           [965] loadk      10  371      ; -573.84881591797
16E7  015D000B           [966] loadk      11  372      ; 7.9486999511719
16EB  9F000008           [967] setlist    8   2        ; index 1 to 3
16EF  01020009           [968] loadk      9   8        ; 30
16F3  9F000006           [969] setlist    6   2        ; index 1 to 3
16F7  1F010001           [970] setlist    1   4        ; index 1 to 5
16FB  00800000           [971] move       0   1      
16FF  1B000100           [972] return     0   2      
1703  1B800000           [973] return     0   1      
                         ** end of function **

                         * code:
1707  03000000           sizecode (3)
170B  22000000           [1] closure    0   0        ; 0 upvalues
170F  1B000100           [2] return     0   2      
1713  1B800000           [3] return     0   1      
                         ** end of function **

1717                     ** end of chunk **
