Pos   Hex Data           Description or Code
------------------------------------------------------------------------
0000                     ** source chunk: PICKUPSDATA.LUA.LC
                         ** global header start **
0000  1B4C7561           header signature: "\27Lua"
0004  50                 version (major:minor hex digits)
0005  01                 endianness (1=little endian)
0006  04                 size of int (bytes)
0007  04                 size of size_t (bytes)
0008  04                 size of Instruction (bytes)
0009  06                 size of OP (bits)
000A  08                 size of A (bits)
000B  09                 size of B (bits)
000C  09                 size of C (bits)
000D  04                 size of number (bytes)
000E  3BAFEF4B           sample number (single)
                         * chunk platform unrecognized
                         ** global header end **
                         
0012                     ** function [0] definition (level 1)
                         ** start of function **
0012  08000000           string size (8)
0016  3D286E6F6E652900   "=(none)"
                         source name: =(none)
001E  00000000           line defined (0)
0022  00                 nups (0)
0023  00                 numparams (0)
0024  00                 is_vararg (0)
0025  02                 maxstacksize (2)
                         * lines:
0026  00000000           sizelineinfo (0)
                         [pc] (line)
                         * locals:
002A  00000000           sizelocvars (0)
                         * upvalues:
002E  00000000           sizeupvalues (0)
                         * constants:
0032  00000000           sizek (0)
                         * functions:
0036  01000000           sizep (1)
                         
003A                     ** function [0] definition (level 2)
                         ** start of function **
003A  00000000           string size (0)
                         source name: (none)
003E  05000000           line defined (5)
0042  00                 nups (0)
0043  00                 numparams (0)
0044  00                 is_vararg (0)
0045  27                 maxstacksize (39)
                         * lines:
0046  00000000           sizelineinfo (0)
                         [pc] (line)
                         * locals:
004A  00000000           sizelocvars (0)
                         * upvalues:
004E  00000000           sizeupvalues (0)
                         * constants:
0052  6E030000           sizek (878)
0056  04                 const type 4
0057  0D000000           string size (13)
005B  47616D654C6F6361+  "GameLoca"
0063  74696F6E00         "tion\0"
                         const [0]: "GameLocation"
0068  03                 const type 3
0069  00000000           const [1]: (0)
006D  03                 const type 3
006E  0000803F           const [2]: (1)
0072  03                 const type 3
0073  00000040           const [3]: (2)
0077  03                 const type 3
0078  00004040           const [4]: (3)
007C  03                 const type 3
007D  00008040           const [5]: (4)
0081  03                 const type 3
0082  0000A040           const [6]: (5)
0086  04                 const type 4
0087  07000000           string size (7)
008B  7069636B757000     "pickup"
                         const [7]: "pickup"
0092  04                 const type 4
0093  08000000           string size (8)
0097  73686F7467756E00   "shotgun"
                         const [8]: "shotgun"
009F  03                 const type 3
00A0  400CA143           const [9]: (322.095703125)
00A4  03                 const type 3
00A5  2C2A9144           const [10]: (1161.3178710938)
00A9  03                 const type 3
00AA  05A38B41           const [11]: (17.454599380493)
00AE  03                 const type 3
00AF  00002041           const [12]: (10)
00B3  04                 const type 4
00B4  05000000           string size (5)
00B8  7465633900         "tec9"
                         const [13]: "tec9"
00BD  03                 const type 3
00BE  FA16A143           const [14]: (322.17950439453)
00C2  03                 const type 3
00C3  58749C44           const [15]: (1251.6357421875)
00C7  03                 const type 3
00C8  07F08B41           const [16]: (17.49220085144)
00CC  03                 const type 3
00CD  00004842           const [17]: (50)
00D1  04                 const type 4
00D2  05000000           string size (5)
00D6  616B343700         "ak47"
                         const [18]: "ak47"
00DB  03                 const type 3
00DC  F2BAA043           const [19]: (321.46051025391)
00E0  03                 const type 3
00E1  CE849844           const [20]: (1220.1501464844)
00E5  03                 const type 3
00E6  3400B641           const [21]: (22.750099182129)
00EA  04                 const type 4
00EB  07000000           string size (7)
00EF  736E6970657200     "sniper"
                         const [22]: "sniper"
00F6  03                 const type 3
00F7  C1B19A43           const [23]: (309.38870239258)
00FB  03                 const type 3
00FC  08509144           const [24]: (1162.5009765625)
0100  03                 const type 3
0101  C1A8DC41           const [25]: (27.582399368286)
0105  03                 const type 3
0106  D93FF643           const [26]: (492.49880981445)
010A  03                 const type 3
010B  32219C44           const [27]: (1249.0373535156)
010F  03                 const type 3
0110  423E8C41           const [28]: (17.53039932251)
0114  03                 const type 3
0115  F8A3EE43           const [29]: (477.28100585938)
0119  03                 const type 3
011A  1B057B44           const [30]: (1004.0797729492)
011E  03                 const type 3
011F  03899241           const [31]: (18.316900253296)
0123  03                 const type 3
0124  E123A743           const [32]: (334.28030395508)
0128  03                 const type 3
0129  3BDF7944           const [33]: (999.48797607422)
012D  03                 const type 3
012E  0D714A41           const [34]: (12.652600288391)
0132  03                 const type 3
0133  20415143           const [35]: (209.25439453125)
0137  03                 const type 3
0138  E5BA9F44           const [36]: (1277.8404541016)
013C  03                 const type 3
013D  A2459141           const [37]: (18.159000396729)
0141  04                 const type 4
0142  08000000           string size (8)
0146  6D6F6C6F746F7600   "molotov"
                         const [38]: "molotov"
014E  03                 const type 3
014F  AD8E1744           const [39]: (606.22930908203)
0153  03                 const type 3
0154  E19B4E44           const [40]: (826.43560791016)
0158  03                 const type 3
0159  364DB441           const [41]: (22.537700653076)
015D  03                 const type 3
015E  CC0E4C43           const [42]: (204.05780029297)
0162  03                 const type 3
0163  750A2B44           const [43]: (684.16339111328)
0167  03                 const type 3
0168  75934F41           const [44]: (12.97350025177)
016C  04                 const type 4
016D  10000000           string size (16)
0171  726F636B65745F6C+  "rocket_l"
0179  61756E6368657200   "auncher\0"
                         const [45]: "rocket_launcher"
0181  03                 const type 3
0182  981EA643           const [46]: (332.23901367188)
0186  03                 const type 3
0187  7AC53244           const [47]: (715.08557128906)
018B  03                 const type 3
018C  1E16B741           const [48]: (22.885799407959)
0190  04                 const type 4
0191  08000000           string size (8)
0195  6772656E61646500   "grenade"
                         const [49]: "grenade"
019D  03                 const type 3
019E  019EA843           const [50]: (337.23440551758)
01A2  03                 const type 3
01A3  66D65244           const [51]: (843.34997558594)
01A7  03                 const type 3
01A8  567D4F41           const [52]: (12.968099594116)
01AC  03                 const type 3
01AD  5464F743           const [53]: (494.78381347656)
01B1  03                 const type 3
01B2  D6F13844           const [54]: (739.77868652344)
01B6  03                 const type 3
01B7  FB5C3641           const [55]: (11.397700309753)
01BB  04                 const type 4
01BC  08000000           string size (8)
01C0  676C6F636B313700   "glock17"
                         const [56]: "glock17"
01C8  03                 const type 3
01C9  6927F643           const [57]: (492.3078918457)
01CD  03                 const type 3
01CE  BBCB6344           const [58]: (911.18328857422)
01D2  03                 const type 3
01D3  EA046C41           const [59]: (14.75119972229)
01D7  03                 const type 3
01D8  0000F041           const [60]: (30)
01DC  04                 const type 4
01DD  0C000000           string size (12)
01E1  6465745F6772656E+  "det_gren"
01E9  61646500           "ade\0"
                         const [61]: "det_grenade"
01ED  03                 const type 3
01EE  7E1D3D42           const [62]: (47.278800964355)
01F2  03                 const type 3
01F3  70F66B44           const [63]: (943.8505859375)
01F7  03                 const type 3
01F8  29CB2E41           const [64]: (10.924599647522)
01FC  03                 const type 3
01FD  DCE69542           const [65]: (74.950897216797)
0201  03                 const type 3
0202  EE458744           const [66]: (1082.1853027344)
0206  03                 const type 3
0207  25868341           const [67]: (16.440500259399)
020B  03                 const type 3
020C  F2419841           const [68]: (19.032199859619)
0210  03                 const type 3
0211  97698E44           const [69]: (1139.2996826172)
0215  03                 const type 3
0216  B1E19B41           const [70]: (19.485200881958)
021A  03                 const type 3
021B  7FEA4B42           const [71]: (50.979000091553)
021F  03                 const type 3
0220  7FEA4BC2           const [72]: (-50.979000091553)
0224  03                 const type 3
0225  39958D44           const [73]: (1132.6632080078)
0229  03                 const type 3
022A  F0A78841           const [74]: (17.082000732422)
022E  03                 const type 3
022F  5B3D0E44           const [75]: (568.95867919922)
0233  03                 const type 3
0234  1D862444           const [76]: (658.09552001953)
0238  03                 const type 3
0239  A52C5141           const [77]: (13.073399543762)
023D  03                 const type 3
023E  C1D1D943           const [78]: (435.63870239258)
0242  03                 const type 3
0243  34EE1244           const [79]: (587.72192382813)
0247  03                 const type 3
0248  C1A84241           const [80]: (12.166199684143)
024C  03                 const type 3
024D  5DE80D44           const [81]: (567.63067626953)
0251  03                 const type 3
0252  381C1244           const [82]: (584.44091796875)
0256  03                 const type 3
0257  0C024141           const [83]: (12.062999725342)
025B  03                 const type 3
025C  F260FE43           const [84]: (508.75738525391)
0260  03                 const type 3
0261  744DFD43           const [85]: (506.60510253906)
0265  03                 const type 3
0266  D42B3541           const [86]: (11.32320022583)
026A  03                 const type 3
026B  BDB3BD43           const [87]: (379.40420532227)
026F  03                 const type 3
0270  20B98E43           const [88]: (285.4462890625)
0274  03                 const type 3
0275  228E3C41           const [89]: (11.784700393677)
0279  03                 const type 3
027A  F30FEF43           const [90]: (478.12460327148)
027E  03                 const type 3
027F  1177C843           const [91]: (400.93020629883)
0283  03                 const type 3
0284  9D803A41           const [92]: (11.656399726868)
0288  03                 const type 3
0289  F4AC0644           const [93]: (538.70239257813)
028D  03                 const type 3
028E  823B8943           const [94]: (274.46490478516)
0292  03                 const type 3
0293  74461B41           const [95]: (9.7047004699707)
0297  03                 const type 3
0298  5F01D943           const [96]: (434.01071166992)
029C  03                 const type 3
029D  19A25C43           const [97]: (220.63319396973)
02A1  03                 const type 3
02A2  77BE3F41           const [98]: (11.984000205994)
02A6  03                 const type 3
02A7  468C9B43           const [99]: (311.09588623047)
02AB  03                 const type 3
02AC  CE69BF43           const [100]: (382.82659912109)
02B0  03                 const type 3
02B1  1C7C5341           const [101]: (13.217800140381)
02B5  03                 const type 3
02B6  C2F6CC43           const [102]: (409.92779541016)
02BA  03                 const type 3
02BB  1372C642           const [103]: (99.222801208496)
02BF  03                 const type 3
02C0  CC5D3641           const [104]: (11.397899627686)
02C4  03                 const type 3
02C5  DB250644           const [105]: (536.59149169922)
02C9  03                 const type 3
02CA  C67CB742           const [106]: (91.743698120117)
02CE  03                 const type 3
02CF  62103341           const [107]: (11.191499710083)
02D3  03                 const type 3
02D4  48B12A43           const [108]: (170.69250488281)
02D8  03                 const type 3
02D9  E79C6C43           const [109]: (236.61289978027)
02DD  03                 const type 3
02DE  7DAE3E41           const [110]: (11.91759967804)
02E2  03                 const type 3
02E3  75423643           const [111]: (182.25959777832)
02E7  03                 const type 3
02E8  7E0C8C41           const [112]: (17.506099700928)
02EC  03                 const type 3
02ED  508DFB40           const [113]: (7.8610000610352)
02F1  03                 const type 3
02F2  32159D42           const [114]: (78.541397094727)
02F6  03                 const type 3
02F7  67D49743           const [115]: (303.65939331055)
02FB  03                 const type 3
02FC  EEFCA441           const [116]: (20.623500823975)
0300  03                 const type 3
0301  7DF0E543           const [117]: (459.87881469727)
0305  03                 const type 3
0306  62E11442           const [118]: (37.220100402832)
030A  03                 const type 3
030B  62E114C2           const [119]: (-37.220100402832)
030F  03                 const type 3
0310  BDE32341           const [120]: (10.243100166321)
0314  03                 const type 3
0315  B19F0C44           const [121]: (562.49517822266)
0319  03                 const type 3
031A  07D0B242           const [122]: (89.406303405762)
031E  03                 const type 3
031F  07D0B2C2           const [123]: (-89.406303405762)
0323  03                 const type 3
0324  6E341741           const [124]: (9.4503002166748)
0328  03                 const type 3
0329  E33EE243           const [125]: (452.49130249023)
032D  03                 const type 3
032E  42588043           const [126]: (256.68951416016)
0332  03                 const type 3
0333  425880C3           const [127]: (-256.68951416016)
0337  03                 const type 3
0338  6FF03C41           const [128]: (11.808699607849)
033C  03                 const type 3
033D  C0B71C44           const [129]: (626.87109375)
0341  03                 const type 3
0342  C3B46543           const [130]: (229.70610046387)
0346  03                 const type 3
0347  C3B465C3           const [131]: (-229.70610046387)
034B  03                 const type 3
034C  75939A41           const [132]: (19.32200050354)
0350  03                 const type 3
0351  854CB443           const [133]: (360.59780883789)
0355  03                 const type 3
0356  E2D8C841           const [134]: (25.105899810791)
035A  03                 const type 3
035B  E2D8C8C1           const [135]: (-25.105899810791)
035F  03                 const type 3
0360  1C7C2541           const [136]: (10.342800140381)
0364  03                 const type 3
0365  1ED7B343           const [137]: (359.68060302734)
0369  03                 const type 3
036A  0B267C43           const [138]: (252.14860534668)
036E  03                 const type 3
036F  0B267CC3           const [139]: (-252.14860534668)
0373  03                 const type 3
0374  BA493641           const [140]: (11.392999649048)
0378  03                 const type 3
0379  14578143           const [141]: (258.68029785156)
037D  03                 const type 3
037E  DEDACF43           const [142]: (415.70989990234)
0382  03                 const type 3
0383  DEDACFC3           const [143]: (-415.70989990234)
0387  03                 const type 3
0388  07F03341           const [144]: (11.24610042572)
038C  03                 const type 3
038D  7BC41C43           const [145]: (156.76750183105)
0391  03                 const type 3
0392  9EEEFB43           const [146]: (503.86419677734)
0396  03                 const type 3
0397  9EEEFBC3           const [147]: (-503.86419677734)
039B  03                 const type 3
039C  69005B41           const [148]: (13.687600135803)
03A0  03                 const type 3
03A1  83E0BC42           const [149]: (94.438499450684)
03A5  03                 const type 3
03A6  75FB1144           const [150]: (583.92901611328)
03AA  03                 const type 3
03AB  75FB11C4           const [151]: (-583.92901611328)
03AF  03                 const type 3
03B0  37895B41           const [152]: (13.720999717712)
03B4  03                 const type 3
03B5  4D738E42           const [153]: (71.225196838379)
03B9  03                 const type 3
03BA  DC909743           const [154]: (303.13171386719)
03BE  03                 const type 3
03BF  DC9097C3           const [155]: (-303.13171386719)
03C3  03                 const type 3
03C4  47724641           const [156]: (12.402899742126)
03C8  03                 const type 3
03C9  66A8B043           const [157]: (353.31561279297)
03CD  03                 const type 3
03CE  66A8B0C3           const [158]: (-353.31561279297)
03D2  03                 const type 3
03D3  2C45D143           const [159]: (418.54040527344)
03D7  03                 const type 3
03D8  2C45D1C3           const [160]: (-418.54040527344)
03DC  03                 const type 3
03DD  E5611C41           const [161]: (9.7739000320435)
03E1  03                 const type 3
03E2  C30BBD43           const [162]: (378.09188842773)
03E6  03                 const type 3
03E7  C30BBDC3           const [163]: (-378.09188842773)
03EB  03                 const type 3
03EC  5E238E43           const [164]: (284.27630615234)
03F0  03                 const type 3
03F1  5E238EC3           const [165]: (-284.27630615234)
03F5  03                 const type 3
03F6  F31F2B41           const [166]: (10.695300102234)
03FA  03                 const type 3
03FB  56E91044           const [167]: (579.64587402344)
03FF  03                 const type 3
0400  56E910C4           const [168]: (-579.64587402344)
0404  03                 const type 3
0405  40EBD143           const [169]: (419.837890625)
0409  03                 const type 3
040A  40EBD1C3           const [170]: (-419.837890625)
040E  03                 const type 3
040F  33C49E41           const [171]: (19.84580039978)
0413  03                 const type 3
0414  D2371C44           const [172]: (624.87219238281)
0418  03                 const type 3
0419  D2371CC4           const [173]: (-624.87219238281)
041D  03                 const type 3
041E  F09D0A44           const [174]: (554.4677734375)
0422  03                 const type 3
0423  F09D0AC4           const [175]: (-554.4677734375)
0427  03                 const type 3
0428  228E2641           const [176]: (10.409700393677)
042C  03                 const type 3
042D  EEC3E743           const [177]: (463.53070068359)
0431  03                 const type 3
0432  EEC3E7C3           const [178]: (-463.53070068359)
0436  03                 const type 3
0437  2DAD0F44           const [179]: (574.70587158203)
043B  03                 const type 3
043C  2DAD0FC4           const [180]: (-574.70587158203)
0440  03                 const type 3
0441  36AB4841           const [181]: (12.541799545288)
0445  03                 const type 3
0446  C5B89743           const [182]: (303.44351196289)
044A  03                 const type 3
044B  C5B897C3           const [183]: (-303.44351196289)
044F  03                 const type 3
0450  ED921644           const [184]: (602.29571533203)
0454  03                 const type 3
0455  ED9216C4           const [185]: (-602.29571533203)
0459  03                 const type 3
045A  AB3E4D41           const [186]: (12.827799797058)
045E  03                 const type 3
045F  D2BF3F43           const [187]: (191.7492980957)
0463  03                 const type 3
0464  D2BF3FC3           const [188]: (-191.7492980957)
0468  03                 const type 3
0469  439CFF43           const [189]: (511.22079467773)
046D  03                 const type 3
046E  439CFFC3           const [190]: (-511.22079467773)
0472  03                 const type 3
0473  DC464D41           const [191]: (12.8297996521)
0477  03                 const type 3
0478  4D54C943           const [192]: (402.65859985352)
047C  03                 const type 3
047D  ECB9E743           const [193]: (463.45251464844)
0481  03                 const type 3
0482  ECB9E7C3           const [194]: (-463.45251464844)
0486  03                 const type 3
0487  5DDC2141           const [195]: (10.116299629211)
048B  03                 const type 3
048C  C9268C43           const [196]: (280.3030090332)
0490  03                 const type 3
0491  4F701744           const [197]: (605.75482177734)
0495  03                 const type 3
0496  4F7017C4           const [198]: (-605.75482177734)
049A  03                 const type 3
049B  2E902141           const [199]: (10.097700119019)
049F  03                 const type 3
04A0  26A4C742           const [200]: (99.820602416992)
04A4  03                 const type 3
04A5  C7F74944           const [201]: (807.87152099609)
04A9  03                 const type 3
04AA  C7F749C4           const [202]: (-807.87152099609)
04AE  03                 const type 3
04AF  EC512741           const [203]: (10.457500457764)
04B3  03                 const type 3
04B4  B6338A43           const [204]: (276.40399169922)
04B8  03                 const type 3
04B9  BE814844           const [205]: (802.02722167969)
04BD  03                 const type 3
04BE  BE8148C4           const [206]: (-802.02722167969)
04C2  03                 const type 3
04C3  E0BE2241           const [207]: (10.171600341797)
04C7  03                 const type 3
04C8  0D2C0844           const [208]: (544.68829345703)
04CC  03                 const type 3
04CD  F74DD643           const [209]: (428.6091003418)
04D1  03                 const type 3
04D2  F74DD6C3           const [210]: (-428.6091003418)
04D6  03                 const type 3
04D7  34113141           const [211]: (11.066699981689)
04DB  03                 const type 3
04DC  3DDAC843           const [212]: (401.70498657227)
04E0  03                 const type 3
04E1  3BDD2944           const [213]: (679.45672607422)
04E5  03                 const type 3
04E6  3BDD29C4           const [214]: (-679.45672607422)
04EA  03                 const type 3
04EB  9D113141           const [215]: (11.066800117493)
04EF  03                 const type 3
04F0  5849E143           const [216]: (450.57299804688)
04F4  03                 const type 3
04F5  013E1444           const [217]: (592.96881103516)
04F9  03                 const type 3
04FA  013E14C4           const [218]: (-592.96881103516)
04FE  03                 const type 3
04FF  DC464041           const [219]: (12.0172996521)
0503  03                 const type 3
0504  A8167B43           const [220]: (251.08850097656)
0508  03                 const type 3
0509  DB6E9244           const [221]: (1171.4642333984)
050D  03                 const type 3
050E  DB6E92C4           const [222]: (-1171.4642333984)
0512  03                 const type 3
0513  832F4141           const [223]: (12.07409954071)
0517  03                 const type 3
0518  C3747E43           const [224]: (254.45610046387)
051C  03                 const type 3
051D  3B857344           const [225]: (974.08172607422)
0521  03                 const type 3
0522  3B8573C4           const [226]: (-974.08172607422)
0526  03                 const type 3
0527  88852941           const [227]: (10.595100402832)
052B  03                 const type 3
052C  F1D34F43           const [228]: (207.82789611816)
0530  03                 const type 3
0531  2685AE44           const [229]: (1396.1608886719)
0535  03                 const type 3
0536  2685AEC4           const [230]: (-1396.1608886719)
053A  03                 const type 3
053B  B8CF9F42           const [231]: (79.905700683594)
053F  03                 const type 3
0540  55C0BF44           const [232]: (1534.0103759766)
0544  03                 const type 3
0545  55C0BFC4           const [233]: (-1534.0103759766)
0549  03                 const type 3
054A  D8813941           const [234]: (11.594200134277)
054E  03                 const type 3
054F  41F14342           const [235]: (48.985599517822)
0553  03                 const type 3
0554  0E8F7444           const [236]: (978.23522949219)
0558  03                 const type 3
0559  0E8F74C4           const [237]: (-978.23522949219)
055D  03                 const type 3
055E  C6DC1F41           const [238]: (9.9913997650146)
0562  03                 const type 3
0563  90C0D742           const [239]: (107.87609863281)
0567  03                 const type 3
0568  90C0D7C2           const [240]: (-107.87609863281)
056C  03                 const type 3
056D  E6DF7344           const [241]: (975.49841308594)
0571  03                 const type 3
0572  E6DF73C4           const [242]: (-975.49841308594)
0576  03                 const type 3
0577  8C4A2741           const [243]: (10.455699920654)
057B  03                 const type 3
057C  4A2C4B43           const [244]: (203.17300415039)
0580  03                 const type 3
0581  4A2C4BC3           const [245]: (-203.17300415039)
0585  03                 const type 3
0586  92688944           const [246]: (1099.2678222656)
058A  03                 const type 3
058B  926889C4           const [247]: (-1099.2678222656)
058F  03                 const type 3
0590  ADFA6041           const [248]: (14.061200141907)
0594  03                 const type 3
0595  27E22B43           const [249]: (171.88340759277)
0599  03                 const type 3
059A  27E22BC3           const [250]: (-171.88340759277)
059E  03                 const type 3
059F  4F43A044           const [251]: (1282.1033935547)
05A3  03                 const type 3
05A4  4F43A0C4           const [252]: (-1282.1033935547)
05A8  03                 const type 3
05A9  D5782741           const [253]: (10.467000007629)
05AD  03                 const type 3
05AE  A43F9042           const [254]: (72.124298095703)
05B2  03                 const type 3
05B3  A43F90C2           const [255]: (-72.124298095703)
05B7  03                 const type 3
05B8  E56BC044           const [256]: (1539.3717041016)
05BC  03                 const type 3
05BD  E56BC0C4           const [257]: (-1539.3717041016)
05C1  03                 const type 3
05C2  E9482741           const [258]: (10.455300331116)
05C6  03                 const type 3
05C7  5C8F6941           const [259]: (14.597499847412)
05CB  03                 const type 3
05CC  1A6DAD44           const [260]: (1387.4094238281)
05D0  03                 const type 3
05D1  1A6DADC4           const [261]: (-1387.4094238281)
05D5  03                 const type 3
05D6  516B2741           const [262]: (10.463700294495)
05DA  03                 const type 3
05DB  1B2F0541           const [263]: (8.3240003585815)
05DF  03                 const type 3
05E0  492E9244           const [264]: (1169.4464111328)
05E4  03                 const type 3
05E5  492E92C4           const [265]: (-1169.4464111328)
05E9  03                 const type 3
05EA  6D562741           const [266]: (10.45860004425)
05EE  03                 const type 3
05EF  7DDF1843           const [267]: (152.87300109863)
05F3  03                 const type 3
05F4  E7B88F44           const [268]: (1149.7781982422)
05F8  03                 const type 3
05F9  E7B88FC4           const [269]: (-1149.7781982422)
05FD  03                 const type 3
05FE  9487FA41           const [270]: (31.316200256348)
0602  03                 const type 3
0603  C4C28C43           const [271]: (281.52160644531)
0607  03                 const type 3
0608  0471BF44           const [272]: (1531.5317382813)
060C  03                 const type 3
060D  0471BFC4           const [273]: (-1531.5317382813)
0611  03                 const type 3
0612  B5153541           const [274]: (11.317799568176)
0616  04                 const type 4
0617  07000000           string size (7)
061B  6865616C746800     "health"
                         const [275]: "health"
0622  03                 const type 3
0623  F56BA843           const [276]: (336.84341430664)
0627  03                 const type 3
0628  626C8C44           const [277]: (1123.3869628906)
062C  03                 const type 3
062D  CA329241           const [278]: (18.274799346924)
0631  03                 const type 3
0632  3481F343           const [279]: (487.00939941406)
0636  03                 const type 3
0637  DD878C44           const [280]: (1124.2457275391)
063B  03                 const type 3
063C  B9FC8241           const [281]: (16.373399734497)
0640  03                 const type 3
0641  220DCF43           const [282]: (414.10260009766)
0645  03                 const type 3
0646  4EDB9844           const [283]: (1222.8532714844)
064A  03                 const type 3
064B  94879341           const [284]: (18.441200256348)
064F  03                 const type 3
0650  7FFACF43           const [285]: (415.95700073242)
0654  03                 const type 3
0655  E9708044           const [286]: (1027.5284423828)
0659  03                 const type 3
065A  1FC81144           const [287]: (583.12689208984)
065E  03                 const type 3
065F  25C25644           const [288]: (859.03350830078)
0663  03                 const type 3
0664  32779741           const [289]: (18.933200836182)
0668  03                 const type 3
0669  0EC69343           const [290]: (295.54730224609)
066D  03                 const type 3
066E  BA0E3D44           const [291]: (756.23010253906)
0672  03                 const type 3
0673  492E4F41           const [292]: (12.948800086975)
0677  03                 const type 3
0678  F77CF043           const [293]: (480.9762878418)
067C  03                 const type 3
067D  2C343144           const [294]: (708.81518554688)
0681  03                 const type 3
0682  4C37CD40           const [295]: (6.4130001068115)
0686  03                 const type 3
0687  A4C88444           const [296]: (1062.2700195313)
068B  03                 const type 3
068C  BDE34341           const [297]: (12.243100166321)
0690  03                 const type 3
0691  AFD10D44           const [298]: (567.27630615234)
0695  03                 const type 3
0696  FE990444           const [299]: (530.40612792969)
069A  03                 const type 3
069B  9C549643           const [300]: (300.66101074219)
069F  03                 const type 3
06A0  D3C5E143           const [301]: (451.54550170898)
06A4  03                 const type 3
06A5  B0722741           const [302]: (10.46549987793)
06A9  03                 const type 3
06AA  9F8DA843           const [303]: (337.10641479492)
06AE  03                 const type 3
06AF  E68E1A43           const [304]: (154.55819702148)
06B3  03                 const type 3
06B4  295C3641           const [305]: (11.397500038147)
06B8  03                 const type 3
06B9  4D230344           const [306]: (524.55157470703)
06BD  03                 const type 3
06BE  24473A43           const [307]: (186.27789306641)
06C2  03                 const type 3
06C3  81046841           const [308]: (14.501099586487)
06C7  03                 const type 3
06C8  F842C742           const [309]: (99.630798339844)
06CC  03                 const type 3
06CD  64AD7F43           const [310]: (255.67730712891)
06D1  03                 const type 3
06D2  E01CAE41           const [311]: (21.764099121094)
06D6  03                 const type 3
06D7  5EFAF843           const [312]: (497.95599365234)
06DB  03                 const type 3
06DC  8C59A942           const [313]: (84.674896240234)
06E0  03                 const type 3
06E1  8C59A9C2           const [314]: (-84.674896240234)
06E5  03                 const type 3
06E6  C2862041           const [315]: (10.032899856567)
06EA  03                 const type 3
06EB  C1594843           const [316]: (200.35060119629)
06EF  03                 const type 3
06F0  986DF643           const [317]: (492.85620117188)
06F4  03                 const type 3
06F5  986DF6C3           const [318]: (-492.85620117188)
06F9  03                 const type 3
06FA  60763741           const [319]: (11.466400146484)
06FE  03                 const type 3
06FF  A2050C43           const [320]: (140.02200317383)
0703  03                 const type 3
0704  4616B543           const [321]: (362.17401123047)
0708  03                 const type 3
0709  4616B5C3           const [322]: (-362.17401123047)
070D  03                 const type 3
070E  E5F23841           const [323]: (11.559300422668)
0712  03                 const type 3
0713  5103BD43           const [324]: (378.02590942383)
0717  03                 const type 3
0718  5103BDC3           const [325]: (-378.02590942383)
071C  03                 const type 3
071D  00E9AC43           const [326]: (345.8203125)
0721  03                 const type 3
0722  00E9ACC3           const [327]: (-345.8203125)
0726  03                 const type 3
0727  31993141           const [328]: (11.099900245667)
072B  03                 const type 3
072C  6BEE0C44           const [329]: (563.72528076172)
0730  03                 const type 3
0731  6BEE0CC4           const [330]: (-563.72528076172)
0735  03                 const type 3
0736  19270944           const [331]: (548.61090087891)
073A  03                 const type 3
073B  192709C4           const [332]: (-548.61090087891)
073F  03                 const type 3
0740  FFB24741           const [333]: (12.481200218201)
0744  03                 const type 3
0745  E01D8243           const [334]: (260.2333984375)
0749  03                 const type 3
074A  A8D13A44           const [335]: (747.27587890625)
074E  03                 const type 3
074F  A8D13AC4           const [336]: (-747.27587890625)
0753  03                 const type 3
0754  AD692241           const [337]: (10.150799751282)
0758  03                 const type 3
0759  D2640144           const [338]: (517.57531738281)
075D  03                 const type 3
075E  FF021344           const [339]: (588.04681396484)
0762  03                 const type 3
0763  FF0213C4           const [340]: (-588.04681396484)
0767  03                 const type 3
0768  4A0C3141           const [341]: (11.065500259399)
076C  03                 const type 3
076D  05D36243           const [342]: (226.82429504395)
0771  03                 const type 3
0772  78868E44           const [343]: (1140.2021484375)
0776  03                 const type 3
0777  78868EC4           const [344]: (-1140.2021484375)
077B  03                 const type 3
077C  098A2C41           const [345]: (10.783699989319)
0780  03                 const type 3
0781  5DBE3F43           const [346]: (191.74360656738)
0785  03                 const type 3
0786  BB34C544           const [347]: (1577.6478271484)
078A  03                 const type 3
078B  BB34C5C4           const [348]: (-1577.6478271484)
078F  03                 const type 3
0790  6A4D2E41           const [349]: (10.893899917603)
0794  03                 const type 3
0795  11C7BC41           const [350]: (23.597200393677)
0799  03                 const type 3
079A  11C7BCC1           const [351]: (-23.597200393677)
079E  03                 const type 3
079F  FD86BD44           const [352]: (1516.2183837891)
07A3  03                 const type 3
07A4  FD86BDC4           const [353]: (-1516.2183837891)
07A8  03                 const type 3
07A9  17482741           const [354]: (10.455100059509)
07AD  03                 const type 3
07AE  705E6A43           const [355]: (234.36889648438)
07B2  03                 const type 3
07B3  705E6AC3           const [356]: (-234.36889648438)
07B7  03                 const type 3
07B8  11A8A244           const [357]: (1301.2520751953)
07BC  03                 const type 3
07BD  11A8A2C4           const [358]: (-1301.2520751953)
07C1  03                 const type 3
07C2  89D21141           const [359]: (9.1139001846313)
07C6  03                 const type 3
07C7  BD230543           const [360]: (133.13960266113)
07CB  03                 const type 3
07CC  BD2305C3           const [361]: (-133.13960266113)
07D0  03                 const type 3
07D1  FD767544           const [362]: (981.85919189453)
07D5  03                 const type 3
07D6  FD7675C4           const [363]: (-981.85919189453)
07DA  03                 const type 3
07DB  3191B743           const [364]: (367.13430786133)
07DF  03                 const type 3
07E0  29E47644           const [365]: (987.56500244141)
07E4  03                 const type 3
07E5  29E476C4           const [366]: (-987.56500244141)
07E9  03                 const type 3
07EA  4D153141           const [367]: (11.067700386047)
07EE  03                 const type 3
07EF  CD3BE742           const [368]: (115.61679840088)
07F3  03                 const type 3
07F4  9A1AA444           const [369]: (1312.8312988281)
07F8  03                 const type 3
07F9  9A1AA4C4           const [370]: (-1312.8312988281)
07FD  03                 const type 3
07FE  34118E40           const [371]: (4.4395999908447)
0802  03                 const type 3
0803  287E3442           const [372]: (45.123199462891)
0807  03                 const type 3
0808  488C5444           const [373]: (850.19189453125)
080C  03                 const type 3
080D  488C54C4           const [374]: (-850.19189453125)
0811  03                 const type 3
0812  925C2741           const [375]: (10.46010017395)
0816  03                 const type 3
0817  6795D642           const [376]: (107.29180145264)
081B  03                 const type 3
081C  6795D6C2           const [377]: (-107.29180145264)
0820  03                 const type 3
0821  D35FC944           const [378]: (1610.9945068359)
0825  03                 const type 3
0826  D35FC9C4           const [379]: (-1610.9945068359)
082A  03                 const type 3
082B  0AD72241           const [380]: (10.177499771118)
082F  04                 const type 4
0830  07000000           string size (7)
0834  61726D6F757200     "armour"
                         const [381]: "armour"
083B  03                 const type 3
083C  338B0C44           const [382]: (562.17498779297)
0840  03                 const type 3
0841  F7BFA144           const [383]: (1293.9989013672)
0845  03                 const type 3
0846  FCA98541           const [384]: (16.708000183105)
084A  03                 const type 3
084B  E9AE9343           const [385]: (295.3664855957)
084F  03                 const type 3
0850  B2796F44           const [386]: (957.90148925781)
0854  03                 const type 3
0855  D42B3841           const [387]: (11.51070022583)
0859  03                 const type 3
085A  6AF21444           const [388]: (595.78771972656)
085E  03                 const type 3
085F  09A62F44           const [389]: (702.59429931641)
0863  03                 const type 3
0864  7D3F4841           const [390]: (12.515500068665)
0868  03                 const type 3
0869  10CC1044           const [391]: (579.1884765625)
086D  03                 const type 3
086E  E396B343           const [392]: (359.17880249023)
0872  03                 const type 3
0873  21308841           const [393]: (17.023500442505)
0877  03                 const type 3
0878  9AA8FF42           const [394]: (127.82929992676)
087C  03                 const type 3
087D  4D53AB43           const [395]: (342.65078735352)
0881  03                 const type 3
0882  0E2D9941           const [396]: (19.146999359131)
0886  03                 const type 3
0887  11EF0844           const [397]: (547.73541259766)
088B  03                 const type 3
088C  2497FF3E           const [398]: (0.49919998645782)
0890  03                 const type 3
0891  CD3B6041           const [399]: (14.01459980011)
0895  03                 const type 3
0896  5EC30E44           const [400]: (571.05261230469)
089A  03                 const type 3
089B  AA7A8043           const [401]: (256.95831298828)
089F  03                 const type 3
08A0  AA7A80C3           const [402]: (-256.95831298828)
08A4  03                 const type 3
08A5  68915F41           const [403]: (13.972999572754)
08A9  03                 const type 3
08AA  FC29A842           const [404]: (84.082000732422)
08AE  03                 const type 3
08AF  48C70A44           const [405]: (555.11376953125)
08B3  03                 const type 3
08B4  48C70AC4           const [406]: (-555.11376953125)
08B8  03                 const type 3
08B9  23DB6F41           const [407]: (14.991000175476)
08BD  03                 const type 3
08BE  0EDFBA43           const [408]: (373.74261474609)
08C2  03                 const type 3
08C3  0EDFBAC3           const [409]: (-373.74261474609)
08C7  03                 const type 3
08C8  FDD65F43           const [410]: (223.83979797363)
08CC  03                 const type 3
08CD  FDD65FC3           const [411]: (-223.83979797363)
08D1  03                 const type 3
08D2  D8F01141           const [412]: (9.1212997436523)
08D6  03                 const type 3
08D7  CF362244           const [413]: (648.85638427734)
08DB  03                 const type 3
08DC  CF3622C4           const [414]: (-648.85638427734)
08E0  03                 const type 3
08E1  80878743           const [415]: (271.05859375)
08E5  03                 const type 3
08E6  808787C3           const [416]: (-271.05859375)
08EA  03                 const type 3
08EB  7DAE1841           const [417]: (9.5425996780396)
08EF  03                 const type 3
08F0  859C9642           const [418]: (75.305702209473)
08F4  03                 const type 3
08F5  80F45A44           const [419]: (875.8203125)
08F9  03                 const type 3
08FA  80F45AC4           const [420]: (-875.8203125)
08FE  03                 const type 3
08FF  8CDB2641           const [421]: (10.428600311279)
0903  03                 const type 3
0904  F2E8DF43           const [422]: (447.81988525391)
0908  03                 const type 3
0909  59FFF843           const [423]: (497.99490356445)
090D  03                 const type 3
090E  59FFF8C3           const [424]: (-497.99490356445)
0912  03                 const type 3
0913  167B9141           const [425]: (18.18510055542)
0917  03                 const type 3
0918  119ED343           const [426]: (423.23489379883)
091C  03                 const type 3
091D  FBCC3F44           const [427]: (767.20281982422)
0921  03                 const type 3
0922  FBCC3FC4           const [428]: (-767.20281982422)
0926  03                 const type 3
0927  E9263141           const [429]: (11.071999549866)
092B  03                 const type 3
092C  96B17C43           const [430]: (252.69369506836)
0930  03                 const type 3
0931  39F58544           const [431]: (1071.6632080078)
0935  03                 const type 3
0936  39F585C4           const [432]: (-1071.6632080078)
093A  03                 const type 3
093B  11363141           const [433]: (11.075699806213)
093F  03                 const type 3
0940  83603C43           const [434]: (188.37699890137)
0944  03                 const type 3
0945  83603CC3           const [435]: (-188.37699890137)
0949  03                 const type 3
094A  88777544           const [436]: (981.86767578125)
094E  03                 const type 3
094F  887775C4           const [437]: (-981.86767578125)
0953  03                 const type 3
0954  4BC83541           const [438]: (11.361399650574)
0958  03                 const type 3
0959  83AFA441           const [439]: (20.585699081421)
095D  03                 const type 3
095E  E406A244           const [440]: (1296.2153320313)
0962  03                 const type 3
0963  E406A2C4           const [441]: (-1296.2153320313)
0967  03                 const type 3
0968  FAED4F41           const [442]: (12.995599746704)
096C  03                 const type 3
096D  95E5FE41           const [443]: (31.862100601196)
0971  03                 const type 3
0972  1807C044           const [444]: (1536.2216796875)
0976  03                 const type 3
0977  1807C0C4           const [445]: (-1536.2216796875)
097B  03                 const type 3
097C  18262741           const [446]: (10.446800231934)
0980  03                 const type 3
0981  E026BC43           const [447]: (376.3037109375)
0985  03                 const type 3
0986  EDC0C544           const [448]: (1582.0289306641)
098A  03                 const type 3
098B  EDC0C5C4           const [449]: (-1582.0289306641)
098F  03                 const type 3
0990  55418A41           const [450]: (17.281900405884)
0994  03                 const type 3
0995  0000C040           const [451]: (6)
0999  03                 const type 3
099A  0000E040           const [452]: (7)
099E  03                 const type 3
099F  00000041           const [453]: (8)
09A3  03                 const type 3
09A4  00001041           const [454]: (9)
09A8  03                 const type 3
09A9  00003041           const [455]: (11)
09AD  03                 const type 3
09AE  A3CB8944           const [456]: (1102.3636474609)
09B2  03                 const type 3
09B3  A3CB89C4           const [457]: (-1102.3636474609)
09B7  03                 const type 3
09B8  8A2EA144           const [458]: (1289.4543457031)
09BC  03                 const type 3
09BD  FBCB9541           const [459]: (18.724599838257)
09C1  03                 const type 3
09C2  50C88944           const [460]: (1102.259765625)
09C6  03                 const type 3
09C7  50C889C4           const [461]: (-1102.259765625)
09CB  03                 const type 3
09CC  8499AB44           const [462]: (1372.7973632813)
09D0  03                 const type 3
09D1  BFC96144           const [463]: (903.15228271484)
09D5  03                 const type 3
09D6  BFC961C4           const [464]: (-903.15228271484)
09DA  03                 const type 3
09DB  77B6B944           const [465]: (1485.7020263672)
09DF  03                 const type 3
09E0  5C204041           const [466]: (12.007900238037)
09E4  03                 const type 3
09E5  3D683D44           const [467]: (757.62872314453)
09E9  03                 const type 3
09EA  3D683DC4           const [468]: (-757.62872314453)
09EE  03                 const type 3
09EF  57EEA644           const [469]: (1335.4481201172)
09F3  03                 const type 3
09F4  234A3C41           const [470]: (11.768099784851)
09F8  03                 const type 3
09F9  FB563F44           const [471]: (765.35906982422)
09FD  03                 const type 3
09FE  FB563FC4           const [472]: (-765.35906982422)
0A02  03                 const type 3
0A03  00689E44           const [473]: (1267.25)
0A07  03                 const type 3
0A08  46B63941           const [474]: (11.607000350952)
0A0C  03                 const type 3
0A0D  8AC41744           const [475]: (607.07092285156)
0A11  03                 const type 3
0A12  8AC417C4           const [476]: (-607.07092285156)
0A16  03                 const type 3
0A17  1AB9A144           const [477]: (1293.7844238281)
0A1B  03                 const type 3
0A1C  0E4F3C41           const [478]: (11.769300460815)
0A20  03                 const type 3
0A21  6900E043           const [479]: (448.0032043457)
0A25  03                 const type 3
0A26  6900E0C3           const [480]: (-448.0032043457)
0A2A  03                 const type 3
0A2B  C1E49E44           const [481]: (1271.1485595703)
0A2F  03                 const type 3
0A30  166A2E41           const [482]: (10.900899887085)
0A34  03                 const type 3
0A35  E4FCBB43           const [483]: (375.97570800781)
0A39  03                 const type 3
0A3A  E4FCBBC3           const [484]: (-375.97570800781)
0A3E  03                 const type 3
0A3F  1D49AC44           const [485]: (1378.2847900391)
0A43  03                 const type 3
0A44  65AA3541           const [486]: (11.354100227356)
0A48  03                 const type 3
0A49  B5977C43           const [487]: (252.59260559082)
0A4D  03                 const type 3
0A4E  B5977CC3           const [488]: (-252.59260559082)
0A52  03                 const type 3
0A53  08E3A344           const [489]: (1311.0947265625)
0A57  03                 const type 3
0A58  66663641           const [490]: (11.39999961853)
0A5C  03                 const type 3
0A5D  4D6B8943           const [491]: (274.83828735352)
0A61  03                 const type 3
0A62  4D6B89C3           const [492]: (-274.83828735352)
0A66  03                 const type 3
0A67  34488C44           const [493]: (1122.2563476563)
0A6B  03                 const type 3
0A6C  20631641           const [494]: (9.3992004394531)
0A70  03                 const type 3
0A71  5A74C043           const [495]: (384.90899658203)
0A75  03                 const type 3
0A76  5A74C0C3           const [496]: (-384.90899658203)
0A7A  03                 const type 3
0A7B  217E8444           const [497]: (1059.9415283203)
0A7F  03                 const type 3
0A80  B1505041           const [498]: (13.019700050354)
0A84  03                 const type 3
0A85  2A211444           const [499]: (592.51818847656)
0A89  03                 const type 3
0A8A  2A2114C4           const [500]: (-592.51818847656)
0A8E  03                 const type 3
0A8F  3C9A9944           const [501]: (1228.8198242188)
0A93  03                 const type 3
0A94  1B2F3141           const [502]: (11.074000358582)
0A98  03                 const type 3
0A99  F9912844           const [503]: (674.28082275391)
0A9D  03                 const type 3
0A9E  F99128C4           const [504]: (-674.28082275391)
0AA2  03                 const type 3
0AA3  CE429144           const [505]: (1162.0876464844)
0AA7  03                 const type 3
0AA8  2C54E141           const [506]: (28.16609954834)
0AAC  03                 const type 3
0AAD  1B9F3844           const [507]: (738.48602294922)
0AB1  03                 const type 3
0AB2  1B9F38C4           const [508]: (-738.48602294922)
0AB6  03                 const type 3
0AB7  EE8A7C44           const [509]: (1010.1707763672)
0ABB  03                 const type 3
0ABC  560E3641           const [510]: (11.378499984741)
0AC0  03                 const type 3
0AC1  0DB16B44           const [511]: (942.76641845703)
0AC5  03                 const type 3
0AC6  0DB16BC4           const [512]: (-942.76641845703)
0ACA  03                 const type 3
0ACB  07369044           const [513]: (1153.6883544922)
0ACF  03                 const type 3
0AD0  637F3241           const [514]: (11.156100273132)
0AD4  03                 const type 3
0AD5  00696244           const [515]: (905.640625)
0AD9  03                 const type 3
0ADA  006962C4           const [516]: (-905.640625)
0ADE  03                 const type 3
0ADF  B0327844           const [517]: (992.7919921875)
0AE3  03                 const type 3
0AE4  95653141           const [518]: (11.087300300598)
0AE8  03                 const type 3
0AE9  5AB86044           const [519]: (898.88049316406)
0AED  03                 const type 3
0AEE  5AB860C4           const [520]: (-898.88049316406)
0AF2  03                 const type 3
0AF3  403B5644           const [521]: (856.92578125)
0AF7  03                 const type 3
0AF8  1B0D3541           const [522]: (11.315699577332)
0AFC  03                 const type 3
0AFD  B77D1E44           const [523]: (633.96429443359)
0B01  03                 const type 3
0B02  B77D1EC4           const [524]: (-633.96429443359)
0B06  03                 const type 3
0B07  FB806344           const [525]: (910.01531982422)
0B0B  03                 const type 3
0B0C  234A3141           const [526]: (11.080599784851)
0B10  03                 const type 3
0B11  6A562344           const [527]: (653.35021972656)
0B15  03                 const type 3
0B16  6A5623C4           const [528]: (-653.35021972656)
0B1A  03                 const type 3
0B1B  E8813F44           const [529]: (766.02978515625)
0B1F  03                 const type 3
0B20  644CF741           const [530]: (30.912300109863)
0B24  03                 const type 3
0B25  07B63544           const [531]: (726.84417724609)
0B29  03                 const type 3
0B2A  07B635C4           const [532]: (-726.84417724609)
0B2E  03                 const type 3
0B2F  39F55144           const [533]: (839.83160400391)
0B33  03                 const type 3
0B34  76713141           const [534]: (11.090200424194)
0B38  03                 const type 3
0B39  486FC843           const [535]: (400.86938476563)
0B3D  03                 const type 3
0B3E  486FC8C3           const [536]: (-400.86938476563)
0B42  03                 const type 3
0B43  36EF5E44           const [537]: (891.73767089844)
0B47  03                 const type 3
0B48  DC682D41           const [538]: (10.83810043335)
0B4C  03                 const type 3
0B4D  DB3A0944           const [539]: (548.91961669922)
0B51  03                 const type 3
0B52  DB3A09C4           const [540]: (-548.91961669922)
0B56  03                 const type 3
0B57  2BDC5344           const [541]: (847.44012451172)
0B5B  03                 const type 3
0B5C  0DE0B741           const [542]: (22.984399795532)
0B60  03                 const type 3
0B61  4A501744           const [543]: (605.25451660156)
0B65  03                 const type 3
0B66  4A5017C4           const [544]: (-605.25451660156)
0B6A  03                 const type 3
0B6B  B4481F44           const [545]: (637.13598632813)
0B6F  03                 const type 3
0B70  7DD0B041           const [546]: (22.101800918579)
0B74  03                 const type 3
0B75  4C0A4044           const [547]: (768.16088867188)
0B79  03                 const type 3
0B7A  4C0A40C4           const [548]: (-768.16088867188)
0B7E  03                 const type 3
0B7F  F9710343           const [549]: (131.44520568848)
0B83  03                 const type 3
0B84  925C3041           const [550]: (11.02260017395)
0B88  03                 const type 3
0B89  D99E5744           const [551]: (862.48199462891)
0B8D  03                 const type 3
0B8E  D99E57C4           const [552]: (-862.48199462891)
0B92  03                 const type 3
0B93  86F88743           const [553]: (271.94158935547)
0B97  03                 const type 3
0B98  96433441           const [554]: (11.266500473022)
0B9C  03                 const type 3
0B9D  A8CA7444           const [555]: (979.16650390625)
0BA1  03                 const type 3
0BA2  A8CA74C4           const [556]: (-979.16650390625)
0BA6  03                 const type 3
0BA7  3C8EED42           const [557]: (118.77780151367)
0BAB  03                 const type 3
0BAC  11361441           const [558]: (9.2631998062134)
0BB0  03                 const type 3
0BB1  D0E33844           const [559]: (739.5595703125)
0BB5  03                 const type 3
0BB6  D0E338C4           const [560]: (-739.5595703125)
0BBA  03                 const type 3
0BBB  8E06C141           const [561]: (24.128200531006)
0BBF  03                 const type 3
0BC0  2EFF3041           const [562]: (11.062299728394)
0BC4  03                 const type 3
0BC5  205F8C44           const [563]: (1122.97265625)
0BC9  03                 const type 3
0BCA  205F8CC4           const [564]: (-1122.97265625)
0BCE  03                 const type 3
0BCF  81A66842           const [565]: (58.162601470947)
0BD3  03                 const type 3
0BD4  5DFE3241           const [566]: (11.187100410461)
0BD8  03                 const type 3
0BD9  E4236144           const [567]: (900.56079101563)
0BDD  03                 const type 3
0BDE  E42361C4           const [568]: (-900.56079101563)
0BE2  03                 const type 3
0BE3  C4B1A041           const [569]: (20.086799621582)
0BE7  03                 const type 3
0BE8  C4B1A0C1           const [570]: (-20.086799621582)
0BEC  03                 const type 3
0BED  C2862E41           const [571]: (10.907899856567)
0BF1  03                 const type 3
0BF2  B1ED7144           const [572]: (967.71392822266)
0BF6  03                 const type 3
0BF7  B1ED71C4           const [573]: (-967.71392822266)
0BFB  03                 const type 3
0BFC  1AC06743           const [574]: (231.75039672852)
0C00  03                 const type 3
0C01  1AC067C3           const [575]: (-231.75039672852)
0C05  03                 const type 3
0C06  BC742F41           const [576]: (10.965999603271)
0C0A  03                 const type 3
0C0B  45039444           const [577]: (1184.1021728516)
0C0F  03                 const type 3
0C10  450394C4           const [578]: (-1184.1021728516)
0C14  03                 const type 3
0C15  11F6AF42           const [579]: (87.980598449707)
0C19  03                 const type 3
0C1A  11F6AFC2           const [580]: (-87.980598449707)
0C1E  03                 const type 3
0C1F  46253741           const [581]: (11.446599960327)
0C23  03                 const type 3
0C24  BBA09844           const [582]: (1221.0228271484)
0C28  03                 const type 3
0C29  BBA098C4           const [583]: (-1221.0228271484)
0C2D  03                 const type 3
0C2E  20427443           const [584]: (244.25830078125)
0C32  03                 const type 3
0C33  204274C3           const [585]: (-244.25830078125)
0C37  03                 const type 3
0C38  E3DF8F44           const [586]: (1150.9964599609)
0C3C  03                 const type 3
0C3D  E3DF8FC4           const [587]: (-1150.9964599609)
0C41  03                 const type 3
0C42  2718CE43           const [588]: (412.18869018555)
0C46  03                 const type 3
0C47  2718CEC3           const [589]: (-412.18869018555)
0C4B  03                 const type 3
0C4C  C5202F41           const [590]: (10.94550037384)
0C50  03                 const type 3
0C51  7C968244           const [591]: (1044.7026367188)
0C55  03                 const type 3
0C56  7C9682C4           const [592]: (-1044.7026367188)
0C5A  03                 const type 3
0C5B  B702D943           const [593]: (434.0212097168)
0C5F  03                 const type 3
0C60  B702D9C3           const [594]: (-434.0212097168)
0C64  03                 const type 3
0C65  006F2E41           const [595]: (10.902099609375)
0C69  03                 const type 3
0C6A  68928F44           const [596]: (1148.5751953125)
0C6E  03                 const type 3
0C6F  68928FC4           const [597]: (-1148.5751953125)
0C73  03                 const type 3
0C74  A1DE2244           const [598]: (651.47857666016)
0C78  03                 const type 3
0C79  A1DE22C4           const [599]: (-651.47857666016)
0C7D  03                 const type 3
0C7E  227DB541           const [600]: (22.686100006104)
0C82  03                 const type 3
0C83  6AE27D44           const [601]: (1015.5377197266)
0C87  03                 const type 3
0C88  6AE27DC4           const [602]: (-1015.5377197266)
0C8C  03                 const type 3
0C8D  4DED1E44           const [603]: (635.70782470703)
0C91  03                 const type 3
0C92  4DED1EC4           const [604]: (-635.70782470703)
0C96  03                 const type 3
0C97  F1633941           const [605]: (11.586899757385)
0C9B  03                 const type 3
0C9C  DB795C44           const [606]: (881.90399169922)
0CA0  03                 const type 3
0CA1  DB795CC4           const [607]: (-881.90399169922)
0CA5  03                 const type 3
0CA6  7DC6AA43           const [608]: (341.55068969727)
0CAA  03                 const type 3
0CAB  7DC6AAC3           const [609]: (-341.55068969727)
0CAF  03                 const type 3
0CB0  BBB83141           const [610]: (11.107600212097)
0CB4  03                 const type 3
0CB5  1B8A4944           const [611]: (806.15789794922)
0CB9  03                 const type 3
0CBA  1B8A49C4           const [612]: (-806.15789794922)
0CBE  03                 const type 3
0CBF  3148B443           const [613]: (360.56399536133)
0CC3  03                 const type 3
0CC4  3148B4C3           const [614]: (-360.56399536133)
0CC8  03                 const type 3
0CC9  8A8E0441           const [615]: (8.2847995758057)
0CCD  03                 const type 3
0CCE  4A986F44           const [616]: (958.37951660156)
0CD2  03                 const type 3
0CD3  4A986FC4           const [617]: (-958.37951660156)
0CD7  03                 const type 3
0CD8  EDC6CA43           const [618]: (405.55410766602)
0CDC  03                 const type 3
0CDD  EDC6CAC3           const [619]: (-405.55410766602)
0CE1  03                 const type 3
0CE2  3D2C3041           const [620]: (11.010800361633)
0CE6  03                 const type 3
0CE7  D53B5D44           const [621]: (884.93487548828)
0CEB  03                 const type 3
0CEC  D53B5DC4           const [622]: (-884.93487548828)
0CF0  03                 const type 3
0CF1  D0D42C44           const [623]: (691.3251953125)
0CF5  03                 const type 3
0CF6  D0D42CC4           const [624]: (-691.3251953125)
0CFA  03                 const type 3
0CFB  5F29CB41           const [625]: (25.39520072937)
0CFF  03                 const type 3
0D00  50307944           const [626]: (996.7548828125)
0D04  03                 const type 3
0D05  503079C4           const [627]: (-996.7548828125)
0D09  03                 const type 3
0D0A  109C5044           const [628]: (834.4384765625)
0D0E  03                 const type 3
0D0F  109C50C4           const [629]: (-834.4384765625)
0D13  03                 const type 3
0D14  5AF5CB40           const [630]: (6.3737001419067)
0D18  03                 const type 3
0D19  4D7C6544           const [631]: (917.94219970703)
0D1D  03                 const type 3
0D1E  4D7C65C4           const [632]: (-917.94219970703)
0D22  03                 const type 3
0D23  B6436B44           const [633]: (941.05798339844)
0D27  03                 const type 3
0D28  B6436BC4           const [634]: (-941.05798339844)
0D2C  03                 const type 3
0D2D  B6F34241           const [635]: (12.184499740601)
0D31  03                 const type 3
0D32  86FB8744           const [636]: (1087.8601074219)
0D36  03                 const type 3
0D37  86FB87C4           const [637]: (-1087.8601074219)
0D3B  03                 const type 3
0D3C  16633244           const [638]: (713.54821777344)
0D40  03                 const type 3
0D41  166332C4           const [639]: (-713.54821777344)
0D45  03                 const type 3
0D46  21B03C41           const [640]: (11.793000221252)
0D4A  03                 const type 3
0D4B  F5B94444           const [641]: (786.90557861328)
0D4F  03                 const type 3
0D50  F5B944C4           const [642]: (-786.90557861328)
0D54  03                 const type 3
0D55  8BCB9844           const [643]: (1222.3607177734)
0D59  03                 const type 3
0D5A  8BCB98C4           const [644]: (-1222.3607177734)
0D5E  03                 const type 3
0D5F  54E32F41           const [645]: (10.993000030518)
0D63  03                 const type 3
0D64  7FDF5C44           const [646]: (883.49212646484)
0D68  03                 const type 3
0D69  7FDF5CC4           const [647]: (-883.49212646484)
0D6D  03                 const type 3
0D6E  E15A9E44           const [648]: (1266.8399658203)
0D72  03                 const type 3
0D73  E15A9EC4           const [649]: (-1266.8399658203)
0D77  03                 const type 3
0D78  27C23B41           const [650]: (11.734900474548)
0D7C  03                 const type 3
0D7D  82BF5744           const [651]: (862.99230957031)
0D81  03                 const type 3
0D82  82BF57C4           const [652]: (-862.99230957031)
0D86  03                 const type 3
0D87  4355BE44           const [653]: (1522.6644287109)
0D8B  03                 const type 3
0D8C  4355BEC4           const [654]: (-1522.6644287109)
0D90  03                 const type 3
0D91  1B2F4241           const [655]: (12.136500358582)
0D95  03                 const type 3
0D96  EA687344           const [656]: (973.63928222656)
0D9A  03                 const type 3
0D9B  EA6873C4           const [657]: (-973.63928222656)
0D9F  03                 const type 3
0DA0  0D65B744           const [658]: (1467.1578369141)
0DA4  03                 const type 3
0DA5  0D65B7C4           const [659]: (-1467.1578369141)
0DA9  03                 const type 3
0DAA  F9314041           const [660]: (12.01220035553)
0DAE  03                 const type 3
0DAF  C80B5944           const [661]: (868.18408203125)
0DB3  03                 const type 3
0DB4  C80B59C4           const [662]: (-868.18408203125)
0DB8  03                 const type 3
0DB9  8461AD44           const [663]: (1387.0473632813)
0DBD  03                 const type 3
0DBE  8461ADC4           const [664]: (-1387.0473632813)
0DC2  03                 const type 3
0DC3  0681E441           const [665]: (28.562999725342)
0DC7  03                 const type 3
0DC8  767F2944           const [666]: (677.99157714844)
0DCC  03                 const type 3
0DCD  767F29C4           const [667]: (-677.99157714844)
0DD1  03                 const type 3
0DD2  AA58BF44           const [668]: (1530.7707519531)
0DD6  03                 const type 3
0DD7  AA58BFC4           const [669]: (-1530.7707519531)
0DDB  03                 const type 3
0DDC  73684741           const [670]: (12.463000297546)
0DE0  03                 const type 3
0DE1  2C7C2644           const [671]: (665.94018554688)
0DE5  03                 const type 3
0DE6  2C7C26C4           const [672]: (-665.94018554688)
0DEA  03                 const type 3
0DEB  B5B3A044           const [673]: (1285.6158447266)
0DEF  03                 const type 3
0DF0  B5B3A0C4           const [674]: (-1285.6158447266)
0DF4  03                 const type 3
0DF5  5BB1EF41           const [675]: (29.961599349976)
0DF9  03                 const type 3
0DFA  4EF28544           const [676]: (1071.5720214844)
0DFE  03                 const type 3
0DFF  4EF285C4           const [677]: (-1071.5720214844)
0E03  03                 const type 3
0E04  36F28144           const [678]: (1039.5690917969)
0E08  03                 const type 3
0E09  36F281C4           const [679]: (-1039.5690917969)
0E0D  03                 const type 3
0E0E  03898C41           const [680]: (17.566900253296)
0E12  03                 const type 3
0E13  EFFFB244           const [681]: (1431.9979248047)
0E17  03                 const type 3
0E18  EFFFB2C4           const [682]: (-1431.9979248047)
0E1C  03                 const type 3
0E1D  FC287444           const [683]: (976.64038085938)
0E21  03                 const type 3
0E22  FC2874C4           const [684]: (-976.64038085938)
0E26  03                 const type 3
0E27  BDE36D41           const [685]: (14.868100166321)
0E2B  03                 const type 3
0E2C  65A3D244           const [686]: (1685.1060791016)
0E30  03                 const type 3
0E31  65A3D2C4           const [687]: (-1685.1060791016)
0E35  03                 const type 3
0E36  EE8F6C44           const [688]: (946.24890136719)
0E3A  03                 const type 3
0E3B  EE8F6CC4           const [689]: (-946.24890136719)
0E3F  03                 const type 3
0E40  E9B76D41           const [690]: (14.857399940491)
0E44  03                 const type 3
0E45  8BCC9D44           const [691]: (1262.3919677734)
0E49  03                 const type 3
0E4A  8BCC9DC4           const [692]: (-1262.3919677734)
0E4E  03                 const type 3
0E4F  3E169D44           const [693]: (1256.6950683594)
0E53  03                 const type 3
0E54  3E169DC4           const [694]: (-1256.6950683594)
0E58  03                 const type 3
0E59  D0D56D41           const [695]: (14.864700317383)
0E5D  03                 const type 3
0E5E  1712A444           const [696]: (1312.5653076172)
0E62  03                 const type 3
0E63  1712A4C4           const [697]: (-1312.5653076172)
0E67  03                 const type 3
0E68  38F71D44           const [698]: (631.86279296875)
0E6C  03                 const type 3
0E6D  38F71DC4           const [699]: (-631.86279296875)
0E71  03                 const type 3
0E72  22FD6D41           const [700]: (14.874300003052)
0E76  03                 const type 3
0E77  DEEBD844           const [701]: (1735.3708496094)
0E7B  03                 const type 3
0E7C  DEEBD8C4           const [702]: (-1735.3708496094)
0E80  03                 const type 3
0E81  491AD844           const [703]: (1728.8214111328)
0E85  03                 const type 3
0E86  491AD8C4           const [704]: (-1728.8214111328)
0E8A  03                 const type 3
0E8B  7FD96D41           const [705]: (14.865599632263)
0E8F  03                 const type 3
0E90  3356A944           const [706]: (1354.6937255859)
0E94  03                 const type 3
0E95  3356A9C4           const [707]: (-1354.6937255859)
0E99  03                 const type 3
0E9A  4C5A4A44           const [708]: (809.41088867188)
0E9E  03                 const type 3
0E9F  4C5A4AC4           const [709]: (-809.41088867188)
0EA3  03                 const type 3
0EA4  4C26A741           const [710]: (20.893699645996)
0EA8  03                 const type 3
0EA9  4DEB6944           const [711]: (935.67657470703)
0EAD  03                 const type 3
0EAE  4DEB69C4           const [712]: (-935.67657470703)
0EB2  03                 const type 3
0EB3  CC40A744           const [713]: (1338.0249023438)
0EB7  03                 const type 3
0EB8  492E3241           const [714]: (11.136300086975)
0EBC  03                 const type 3
0EBD  2BEA4344           const [715]: (783.65887451172)
0EC1  03                 const type 3
0EC2  2BEA43C4           const [716]: (-783.65887451172)
0EC6  03                 const type 3
0EC7  F25ABA44           const [717]: (1490.8420410156)
0ECB  03                 const type 3
0ECC  B7D14341           const [718]: (12.238699913025)
0ED0  03                 const type 3
0ED1  8A9C4D44           const [719]: (822.44592285156)
0ED5  03                 const type 3
0ED6  8A9C4DC4           const [720]: (-822.44592285156)
0EDA  03                 const type 3
0EDB  9EA28F44           const [721]: (1149.0817871094)
0EDF  03                 const type 3
0EE0  FCA94641           const [722]: (12.416500091553)
0EE4  03                 const type 3
0EE5  6CB81444           const [723]: (594.88159179688)
0EE9  03                 const type 3
0EEA  6CB814C4           const [724]: (-594.88159179688)
0EEE  03                 const type 3
0EEF  312FA944           const [725]: (1353.4747314453)
0EF3  03                 const type 3
0EF4  EE5A3C41           const [726]: (11.772199630737)
0EF8  03                 const type 3
0EF9  58AAAC43           const [727]: (345.33081054688)
0EFD  03                 const type 3
0EFE  58AAACC3           const [728]: (-345.33081054688)
0F02  03                 const type 3
0F03  4F679244           const [729]: (1171.2283935547)
0F07  03                 const type 3
0F08  4BEA3741           const [730]: (11.494700431824)
0F0C  03                 const type 3
0F0D  C93A5544           const [731]: (852.91851806641)
0F11  03                 const type 3
0F12  C93A55C4           const [732]: (-852.91851806641)
0F16  03                 const type 3
0F17  E55A4744           const [733]: (797.42022705078)
0F1B  03                 const type 3
0F1C  2F6E3141           const [734]: (11.089400291443)
0F20  03                 const type 3
0F21  235AF043           const [735]: (480.70419311523)
0F25  03                 const type 3
0F26  235AF0C3           const [736]: (-480.70419311523)
0F2A  03                 const type 3
0F2B  91256E44           const [737]: (952.58697509766)
0F2F  03                 const type 3
0F30  A54E6441           const [738]: (14.269200325012)
0F34  03                 const type 3
0F35  9C433444           const [739]: (721.05639648438)
0F39  03                 const type 3
0F3A  9C4334C4           const [740]: (-721.05639648438)
0F3E  03                 const type 3
0F3F  CC3FB643           const [741]: (364.49841308594)
0F43  03                 const type 3
0F44  789C3141           const [742]: (11.100700378418)
0F48  03                 const type 3
0F49  C59A8844           const [743]: (1092.8365478516)
0F4D  03                 const type 3
0F4E  C59A88C4           const [744]: (-1092.8365478516)
0F52  03                 const type 3
0F53  BE61E442           const [745]: (114.19090270996)
0F57  03                 const type 3
0F58  0B463441           const [746]: (11.267100334167)
0F5C  03                 const type 3
0F5D  DAEF6944           const [747]: (935.74768066406)
0F61  03                 const type 3
0F62  DAEF69C4           const [748]: (-935.74768066406)
0F66  03                 const type 3
0F67  29ADE842           const [749]: (116.33820343018)
0F6B  03                 const type 3
0F6C  29ADE8C2           const [750]: (-116.33820343018)
0F70  03                 const type 3
0F71  99BBD440           const [751]: (6.6479001045227)
0F75  03                 const type 3
0F76  6A689744           const [752]: (1211.2629394531)
0F7A  03                 const type 3
0F7B  6A6897C4           const [753]: (-1211.2629394531)
0F7F  03                 const type 3
0F80  2933E643           const [754]: (460.3996887207)
0F84  03                 const type 3
0F85  2933E6C3           const [755]: (-460.3996887207)
0F89  03                 const type 3
0F8A  AED82F41           const [756]: (10.990400314331)
0F8E  03                 const type 3
0F8F  22928544           const [757]: (1068.5666503906)
0F93  03                 const type 3
0F94  229285C4           const [758]: (-1068.5666503906)
0F98  03                 const type 3
0F99  91BF1D44           const [759]: (630.99322509766)
0F9D  03                 const type 3
0F9E  91BF1DC4           const [760]: (-630.99322509766)
0FA2  03                 const type 3
0FA3  12833241           const [761]: (11.156999588013)
0FA7  03                 const type 3
0FA8  51F75C44           const [762]: (883.86431884766)
0FAC  03                 const type 3
0FAD  51F75CC4           const [763]: (-883.86431884766)
0FB1  03                 const type 3
0FB2  AD2AC943           const [764]: (402.33340454102)
0FB6  03                 const type 3
0FB7  AD2AC9C3           const [765]: (-402.33340454102)
0FBB  03                 const type 3
0FBC  AE475641           const [766]: (13.392499923706)
0FC0  03                 const type 3
0FC1  7F995244           const [767]: (842.39837646484)
0FC5  03                 const type 3
0FC6  7F9952C4           const [768]: (-842.39837646484)
0FCA  03                 const type 3
0FCB  838D6F44           const [769]: (958.21112060547)
0FCF  03                 const type 3
0FD0  838D6FC4           const [770]: (-958.21112060547)
0FD4  03                 const type 3
0FD5  C4B13141           const [771]: (11.105899810791)
0FD9  03                 const type 3
0FDA  A2193B44           const [772]: (748.40051269531)
0FDE  03                 const type 3
0FDF  A2193BC4           const [773]: (-748.40051269531)
0FE3  03                 const type 3
0FE4  0E2A9D44           const [774]: (1257.3142089844)
0FE8  03                 const type 3
0FE9  0E2A9DC4           const [775]: (-1257.3142089844)
0FED  03                 const type 3
0FEE  34803141           const [776]: (11.093799591064)
0FF2  03                 const type 3
0FF3  0E237644           const [777]: (984.54772949219)
0FF7  03                 const type 3
0FF8  0E2376C4           const [778]: (-984.54772949219)
0FFC  03                 const type 3
0FFD  EC69A044           const [779]: (1283.3100585938)
1001  03                 const type 3
1002  EC69A0C4           const [780]: (-1283.3100585938)
1006  03                 const type 3
1007  1815E141           const [781]: (28.135299682617)
100B  03                 const type 3
100C  ACCF9044           const [782]: (1158.4897460938)
1010  03                 const type 3
1011  ACCF90C4           const [783]: (-1158.4897460938)
1015  03                 const type 3
1016  DF7B7744           const [784]: (989.93548583984)
101A  03                 const type 3
101B  DF7B77C4           const [785]: (-989.93548583984)
101F  03                 const type 3
1020  F5DB6D41           const [786]: (14.866200447083)
1024  03                 const type 3
1025  E766B344           const [787]: (1435.2156982422)
1029  03                 const type 3
102A  E766B3C4           const [788]: (-1435.2156982422)
102E  03                 const type 3
102F  21534944           const [789]: (805.29888916016)
1033  03                 const type 3
1034  215349C4           const [790]: (-805.29888916016)
1038  03                 const type 3
1039  6ADE6D41           const [791]: (14.866800308228)
103D  03                 const type 3
103E  D9D2CB44           const [792]: (1630.5889892578)
1042  03                 const type 3
1043  D9D2CBC4           const [793]: (-1630.5889892578)
1047  03                 const type 3
1048  80EB1F44           const [794]: (639.6796875)
104C  03                 const type 3
104D  80EB1FC4           const [795]: (-639.6796875)
1051  03                 const type 3
1052  F6286E41           const [796]: (14.885000228882)
1056  03                 const type 3
1057  D4BBC644           const [797]: (1589.8696289063)
105B  03                 const type 3
105C  D4BBC6C4           const [798]: (-1589.8696289063)
1060  03                 const type 3
1061  296CAA43           const [799]: (340.8450012207)
1065  03                 const type 3
1066  296CAAC3           const [800]: (-340.8450012207)
106A  03                 const type 3
106B  CDCC6D41           const [801]: (14.862500190735)
106F  03                 const type 3
1070  5BBC8744           const [802]: (1085.8861083984)
1074  03                 const type 3
1075  5BBC87C4           const [803]: (-1085.8861083984)
1079  03                 const type 3
107A  1DE0A844           const [804]: (1351.0035400391)
107E  03                 const type 3
107F  7E1D1841           const [805]: (9.5072002410889)
1083  03                 const type 3
1084  92DBE543           const [806]: (459.71539306641)
1088  03                 const type 3
1089  92DBE5C3           const [807]: (-459.71539306641)
108D  03                 const type 3
108E  ACB59644           const [808]: (1205.6772460938)
1092  03                 const type 3
1093  4BEA1A41           const [809]: (9.6822004318237)
1097  03                 const type 3
1098  09898143           const [810]: (259.0705871582)
109C  03                 const type 3
109D  098981C3           const [811]: (-259.0705871582)
10A1  03                 const type 3
10A2  9755B344           const [812]: (1434.6746826172)
10A6  03                 const type 3
10A7  51033944           const [813]: (740.05181884766)
10AB  03                 const type 3
10AC  510339C4           const [814]: (-740.05181884766)
10B0  03                 const type 3
10B1  523B8744           const [815]: (1081.8537597656)
10B5  03                 const type 3
10B6  014D1B41           const [816]: (9.7062997817993)
10BA  03                 const type 3
10BB  9F086644           const [817]: (920.13470458984)
10BF  03                 const type 3
10C0  9F0866C4           const [818]: (-920.13470458984)
10C4  03                 const type 3
10C5  8B296C44           const [819]: (944.64910888672)
10C9  03                 const type 3
10CA  7C613141           const [820]: (11.08629989624)
10CE  03                 const type 3
10CF  70070D44           const [821]: (564.1162109375)
10D3  03                 const type 3
10D4  70070DC4           const [822]: (-564.1162109375)
10D8  03                 const type 3
10D9  F90C2F44           const [823]: (700.20269775391)
10DD  03                 const type 3
10DE  F30EA541           const [824]: (20.632299423218)
10E2  03                 const type 3
10E3  AE943A44           const [825]: (746.32312011719)
10E7  03                 const type 3
10E8  AE943AC4           const [826]: (-746.32312011719)
10EC  03                 const type 3
10ED  36FC7343           const [827]: (243.98519897461)
10F1  03                 const type 3
10F2  33338841           const [828]: (17.02499961853)
10F6  03                 const type 3
10F7  33BF6E44           const [829]: (954.98748779297)
10FB  03                 const type 3
10FC  33BF6EC4           const [830]: (-954.98748779297)
1100  03                 const type 3
1101  7CEA8743           const [831]: (271.83190917969)
1105  03                 const type 3
1106  53D26244           const [832]: (907.28631591797)
110A  03                 const type 3
110B  53D262C4           const [833]: (-907.28631591797)
110F  03                 const type 3
1110  60364942           const [834]: (50.303100585938)
1114  03                 const type 3
1115  575B2141           const [835]: (10.084799766541)
1119  03                 const type 3
111A  D8CD9144           const [836]: (1166.4326171875)
111E  03                 const type 3
111F  D8CD91C4           const [837]: (-1166.4326171875)
1123  03                 const type 3
1124  50FCB142           const [838]: (88.992797851563)
1128  03                 const type 3
1129  7B143241           const [839]: (11.130000114441)
112D  03                 const type 3
112E  BA957F44           const [840]: (1022.3394775391)
1132  03                 const type 3
1133  BA957FC4           const [841]: (-1022.3394775391)
1137  03                 const type 3
1138  6D95E343           const [842]: (455.16738891602)
113C  03                 const type 3
113D  6D95E3C3           const [843]: (-455.16738891602)
1141  03                 const type 3
1142  F38E8B41           const [844]: (17.444799423218)
1146  03                 const type 3
1147  FAB88C44           const [845]: (1125.7805175781)
114B  03                 const type 3
114C  FAB88CC4           const [846]: (-1125.7805175781)
1150  03                 const type 3
1151  44A51844           const [847]: (610.58227539063)
1155  03                 const type 3
1156  44A518C4           const [848]: (-610.58227539063)
115A  03                 const type 3
115B  E17AD041           const [849]: (26.059999465942)
115F  03                 const type 3
1160  0D414944           const [850]: (805.01641845703)
1164  03                 const type 3
1165  0D4149C4           const [851]: (-805.01641845703)
1169  03                 const type 3
116A  591FA343           const [852]: (326.24490356445)
116E  03                 const type 3
116F  591FA3C3           const [853]: (-326.24490356445)
1173  03                 const type 3
1174  7A1D8344           const [854]: (1048.9211425781)
1178  03                 const type 3
1179  7A1D83C4           const [855]: (-1048.9211425781)
117D  03                 const type 3
117E  83303F44           const [856]: (764.75799560547)
1182  03                 const type 3
1183  83303FC4           const [857]: (-764.75799560547)
1187  03                 const type 3
1188  992A4041           const [858]: (12.01039981842)
118C  03                 const type 3
118D  F1135D44           const [859]: (884.31158447266)
1191  03                 const type 3
1192  F1135DC4           const [860]: (-884.31158447266)
1196  03                 const type 3
1197  65C57D44           const [861]: (1015.0842895508)
119B  03                 const type 3
119C  65C57DC4           const [862]: (-1015.0842895508)
11A0  03                 const type 3
11A1  F7066641           const [863]: (14.376700401306)
11A5  03                 const type 3
11A6  D69E2C44           const [864]: (690.48181152344)
11AA  03                 const type 3
11AB  D69E2CC4           const [865]: (-690.48181152344)
11AF  03                 const type 3
11B0  F421C644           const [866]: (1585.0610351563)
11B4  03                 const type 3
11B5  F421C6C4           const [867]: (-1585.0610351563)
11B9  03                 const type 3
11BA  3F574841           const [868]: (12.521300315857)
11BE  03                 const type 3
11BF  1AC4AC44           const [869]: (1382.1281738281)
11C3  03                 const type 3
11C4  1AC4ACC4           const [870]: (-1382.1281738281)
11C8  03                 const type 3
11C9  9A99B743           const [871]: (367.20001220703)
11CD  03                 const type 3
11CE  9A99B7C3           const [872]: (-367.20001220703)
11D2  03                 const type 3
11D3  B1E16D41           const [873]: (14.867600440979)
11D7  03                 const type 3
11D8  E382BD44           const [874]: (1516.0902099609)
11DC  03                 const type 3
11DD  E382BDC4           const [875]: (-1516.0902099609)
11E1  03                 const type 3
11E2  51A34A44           const [876]: (810.55181884766)
11E6  03                 const type 3
11E7  51A34AC4           const [877]: (-810.55181884766)
                         * functions:
11EB  00000000           sizep (0)
                         * code:
11EF  D7080000           sizecode (2263)
11F3  0A000000           [0001] newtable   0   0   0    ; array=0, hash=0
11F7  05000001           [0002] getglobal  1   0        ; GameLocation
11FB  99800001           [0003] call       1   1   2  
11FF  D5BE0001           [0004] eq         1   1   251  ; 0, to [6] if false
1203  D4048000           [0005] jmp        20           ; to [26]
1207  05000001           [0006] getglobal  1   0        ; GameLocation
120B  99800001           [0007] call       1   1   2  
120F  15BF0001           [0008] eq         1   1   252  ; 1, to [10] if false
1213  D4038000           [0009] jmp        16           ; to [26]
1217  05000001           [0010] getglobal  1   0        ; GameLocation
121B  99800001           [0011] call       1   1   2  
121F  55BF0001           [0012] eq         1   1   253  ; 2, to [14] if false
1223  D4028000           [0013] jmp        12           ; to [26]
1227  05000001           [0014] getglobal  1   0        ; GameLocation
122B  99800001           [0015] call       1   1   2  
122F  95BF0001           [0016] eq         1   1   254  ; 3, to [18] if false
1233  D4018000           [0017] jmp        8            ; to [26]
1237  05000001           [0018] getglobal  1   0        ; GameLocation
123B  99800001           [0019] call       1   1   2  
123F  D5BF0001           [0020] eq         1   1   255  ; 4, to [22] if false
1243  D4008000           [0021] jmp        4            ; to [26]
1247  05000001           [0022] getglobal  1   0        ; GameLocation
124B  99800001           [0023] call       1   1   2  
124F  15C00000           [0024] eq         0   1   256  ; 5, to [26] if true
1253  542F8100           [0025] jmp        1214         ; to [1240]
1257  0A001601           [0026] newtable   1   44  0    ; array=128, hash=0
125B  0A800102           [0027] newtable   2   3   0    ; array=3, hash=0
125F  C5010003           [0028] getglobal  3   7        ; pickup
1263  86C00103           [0029] gettable   3   3   258  ; "shotgun"
1267  0A800104           [0030] newtable   4   3   0    ; array=3, hash=0
126B  41020005           [0031] loadk      5   9        ; 322.095703125
126F  81020006           [0032] loadk      6   10       ; 1161.3178710938
1273  C1020007           [0033] loadk      7   11       ; 17.454599380493
1277  9F000004           [0034] setlist    4   2        ; index 1 to 3
127B  01030005           [0035] loadk      5   12       ; 10
127F  9F000002           [0036] setlist    2   2        ; index 1 to 3
1283  0A800103           [0037] newtable   3   3   0    ; array=3, hash=0
1287  C5010004           [0038] getglobal  4   7        ; pickup
128B  C6410204           [0039] gettable   4   4   263  ; "tec9"
128F  0A800105           [0040] newtable   5   3   0    ; array=3, hash=0
1293  81030006           [0041] loadk      6   14       ; 322.17950439453
1297  C1030007           [0042] loadk      7   15       ; 1251.6357421875
129B  01040008           [0043] loadk      8   16       ; 17.49220085144
129F  9F000005           [0044] setlist    5   2        ; index 1 to 3
12A3  41040006           [0045] loadk      6   17       ; 50
12A7  9F000003           [0046] setlist    3   2        ; index 1 to 3
12AB  0A800104           [0047] newtable   4   3   0    ; array=3, hash=0
12AF  C5010005           [0048] getglobal  5   7        ; pickup
12B3  06C30205           [0049] gettable   5   5   268  ; "ak47"
12B7  0A800106           [0050] newtable   6   3   0    ; array=3, hash=0
12BB  C1040007           [0051] loadk      7   19       ; 321.46051025391
12BF  01050008           [0052] loadk      8   20       ; 1220.1501464844
12C3  41050009           [0053] loadk      9   21       ; 22.750099182129
12C7  9F000006           [0054] setlist    6   2        ; index 1 to 3
12CB  41040007           [0055] loadk      7   17       ; 50
12CF  9F000004           [0056] setlist    4   2        ; index 1 to 3
12D3  0A800105           [0057] newtable   5   3   0    ; array=3, hash=0
12D7  C5010006           [0058] getglobal  6   7        ; pickup
12DB  06440306           [0059] gettable   6   6   272  ; "sniper"
12DF  0A800107           [0060] newtable   7   3   0    ; array=3, hash=0
12E3  C1050008           [0061] loadk      8   23       ; 309.38870239258
12E7  01060009           [0062] loadk      9   24       ; 1162.5009765625
12EB  4106000A           [0063] loadk      10  25       ; 27.582399368286
12EF  9F000007           [0064] setlist    7   2        ; index 1 to 3
12F3  01030008           [0065] loadk      8   12       ; 10
12F7  9F000005           [0066] setlist    5   2        ; index 1 to 3
12FB  0A800106           [0067] newtable   6   3   0    ; array=3, hash=0
12FF  C5010007           [0068] getglobal  7   7        ; pickup
1303  86C00307           [0069] gettable   7   7   258  ; "shotgun"
1307  0A800108           [0070] newtable   8   3   0    ; array=3, hash=0
130B  81060009           [0071] loadk      9   26       ; 492.49880981445
130F  C106000A           [0072] loadk      10  27       ; 1249.0373535156
1313  0107000B           [0073] loadk      11  28       ; 17.53039932251
1317  9F000008           [0074] setlist    8   2        ; index 1 to 3
131B  01030009           [0075] loadk      9   12       ; 10
131F  9F000006           [0076] setlist    6   2        ; index 1 to 3
1323  0A800107           [0077] newtable   7   3   0    ; array=3, hash=0
1327  C5010008           [0078] getglobal  8   7        ; pickup
132B  C6410408           [0079] gettable   8   8   263  ; "tec9"
132F  0A800109           [0080] newtable   9   3   0    ; array=3, hash=0
1333  4107000A           [0081] loadk      10  29       ; 477.28100585938
1337  8107000B           [0082] loadk      11  30       ; 1004.0797729492
133B  C107000C           [0083] loadk      12  31       ; 18.316900253296
133F  9F000009           [0084] setlist    9   2        ; index 1 to 3
1343  4104000A           [0085] loadk      10  17       ; 50
1347  9F000007           [0086] setlist    7   2        ; index 1 to 3
134B  0A800108           [0087] newtable   8   3   0    ; array=3, hash=0
134F  C5010009           [0088] getglobal  9   7        ; pickup
1353  06C30409           [0089] gettable   9   9   268  ; "ak47"
1357  0A80010A           [0090] newtable   10  3   0    ; array=3, hash=0
135B  0108000B           [0091] loadk      11  32       ; 334.28030395508
135F  4108000C           [0092] loadk      12  33       ; 999.48797607422
1363  8108000D           [0093] loadk      13  34       ; 12.652600288391
1367  9F00000A           [0094] setlist    10  2        ; index 1 to 3
136B  4104000B           [0095] loadk      11  17       ; 50
136F  9F000008           [0096] setlist    8   2        ; index 1 to 3
1373  0A800109           [0097] newtable   9   3   0    ; array=3, hash=0
1377  C501000A           [0098] getglobal  10  7        ; pickup
137B  8640050A           [0099] gettable   10  10  258  ; "shotgun"
137F  0A80010B           [0100] newtable   11  3   0    ; array=3, hash=0
1383  C108000C           [0101] loadk      12  35       ; 209.25439453125
1387  0109000D           [0102] loadk      13  36       ; 1277.8404541016
138B  4109000E           [0103] loadk      14  37       ; 18.159000396729
138F  9F00000B           [0104] setlist    11  2        ; index 1 to 3
1393  0103000C           [0105] loadk      12  12       ; 10
1397  9F000009           [0106] setlist    9   2        ; index 1 to 3
139B  0A80010A           [0107] newtable   10  3   0    ; array=3, hash=0
139F  C501000B           [0108] getglobal  11  7        ; pickup
13A3  06C8050B           [0109] gettable   11  11  288  ; "molotov"
13A7  0A80010C           [0110] newtable   12  3   0    ; array=3, hash=0
13AB  C109000D           [0111] loadk      13  39       ; 606.22930908203
13AF  010A000E           [0112] loadk      14  40       ; 826.43560791016
13B3  410A000F           [0113] loadk      15  41       ; 22.537700653076
13B7  9F00000C           [0114] setlist    12  2        ; index 1 to 3
13BB  8101000D           [0115] loadk      13  6        ; 5
13BF  9F00000A           [0116] setlist    10  2        ; index 1 to 3
13C3  0A80010B           [0117] newtable   11  3   0    ; array=3, hash=0
13C7  C501000C           [0118] getglobal  12  7        ; pickup
13CB  C641060C           [0119] gettable   12  12  263  ; "tec9"
13CF  0A80010D           [0120] newtable   13  3   0    ; array=3, hash=0
13D3  810A000E           [0121] loadk      14  42       ; 204.05780029297
13D7  C10A000F           [0122] loadk      15  43       ; 684.16339111328
13DB  010B0010           [0123] loadk      16  44       ; 12.97350025177
13DF  9F00000D           [0124] setlist    13  2        ; index 1 to 3
13E3  4104000E           [0125] loadk      14  17       ; 50
13E7  9F00000B           [0126] setlist    11  2        ; index 1 to 3
13EB  0A80010C           [0127] newtable   12  3   0    ; array=3, hash=0
13EF  C501000D           [0128] getglobal  13  7        ; pickup
13F3  C6C9060D           [0129] gettable   13  13  295  ; "rocket_launcher"
13F7  0A80010E           [0130] newtable   14  3   0    ; array=3, hash=0
13FB  810B000F           [0131] loadk      15  46       ; 332.23901367188
13FF  C10B0010           [0132] loadk      16  47       ; 715.08557128906
1403  010C0011           [0133] loadk      17  48       ; 22.885799407959
1407  9F00000E           [0134] setlist    14  2        ; index 1 to 3
140B  8101000F           [0135] loadk      15  6        ; 5
140F  9F00000C           [0136] setlist    12  2        ; index 1 to 3
1413  0A80010D           [0137] newtable   13  3   0    ; array=3, hash=0
1417  C501000E           [0138] getglobal  14  7        ; pickup
141B  C64A070E           [0139] gettable   14  14  299  ; "grenade"
141F  0A80010F           [0140] newtable   15  3   0    ; array=3, hash=0
1423  810C0010           [0141] loadk      16  50       ; 337.23440551758
1427  C10C0011           [0142] loadk      17  51       ; 843.34997558594
142B  010D0012           [0143] loadk      18  52       ; 12.968099594116
142F  9F00000F           [0144] setlist    15  2        ; index 1 to 3
1433  81010010           [0145] loadk      16  6        ; 5
1437  9F00000D           [0146] setlist    13  2        ; index 1 to 3
143B  0A80010E           [0147] newtable   14  3   0    ; array=3, hash=0
143F  C501000F           [0148] getglobal  15  7        ; pickup
1443  86C0070F           [0149] gettable   15  15  258  ; "shotgun"
1447  0A800110           [0150] newtable   16  3   0    ; array=3, hash=0
144B  410D0011           [0151] loadk      17  53       ; 494.78381347656
144F  810D0012           [0152] loadk      18  54       ; 739.77868652344
1453  C10D0013           [0153] loadk      19  55       ; 11.397700309753
1457  9F000010           [0154] setlist    16  2        ; index 1 to 3
145B  01030011           [0155] loadk      17  12       ; 10
145F  9F00000E           [0156] setlist    14  2        ; index 1 to 3
1463  0A80010F           [0157] newtable   15  3   0    ; array=3, hash=0
1467  C5010010           [0158] getglobal  16  7        ; pickup
146B  864C0810           [0159] gettable   16  16  306  ; "glock17"
146F  0A800111           [0160] newtable   17  3   0    ; array=3, hash=0
1473  410E0012           [0161] loadk      18  57       ; 492.3078918457
1477  810E0013           [0162] loadk      19  58       ; 911.18328857422
147B  C10E0014           [0163] loadk      20  59       ; 14.75119972229
147F  9F000011           [0164] setlist    17  2        ; index 1 to 3
1483  010F0012           [0165] loadk      18  60       ; 30
1487  9F00000F           [0166] setlist    15  2        ; index 1 to 3
148B  0A800110           [0167] newtable   16  3   0    ; array=3, hash=0
148F  C5010011           [0168] getglobal  17  7        ; pickup
1493  C6CD0811           [0169] gettable   17  17  311  ; "det_grenade"
1497  0A800112           [0170] newtable   18  3   0    ; array=3, hash=0
149B  810F0013           [0171] loadk      19  62       ; 47.278800964355
149F  C10F0014           [0172] loadk      20  63       ; 943.8505859375
14A3  01100015           [0173] loadk      21  64       ; 10.924599647522
14A7  9F000012           [0174] setlist    18  2        ; index 1 to 3
14AB  81010013           [0175] loadk      19  6        ; 5
14AF  9F000010           [0176] setlist    16  2        ; index 1 to 3
14B3  0A800111           [0177] newtable   17  3   0    ; array=3, hash=0
14B7  C5010012           [0178] getglobal  18  7        ; pickup
14BB  C6410912           [0179] gettable   18  18  263  ; "tec9"
14BF  0A800113           [0180] newtable   19  3   0    ; array=3, hash=0
14C3  41100014           [0181] loadk      20  65       ; 74.950897216797
14C7  81100015           [0182] loadk      21  66       ; 1082.1853027344
14CB  C1100016           [0183] loadk      22  67       ; 16.440500259399
14CF  9F000013           [0184] setlist    19  2        ; index 1 to 3
14D3  41040014           [0185] loadk      20  17       ; 50
14D7  9F000011           [0186] setlist    17  2        ; index 1 to 3
14DB  0A800112           [0187] newtable   18  3   0    ; array=3, hash=0
14DF  C5010013           [0188] getglobal  19  7        ; pickup
14E3  06C30913           [0189] gettable   19  19  268  ; "ak47"
14E7  0A800114           [0190] newtable   20  3   0    ; array=3, hash=0
14EB  01110015           [0191] loadk      21  68       ; 19.032199859619
14EF  41110016           [0192] loadk      22  69       ; 1139.2996826172
14F3  81110017           [0193] loadk      23  70       ; 19.485200881958
14F7  9F000014           [0194] setlist    20  2        ; index 1 to 3
14FB  41040015           [0195] loadk      21  17       ; 50
14FF  9F000012           [0196] setlist    18  2        ; index 1 to 3
1503  0A800113           [0197] newtable   19  3   0    ; array=3, hash=0
1507  C5010014           [0198] getglobal  20  7        ; pickup
150B  C64A0A14           [0199] gettable   20  20  299  ; "grenade"
150F  0A800115           [0200] newtable   21  3   0    ; array=3, hash=0
1513  01120016           [0201] loadk      22  72       ; -50.979000091553
1517  41120017           [0202] loadk      23  73       ; 1132.6632080078
151B  81120018           [0203] loadk      24  74       ; 17.082000732422
151F  9F000015           [0204] setlist    21  2        ; index 1 to 3
1523  81010016           [0205] loadk      22  6        ; 5
1527  9F000013           [0206] setlist    19  2        ; index 1 to 3
152B  0A800114           [0207] newtable   20  3   0    ; array=3, hash=0
152F  C5010015           [0208] getglobal  21  7        ; pickup
1533  C6C10A15           [0209] gettable   21  21  263  ; "tec9"
1537  0A800116           [0210] newtable   22  3   0    ; array=3, hash=0
153B  C1120017           [0211] loadk      23  75       ; 568.95867919922
153F  01130018           [0212] loadk      24  76       ; 658.09552001953
1543  41130019           [0213] loadk      25  77       ; 13.073399543762
1547  9F000016           [0214] setlist    22  2        ; index 1 to 3
154B  41040017           [0215] loadk      23  17       ; 50
154F  9F000014           [0216] setlist    20  2        ; index 1 to 3
1553  0A800115           [0217] newtable   21  3   0    ; array=3, hash=0
1557  C5010016           [0218] getglobal  22  7        ; pickup
155B  864C0B16           [0219] gettable   22  22  306  ; "glock17"
155F  0A800117           [0220] newtable   23  3   0    ; array=3, hash=0
1563  81130018           [0221] loadk      24  78       ; 435.63870239258
1567  C1130019           [0222] loadk      25  79       ; 587.72192382813
156B  0114001A           [0223] loadk      26  80       ; 12.166199684143
156F  9F000017           [0224] setlist    23  2        ; index 1 to 3
1573  010F0018           [0225] loadk      24  60       ; 30
1577  9F000015           [0226] setlist    21  2        ; index 1 to 3
157B  0A800116           [0227] newtable   22  3   0    ; array=3, hash=0
157F  C5010017           [0228] getglobal  23  7        ; pickup
1583  06C30B17           [0229] gettable   23  23  268  ; "ak47"
1587  0A800118           [0230] newtable   24  3   0    ; array=3, hash=0
158B  41140019           [0231] loadk      25  81       ; 567.63067626953
158F  8114001A           [0232] loadk      26  82       ; 584.44091796875
1593  C114001B           [0233] loadk      27  83       ; 12.062999725342
1597  9F000018           [0234] setlist    24  2        ; index 1 to 3
159B  41040019           [0235] loadk      25  17       ; 50
159F  9F000016           [0236] setlist    22  2        ; index 1 to 3
15A3  0A800117           [0237] newtable   23  3   0    ; array=3, hash=0
15A7  C5010018           [0238] getglobal  24  7        ; pickup
15AB  86400C18           [0239] gettable   24  24  258  ; "shotgun"
15AF  0A800119           [0240] newtable   25  3   0    ; array=3, hash=0
15B3  0115001A           [0241] loadk      26  84       ; 508.75738525391
15B7  4115001B           [0242] loadk      27  85       ; 506.60510253906
15BB  8115001C           [0243] loadk      28  86       ; 11.32320022583
15BF  9F000019           [0244] setlist    25  2        ; index 1 to 3
15C3  0103001A           [0245] loadk      26  12       ; 10
15C7  9F000017           [0246] setlist    23  2        ; index 1 to 3
15CB  0A800118           [0247] newtable   24  3   0    ; array=3, hash=0
15CF  C5010019           [0248] getglobal  25  7        ; pickup
15D3  06C30C19           [0249] gettable   25  25  268  ; "ak47"
15D7  0A80011A           [0250] newtable   26  3   0    ; array=3, hash=0
15DB  C115001B           [0251] loadk      27  87       ; 379.40420532227
15DF  0116001C           [0252] loadk      28  88       ; 285.4462890625
15E3  4116001D           [0253] loadk      29  89       ; 11.784700393677
15E7  9F00001A           [0254] setlist    26  2        ; index 1 to 3
15EB  4104001B           [0255] loadk      27  17       ; 50
15EF  9F000018           [0256] setlist    24  2        ; index 1 to 3
15F3  0A800119           [0257] newtable   25  3   0    ; array=3, hash=0
15F7  C501001A           [0258] getglobal  26  7        ; pickup
15FB  C64A0D1A           [0259] gettable   26  26  299  ; "grenade"
15FF  0A80011B           [0260] newtable   27  3   0    ; array=3, hash=0
1603  8116001C           [0261] loadk      28  90       ; 478.12460327148
1607  C116001D           [0262] loadk      29  91       ; 400.93020629883
160B  0117001E           [0263] loadk      30  92       ; 11.656399726868
160F  9F00001B           [0264] setlist    27  2        ; index 1 to 3
1613  8101001C           [0265] loadk      28  6        ; 5
1617  9F000019           [0266] setlist    25  2        ; index 1 to 3
161B  0A80011A           [0267] newtable   26  3   0    ; array=3, hash=0
161F  C501001B           [0268] getglobal  27  7        ; pickup
1623  06C40D1B           [0269] gettable   27  27  272  ; "sniper"
1627  0A80011C           [0270] newtable   28  3   0    ; array=3, hash=0
162B  4117001D           [0271] loadk      29  93       ; 538.70239257813
162F  8117001E           [0272] loadk      30  94       ; 274.46490478516
1633  C117001F           [0273] loadk      31  95       ; 9.7047004699707
1637  9F00001C           [0274] setlist    28  2        ; index 1 to 3
163B  0103001D           [0275] loadk      29  12       ; 10
163F  9F00001A           [0276] setlist    26  2        ; index 1 to 3
1643  0A80011B           [0277] newtable   27  3   0    ; array=3, hash=0
1647  C501001C           [0278] getglobal  28  7        ; pickup
164B  864C0E1C           [0279] gettable   28  28  306  ; "glock17"
164F  0A80011D           [0280] newtable   29  3   0    ; array=3, hash=0
1653  0118001E           [0281] loadk      30  96       ; 434.01071166992
1657  4118001F           [0282] loadk      31  97       ; 220.63319396973
165B  81180020           [0283] loadk      32  98       ; 11.984000205994
165F  9F00001D           [0284] setlist    29  2        ; index 1 to 3
1663  010F001E           [0285] loadk      30  60       ; 30
1667  9F00001B           [0286] setlist    27  2        ; index 1 to 3
166B  0A80011C           [0287] newtable   28  3   0    ; array=3, hash=0
166F  C501001D           [0288] getglobal  29  7        ; pickup
1673  06C30E1D           [0289] gettable   29  29  268  ; "ak47"
1677  0A80011E           [0290] newtable   30  3   0    ; array=3, hash=0
167B  C118001F           [0291] loadk      31  99       ; 311.09588623047
167F  01190020           [0292] loadk      32  100      ; 382.82659912109
1683  41190021           [0293] loadk      33  101      ; 13.217800140381
1687  9F00001E           [0294] setlist    30  2        ; index 1 to 3
168B  4104001F           [0295] loadk      31  17       ; 50
168F  9F00001C           [0296] setlist    28  2        ; index 1 to 3
1693  0A80011D           [0297] newtable   29  3   0    ; array=3, hash=0
1697  C501001E           [0298] getglobal  30  7        ; pickup
169B  C6410F1E           [0299] gettable   30  30  263  ; "tec9"
169F  0A80011F           [0300] newtable   31  3   0    ; array=3, hash=0
16A3  81190020           [0301] loadk      32  102      ; 409.92779541016
16A7  C1190021           [0302] loadk      33  103      ; 99.222801208496
16AB  011A0022           [0303] loadk      34  104      ; 11.397899627686
16AF  9F00001F           [0304] setlist    31  2        ; index 1 to 3
16B3  41040020           [0305] loadk      32  17       ; 50
16B7  9F00001D           [0306] setlist    29  2        ; index 1 to 3
16BB  0A80011E           [0307] newtable   30  3   0    ; array=3, hash=0
16BF  C501001F           [0308] getglobal  31  7        ; pickup
16C3  06C30F1F           [0309] gettable   31  31  268  ; "ak47"
16C7  0A800120           [0310] newtable   32  3   0    ; array=3, hash=0
16CB  411A0021           [0311] loadk      33  105      ; 536.59149169922
16CF  811A0022           [0312] loadk      34  106      ; 91.743698120117
16D3  C11A0023           [0313] loadk      35  107      ; 11.191499710083
16D7  9F000020           [0314] setlist    32  2        ; index 1 to 3
16DB  41040021           [0315] loadk      33  17       ; 50
16DF  9F00001E           [0316] setlist    30  2        ; index 1 to 3
16E3  0A80011F           [0317] newtable   31  3   0    ; array=3, hash=0
16E7  C5010020           [0318] getglobal  32  7        ; pickup
16EB  06481020           [0319] gettable   32  32  288  ; "molotov"
16EF  0A800121           [0320] newtable   33  3   0    ; array=3, hash=0
16F3  011B0022           [0321] loadk      34  108      ; 170.69250488281
16F7  411B0023           [0322] loadk      35  109      ; 236.61289978027
16FB  811B0024           [0323] loadk      36  110      ; 11.91759967804
16FF  9F000021           [0324] setlist    33  2        ; index 1 to 3
1703  81010022           [0325] loadk      34  6        ; 5
1707  9F00001F           [0326] setlist    31  2        ; index 1 to 3
170B  0A800120           [0327] newtable   32  3   0    ; array=3, hash=0
170F  C5010021           [0328] getglobal  33  7        ; pickup
1713  C6CD1021           [0329] gettable   33  33  311  ; "det_grenade"
1717  0A800122           [0330] newtable   34  3   0    ; array=3, hash=0
171B  C11B0023           [0331] loadk      35  111      ; 182.25959777832
171F  011C0024           [0332] loadk      36  112      ; 17.506099700928
1723  411C0025           [0333] loadk      37  113      ; 7.8610000610352
1727  9F000022           [0334] setlist    34  2        ; index 1 to 3
172B  81010023           [0335] loadk      35  6        ; 5
172F  9F000020           [0336] setlist    32  2        ; index 1 to 3
1733  0A800121           [0337] newtable   33  3   0    ; array=3, hash=0
1737  C5010022           [0338] getglobal  34  7        ; pickup
173B  C64A1122           [0339] gettable   34  34  299  ; "grenade"
173F  0A800123           [0340] newtable   35  3   0    ; array=3, hash=0
1743  811C0024           [0341] loadk      36  114      ; 78.541397094727
1747  C11C0025           [0342] loadk      37  115      ; 303.65939331055
174B  011D0026           [0343] loadk      38  116      ; 20.623500823975
174F  9F000023           [0344] setlist    35  2        ; index 1 to 3
1753  81010024           [0345] loadk      36  6        ; 5
1757  9F000021           [0346] setlist    33  2        ; index 1 to 3
175B  DF070001           [0347] setlist    1   31       ; index 1 to 32
175F  0A800102           [0348] newtable   2   3   0    ; array=3, hash=0
1763  C5010003           [0349] getglobal  3   7        ; pickup
1767  86C00103           [0350] gettable   3   3   258  ; "shotgun"
176B  0A800104           [0351] newtable   4   3   0    ; array=3, hash=0
176F  411D0005           [0352] loadk      5   117      ; 459.87881469727
1773  C11D0006           [0353] loadk      6   119      ; -37.220100402832
1777  011E0007           [0354] loadk      7   120      ; 10.243100166321
177B  9F000004           [0355] setlist    4   2        ; index 1 to 3
177F  01030005           [0356] loadk      5   12       ; 10
1783  9F000002           [0357] setlist    2   2        ; index 1 to 3
1787  0A800103           [0358] newtable   3   3   0    ; array=3, hash=0
178B  C5010004           [0359] getglobal  4   7        ; pickup
178F  C64D0204           [0360] gettable   4   4   311  ; "det_grenade"
1793  0A800105           [0361] newtable   5   3   0    ; array=3, hash=0
1797  411E0006           [0362] loadk      6   121      ; 562.49517822266
179B  C11E0007           [0363] loadk      7   123      ; -89.406303405762
179F  011F0008           [0364] loadk      8   124      ; 9.4503002166748
17A3  9F000005           [0365] setlist    5   2        ; index 1 to 3
17A7  81010006           [0366] loadk      6   6        ; 5
17AB  9F000003           [0367] setlist    3   2        ; index 1 to 3
17AF  0A800104           [0368] newtable   4   3   0    ; array=3, hash=0
17B3  C5010005           [0369] getglobal  5   7        ; pickup
17B7  86C00205           [0370] gettable   5   5   258  ; "shotgun"
17BB  0A800106           [0371] newtable   6   3   0    ; array=3, hash=0
17BF  411F0007           [0372] loadk      7   125      ; 452.49130249023
17C3  C11F0008           [0373] loadk      8   127      ; -256.68951416016
17C7  01200009           [0374] loadk      9   128      ; 11.808699607849
17CB  9F000006           [0375] setlist    6   2        ; index 1 to 3
17CF  01030007           [0376] loadk      7   12       ; 10
17D3  9F000004           [0377] setlist    4   2        ; index 1 to 3
17D7  0A800105           [0378] newtable   5   3   0    ; array=3, hash=0
17DB  C5010006           [0379] getglobal  6   7        ; pickup
17DF  C6490306           [0380] gettable   6   6   295  ; "rocket_launcher"
17E3  0A800107           [0381] newtable   7   3   0    ; array=3, hash=0
17E7  41200008           [0382] loadk      8   129      ; 626.87109375
17EB  C1200009           [0383] loadk      9   131      ; -229.70610046387
17EF  0121000A           [0384] loadk      10  132      ; 19.32200050354
17F3  9F000007           [0385] setlist    7   2        ; index 1 to 3
17F7  81010008           [0386] loadk      8   6        ; 5
17FB  9F000005           [0387] setlist    5   2        ; index 1 to 3
17FF  0A800106           [0388] newtable   6   3   0    ; array=3, hash=0
1803  C5010007           [0389] getglobal  7   7        ; pickup
1807  86C00307           [0390] gettable   7   7   258  ; "shotgun"
180B  0A800108           [0391] newtable   8   3   0    ; array=3, hash=0
180F  41210009           [0392] loadk      9   133      ; 360.59780883789
1813  C121000A           [0393] loadk      10  135      ; -25.105899810791
1817  0122000B           [0394] loadk      11  136      ; 10.342800140381
181B  9F000008           [0395] setlist    8   2        ; index 1 to 3
181F  01030009           [0396] loadk      9   12       ; 10
1823  9F000006           [0397] setlist    6   2        ; index 1 to 3
1827  0A800107           [0398] newtable   7   3   0    ; array=3, hash=0
182B  C5010008           [0399] getglobal  8   7        ; pickup
182F  06430408           [0400] gettable   8   8   268  ; "ak47"
1833  0A800109           [0401] newtable   9   3   0    ; array=3, hash=0
1837  4122000A           [0402] loadk      10  137      ; 359.68060302734
183B  C122000B           [0403] loadk      11  139      ; -252.14860534668
183F  0123000C           [0404] loadk      12  140      ; 11.392999649048
1843  9F000009           [0405] setlist    9   2        ; index 1 to 3
1847  4104000A           [0406] loadk      10  17       ; 50
184B  9F000007           [0407] setlist    7   2        ; index 1 to 3
184F  0A800108           [0408] newtable   8   3   0    ; array=3, hash=0
1853  C5010009           [0409] getglobal  9   7        ; pickup
1857  06C80409           [0410] gettable   9   9   288  ; "molotov"
185B  0A80010A           [0411] newtable   10  3   0    ; array=3, hash=0
185F  4123000B           [0412] loadk      11  141      ; 258.68029785156
1863  C123000C           [0413] loadk      12  143      ; -415.70989990234
1867  0124000D           [0414] loadk      13  144      ; 11.24610042572
186B  9F00000A           [0415] setlist    10  2        ; index 1 to 3
186F  8101000B           [0416] loadk      11  6        ; 5
1873  9F000008           [0417] setlist    8   2        ; index 1 to 3
1877  0A800109           [0418] newtable   9   3   0    ; array=3, hash=0
187B  C501000A           [0419] getglobal  10  7        ; pickup
187F  8640050A           [0420] gettable   10  10  258  ; "shotgun"
1883  0A80010B           [0421] newtable   11  3   0    ; array=3, hash=0
1887  4124000C           [0422] loadk      12  145      ; 156.76750183105
188B  C124000D           [0423] loadk      13  147      ; -503.86419677734
188F  0125000E           [0424] loadk      14  148      ; 13.687600135803
1893  9F00000B           [0425] setlist    11  2        ; index 1 to 3
1897  0103000C           [0426] loadk      12  12       ; 10
189B  9F000009           [0427] setlist    9   2        ; index 1 to 3
189F  0A80010A           [0428] newtable   10  3   0    ; array=3, hash=0
18A3  C501000B           [0429] getglobal  11  7        ; pickup
18A7  06C3050B           [0430] gettable   11  11  268  ; "ak47"
18AB  0A80010C           [0431] newtable   12  3   0    ; array=3, hash=0
18AF  4125000D           [0432] loadk      13  149      ; 94.438499450684
18B3  C125000E           [0433] loadk      14  151      ; -583.92901611328
18B7  0126000F           [0434] loadk      15  152      ; 13.720999717712
18BB  9F00000C           [0435] setlist    12  2        ; index 1 to 3
18BF  4104000D           [0436] loadk      13  17       ; 50
18C3  9F00000A           [0437] setlist    10  2        ; index 1 to 3
18C7  0A80010B           [0438] newtable   11  3   0    ; array=3, hash=0
18CB  C501000C           [0439] getglobal  12  7        ; pickup
18CF  C649060C           [0440] gettable   12  12  295  ; "rocket_launcher"
18D3  0A80010D           [0441] newtable   13  3   0    ; array=3, hash=0
18D7  4126000E           [0442] loadk      14  153      ; 71.225196838379
18DB  C126000F           [0443] loadk      15  155      ; -303.13171386719
18DF  01270010           [0444] loadk      16  156      ; 12.402899742126
18E3  9F00000D           [0445] setlist    13  2        ; index 1 to 3
18E7  8101000E           [0446] loadk      14  6        ; 5
18EB  9F00000B           [0447] setlist    11  2        ; index 1 to 3
18EF  0A80010C           [0448] newtable   12  3   0    ; array=3, hash=0
18F3  C501000D           [0449] getglobal  13  7        ; pickup
18F7  C6C1060D           [0450] gettable   13  13  263  ; "tec9"
18FB  0A80010E           [0451] newtable   14  3   0    ; array=3, hash=0
18FF  8127000F           [0452] loadk      15  158      ; -353.31561279297
1903  01280010           [0453] loadk      16  160      ; -418.54040527344
1907  41280011           [0454] loadk      17  161      ; 9.7739000320435
190B  9F00000E           [0455] setlist    14  2        ; index 1 to 3
190F  4104000F           [0456] loadk      15  17       ; 50
1913  9F00000C           [0457] setlist    12  2        ; index 1 to 3
1917  0A80010D           [0458] newtable   13  3   0    ; array=3, hash=0
191B  C501000E           [0459] getglobal  14  7        ; pickup
191F  0643070E           [0460] gettable   14  14  268  ; "ak47"
1923  0A80010F           [0461] newtable   15  3   0    ; array=3, hash=0
1927  C1280010           [0462] loadk      16  163      ; -378.09188842773
192B  41290011           [0463] loadk      17  165      ; -284.27630615234
192F  81290012           [0464] loadk      18  166      ; 10.695300102234
1933  9F00000F           [0465] setlist    15  2        ; index 1 to 3
1937  41040010           [0466] loadk      16  17       ; 50
193B  9F00000D           [0467] setlist    13  2        ; index 1 to 3
193F  0A80010E           [0468] newtable   14  3   0    ; array=3, hash=0
1943  C501000F           [0469] getglobal  15  7        ; pickup
1947  06C4070F           [0470] gettable   15  15  272  ; "sniper"
194B  0A800110           [0471] newtable   16  3   0    ; array=3, hash=0
194F  012A0011           [0472] loadk      17  168      ; -579.64587402344
1953  812A0012           [0473] loadk      18  170      ; -419.837890625
1957  C12A0013           [0474] loadk      19  171      ; 19.84580039978
195B  9F000010           [0475] setlist    16  2        ; index 1 to 3
195F  01030011           [0476] loadk      17  12       ; 10
1963  9F00000E           [0477] setlist    14  2        ; index 1 to 3
1967  0A80010F           [0478] newtable   15  3   0    ; array=3, hash=0
196B  C5010010           [0479] getglobal  16  7        ; pickup
196F  C64A0810           [0480] gettable   16  16  299  ; "grenade"
1973  0A800111           [0481] newtable   17  3   0    ; array=3, hash=0
1977  412B0012           [0482] loadk      18  173      ; -624.87219238281
197B  C12B0013           [0483] loadk      19  175      ; -554.4677734375
197F  012C0014           [0484] loadk      20  176      ; 10.409700393677
1983  9F000011           [0485] setlist    17  2        ; index 1 to 3
1987  81010012           [0486] loadk      18  6        ; 5
198B  9F00000F           [0487] setlist    15  2        ; index 1 to 3
198F  0A800110           [0488] newtable   16  3   0    ; array=3, hash=0
1993  C5010011           [0489] getglobal  17  7        ; pickup
1997  C6C10811           [0490] gettable   17  17  263  ; "tec9"
199B  0A800112           [0491] newtable   18  3   0    ; array=3, hash=0
199F  812C0013           [0492] loadk      19  178      ; -463.53070068359
19A3  012D0014           [0493] loadk      20  180      ; -574.70587158203
19A7  412D0015           [0494] loadk      21  181      ; 12.541799545288
19AB  9F000012           [0495] setlist    18  2        ; index 1 to 3
19AF  41040013           [0496] loadk      19  17       ; 50
19B3  9F000010           [0497] setlist    16  2        ; index 1 to 3
19B7  0A800111           [0498] newtable   17  3   0    ; array=3, hash=0
19BB  C5010012           [0499] getglobal  18  7        ; pickup
19BF  06430912           [0500] gettable   18  18  268  ; "ak47"
19C3  0A800113           [0501] newtable   19  3   0    ; array=3, hash=0
19C7  C12D0014           [0502] loadk      20  183      ; -303.44351196289
19CB  412E0015           [0503] loadk      21  185      ; -602.29571533203
19CF  812E0016           [0504] loadk      22  186      ; 12.827799797058
19D3  9F000013           [0505] setlist    19  2        ; index 1 to 3
19D7  41040014           [0506] loadk      20  17       ; 50
19DB  9F000011           [0507] setlist    17  2        ; index 1 to 3
19DF  0A800112           [0508] newtable   18  3   0    ; array=3, hash=0
19E3  C5010013           [0509] getglobal  19  7        ; pickup
19E7  C6CD0913           [0510] gettable   19  19  311  ; "det_grenade"
19EB  0A800114           [0511] newtable   20  3   0    ; array=3, hash=0
19EF  012F0015           [0512] loadk      21  188      ; -191.7492980957
19F3  812F0016           [0513] loadk      22  190      ; -511.22079467773
19F7  C12F0017           [0514] loadk      23  191      ; 12.8297996521
19FB  9F000014           [0515] setlist    20  2        ; index 1 to 3
19FF  81010015           [0516] loadk      21  6        ; 5
1A03  9F000012           [0517] setlist    18  2        ; index 1 to 3
1A07  0A800113           [0518] newtable   19  3   0    ; array=3, hash=0
1A0B  C5010014           [0519] getglobal  20  7        ; pickup
1A0F  06430A14           [0520] gettable   20  20  268  ; "ak47"
1A13  0A800115           [0521] newtable   21  3   0    ; array=3, hash=0
1A17  01300016           [0522] loadk      22  192      ; 402.65859985352
1A1B  81300017           [0523] loadk      23  194      ; -463.45251464844
1A1F  C1300018           [0524] loadk      24  195      ; 10.116299629211
1A23  9F000015           [0525] setlist    21  2        ; index 1 to 3
1A27  41040016           [0526] loadk      22  17       ; 50
1A2B  9F000013           [0527] setlist    19  2        ; index 1 to 3
1A2F  0A800114           [0528] newtable   20  3   0    ; array=3, hash=0
1A33  C5010015           [0529] getglobal  21  7        ; pickup
1A37  C6C90A15           [0530] gettable   21  21  295  ; "rocket_launcher"
1A3B  0A800116           [0531] newtable   22  3   0    ; array=3, hash=0
1A3F  01310017           [0532] loadk      23  196      ; 280.3030090332
1A43  81310018           [0533] loadk      24  198      ; -605.75482177734
1A47  C1310019           [0534] loadk      25  199      ; 10.097700119019
1A4B  9F000016           [0535] setlist    22  2        ; index 1 to 3
1A4F  81010017           [0536] loadk      23  6        ; 5
1A53  9F000014           [0537] setlist    20  2        ; index 1 to 3
1A57  0A800115           [0538] newtable   21  3   0    ; array=3, hash=0
1A5B  C5010016           [0539] getglobal  22  7        ; pickup
1A5F  06430B16           [0540] gettable   22  22  268  ; "ak47"
1A63  0A800117           [0541] newtable   23  3   0    ; array=3, hash=0
1A67  01320018           [0542] loadk      24  200      ; 99.820602416992
1A6B  81320019           [0543] loadk      25  202      ; -807.87152099609
1A6F  C132001A           [0544] loadk      26  203      ; 10.457500457764
1A73  9F000017           [0545] setlist    23  2        ; index 1 to 3
1A77  41040018           [0546] loadk      24  17       ; 50
1A7B  9F000015           [0547] setlist    21  2        ; index 1 to 3
1A7F  0A800116           [0548] newtable   22  3   0    ; array=3, hash=0
1A83  C5010017           [0549] getglobal  23  7        ; pickup
1A87  C6CA0B17           [0550] gettable   23  23  299  ; "grenade"
1A8B  0A800118           [0551] newtable   24  3   0    ; array=3, hash=0
1A8F  01330019           [0552] loadk      25  204      ; 276.40399169922
1A93  8133001A           [0553] loadk      26  206      ; -802.02722167969
1A97  C133001B           [0554] loadk      27  207      ; 10.171600341797
1A9B  9F000018           [0555] setlist    24  2        ; index 1 to 3
1A9F  81010019           [0556] loadk      25  6        ; 5
1AA3  9F000016           [0557] setlist    22  2        ; index 1 to 3
1AA7  0A800117           [0558] newtable   23  3   0    ; array=3, hash=0
1AAB  C5010018           [0559] getglobal  24  7        ; pickup
1AAF  864C0C18           [0560] gettable   24  24  306  ; "glock17"
1AB3  0A800119           [0561] newtable   25  3   0    ; array=3, hash=0
1AB7  0134001A           [0562] loadk      26  208      ; 544.68829345703
1ABB  8134001B           [0563] loadk      27  210      ; -428.6091003418
1ABF  C134001C           [0564] loadk      28  211      ; 11.066699981689
1AC3  9F000019           [0565] setlist    25  2        ; index 1 to 3
1AC7  010F001A           [0566] loadk      26  60       ; 30
1ACB  9F000017           [0567] setlist    23  2        ; index 1 to 3
1ACF  0A800118           [0568] newtable   24  3   0    ; array=3, hash=0
1AD3  C5010019           [0569] getglobal  25  7        ; pickup
1AD7  86C00C19           [0570] gettable   25  25  258  ; "shotgun"
1ADB  0A80011A           [0571] newtable   26  3   0    ; array=3, hash=0
1ADF  0135001B           [0572] loadk      27  212      ; 401.70498657227
1AE3  8135001C           [0573] loadk      28  214      ; -679.45672607422
1AE7  C135001D           [0574] loadk      29  215      ; 11.066800117493
1AEB  9F00001A           [0575] setlist    26  2        ; index 1 to 3
1AEF  0103001B           [0576] loadk      27  12       ; 10
1AF3  9F000018           [0577] setlist    24  2        ; index 1 to 3
1AF7  0A800119           [0578] newtable   25  3   0    ; array=3, hash=0
1AFB  C501001A           [0579] getglobal  26  7        ; pickup
1AFF  C64D0D1A           [0580] gettable   26  26  311  ; "det_grenade"
1B03  0A80011B           [0581] newtable   27  3   0    ; array=3, hash=0
1B07  0136001C           [0582] loadk      28  216      ; 450.57299804688
1B0B  8136001D           [0583] loadk      29  218      ; -592.96881103516
1B0F  C136001E           [0584] loadk      30  219      ; 12.0172996521
1B13  9F00001B           [0585] setlist    27  2        ; index 1 to 3
1B17  8101001C           [0586] loadk      28  6        ; 5
1B1B  9F000019           [0587] setlist    25  2        ; index 1 to 3
1B1F  0A80011A           [0588] newtable   26  3   0    ; array=3, hash=0
1B23  C501001B           [0589] getglobal  27  7        ; pickup
1B27  86C00D1B           [0590] gettable   27  27  258  ; "shotgun"
1B2B  0A80011C           [0591] newtable   28  3   0    ; array=3, hash=0
1B2F  0137001D           [0592] loadk      29  220      ; 251.08850097656
1B33  8137001E           [0593] loadk      30  222      ; -1171.4642333984
1B37  C137001F           [0594] loadk      31  223      ; 12.07409954071
1B3B  9F00001C           [0595] setlist    28  2        ; index 1 to 3
1B3F  0103001D           [0596] loadk      29  12       ; 10
1B43  9F00001A           [0597] setlist    26  2        ; index 1 to 3
1B47  0A80011B           [0598] newtable   27  3   0    ; array=3, hash=0
1B4B  C501001C           [0599] getglobal  28  7        ; pickup
1B4F  C6410E1C           [0600] gettable   28  28  263  ; "tec9"
1B53  0A80011D           [0601] newtable   29  3   0    ; array=3, hash=0
1B57  0138001E           [0602] loadk      30  224      ; 254.45610046387
1B5B  8138001F           [0603] loadk      31  226      ; -974.08172607422
1B5F  C1380020           [0604] loadk      32  227      ; 10.595100402832
1B63  9F00001D           [0605] setlist    29  2        ; index 1 to 3
1B67  4104001E           [0606] loadk      30  17       ; 50
1B6B  9F00001B           [0607] setlist    27  2        ; index 1 to 3
1B6F  0A80011C           [0608] newtable   28  3   0    ; array=3, hash=0
1B73  C501001D           [0609] getglobal  29  7        ; pickup
1B77  06C30E1D           [0610] gettable   29  29  268  ; "ak47"
1B7B  0A80011E           [0611] newtable   30  3   0    ; array=3, hash=0
1B7F  0139001F           [0612] loadk      31  228      ; 207.82789611816
1B83  81390020           [0613] loadk      32  230      ; -1396.1608886719
1B87  C1370021           [0614] loadk      33  223      ; 12.07409954071
1B8B  9F00001E           [0615] setlist    30  2        ; index 1 to 3
1B8F  4104001F           [0616] loadk      31  17       ; 50
1B93  9F00001C           [0617] setlist    28  2        ; index 1 to 3
1B97  0A80011D           [0618] newtable   29  3   0    ; array=3, hash=0
1B9B  C501001E           [0619] getglobal  30  7        ; pickup
1B9F  86400F1E           [0620] gettable   30  30  258  ; "shotgun"
1BA3  0A80011F           [0621] newtable   31  3   0    ; array=3, hash=0
1BA7  C1390020           [0622] loadk      32  231      ; 79.905700683594
1BAB  413A0021           [0623] loadk      33  233      ; -1534.0103759766
1BAF  813A0022           [0624] loadk      34  234      ; 11.594200134277
1BB3  9F00001F           [0625] setlist    31  2        ; index 1 to 3
1BB7  01030020           [0626] loadk      32  12       ; 10
1BBB  9F00001D           [0627] setlist    29  2        ; index 1 to 3
1BBF  0A80011E           [0628] newtable   30  3   0    ; array=3, hash=0
1BC3  C501001F           [0629] getglobal  31  7        ; pickup
1BC7  C6C10F1F           [0630] gettable   31  31  263  ; "tec9"
1BCB  0A800120           [0631] newtable   32  3   0    ; array=3, hash=0
1BCF  C13A0021           [0632] loadk      33  235      ; 48.985599517822
1BD3  413B0022           [0633] loadk      34  237      ; -978.23522949219
1BD7  813B0023           [0634] loadk      35  238      ; 9.9913997650146
1BDB  9F000020           [0635] setlist    32  2        ; index 1 to 3
1BDF  41040021           [0636] loadk      33  17       ; 50
1BE3  9F00001E           [0637] setlist    30  2        ; index 1 to 3
1BE7  0A80011F           [0638] newtable   31  3   0    ; array=3, hash=0
1BEB  C5010020           [0639] getglobal  32  7        ; pickup
1BEF  06431020           [0640] gettable   32  32  268  ; "ak47"
1BF3  0A800121           [0641] newtable   33  3   0    ; array=3, hash=0
1BF7  013C0022           [0642] loadk      34  240      ; -107.87609863281
1BFB  813C0023           [0643] loadk      35  242      ; -975.49841308594
1BFF  C13C0024           [0644] loadk      36  243      ; 10.455699920654
1C03  9F000021           [0645] setlist    33  2        ; index 1 to 3
1C07  41040022           [0646] loadk      34  17       ; 50
1C0B  9F00001F           [0647] setlist    31  2        ; index 1 to 3
1C0F  0A800120           [0648] newtable   32  3   0    ; array=3, hash=0
1C13  C5010021           [0649] getglobal  33  7        ; pickup
1C17  86C01021           [0650] gettable   33  33  258  ; "shotgun"
1C1B  0A800122           [0651] newtable   34  3   0    ; array=3, hash=0
1C1F  413D0023           [0652] loadk      35  245      ; -203.17300415039
1C23  C13D0024           [0653] loadk      36  247      ; -1099.2678222656
1C27  013E0025           [0654] loadk      37  248      ; 14.061200141907
1C2B  9F000022           [0655] setlist    34  2        ; index 1 to 3
1C2F  01030023           [0656] loadk      35  12       ; 10
1C33  9F000020           [0657] setlist    32  2        ; index 1 to 3
1C37  0A800121           [0658] newtable   33  3   0    ; array=3, hash=0
1C3B  C5010022           [0659] getglobal  34  7        ; pickup
1C3F  06481122           [0660] gettable   34  34  288  ; "molotov"
1C43  0A800123           [0661] newtable   35  3   0    ; array=3, hash=0
1C47  813E0024           [0662] loadk      36  250      ; -171.88340759277
1C4B  013F0025           [0663] loadk      37  252      ; -1282.1033935547
1C4F  413F0026           [0664] loadk      38  253      ; 10.467000007629
1C53  9F000023           [0665] setlist    35  2        ; index 1 to 3
1C57  81010024           [0666] loadk      36  6        ; 5
1C5B  9F000021           [0667] setlist    33  2        ; index 1 to 3
1C5F  DF0F0001           [0668] setlist    1   63       ; index 33 to 64
1C63  0A800102           [0669] newtable   2   3   0    ; array=3, hash=0
1C67  C5010003           [0670] getglobal  3   7        ; pickup
1C6B  C6CA0103           [0671] gettable   3   3   299  ; "grenade"
1C6F  0A800104           [0672] newtable   4   3   0    ; array=3, hash=0
1C73  C13F0005           [0673] loadk      5   255      ; -72.124298095703
1C77  41400006           [0674] loadk      6   257      ; -1539.3717041016
1C7B  81400007           [0675] loadk      7   258      ; 10.455300331116
1C7F  9F000004           [0676] setlist    4   2        ; index 1 to 3
1C83  81010005           [0677] loadk      5   6        ; 5
1C87  9F000002           [0678] setlist    2   2        ; index 1 to 3
1C8B  0A800103           [0679] newtable   3   3   0    ; array=3, hash=0
1C8F  C5010004           [0680] getglobal  4   7        ; pickup
1C93  06480204           [0681] gettable   4   4   288  ; "molotov"
1C97  0A800105           [0682] newtable   5   3   0    ; array=3, hash=0
1C9B  C1400006           [0683] loadk      6   259      ; 14.597499847412
1C9F  41410007           [0684] loadk      7   261      ; -1387.4094238281
1CA3  81410008           [0685] loadk      8   262      ; 10.463700294495
1CA7  9F000005           [0686] setlist    5   2        ; index 1 to 3
1CAB  81010006           [0687] loadk      6   6        ; 5
1CAF  9F000003           [0688] setlist    3   2        ; index 1 to 3
1CB3  0A800104           [0689] newtable   4   3   0    ; array=3, hash=0
1CB7  C5010005           [0690] getglobal  5   7        ; pickup
1CBB  C6C90205           [0691] gettable   5   5   295  ; "rocket_launcher"
1CBF  0A800106           [0692] newtable   6   3   0    ; array=3, hash=0
1CC3  C1410007           [0693] loadk      7   263      ; 8.3240003585815
1CC7  41420008           [0694] loadk      8   265      ; -1169.4464111328
1CCB  81420009           [0695] loadk      9   266      ; 10.45860004425
1CCF  9F000006           [0696] setlist    6   2        ; index 1 to 3
1CD3  81010007           [0697] loadk      7   6        ; 5
1CD7  9F000004           [0698] setlist    4   2        ; index 1 to 3
1CDB  0A800105           [0699] newtable   5   3   0    ; array=3, hash=0
1CDF  C5010006           [0700] getglobal  6   7        ; pickup
1CE3  C64D0306           [0701] gettable   6   6   311  ; "det_grenade"
1CE7  0A800107           [0702] newtable   7   3   0    ; array=3, hash=0
1CEB  C1420008           [0703] loadk      8   267      ; 152.87300109863
1CEF  41430009           [0704] loadk      9   269      ; -1149.7781982422
1CF3  8143000A           [0705] loadk      10  270      ; 31.316200256348
1CF7  9F000007           [0706] setlist    7   2        ; index 1 to 3
1CFB  81010008           [0707] loadk      8   6        ; 5
1CFF  9F000005           [0708] setlist    5   2        ; index 1 to 3
1D03  0A800106           [0709] newtable   6   3   0    ; array=3, hash=0
1D07  C5010007           [0710] getglobal  7   7        ; pickup
1D0B  C6C90307           [0711] gettable   7   7   295  ; "rocket_launcher"
1D0F  0A800108           [0712] newtable   8   3   0    ; array=3, hash=0
1D13  C1430009           [0713] loadk      9   271      ; 281.52160644531
1D17  4144000A           [0714] loadk      10  273      ; -1531.5317382813
1D1B  8144000B           [0715] loadk      11  274      ; 11.317799568176
1D1F  9F000008           [0716] setlist    8   2        ; index 1 to 3
1D23  81010009           [0717] loadk      9   6        ; 5
1D27  9F000006           [0718] setlist    6   2        ; index 1 to 3
1D2B  0A800107           [0719] newtable   7   3   0    ; array=3, hash=0
1D2F  C5010008           [0720] getglobal  8   7        ; pickup
1D33  C1440009           [0721] loadk      9   275      ; "health"
1D37  46020408           [0722] gettable   8   8   9  
1D3B  0A800109           [0723] newtable   9   3   0    ; array=3, hash=0
1D3F  0145000A           [0724] loadk      10  276      ; 336.84341430664
1D43  4145000B           [0725] loadk      11  277      ; 1123.3869628906
1D47  8145000C           [0726] loadk      12  278      ; 18.274799346924
1D4B  9F000009           [0727] setlist    9   2        ; index 1 to 3
1D4F  8100000A           [0728] loadk      10  2        ; 1
1D53  9F000007           [0729] setlist    7   2        ; index 1 to 3
1D57  0A800108           [0730] newtable   8   3   0    ; array=3, hash=0
1D5B  C5010009           [0731] getglobal  9   7        ; pickup
1D5F  C144000A           [0732] loadk      10  275      ; "health"
1D63  86820409           [0733] gettable   9   9   10 
1D67  0A80010A           [0734] newtable   10  3   0    ; array=3, hash=0
1D6B  C145000B           [0735] loadk      11  279      ; 487.00939941406
1D6F  0146000C           [0736] loadk      12  280      ; 1124.2457275391
1D73  4146000D           [0737] loadk      13  281      ; 16.373399734497
1D77  9F00000A           [0738] setlist    10  2        ; index 1 to 3
1D7B  8100000B           [0739] loadk      11  2        ; 1
1D7F  9F000008           [0740] setlist    8   2        ; index 1 to 3
1D83  0A800109           [0741] newtable   9   3   0    ; array=3, hash=0
1D87  C501000A           [0742] getglobal  10  7        ; pickup
1D8B  C144000B           [0743] loadk      11  275      ; "health"
1D8F  C602050A           [0744] gettable   10  10  11 
1D93  0A80010B           [0745] newtable   11  3   0    ; array=3, hash=0
1D97  8146000C           [0746] loadk      12  282      ; 414.10260009766
1D9B  C146000D           [0747] loadk      13  283      ; 1222.8532714844
1D9F  0147000E           [0748] loadk      14  284      ; 18.441200256348
1DA3  9F00000B           [0749] setlist    11  2        ; index 1 to 3
1DA7  8100000C           [0750] loadk      12  2        ; 1
1DAB  9F000009           [0751] setlist    9   2        ; index 1 to 3
1DAF  0A80010A           [0752] newtable   10  3   0    ; array=3, hash=0
1DB3  C501000B           [0753] getglobal  11  7        ; pickup
1DB7  C144000C           [0754] loadk      12  275      ; "health"
1DBB  0683050B           [0755] gettable   11  11  12 
1DBF  0A80010C           [0756] newtable   12  3   0    ; array=3, hash=0
1DC3  4147000D           [0757] loadk      13  285      ; 415.95700073242
1DC7  8147000E           [0758] loadk      14  286      ; 1027.5284423828
1DCB  C107000F           [0759] loadk      15  31       ; 18.316900253296
1DCF  9F00000C           [0760] setlist    12  2        ; index 1 to 3
1DD3  8100000D           [0761] loadk      13  2        ; 1
1DD7  9F00000A           [0762] setlist    10  2        ; index 1 to 3
1DDB  0A80010B           [0763] newtable   11  3   0    ; array=3, hash=0
1DDF  C501000C           [0764] getglobal  12  7        ; pickup
1DE3  C144000D           [0765] loadk      13  275      ; "health"
1DE7  4603060C           [0766] gettable   12  12  13 
1DEB  0A80010D           [0767] newtable   13  3   0    ; array=3, hash=0
1DEF  C147000E           [0768] loadk      14  287      ; 583.12689208984
1DF3  0148000F           [0769] loadk      15  288      ; 859.03350830078
1DF7  41480010           [0770] loadk      16  289      ; 18.933200836182
1DFB  9F00000D           [0771] setlist    13  2        ; index 1 to 3
1DFF  8100000E           [0772] loadk      14  2        ; 1
1E03  9F00000B           [0773] setlist    11  2        ; index 1 to 3
1E07  0A80010C           [0774] newtable   12  3   0    ; array=3, hash=0
1E0B  C501000D           [0775] getglobal  13  7        ; pickup
1E0F  C144000E           [0776] loadk      14  275      ; "health"
1E13  8683060D           [0777] gettable   13  13  14 
1E17  0A80010E           [0778] newtable   14  3   0    ; array=3, hash=0
1E1B  8148000F           [0779] loadk      15  290      ; 295.54730224609
1E1F  C1480010           [0780] loadk      16  291      ; 756.23010253906
1E23  01490011           [0781] loadk      17  292      ; 12.948800086975
1E27  9F00000E           [0782] setlist    14  2        ; index 1 to 3
1E2B  8100000F           [0783] loadk      15  2        ; 1
1E2F  9F00000C           [0784] setlist    12  2        ; index 1 to 3
1E33  0A80010D           [0785] newtable   13  3   0    ; array=3, hash=0
1E37  C501000E           [0786] getglobal  14  7        ; pickup
1E3B  C144000F           [0787] loadk      15  275      ; "health"
1E3F  C603070E           [0788] gettable   14  14  15 
1E43  0A80010F           [0789] newtable   15  3   0    ; array=3, hash=0
1E47  41490010           [0790] loadk      16  293      ; 480.9762878418
1E4B  81490011           [0791] loadk      17  294      ; 708.81518554688
1E4F  C10D0012           [0792] loadk      18  55       ; 11.397700309753
1E53  9F00000F           [0793] setlist    15  2        ; index 1 to 3
1E57  81000010           [0794] loadk      16  2        ; 1
1E5B  9F00000D           [0795] setlist    13  2        ; index 1 to 3
1E5F  0A80010E           [0796] newtable   14  3   0    ; array=3, hash=0
1E63  C501000F           [0797] getglobal  15  7        ; pickup
1E67  C1440010           [0798] loadk      16  275      ; "health"
1E6B  0684070F           [0799] gettable   15  15  16 
1E6F  0A800110           [0800] newtable   16  3   0    ; array=3, hash=0
1E73  C1490011           [0801] loadk      17  295      ; 6.4130001068115
1E77  014A0012           [0802] loadk      18  296      ; 1062.2700195313
1E7B  414A0013           [0803] loadk      19  297      ; 12.243100166321
1E7F  9F000010           [0804] setlist    16  2        ; index 1 to 3
1E83  81000011           [0805] loadk      17  2        ; 1
1E87  9F00000E           [0806] setlist    14  2        ; index 1 to 3
1E8B  0A80010F           [0807] newtable   15  3   0    ; array=3, hash=0
1E8F  C5010010           [0808] getglobal  16  7        ; pickup
1E93  C1440011           [0809] loadk      17  275      ; "health"
1E97  46040810           [0810] gettable   16  16  17 
1E9B  0A800111           [0811] newtable   17  3   0    ; array=3, hash=0
1E9F  814A0012           [0812] loadk      18  298      ; 567.27630615234
1EA3  C14A0013           [0813] loadk      19  299      ; 530.40612792969
1EA7  C1140014           [0814] loadk      20  83       ; 12.062999725342
1EAB  9F000011           [0815] setlist    17  2        ; index 1 to 3
1EAF  81000012           [0816] loadk      18  2        ; 1
1EB3  9F00000F           [0817] setlist    15  2        ; index 1 to 3
1EB7  0A800110           [0818] newtable   16  3   0    ; array=3, hash=0
1EBB  C5010011           [0819] getglobal  17  7        ; pickup
1EBF  C1440012           [0820] loadk      18  275      ; "health"
1EC3  86840811           [0821] gettable   17  17  18 
1EC7  0A800112           [0822] newtable   18  3   0    ; array=3, hash=0
1ECB  014B0013           [0823] loadk      19  300      ; 300.66101074219
1ECF  414B0014           [0824] loadk      20  301      ; 451.54550170898
1ED3  814B0015           [0825] loadk      21  302      ; 10.46549987793
1ED7  9F000012           [0826] setlist    18  2        ; index 1 to 3
1EDB  81000013           [0827] loadk      19  2        ; 1
1EDF  9F000010           [0828] setlist    16  2        ; index 1 to 3
1EE3  0A800111           [0829] newtable   17  3   0    ; array=3, hash=0
1EE7  C5010012           [0830] getglobal  18  7        ; pickup
1EEB  C1440013           [0831] loadk      19  275      ; "health"
1EEF  C6040912           [0832] gettable   18  18  19 
1EF3  0A800113           [0833] newtable   19  3   0    ; array=3, hash=0
1EF7  C14B0014           [0834] loadk      20  303      ; 337.10641479492
1EFB  014C0015           [0835] loadk      21  304      ; 154.55819702148
1EFF  414C0016           [0836] loadk      22  305      ; 11.397500038147
1F03  9F000013           [0837] setlist    19  2        ; index 1 to 3
1F07  81000014           [0838] loadk      20  2        ; 1
1F0B  9F000011           [0839] setlist    17  2        ; index 1 to 3
1F0F  0A800112           [0840] newtable   18  3   0    ; array=3, hash=0
1F13  C5010013           [0841] getglobal  19  7        ; pickup
1F17  C1440014           [0842] loadk      20  275      ; "health"
1F1B  06850913           [0843] gettable   19  19  20 
1F1F  0A800114           [0844] newtable   20  3   0    ; array=3, hash=0
1F23  814C0015           [0845] loadk      21  306      ; 524.55157470703
1F27  C14C0016           [0846] loadk      22  307      ; 186.27789306641
1F2B  014D0017           [0847] loadk      23  308      ; 14.501099586487
1F2F  9F000014           [0848] setlist    20  2        ; index 1 to 3
1F33  81000015           [0849] loadk      21  2        ; 1
1F37  9F000012           [0850] setlist    18  2        ; index 1 to 3
1F3B  0A800113           [0851] newtable   19  3   0    ; array=3, hash=0
1F3F  C5010014           [0852] getglobal  20  7        ; pickup
1F43  C1440015           [0853] loadk      21  275      ; "health"
1F47  46050A14           [0854] gettable   20  20  21 
1F4B  0A800115           [0855] newtable   21  3   0    ; array=3, hash=0
1F4F  414D0016           [0856] loadk      22  309      ; 99.630798339844
1F53  814D0017           [0857] loadk      23  310      ; 255.67730712891
1F57  C14D0018           [0858] loadk      24  311      ; 21.764099121094
1F5B  9F000015           [0859] setlist    21  2        ; index 1 to 3
1F5F  81000016           [0860] loadk      22  2        ; 1
1F63  9F000013           [0861] setlist    19  2        ; index 1 to 3
1F67  0A800114           [0862] newtable   20  3   0    ; array=3, hash=0
1F6B  C5010015           [0863] getglobal  21  7        ; pickup
1F6F  C1440016           [0864] loadk      22  275      ; "health"
1F73  86850A15           [0865] gettable   21  21  22 
1F77  0A800116           [0866] newtable   22  3   0    ; array=3, hash=0
1F7B  014E0017           [0867] loadk      23  312      ; 497.95599365234
1F7F  814E0018           [0868] loadk      24  314      ; -84.674896240234
1F83  C14E0019           [0869] loadk      25  315      ; 10.032899856567
1F87  9F000016           [0870] setlist    22  2        ; index 1 to 3
1F8B  81000017           [0871] loadk      23  2        ; 1
1F8F  9F000014           [0872] setlist    20  2        ; index 1 to 3
1F93  0A800115           [0873] newtable   21  3   0    ; array=3, hash=0
1F97  C5010016           [0874] getglobal  22  7        ; pickup
1F9B  C1440017           [0875] loadk      23  275      ; "health"
1F9F  C6050B16           [0876] gettable   22  22  23 
1FA3  0A800117           [0877] newtable   23  3   0    ; array=3, hash=0
1FA7  014F0018           [0878] loadk      24  316      ; 200.35060119629
1FAB  814F0019           [0879] loadk      25  318      ; -492.85620117188
1FAF  C14F001A           [0880] loadk      26  319      ; 11.466400146484
1FB3  9F000017           [0881] setlist    23  2        ; index 1 to 3
1FB7  81000018           [0882] loadk      24  2        ; 1
1FBB  9F000015           [0883] setlist    21  2        ; index 1 to 3
1FBF  0A800116           [0884] newtable   22  3   0    ; array=3, hash=0
1FC3  C5010017           [0885] getglobal  23  7        ; pickup
1FC7  C1440018           [0886] loadk      24  275      ; "health"
1FCB  06860B17           [0887] gettable   23  23  24 
1FCF  0A800118           [0888] newtable   24  3   0    ; array=3, hash=0
1FD3  01500019           [0889] loadk      25  320      ; 140.02200317383
1FD7  8150001A           [0890] loadk      26  322      ; -362.17401123047
1FDB  C150001B           [0891] loadk      27  323      ; 11.559300422668
1FDF  9F000018           [0892] setlist    24  2        ; index 1 to 3
1FE3  81000019           [0893] loadk      25  2        ; 1
1FE7  9F000016           [0894] setlist    22  2        ; index 1 to 3
1FEB  0A800117           [0895] newtable   23  3   0    ; array=3, hash=0
1FEF  C5010018           [0896] getglobal  24  7        ; pickup
1FF3  C1440019           [0897] loadk      25  275      ; "health"
1FF7  46060C18           [0898] gettable   24  24  25 
1FFB  0A800119           [0899] newtable   25  3   0    ; array=3, hash=0
1FFF  4151001A           [0900] loadk      26  325      ; -378.02590942383
2003  C151001B           [0901] loadk      27  327      ; -345.8203125
2007  0152001C           [0902] loadk      28  328      ; 11.099900245667
200B  9F000019           [0903] setlist    25  2        ; index 1 to 3
200F  8100001A           [0904] loadk      26  2        ; 1
2013  9F000017           [0905] setlist    23  2        ; index 1 to 3
2017  0A800118           [0906] newtable   24  3   0    ; array=3, hash=0
201B  C5010019           [0907] getglobal  25  7        ; pickup
201F  C144001A           [0908] loadk      26  275      ; "health"
2023  86860C19           [0909] gettable   25  25  26 
2027  0A80011A           [0910] newtable   26  3   0    ; array=3, hash=0
202B  8152001B           [0911] loadk      27  330      ; -563.72528076172
202F  0153001C           [0912] loadk      28  332      ; -548.61090087891
2033  4153001D           [0913] loadk      29  333      ; 12.481200218201
2037  9F00001A           [0914] setlist    26  2        ; index 1 to 3
203B  8100001B           [0915] loadk      27  2        ; 1
203F  9F000018           [0916] setlist    24  2        ; index 1 to 3
2043  0A800119           [0917] newtable   25  3   0    ; array=3, hash=0
2047  C501001A           [0918] getglobal  26  7        ; pickup
204B  C144001B           [0919] loadk      27  275      ; "health"
204F  C6060D1A           [0920] gettable   26  26  27 
2053  0A80011B           [0921] newtable   27  3   0    ; array=3, hash=0
2057  8153001C           [0922] loadk      28  334      ; 260.2333984375
205B  0154001D           [0923] loadk      29  336      ; -747.27587890625
205F  4154001E           [0924] loadk      30  337      ; 10.150799751282
2063  9F00001B           [0925] setlist    27  2        ; index 1 to 3
2067  8100001C           [0926] loadk      28  2        ; 1
206B  9F000019           [0927] setlist    25  2        ; index 1 to 3
206F  0A80011A           [0928] newtable   26  3   0    ; array=3, hash=0
2073  C501001B           [0929] getglobal  27  7        ; pickup
2077  C144001C           [0930] loadk      28  275      ; "health"
207B  06870D1B           [0931] gettable   27  27  28 
207F  0A80011C           [0932] newtable   28  3   0    ; array=3, hash=0
2083  8154001D           [0933] loadk      29  338      ; 517.57531738281
2087  0155001E           [0934] loadk      30  340      ; -588.04681396484
208B  4155001F           [0935] loadk      31  341      ; 11.065500259399
208F  9F00001C           [0936] setlist    28  2        ; index 1 to 3
2093  8100001D           [0937] loadk      29  2        ; 1
2097  9F00001A           [0938] setlist    26  2        ; index 1 to 3
209B  0A80011B           [0939] newtable   27  3   0    ; array=3, hash=0
209F  C501001C           [0940] getglobal  28  7        ; pickup
20A3  C144001D           [0941] loadk      29  275      ; "health"
20A7  46070E1C           [0942] gettable   28  28  29 
20AB  0A80011D           [0943] newtable   29  3   0    ; array=3, hash=0
20AF  8155001E           [0944] loadk      30  342      ; 226.82429504395
20B3  0156001F           [0945] loadk      31  344      ; -1140.2021484375
20B7  41560020           [0946] loadk      32  345      ; 10.783699989319
20BB  9F00001D           [0947] setlist    29  2        ; index 1 to 3
20BF  8100001E           [0948] loadk      30  2        ; 1
20C3  9F00001B           [0949] setlist    27  2        ; index 1 to 3
20C7  0A80011C           [0950] newtable   28  3   0    ; array=3, hash=0
20CB  C501001D           [0951] getglobal  29  7        ; pickup
20CF  C144001E           [0952] loadk      30  275      ; "health"
20D3  86870E1D           [0953] gettable   29  29  30 
20D7  0A80011E           [0954] newtable   30  3   0    ; array=3, hash=0
20DB  8156001F           [0955] loadk      31  346      ; 191.74360656738
20DF  01570020           [0956] loadk      32  348      ; -1577.6478271484
20E3  41570021           [0957] loadk      33  349      ; 10.893899917603
20E7  9F00001E           [0958] setlist    30  2        ; index 1 to 3
20EB  8100001F           [0959] loadk      31  2        ; 1
20EF  9F00001C           [0960] setlist    28  2        ; index 1 to 3
20F3  0A80011D           [0961] newtable   29  3   0    ; array=3, hash=0
20F7  C501001E           [0962] getglobal  30  7        ; pickup
20FB  C144001F           [0963] loadk      31  275      ; "health"
20FF  C6070F1E           [0964] gettable   30  30  31 
2103  0A80011F           [0965] newtable   31  3   0    ; array=3, hash=0
2107  C1570020           [0966] loadk      32  351      ; -23.597200393677
210B  41580021           [0967] loadk      33  353      ; -1516.2183837891
210F  81580022           [0968] loadk      34  354      ; 10.455100059509
2113  9F00001F           [0969] setlist    31  2        ; index 1 to 3
2117  81000020           [0970] loadk      32  2        ; 1
211B  9F00001D           [0971] setlist    29  2        ; index 1 to 3
211F  0A80011E           [0972] newtable   30  3   0    ; array=3, hash=0
2123  C501001F           [0973] getglobal  31  7        ; pickup
2127  C1440020           [0974] loadk      32  275      ; "health"
212B  06880F1F           [0975] gettable   31  31  32 
212F  0A800120           [0976] newtable   32  3   0    ; array=3, hash=0
2133  01590021           [0977] loadk      33  356      ; -234.36889648438
2137  81590022           [0978] loadk      34  358      ; -1301.2520751953
213B  C1590023           [0979] loadk      35  359      ; 9.1139001846313
213F  9F000020           [0980] setlist    32  2        ; index 1 to 3
2143  81000021           [0981] loadk      33  2        ; 1
2147  9F00001E           [0982] setlist    30  2        ; index 1 to 3
214B  0A80011F           [0983] newtable   31  3   0    ; array=3, hash=0
214F  C5010020           [0984] getglobal  32  7        ; pickup
2153  C1440021           [0985] loadk      33  275      ; "health"
2157  46081020           [0986] gettable   32  32  33 
215B  0A800121           [0987] newtable   33  3   0    ; array=3, hash=0
215F  415A0022           [0988] loadk      34  361      ; -133.13960266113
2163  C15A0023           [0989] loadk      35  363      ; -981.85919189453
2167  C13C0024           [0990] loadk      36  243      ; 10.455699920654
216B  9F000021           [0991] setlist    33  2        ; index 1 to 3
216F  81000022           [0992] loadk      34  2        ; 1
2173  9F00001F           [0993] setlist    31  2        ; index 1 to 3
2177  0A800120           [0994] newtable   32  3   0    ; array=3, hash=0
217B  C5010021           [0995] getglobal  33  7        ; pickup
217F  C1440022           [0996] loadk      34  275      ; "health"
2183  86881021           [0997] gettable   33  33  34 
2187  0A800122           [0998] newtable   34  3   0    ; array=3, hash=0
218B  015B0023           [0999] loadk      35  364      ; 367.13430786133
218F  815B0024           [1000] loadk      36  366      ; -987.56500244141
2193  C15B0025           [1001] loadk      37  367      ; 11.067700386047
2197  9F000022           [1002] setlist    34  2        ; index 1 to 3
219B  81000023           [1003] loadk      35  2        ; 1
219F  9F000020           [1004] setlist    32  2        ; index 1 to 3
21A3  0A800121           [1005] newtable   33  3   0    ; array=3, hash=0
21A7  C5010022           [1006] getglobal  34  7        ; pickup
21AB  C1440023           [1007] loadk      35  275      ; "health"
21AF  C6081122           [1008] gettable   34  34  35 
21B3  0A800123           [1009] newtable   35  3   0    ; array=3, hash=0
21B7  015C0024           [1010] loadk      36  368      ; 115.61679840088
21BB  815C0025           [1011] loadk      37  370      ; -1312.8312988281
21BF  C15C0026           [1012] loadk      38  371      ; 4.4395999908447
21C3  9F000023           [1013] setlist    35  2        ; index 1 to 3
21C7  81000024           [1014] loadk      36  2        ; 1
21CB  9F000021           [1015] setlist    33  2        ; index 1 to 3
21CF  DF170001           [1016] setlist    1   95       ; index 65 to 96
21D3  0A800102           [1017] newtable   2   3   0    ; array=3, hash=0
21D7  C5010003           [1018] getglobal  3   7        ; pickup
21DB  C1440004           [1019] loadk      4   275      ; "health"
21DF  06810103           [1020] gettable   3   3   4  
21E3  0A800104           [1021] newtable   4   3   0    ; array=3, hash=0
21E7  015D0005           [1022] loadk      5   372      ; 45.123199462891
21EB  815D0006           [1023] loadk      6   374      ; -850.19189453125
21EF  C15D0007           [1024] loadk      7   375      ; 10.46010017395
21F3  9F000004           [1025] setlist    4   2        ; index 1 to 3
21F7  81000005           [1026] loadk      5   2        ; 1
21FB  9F000002           [1027] setlist    2   2        ; index 1 to 3
21FF  0A800103           [1028] newtable   3   3   0    ; array=3, hash=0
2203  C5010004           [1029] getglobal  4   7        ; pickup
2207  C1440005           [1030] loadk      5   275      ; "health"
220B  46010204           [1031] gettable   4   4   5  
220F  0A800105           [1032] newtable   5   3   0    ; array=3, hash=0
2213  415E0006           [1033] loadk      6   377      ; -107.29180145264
2217  C15E0007           [1034] loadk      7   379      ; -1610.9945068359
221B  015F0008           [1035] loadk      8   380      ; 10.177499771118
221F  9F000005           [1036] setlist    5   2        ; index 1 to 3
2223  81000006           [1037] loadk      6   2        ; 1
2227  9F000003           [1038] setlist    3   2        ; index 1 to 3
222B  0A800104           [1039] newtable   4   3   0    ; array=3, hash=0
222F  C5010005           [1040] getglobal  5   7        ; pickup
2233  415F0006           [1041] loadk      6   381      ; "armour"
2237  86810205           [1042] gettable   5   5   6  
223B  0A800106           [1043] newtable   6   3   0    ; array=3, hash=0
223F  815F0007           [1044] loadk      7   382      ; 562.17498779297
2243  C15F0008           [1045] loadk      8   383      ; 1293.9989013672
2247  01600009           [1046] loadk      9   384      ; 16.708000183105
224B  9F000006           [1047] setlist    6   2        ; index 1 to 3
224F  81000007           [1048] loadk      7   2        ; 1
2253  9F000004           [1049] setlist    4   2        ; index 1 to 3
2257  0A800105           [1050] newtable   5   3   0    ; array=3, hash=0
225B  C5010006           [1051] getglobal  6   7        ; pickup
225F  415F0007           [1052] loadk      7   381      ; "armour"
2263  C6010306           [1053] gettable   6   6   7  
2267  0A800107           [1054] newtable   7   3   0    ; array=3, hash=0
226B  41600008           [1055] loadk      8   385      ; 295.3664855957
226F  81600009           [1056] loadk      9   386      ; 957.90148925781
2273  C160000A           [1057] loadk      10  387      ; 11.51070022583
2277  9F000007           [1058] setlist    7   2        ; index 1 to 3
227B  81000008           [1059] loadk      8   2        ; 1
227F  9F000005           [1060] setlist    5   2        ; index 1 to 3
2283  0A800106           [1061] newtable   6   3   0    ; array=3, hash=0
2287  C5010007           [1062] getglobal  7   7        ; pickup
228B  415F0008           [1063] loadk      8   381      ; "armour"
228F  06820307           [1064] gettable   7   7   8  
2293  0A800108           [1065] newtable   8   3   0    ; array=3, hash=0
2297  01610009           [1066] loadk      9   388      ; 595.78771972656
229B  4161000A           [1067] loadk      10  389      ; 702.59429931641
229F  8161000B           [1068] loadk      11  390      ; 12.515500068665
22A3  9F000008           [1069] setlist    8   2        ; index 1 to 3
22A7  81000009           [1070] loadk      9   2        ; 1
22AB  9F000006           [1071] setlist    6   2        ; index 1 to 3
22AF  0A800107           [1072] newtable   7   3   0    ; array=3, hash=0
22B3  C5010008           [1073] getglobal  8   7        ; pickup
22B7  415F0009           [1074] loadk      9   381      ; "armour"
22BB  46020408           [1075] gettable   8   8   9  
22BF  0A800109           [1076] newtable   9   3   0    ; array=3, hash=0
22C3  C161000A           [1077] loadk      10  391      ; 579.1884765625
22C7  0162000B           [1078] loadk      11  392      ; 359.17880249023
22CB  4162000C           [1079] loadk      12  393      ; 17.023500442505
22CF  9F000009           [1080] setlist    9   2        ; index 1 to 3
22D3  8100000A           [1081] loadk      10  2        ; 1
22D7  9F000007           [1082] setlist    7   2        ; index 1 to 3
22DB  0A800108           [1083] newtable   8   3   0    ; array=3, hash=0
22DF  C5010009           [1084] getglobal  9   7        ; pickup
22E3  415F000A           [1085] loadk      10  381      ; "armour"
22E7  86820409           [1086] gettable   9   9   10 
22EB  0A80010A           [1087] newtable   10  3   0    ; array=3, hash=0
22EF  8162000B           [1088] loadk      11  394      ; 127.82929992676
22F3  C162000C           [1089] loadk      12  395      ; 342.65078735352
22F7  0163000D           [1090] loadk      13  396      ; 19.146999359131
22FB  9F00000A           [1091] setlist    10  2        ; index 1 to 3
22FF  8100000B           [1092] loadk      11  2        ; 1
2303  9F000008           [1093] setlist    8   2        ; index 1 to 3
2307  0A800109           [1094] newtable   9   3   0    ; array=3, hash=0
230B  C501000A           [1095] getglobal  10  7        ; pickup
230F  415F000B           [1096] loadk      11  381      ; "armour"
2313  C602050A           [1097] gettable   10  10  11 
2317  0A80010B           [1098] newtable   11  3   0    ; array=3, hash=0
231B  4163000C           [1099] loadk      12  397      ; 547.73541259766
231F  8163000D           [1100] loadk      13  398      ; 0.49919998645782
2323  C163000E           [1101] loadk      14  399      ; 14.01459980011
2327  9F00000B           [1102] setlist    11  2        ; index 1 to 3
232B  8100000C           [1103] loadk      12  2        ; 1
232F  9F000009           [1104] setlist    9   2        ; index 1 to 3
2333  0A80010A           [1105] newtable   10  3   0    ; array=3, hash=0
2337  C501000B           [1106] getglobal  11  7        ; pickup
233B  415F000C           [1107] loadk      12  381      ; "armour"
233F  0683050B           [1108] gettable   11  11  12 
2343  0A80010C           [1109] newtable   12  3   0    ; array=3, hash=0
2347  0164000D           [1110] loadk      13  400      ; 571.05261230469
234B  8164000E           [1111] loadk      14  402      ; -256.95831298828
234F  C164000F           [1112] loadk      15  403      ; 13.972999572754
2353  9F00000C           [1113] setlist    12  2        ; index 1 to 3
2357  8100000D           [1114] loadk      13  2        ; 1
235B  9F00000A           [1115] setlist    10  2        ; index 1 to 3
235F  0A80010B           [1116] newtable   11  3   0    ; array=3, hash=0
2363  C501000C           [1117] getglobal  12  7        ; pickup
2367  415F000D           [1118] loadk      13  381      ; "armour"
236B  4603060C           [1119] gettable   12  12  13 
236F  0A80010D           [1120] newtable   13  3   0    ; array=3, hash=0
2373  0165000E           [1121] loadk      14  404      ; 84.082000732422
2377  8165000F           [1122] loadk      15  406      ; -555.11376953125
237B  C1650010           [1123] loadk      16  407      ; 14.991000175476
237F  9F00000D           [1124] setlist    13  2        ; index 1 to 3
2383  8100000E           [1125] loadk      14  2        ; 1
2387  9F00000B           [1126] setlist    11  2        ; index 1 to 3
238B  0A80010C           [1127] newtable   12  3   0    ; array=3, hash=0
238F  C501000D           [1128] getglobal  13  7        ; pickup
2393  415F000E           [1129] loadk      14  381      ; "armour"
2397  8683060D           [1130] gettable   13  13  14 
239B  0A80010E           [1131] newtable   14  3   0    ; array=3, hash=0
239F  4166000F           [1132] loadk      15  409      ; -373.74261474609
23A3  C1660010           [1133] loadk      16  411      ; -223.83979797363
23A7  01670011           [1134] loadk      17  412      ; 9.1212997436523
23AB  9F00000E           [1135] setlist    14  2        ; index 1 to 3
23AF  8100000F           [1136] loadk      15  2        ; 1
23B3  9F00000C           [1137] setlist    12  2        ; index 1 to 3
23B7  0A80010D           [1138] newtable   13  3   0    ; array=3, hash=0
23BB  C501000E           [1139] getglobal  14  7        ; pickup
23BF  415F000F           [1140] loadk      15  381      ; "armour"
23C3  C603070E           [1141] gettable   14  14  15 
23C7  0A80010F           [1142] newtable   15  3   0    ; array=3, hash=0
23CB  81670010           [1143] loadk      16  414      ; -648.85638427734
23CF  01680011           [1144] loadk      17  416      ; -271.05859375
23D3  41680012           [1145] loadk      18  417      ; 9.5425996780396
23D7  9F00000F           [1146] setlist    15  2        ; index 1 to 3
23DB  81000010           [1147] loadk      16  2        ; 1
23DF  9F00000D           [1148] setlist    13  2        ; index 1 to 3
23E3  0A80010E           [1149] newtable   14  3   0    ; array=3, hash=0
23E7  C501000F           [1150] getglobal  15  7        ; pickup
23EB  415F0010           [1151] loadk      16  381      ; "armour"
23EF  0684070F           [1152] gettable   15  15  16 
23F3  0A800110           [1153] newtable   16  3   0    ; array=3, hash=0
23F7  81680011           [1154] loadk      17  418      ; 75.305702209473
23FB  01690012           [1155] loadk      18  420      ; -875.8203125
23FF  41690013           [1156] loadk      19  421      ; 10.428600311279
2403  9F000010           [1157] setlist    16  2        ; index 1 to 3
2407  81000011           [1158] loadk      17  2        ; 1
240B  9F00000E           [1159] setlist    14  2        ; index 1 to 3
240F  0A80010F           [1160] newtable   15  3   0    ; array=3, hash=0
2413  C5010010           [1161] getglobal  16  7        ; pickup
2417  415F0011           [1162] loadk      17  381      ; "armour"
241B  46040810           [1163] gettable   16  16  17 
241F  0A800111           [1164] newtable   17  3   0    ; array=3, hash=0
2423  81690012           [1165] loadk      18  422      ; 447.81988525391
2427  016A0013           [1166] loadk      19  424      ; -497.99490356445
242B  416A0014           [1167] loadk      20  425      ; 18.18510055542
242F  9F000011           [1168] setlist    17  2        ; index 1 to 3
2433  81000012           [1169] loadk      18  2        ; 1
2437  9F00000F           [1170] setlist    15  2        ; index 1 to 3
243B  0A800110           [1171] newtable   16  3   0    ; array=3, hash=0
243F  C5010011           [1172] getglobal  17  7        ; pickup
2443  415F0012           [1173] loadk      18  381      ; "armour"
2447  86840811           [1174] gettable   17  17  18 
244B  0A800112           [1175] newtable   18  3   0    ; array=3, hash=0
244F  816A0013           [1176] loadk      19  426      ; 423.23489379883
2453  016B0014           [1177] loadk      20  428      ; -767.20281982422
2457  416B0015           [1178] loadk      21  429      ; 11.071999549866
245B  9F000012           [1179] setlist    18  2        ; index 1 to 3
245F  81000013           [1180] loadk      19  2        ; 1
2463  9F000010           [1181] setlist    16  2        ; index 1 to 3
2467  0A800111           [1182] newtable   17  3   0    ; array=3, hash=0
246B  C5010012           [1183] getglobal  18  7        ; pickup
246F  415F0013           [1184] loadk      19  381      ; "armour"
2473  C6040912           [1185] gettable   18  18  19 
2477  0A800113           [1186] newtable   19  3   0    ; array=3, hash=0
247B  816B0014           [1187] loadk      20  430      ; 252.69369506836
247F  016C0015           [1188] loadk      21  432      ; -1071.6632080078
2483  416C0016           [1189] loadk      22  433      ; 11.075699806213
2487  9F000013           [1190] setlist    19  2        ; index 1 to 3
248B  81000014           [1191] loadk      20  2        ; 1
248F  9F000011           [1192] setlist    17  2        ; index 1 to 3
2493  0A800112           [1193] newtable   18  3   0    ; array=3, hash=0
2497  C5010013           [1194] getglobal  19  7        ; pickup
249B  415F0014           [1195] loadk      20  381      ; "armour"
249F  06850913           [1196] gettable   19  19  20 
24A3  0A800114           [1197] newtable   20  3   0    ; array=3, hash=0
24A7  C16C0015           [1198] loadk      21  435      ; -188.37699890137
24AB  416D0016           [1199] loadk      22  437      ; -981.86767578125
24AF  816D0017           [1200] loadk      23  438      ; 11.361399650574
24B3  9F000014           [1201] setlist    20  2        ; index 1 to 3
24B7  81000015           [1202] loadk      21  2        ; 1
24BB  9F000012           [1203] setlist    18  2        ; index 1 to 3
24BF  0A800113           [1204] newtable   19  3   0    ; array=3, hash=0
24C3  C5010014           [1205] getglobal  20  7        ; pickup
24C7  415F0015           [1206] loadk      21  381      ; "armour"
24CB  46050A14           [1207] gettable   20  20  21 
24CF  0A800115           [1208] newtable   21  3   0    ; array=3, hash=0
24D3  C16D0016           [1209] loadk      22  439      ; 20.585699081421
24D7  416E0017           [1210] loadk      23  441      ; -1296.2153320313
24DB  816E0018           [1211] loadk      24  442      ; 12.995599746704
24DF  9F000015           [1212] setlist    21  2        ; index 1 to 3
24E3  81000016           [1213] loadk      22  2        ; 1
24E7  9F000013           [1214] setlist    19  2        ; index 1 to 3
24EB  0A800114           [1215] newtable   20  3   0    ; array=3, hash=0
24EF  C5010015           [1216] getglobal  21  7        ; pickup
24F3  415F0016           [1217] loadk      22  381      ; "armour"
24F7  86850A15           [1218] gettable   21  21  22 
24FB  0A800116           [1219] newtable   22  3   0    ; array=3, hash=0
24FF  C16E0017           [1220] loadk      23  443      ; 31.862100601196
2503  416F0018           [1221] loadk      24  445      ; -1536.2216796875
2507  816F0019           [1222] loadk      25  446      ; 10.446800231934
250B  9F000016           [1223] setlist    22  2        ; index 1 to 3
250F  81000017           [1224] loadk      23  2        ; 1
2513  9F000014           [1225] setlist    20  2        ; index 1 to 3
2517  0A800115           [1226] newtable   21  3   0    ; array=3, hash=0
251B  C5010016           [1227] getglobal  22  7        ; pickup
251F  415F0017           [1228] loadk      23  381      ; "armour"
2523  C6050B16           [1229] gettable   22  22  23 
2527  0A800117           [1230] newtable   23  3   0    ; array=3, hash=0
252B  C16F0018           [1231] loadk      24  447      ; 376.3037109375
252F  41700019           [1232] loadk      25  449      ; -1582.0289306641
2533  8170001A           [1233] loadk      26  450      ; 17.281900405884
2537  9F000017           [1234] setlist    23  2        ; index 1 to 3
253B  81000018           [1235] loadk      24  2        ; 1
253F  9F000015           [1236] setlist    21  2        ; index 1 to 3
2543  DF1C0001           [1237] setlist    1   115      ; index 97 to 116
2547  00800000           [1238] move       0   1      
254B  54FF8000           [1239] jmp        1022         ; to [2262]
254F  05000001           [1240] getglobal  1   0        ; GameLocation
2553  99800001           [1241] call       1   1   2  
2557  C1700002           [1242] loadk      2   451      ; 6
255B  95800001           [1243] eq         1   1   2    ; to [1245] if false
255F  D4058000           [1244] jmp        24           ; to [1269]
2563  05000001           [1245] getglobal  1   0        ; GameLocation
2567  99800001           [1246] call       1   1   2  
256B  01710002           [1247] loadk      2   452      ; 7
256F  95800001           [1248] eq         1   1   2    ; to [1250] if false
2573  94048000           [1249] jmp        19           ; to [1269]
2577  05000001           [1250] getglobal  1   0        ; GameLocation
257B  99800001           [1251] call       1   1   2  
257F  41710002           [1252] loadk      2   453      ; 8
2583  95800001           [1253] eq         1   1   2    ; to [1255] if false
2587  54038000           [1254] jmp        14           ; to [1269]
258B  05000001           [1255] getglobal  1   0        ; GameLocation
258F  99800001           [1256] call       1   1   2  
2593  81710002           [1257] loadk      2   454      ; 9
2597  95800001           [1258] eq         1   1   2    ; to [1260] if false
259B  14028000           [1259] jmp        9            ; to [1269]
259F  05000001           [1260] getglobal  1   0        ; GameLocation
25A3  99800001           [1261] call       1   1   2  
25A7  95C10001           [1262] eq         1   1   262  ; 10, to [1264] if false
25AB  14018000           [1263] jmp        5            ; to [1269]
25AF  05000001           [1264] getglobal  1   0        ; GameLocation
25B3  99800001           [1265] call       1   1   2  
25B7  C1710002           [1266] loadk      2   455      ; 11
25BB  95800000           [1267] eq         0   1   2    ; to [1269] if true
25BF  14F88000           [1268] jmp        993          ; to [2262]
25C3  0A001301           [1269] newtable   1   38  0    ; array=96, hash=0
25C7  0A800102           [1270] newtable   2   3   0    ; array=3, hash=0
25CB  C5010003           [1271] getglobal  3   7        ; pickup
25CF  C6C10103           [1272] gettable   3   3   263  ; "tec9"
25D3  0A800104           [1273] newtable   4   3   0    ; array=3, hash=0
25D7  41720005           [1274] loadk      5   457      ; -1102.3636474609
25DB  81720006           [1275] loadk      6   458      ; 1289.4543457031
25DF  C1720007           [1276] loadk      7   459      ; 18.724599838257
25E3  9F000004           [1277] setlist    4   2        ; index 1 to 3
25E7  41040005           [1278] loadk      5   17       ; 50
25EB  9F000002           [1279] setlist    2   2        ; index 1 to 3
25EF  0A800103           [1280] newtable   3   3   0    ; array=3, hash=0
25F3  C5010004           [1281] getglobal  4   7        ; pickup
25F7  C64A0204           [1282] gettable   4   4   299  ; "grenade"
25FB  0A800105           [1283] newtable   5   3   0    ; array=3, hash=0
25FF  41730006           [1284] loadk      6   461      ; -1102.259765625
2603  81730007           [1285] loadk      7   462      ; 1372.7973632813
2607  C1720008           [1286] loadk      8   459      ; 18.724599838257
260B  9F000005           [1287] setlist    5   2        ; index 1 to 3
260F  81010006           [1288] loadk      6   6        ; 5
2613  9F000003           [1289] setlist    3   2        ; index 1 to 3
2617  0A800104           [1290] newtable   4   3   0    ; array=3, hash=0
261B  C5010005           [1291] getglobal  5   7        ; pickup
261F  06C30205           [1292] gettable   5   5   268  ; "ak47"
2623  0A800106           [1293] newtable   6   3   0    ; array=3, hash=0
2627  01740007           [1294] loadk      7   464      ; -903.15228271484
262B  41740008           [1295] loadk      8   465      ; 1485.7020263672
262F  81740009           [1296] loadk      9   466      ; 12.007900238037
2633  9F000006           [1297] setlist    6   2        ; index 1 to 3
2637  41040007           [1298] loadk      7   17       ; 50
263B  9F000004           [1299] setlist    4   2        ; index 1 to 3
263F  0A800105           [1300] newtable   5   3   0    ; array=3, hash=0
2643  C5010006           [1301] getglobal  6   7        ; pickup
2647  06480306           [1302] gettable   6   6   288  ; "molotov"
264B  0A800107           [1303] newtable   7   3   0    ; array=3, hash=0
264F  01750008           [1304] loadk      8   468      ; -757.62872314453
2653  41750009           [1305] loadk      9   469      ; 1335.4481201172
2657  8175000A           [1306] loadk      10  470      ; 11.768099784851
265B  9F000007           [1307] setlist    7   2        ; index 1 to 3
265F  81010008           [1308] loadk      8   6        ; 5
2663  9F000005           [1309] setlist    5   2        ; index 1 to 3
2667  0A800106           [1310] newtable   6   3   0    ; array=3, hash=0
266B  C5010007           [1311] getglobal  7   7        ; pickup
266F  86C00307           [1312] gettable   7   7   258  ; "shotgun"
2673  0A800108           [1313] newtable   8   3   0    ; array=3, hash=0
2677  01760009           [1314] loadk      9   472      ; -765.35906982422
267B  4176000A           [1315] loadk      10  473      ; 1267.25
267F  8176000B           [1316] loadk      11  474      ; 11.607000350952
2683  9F000008           [1317] setlist    8   2        ; index 1 to 3
2687  01030009           [1318] loadk      9   12       ; 10
268B  9F000006           [1319] setlist    6   2        ; index 1 to 3
268F  0A800107           [1320] newtable   7   3   0    ; array=3, hash=0
2693  C5010008           [1321] getglobal  8   7        ; pickup
2697  C6410408           [1322] gettable   8   8   263  ; "tec9"
269B  0A800109           [1323] newtable   9   3   0    ; array=3, hash=0
269F  0177000A           [1324] loadk      10  476      ; -607.07092285156
26A3  4177000B           [1325] loadk      11  477      ; 1293.7844238281
26A7  8177000C           [1326] loadk      12  478      ; 11.769300460815
26AB  9F000009           [1327] setlist    9   2        ; index 1 to 3
26AF  4104000A           [1328] loadk      10  17       ; 50
26B3  9F000007           [1329] setlist    7   2        ; index 1 to 3
26B7  0A800108           [1330] newtable   8   3   0    ; array=3, hash=0
26BB  C5010009           [1331] getglobal  9   7        ; pickup
26BF  06C30409           [1332] gettable   9   9   268  ; "ak47"
26C3  0A80010A           [1333] newtable   10  3   0    ; array=3, hash=0
26C7  0178000B           [1334] loadk      11  480      ; -448.0032043457
26CB  4178000C           [1335] loadk      12  481      ; 1271.1485595703
26CF  8178000D           [1336] loadk      13  482      ; 10.900899887085
26D3  9F00000A           [1337] setlist    10  2        ; index 1 to 3
26D7  4104000B           [1338] loadk      11  17       ; 50
26DB  9F000008           [1339] setlist    8   2        ; index 1 to 3
26DF  0A800109           [1340] newtable   9   3   0    ; array=3, hash=0
26E3  C501000A           [1341] getglobal  10  7        ; pickup
26E7  864C050A           [1342] gettable   10  10  306  ; "glock17"
26EB  0A80010B           [1343] newtable   11  3   0    ; array=3, hash=0
26EF  0179000C           [1344] loadk      12  484      ; -375.97570800781
26F3  4179000D           [1345] loadk      13  485      ; 1378.2847900391
26F7  8179000E           [1346] loadk      14  486      ; 11.354100227356
26FB  9F00000B           [1347] setlist    11  2        ; index 1 to 3
26FF  010F000C           [1348] loadk      12  60       ; 30
2703  9F000009           [1349] setlist    9   2        ; index 1 to 3
2707  0A80010A           [1350] newtable   10  3   0    ; array=3, hash=0
270B  C501000B           [1351] getglobal  11  7        ; pickup
270F  C6CA050B           [1352] gettable   11  11  299  ; "grenade"
2713  0A80010C           [1353] newtable   12  3   0    ; array=3, hash=0
2717  017A000D           [1354] loadk      13  488      ; -252.59260559082
271B  417A000E           [1355] loadk      14  489      ; 1311.0947265625
271F  817A000F           [1356] loadk      15  490      ; 11.39999961853
2723  9F00000C           [1357] setlist    12  2        ; index 1 to 3
2727  8101000D           [1358] loadk      13  6        ; 5
272B  9F00000A           [1359] setlist    10  2        ; index 1 to 3
272F  0A80010B           [1360] newtable   11  3   0    ; array=3, hash=0
2733  C501000C           [1361] getglobal  12  7        ; pickup
2737  8640060C           [1362] gettable   12  12  258  ; "shotgun"
273B  0A80010D           [1363] newtable   13  3   0    ; array=3, hash=0
273F  017B000E           [1364] loadk      14  492      ; -274.83828735352
2743  417B000F           [1365] loadk      15  493      ; 1122.2563476563
2747  817B0010           [1366] loadk      16  494      ; 9.3992004394531
274B  9F00000D           [1367] setlist    13  2        ; index 1 to 3
274F  0103000E           [1368] loadk      14  12       ; 10
2753  9F00000B           [1369] setlist    11  2        ; index 1 to 3
2757  0A80010C           [1370] newtable   12  3   0    ; array=3, hash=0
275B  C501000D           [1371] getglobal  13  7        ; pickup
275F  C6C9060D           [1372] gettable   13  13  295  ; "rocket_launcher"
2763  0A80010E           [1373] newtable   14  3   0    ; array=3, hash=0
2767  017C000F           [1374] loadk      15  496      ; -384.90899658203
276B  417C0010           [1375] loadk      16  497      ; 1059.9415283203
276F  817C0011           [1376] loadk      17  498      ; 13.019700050354
2773  9F00000E           [1377] setlist    14  2        ; index 1 to 3
2777  8101000F           [1378] loadk      15  6        ; 5
277B  9F00000C           [1379] setlist    12  2        ; index 1 to 3
277F  0A80010D           [1380] newtable   13  3   0    ; array=3, hash=0
2783  C501000E           [1381] getglobal  14  7        ; pickup
2787  0648070E           [1382] gettable   14  14  288  ; "molotov"
278B  0A80010F           [1383] newtable   15  3   0    ; array=3, hash=0
278F  017D0010           [1384] loadk      16  500      ; -592.51818847656
2793  417D0011           [1385] loadk      17  501      ; 1228.8198242188
2797  817D0012           [1386] loadk      18  502      ; 11.074000358582
279B  9F00000F           [1387] setlist    15  2        ; index 1 to 3
279F  81010010           [1388] loadk      16  6        ; 5
27A3  9F00000D           [1389] setlist    13  2        ; index 1 to 3
27A7  0A80010E           [1390] newtable   14  3   0    ; array=3, hash=0
27AB  C501000F           [1391] getglobal  15  7        ; pickup
27AF  06C4070F           [1392] gettable   15  15  272  ; "sniper"
27B3  0A800110           [1393] newtable   16  3   0    ; array=3, hash=0
27B7  017E0011           [1394] loadk      17  504      ; -674.28082275391
27BB  417E0012           [1395] loadk      18  505      ; 1162.0876464844
27BF  817E0013           [1396] loadk      19  506      ; 28.16609954834
27C3  9F000010           [1397] setlist    16  2        ; index 1 to 3
27C7  01030011           [1398] loadk      17  12       ; 10
27CB  9F00000E           [1399] setlist    14  2        ; index 1 to 3
27CF  0A80010F           [1400] newtable   15  3   0    ; array=3, hash=0
27D3  C5010010           [1401] getglobal  16  7        ; pickup
27D7  C6410810           [1402] gettable   16  16  263  ; "tec9"
27DB  0A800111           [1403] newtable   17  3   0    ; array=3, hash=0
27DF  017F0012           [1404] loadk      18  508      ; -738.48602294922
27E3  417F0013           [1405] loadk      19  509      ; 1010.1707763672
27E7  817F0014           [1406] loadk      20  510      ; 11.378499984741
27EB  9F000011           [1407] setlist    17  2        ; index 1 to 3
27EF  41040012           [1408] loadk      18  17       ; 50
27F3  9F00000F           [1409] setlist    15  2        ; index 1 to 3
27F7  0A800110           [1410] newtable   16  3   0    ; array=3, hash=0
27FB  C5010011           [1411] getglobal  17  7        ; pickup
27FF  C6CD0811           [1412] gettable   17  17  311  ; "det_grenade"
2803  0A800112           [1413] newtable   18  3   0    ; array=3, hash=0
2807  01800013           [1414] loadk      19  512      ; -942.76641845703
280B  41800014           [1415] loadk      20  513      ; 1153.6883544922
280F  81800015           [1416] loadk      21  514      ; 11.156100273132
2813  9F000012           [1417] setlist    18  2        ; index 1 to 3
2817  81010013           [1418] loadk      19  6        ; 5
281B  9F000010           [1419] setlist    16  2        ; index 1 to 3
281F  0A800111           [1420] newtable   17  3   0    ; array=3, hash=0
2823  C5010012           [1421] getglobal  18  7        ; pickup
2827  C6490912           [1422] gettable   18  18  295  ; "rocket_launcher"
282B  0A800113           [1423] newtable   19  3   0    ; array=3, hash=0
282F  01810014           [1424] loadk      20  516      ; -905.640625
2833  41810015           [1425] loadk      21  517      ; 992.7919921875
2837  81810016           [1426] loadk      22  518      ; 11.087300300598
283B  9F000013           [1427] setlist    19  2        ; index 1 to 3
283F  81010014           [1428] loadk      20  6        ; 5
2843  9F000011           [1429] setlist    17  2        ; index 1 to 3
2847  0A800112           [1430] newtable   18  3   0    ; array=3, hash=0
284B  C5010013           [1431] getglobal  19  7        ; pickup
284F  86CC0913           [1432] gettable   19  19  306  ; "glock17"
2853  0A800114           [1433] newtable   20  3   0    ; array=3, hash=0
2857  01820015           [1434] loadk      21  520      ; -898.88049316406
285B  41820016           [1435] loadk      22  521      ; 856.92578125
285F  81820017           [1436] loadk      23  522      ; 11.315699577332
2863  9F000014           [1437] setlist    20  2        ; index 1 to 3
2867  010F0015           [1438] loadk      21  60       ; 30
286B  9F000012           [1439] setlist    18  2        ; index 1 to 3
286F  0A800113           [1440] newtable   19  3   0    ; array=3, hash=0
2873  C5010014           [1441] getglobal  20  7        ; pickup
2877  86400A14           [1442] gettable   20  20  258  ; "shotgun"
287B  0A800115           [1443] newtable   21  3   0    ; array=3, hash=0
287F  01830016           [1444] loadk      22  524      ; -633.96429443359
2883  41830017           [1445] loadk      23  525      ; 910.01531982422
2887  81830018           [1446] loadk      24  526      ; 11.080599784851
288B  9F000015           [1447] setlist    21  2        ; index 1 to 3
288F  01030016           [1448] loadk      22  12       ; 10
2893  9F000013           [1449] setlist    19  2        ; index 1 to 3
2897  0A800114           [1450] newtable   20  3   0    ; array=3, hash=0
289B  C5010015           [1451] getglobal  21  7        ; pickup
289F  06C40A15           [1452] gettable   21  21  272  ; "sniper"
28A3  0A800116           [1453] newtable   22  3   0    ; array=3, hash=0
28A7  01840017           [1454] loadk      23  528      ; -653.35021972656
28AB  41840018           [1455] loadk      24  529      ; 766.02978515625
28AF  81840019           [1456] loadk      25  530      ; 30.912300109863
28B3  9F000016           [1457] setlist    22  2        ; index 1 to 3
28B7  01030017           [1458] loadk      23  12       ; 10
28BB  9F000014           [1459] setlist    20  2        ; index 1 to 3
28BF  0A800115           [1460] newtable   21  3   0    ; array=3, hash=0
28C3  C5010016           [1461] getglobal  22  7        ; pickup
28C7  C64D0B16           [1462] gettable   22  22  311  ; "det_grenade"
28CB  0A800117           [1463] newtable   23  3   0    ; array=3, hash=0
28CF  01850018           [1464] loadk      24  532      ; -726.84417724609
28D3  41850019           [1465] loadk      25  533      ; 839.83160400391
28D7  8185001A           [1466] loadk      26  534      ; 11.090200424194
28DB  9F000017           [1467] setlist    23  2        ; index 1 to 3
28DF  81010018           [1468] loadk      24  6        ; 5
28E3  9F000015           [1469] setlist    21  2        ; index 1 to 3
28E7  0A800116           [1470] newtable   22  3   0    ; array=3, hash=0
28EB  C5010017           [1471] getglobal  23  7        ; pickup
28EF  C6C10B17           [1472] gettable   23  23  263  ; "tec9"
28F3  0A800118           [1473] newtable   24  3   0    ; array=3, hash=0
28F7  01860019           [1474] loadk      25  536      ; -400.86938476563
28FB  4186001A           [1475] loadk      26  537      ; 891.73767089844
28FF  8186001B           [1476] loadk      27  538      ; 10.83810043335
2903  9F000018           [1477] setlist    24  2        ; index 1 to 3
2907  41040019           [1478] loadk      25  17       ; 50
290B  9F000016           [1479] setlist    22  2        ; index 1 to 3
290F  0A800117           [1480] newtable   23  3   0    ; array=3, hash=0
2913  C5010018           [1481] getglobal  24  7        ; pickup
2917  C6490C18           [1482] gettable   24  24  295  ; "rocket_launcher"
291B  0A800119           [1483] newtable   25  3   0    ; array=3, hash=0
291F  0187001A           [1484] loadk      26  540      ; -548.91961669922
2923  4187001B           [1485] loadk      27  541      ; 847.44012451172
2927  8187001C           [1486] loadk      28  542      ; 22.984399795532
292B  9F000019           [1487] setlist    25  2        ; index 1 to 3
292F  8101001A           [1488] loadk      26  6        ; 5
2933  9F000017           [1489] setlist    23  2        ; index 1 to 3
2937  0A800118           [1490] newtable   24  3   0    ; array=3, hash=0
293B  C5010019           [1491] getglobal  25  7        ; pickup
293F  C6C90C19           [1492] gettable   25  25  295  ; "rocket_launcher"
2943  0A80011A           [1493] newtable   26  3   0    ; array=3, hash=0
2947  0188001B           [1494] loadk      27  544      ; -605.25451660156
294B  4188001C           [1495] loadk      28  545      ; 637.13598632813
294F  8188001D           [1496] loadk      29  546      ; 22.101800918579
2953  9F00001A           [1497] setlist    26  2        ; index 1 to 3
2957  8101001B           [1498] loadk      27  6        ; 5
295B  9F000018           [1499] setlist    24  2        ; index 1 to 3
295F  0A800119           [1500] newtable   25  3   0    ; array=3, hash=0
2963  C501001A           [1501] getglobal  26  7        ; pickup
2967  06430D1A           [1502] gettable   26  26  268  ; "ak47"
296B  0A80011B           [1503] newtable   27  3   0    ; array=3, hash=0
296F  0189001C           [1504] loadk      28  548      ; -768.16088867188
2973  4189001D           [1505] loadk      29  549      ; 131.44520568848
2977  8189001E           [1506] loadk      30  550      ; 11.02260017395
297B  9F00001B           [1507] setlist    27  2        ; index 1 to 3
297F  4104001C           [1508] loadk      28  17       ; 50
2983  9F000019           [1509] setlist    25  2        ; index 1 to 3
2987  0A80011A           [1510] newtable   26  3   0    ; array=3, hash=0
298B  C501001B           [1511] getglobal  27  7        ; pickup
298F  86CC0D1B           [1512] gettable   27  27  306  ; "glock17"
2993  0A80011C           [1513] newtable   28  3   0    ; array=3, hash=0
2997  018A001D           [1514] loadk      29  552      ; -862.48199462891
299B  418A001E           [1515] loadk      30  553      ; 271.94158935547
299F  818A001F           [1516] loadk      31  554      ; 11.266500473022
29A3  9F00001C           [1517] setlist    28  2        ; index 1 to 3
29A7  010F001D           [1518] loadk      29  60       ; 30
29AB  9F00001A           [1519] setlist    26  2        ; index 1 to 3
29AF  0A80011B           [1520] newtable   27  3   0    ; array=3, hash=0
29B3  C501001C           [1521] getglobal  28  7        ; pickup
29B7  86400E1C           [1522] gettable   28  28  258  ; "shotgun"
29BB  0A80011D           [1523] newtable   29  3   0    ; array=3, hash=0
29BF  018B001E           [1524] loadk      30  556      ; -979.16650390625
29C3  418B001F           [1525] loadk      31  557      ; 118.77780151367
29C7  818B0020           [1526] loadk      32  558      ; 9.2631998062134
29CB  9F00001D           [1527] setlist    29  2        ; index 1 to 3
29CF  0103001E           [1528] loadk      30  12       ; 10
29D3  9F00001B           [1529] setlist    27  2        ; index 1 to 3
29D7  0A80011C           [1530] newtable   28  3   0    ; array=3, hash=0
29DB  C501001D           [1531] getglobal  29  7        ; pickup
29DF  C6C10E1D           [1532] gettable   29  29  263  ; "tec9"
29E3  0A80011E           [1533] newtable   30  3   0    ; array=3, hash=0
29E7  018C001F           [1534] loadk      31  560      ; -739.5595703125
29EB  418C0020           [1535] loadk      32  561      ; 24.128200531006
29EF  818C0021           [1536] loadk      33  562      ; 11.062299728394
29F3  9F00001E           [1537] setlist    30  2        ; index 1 to 3
29F7  4104001F           [1538] loadk      31  17       ; 50
29FB  9F00001C           [1539] setlist    28  2        ; index 1 to 3
29FF  0A80011D           [1540] newtable   29  3   0    ; array=3, hash=0
2A03  C501001E           [1541] getglobal  30  7        ; pickup
2A07  C64D0F1E           [1542] gettable   30  30  311  ; "det_grenade"
2A0B  0A80011F           [1543] newtable   31  3   0    ; array=3, hash=0
2A0F  018D0020           [1544] loadk      32  564      ; -1122.97265625
2A13  418D0021           [1545] loadk      33  565      ; 58.162601470947
2A17  818D0022           [1546] loadk      34  566      ; 11.187100410461
2A1B  9F00001F           [1547] setlist    31  2        ; index 1 to 3
2A1F  81010020           [1548] loadk      32  6        ; 5
2A23  9F00001D           [1549] setlist    29  2        ; index 1 to 3
2A27  0A80011E           [1550] newtable   30  3   0    ; array=3, hash=0
2A2B  C501001F           [1551] getglobal  31  7        ; pickup
2A2F  86CC0F1F           [1552] gettable   31  31  306  ; "glock17"
2A33  0A800120           [1553] newtable   32  3   0    ; array=3, hash=0
2A37  018E0021           [1554] loadk      33  568      ; -900.56079101563
2A3B  818E0022           [1555] loadk      34  570      ; -20.086799621582
2A3F  C18E0023           [1556] loadk      35  571      ; 10.907899856567
2A43  9F000020           [1557] setlist    32  2        ; index 1 to 3
2A47  010F0021           [1558] loadk      33  60       ; 30
2A4B  9F00001E           [1559] setlist    30  2        ; index 1 to 3
2A4F  0A80011F           [1560] newtable   31  3   0    ; array=3, hash=0
2A53  C5010020           [1561] getglobal  32  7        ; pickup
2A57  06481020           [1562] gettable   32  32  288  ; "molotov"
2A5B  0A800121           [1563] newtable   33  3   0    ; array=3, hash=0
2A5F  418F0022           [1564] loadk      34  573      ; -967.71392822266
2A63  C18F0023           [1565] loadk      35  575      ; -231.75039672852
2A67  01900024           [1566] loadk      36  576      ; 10.965999603271
2A6B  9F000021           [1567] setlist    33  2        ; index 1 to 3
2A6F  81010022           [1568] loadk      34  6        ; 5
2A73  9F00001F           [1569] setlist    31  2        ; index 1 to 3
2A77  0A800120           [1570] newtable   32  3   0    ; array=3, hash=0
2A7B  C5010021           [1571] getglobal  33  7        ; pickup
2A7F  06C31021           [1572] gettable   33  33  268  ; "ak47"
2A83  0A800122           [1573] newtable   34  3   0    ; array=3, hash=0
2A87  81900023           [1574] loadk      35  578      ; -1184.1021728516
2A8B  01910024           [1575] loadk      36  580      ; -87.980598449707
2A8F  41910025           [1576] loadk      37  581      ; 11.446599960327
2A93  9F000022           [1577] setlist    34  2        ; index 1 to 3
2A97  41040023           [1578] loadk      35  17       ; 50
2A9B  9F000020           [1579] setlist    32  2        ; index 1 to 3
2A9F  0A800121           [1580] newtable   33  3   0    ; array=3, hash=0
2AA3  C5010022           [1581] getglobal  34  7        ; pickup
2AA7  C64D1122           [1582] gettable   34  34  311  ; "det_grenade"
2AAB  0A800123           [1583] newtable   35  3   0    ; array=3, hash=0
2AAF  C1910024           [1584] loadk      36  583      ; -1221.0228271484
2AB3  41920025           [1585] loadk      37  585      ; -244.25830078125
2AB7  41910026           [1586] loadk      38  581      ; 11.446599960327
2ABB  9F000023           [1587] setlist    35  2        ; index 1 to 3
2ABF  81010024           [1588] loadk      36  6        ; 5
2AC3  9F000021           [1589] setlist    33  2        ; index 1 to 3
2AC7  DF070001           [1590] setlist    1   31       ; index 1 to 32
2ACB  0A800102           [1591] newtable   2   3   0    ; array=3, hash=0
2ACF  C5010003           [1592] getglobal  3   7        ; pickup
2AD3  C6CD0103           [1593] gettable   3   3   311  ; "det_grenade"
2AD7  0A800104           [1594] newtable   4   3   0    ; array=3, hash=0
2ADB  C1920005           [1595] loadk      5   587      ; -1150.9964599609
2ADF  41930006           [1596] loadk      6   589      ; -412.18869018555
2AE3  81930007           [1597] loadk      7   590      ; 10.94550037384
2AE7  9F000004           [1598] setlist    4   2        ; index 1 to 3
2AEB  81010005           [1599] loadk      5   6        ; 5
2AEF  9F000002           [1600] setlist    2   2        ; index 1 to 3
2AF3  0A800103           [1601] newtable   3   3   0    ; array=3, hash=0
2AF7  C5010004           [1602] getglobal  4   7        ; pickup
2AFB  06430204           [1603] gettable   4   4   268  ; "ak47"
2AFF  0A800105           [1604] newtable   5   3   0    ; array=3, hash=0
2B03  01940006           [1605] loadk      6   592      ; -1044.7026367188
2B07  81940007           [1606] loadk      7   594      ; -434.0212097168
2B0B  C1940008           [1607] loadk      8   595      ; 10.902099609375
2B0F  9F000005           [1608] setlist    5   2        ; index 1 to 3
2B13  41040006           [1609] loadk      6   17       ; 50
2B17  9F000003           [1610] setlist    3   2        ; index 1 to 3
2B1B  0A800104           [1611] newtable   4   3   0    ; array=3, hash=0
2B1F  C5010005           [1612] getglobal  5   7        ; pickup
2B23  06C40205           [1613] gettable   5   5   272  ; "sniper"
2B27  0A800106           [1614] newtable   6   3   0    ; array=3, hash=0
2B2B  41950007           [1615] loadk      7   597      ; -1148.5751953125
2B2F  C1950008           [1616] loadk      8   599      ; -651.47857666016
2B33  01960009           [1617] loadk      9   600      ; 22.686100006104
2B37  9F000006           [1618] setlist    6   2        ; index 1 to 3
2B3B  01030007           [1619] loadk      7   12       ; 10
2B3F  9F000004           [1620] setlist    4   2        ; index 1 to 3
2B43  0A800105           [1621] newtable   5   3   0    ; array=3, hash=0
2B47  C5010006           [1622] getglobal  6   7        ; pickup
2B4B  C6410306           [1623] gettable   6   6   263  ; "tec9"
2B4F  0A800107           [1624] newtable   7   3   0    ; array=3, hash=0
2B53  81960008           [1625] loadk      8   602      ; -1015.5377197266
2B57  01970009           [1626] loadk      9   604      ; -635.70782470703
2B5B  4197000A           [1627] loadk      10  605      ; 11.586899757385
2B5F  9F000007           [1628] setlist    7   2        ; index 1 to 3
2B63  41040008           [1629] loadk      8   17       ; 50
2B67  9F000005           [1630] setlist    5   2        ; index 1 to 3
2B6B  0A800106           [1631] newtable   6   3   0    ; array=3, hash=0
2B6F  C5010007           [1632] getglobal  7   7        ; pickup
2B73  86C00307           [1633] gettable   7   7   258  ; "shotgun"
2B77  0A800108           [1634] newtable   8   3   0    ; array=3, hash=0
2B7B  C1970009           [1635] loadk      9   607      ; -881.90399169922
2B7F  4198000A           [1636] loadk      10  609      ; -341.55068969727
2B83  8198000B           [1637] loadk      11  610      ; 11.107600212097
2B87  9F000008           [1638] setlist    8   2        ; index 1 to 3
2B8B  01030009           [1639] loadk      9   12       ; 10
2B8F  9F000006           [1640] setlist    6   2        ; index 1 to 3
2B93  0A800107           [1641] newtable   7   3   0    ; array=3, hash=0
2B97  C5010008           [1642] getglobal  8   7        ; pickup
2B9B  06430408           [1643] gettable   8   8   268  ; "ak47"
2B9F  0A800109           [1644] newtable   9   3   0    ; array=3, hash=0
2BA3  0199000A           [1645] loadk      10  612      ; -806.15789794922
2BA7  8199000B           [1646] loadk      11  614      ; -360.56399536133
2BAB  C199000C           [1647] loadk      12  615      ; 8.2847995758057
2BAF  9F000009           [1648] setlist    9   2        ; index 1 to 3
2BB3  4104000A           [1649] loadk      10  17       ; 50
2BB7  9F000007           [1650] setlist    7   2        ; index 1 to 3
2BBB  0A800108           [1651] newtable   8   3   0    ; array=3, hash=0
2BBF  C5010009           [1652] getglobal  9   7        ; pickup
2BC3  86CC0409           [1653] gettable   9   9   306  ; "glock17"
2BC7  0A80010A           [1654] newtable   10  3   0    ; array=3, hash=0
2BCB  419A000B           [1655] loadk      11  617      ; -958.37951660156
2BCF  C19A000C           [1656] loadk      12  619      ; -405.55410766602
2BD3  019B000D           [1657] loadk      13  620      ; 11.010800361633
2BD7  9F00000A           [1658] setlist    10  2        ; index 1 to 3
2BDB  010F000B           [1659] loadk      11  60       ; 30
2BDF  9F000008           [1660] setlist    8   2        ; index 1 to 3
2BE3  0A800109           [1661] newtable   9   3   0    ; array=3, hash=0
2BE7  C501000A           [1662] getglobal  10  7        ; pickup
2BEB  0644050A           [1663] gettable   10  10  272  ; "sniper"
2BEF  0A80010B           [1664] newtable   11  3   0    ; array=3, hash=0
2BF3  819B000C           [1665] loadk      12  622      ; -884.93487548828
2BF7  019C000D           [1666] loadk      13  624      ; -691.3251953125
2BFB  419C000E           [1667] loadk      14  625      ; 25.39520072937
2BFF  9F00000B           [1668] setlist    11  2        ; index 1 to 3
2C03  0103000C           [1669] loadk      12  12       ; 10
2C07  9F000009           [1670] setlist    9   2        ; index 1 to 3
2C0B  0A80010A           [1671] newtable   10  3   0    ; array=3, hash=0
2C0F  C501000B           [1672] getglobal  11  7        ; pickup
2C13  C6CA050B           [1673] gettable   11  11  299  ; "grenade"
2C17  0A80010C           [1674] newtable   12  3   0    ; array=3, hash=0
2C1B  C19C000D           [1675] loadk      13  627      ; -996.7548828125
2C1F  419D000E           [1676] loadk      14  629      ; -834.4384765625
2C23  819D000F           [1677] loadk      15  630      ; 6.3737001419067
2C27  9F00000C           [1678] setlist    12  2        ; index 1 to 3
2C2B  8101000D           [1679] loadk      13  6        ; 5
2C2F  9F00000A           [1680] setlist    10  2        ; index 1 to 3
2C33  0A80010B           [1681] newtable   11  3   0    ; array=3, hash=0
2C37  C501000C           [1682] getglobal  12  7        ; pickup
2C3B  0643060C           [1683] gettable   12  12  268  ; "ak47"
2C3F  0A80010D           [1684] newtable   13  3   0    ; array=3, hash=0
2C43  019E000E           [1685] loadk      14  632      ; -917.94219970703
2C47  819E000F           [1686] loadk      15  634      ; -941.05798339844
2C4B  C19E0010           [1687] loadk      16  635      ; 12.184499740601
2C4F  9F00000D           [1688] setlist    13  2        ; index 1 to 3
2C53  4104000E           [1689] loadk      14  17       ; 50
2C57  9F00000B           [1690] setlist    11  2        ; index 1 to 3
2C5B  0A80010C           [1691] newtable   12  3   0    ; array=3, hash=0
2C5F  C501000D           [1692] getglobal  13  7        ; pickup
2C63  86CC060D           [1693] gettable   13  13  306  ; "glock17"
2C67  0A80010E           [1694] newtable   14  3   0    ; array=3, hash=0
2C6B  419F000F           [1695] loadk      15  637      ; -1087.8601074219
2C6F  C19F0010           [1696] loadk      16  639      ; -713.54821777344
2C73  01A00011           [1697] loadk      17  640      ; 11.793000221252
2C77  9F00000E           [1698] setlist    14  2        ; index 1 to 3
2C7B  010F000F           [1699] loadk      15  60       ; 30
2C7F  9F00000C           [1700] setlist    12  2        ; index 1 to 3
2C83  0A80010D           [1701] newtable   13  3   0    ; array=3, hash=0
2C87  C501000E           [1702] getglobal  14  7        ; pickup
2C8B  C641070E           [1703] gettable   14  14  263  ; "tec9"
2C8F  0A80010F           [1704] newtable   15  3   0    ; array=3, hash=0
2C93  81A00010           [1705] loadk      16  642      ; -786.90557861328
2C97  01A10011           [1706] loadk      17  644      ; -1222.3607177734
2C9B  41A10012           [1707] loadk      18  645      ; 10.993000030518
2C9F  9F00000F           [1708] setlist    15  2        ; index 1 to 3
2CA3  41040010           [1709] loadk      16  17       ; 50
2CA7  9F00000D           [1710] setlist    13  2        ; index 1 to 3
2CAB  0A80010E           [1711] newtable   14  3   0    ; array=3, hash=0
2CAF  C501000F           [1712] getglobal  15  7        ; pickup
2CB3  86C0070F           [1713] gettable   15  15  258  ; "shotgun"
2CB7  0A800110           [1714] newtable   16  3   0    ; array=3, hash=0
2CBB  C1A10011           [1715] loadk      17  647      ; -883.49212646484
2CBF  41A20012           [1716] loadk      18  649      ; -1266.8399658203
2CC3  81A20013           [1717] loadk      19  650      ; 11.734900474548
2CC7  9F000010           [1718] setlist    16  2        ; index 1 to 3
2CCB  01030011           [1719] loadk      17  12       ; 10
2CCF  9F00000E           [1720] setlist    14  2        ; index 1 to 3
2CD3  0A80010F           [1721] newtable   15  3   0    ; array=3, hash=0
2CD7  C5010010           [1722] getglobal  16  7        ; pickup
2CDB  06430810           [1723] gettable   16  16  268  ; "ak47"
2CDF  0A800111           [1724] newtable   17  3   0    ; array=3, hash=0
2CE3  01A30012           [1725] loadk      18  652      ; -862.99230957031
2CE7  81A30013           [1726] loadk      19  654      ; -1522.6644287109
2CEB  C1A30014           [1727] loadk      20  655      ; 12.136500358582
2CEF  9F000011           [1728] setlist    17  2        ; index 1 to 3
2CF3  41040012           [1729] loadk      18  17       ; 50
2CF7  9F00000F           [1730] setlist    15  2        ; index 1 to 3
2CFB  0A800110           [1731] newtable   16  3   0    ; array=3, hash=0
2CFF  C5010011           [1732] getglobal  17  7        ; pickup
2D03  C6C10811           [1733] gettable   17  17  263  ; "tec9"
2D07  0A800112           [1734] newtable   18  3   0    ; array=3, hash=0
2D0B  41A40013           [1735] loadk      19  657      ; -973.63928222656
2D0F  C1A40014           [1736] loadk      20  659      ; -1467.1578369141
2D13  01A50015           [1737] loadk      21  660      ; 12.01220035553
2D17  9F000012           [1738] setlist    18  2        ; index 1 to 3
2D1B  41040013           [1739] loadk      19  17       ; 50
2D1F  9F000010           [1740] setlist    16  2        ; index 1 to 3
2D23  0A800111           [1741] newtable   17  3   0    ; array=3, hash=0
2D27  C5010012           [1742] getglobal  18  7        ; pickup
2D2B  06440912           [1743] gettable   18  18  272  ; "sniper"
2D2F  0A800113           [1744] newtable   19  3   0    ; array=3, hash=0
2D33  81A50014           [1745] loadk      20  662      ; -868.18408203125
2D37  01A60015           [1746] loadk      21  664      ; -1387.0473632813
2D3B  41A60016           [1747] loadk      22  665      ; 28.562999725342
2D3F  9F000013           [1748] setlist    19  2        ; index 1 to 3
2D43  01030014           [1749] loadk      20  12       ; 10
2D47  9F000011           [1750] setlist    17  2        ; index 1 to 3
2D4B  0A800112           [1751] newtable   18  3   0    ; array=3, hash=0
2D4F  C5010013           [1752] getglobal  19  7        ; pickup
2D53  06C80913           [1753] gettable   19  19  288  ; "molotov"
2D57  0A800114           [1754] newtable   20  3   0    ; array=3, hash=0
2D5B  C1A60015           [1755] loadk      21  667      ; -677.99157714844
2D5F  41A70016           [1756] loadk      22  669      ; -1530.7707519531
2D63  81A70017           [1757] loadk      23  670      ; 12.463000297546
2D67  9F000014           [1758] setlist    20  2        ; index 1 to 3
2D6B  81010015           [1759] loadk      21  6        ; 5
2D6F  9F000012           [1760] setlist    18  2        ; index 1 to 3
2D73  0A800113           [1761] newtable   19  3   0    ; array=3, hash=0
2D77  C5010014           [1762] getglobal  20  7        ; pickup
2D7B  C6490A14           [1763] gettable   20  20  295  ; "rocket_launcher"
2D7F  0A800115           [1764] newtable   21  3   0    ; array=3, hash=0
2D83  01A80016           [1765] loadk      22  672      ; -665.94018554688
2D87  81A80017           [1766] loadk      23  674      ; -1285.6158447266
2D8B  C1A80018           [1767] loadk      24  675      ; 29.961599349976
2D8F  9F000015           [1768] setlist    21  2        ; index 1 to 3
2D93  81010016           [1769] loadk      22  6        ; 5
2D97  9F000013           [1770] setlist    19  2        ; index 1 to 3
2D9B  0A800114           [1771] newtable   20  3   0    ; array=3, hash=0
2D9F  C5010015           [1772] getglobal  21  7        ; pickup
2DA3  C6C10A15           [1773] gettable   21  21  263  ; "tec9"
2DA7  0A800116           [1774] newtable   22  3   0    ; array=3, hash=0
2DAB  41A90017           [1775] loadk      23  677      ; -1071.5720214844
2DAF  C1A90018           [1776] loadk      24  679      ; -1039.5690917969
2DB3  01AA0019           [1777] loadk      25  680      ; 17.566900253296
2DB7  9F000016           [1778] setlist    22  2        ; index 1 to 3
2DBB  41040017           [1779] loadk      23  17       ; 50
2DBF  9F000014           [1780] setlist    20  2        ; index 1 to 3
2DC3  0A800115           [1781] newtable   21  3   0    ; array=3, hash=0
2DC7  C5010016           [1782] getglobal  22  7        ; pickup
2DCB  06430B16           [1783] gettable   22  22  268  ; "ak47"
2DCF  0A800117           [1784] newtable   23  3   0    ; array=3, hash=0
2DD3  81AA0018           [1785] loadk      24  682      ; -1431.9979248047
2DD7  01AB0019           [1786] loadk      25  684      ; -976.64038085938
2DDB  41AB001A           [1787] loadk      26  685      ; 14.868100166321
2DDF  9F000017           [1788] setlist    23  2        ; index 1 to 3
2DE3  41040018           [1789] loadk      24  17       ; 50
2DE7  9F000015           [1790] setlist    21  2        ; index 1 to 3
2DEB  0A800116           [1791] newtable   22  3   0    ; array=3, hash=0
2DEF  C5010017           [1792] getglobal  23  7        ; pickup
2DF3  06C40B17           [1793] gettable   23  23  272  ; "sniper"
2DF7  0A800118           [1794] newtable   24  3   0    ; array=3, hash=0
2DFB  C1AB0019           [1795] loadk      25  687      ; -1685.1060791016
2DFF  41AC001A           [1796] loadk      26  689      ; -946.24890136719
2E03  81AC001B           [1797] loadk      27  690      ; 14.857399940491
2E07  9F000018           [1798] setlist    24  2        ; index 1 to 3
2E0B  01030019           [1799] loadk      25  12       ; 10
2E0F  9F000016           [1800] setlist    22  2        ; index 1 to 3
2E13  0A800117           [1801] newtable   23  3   0    ; array=3, hash=0
2E17  C5010018           [1802] getglobal  24  7        ; pickup
2E1B  C64A0C18           [1803] gettable   24  24  299  ; "grenade"
2E1F  0A800119           [1804] newtable   25  3   0    ; array=3, hash=0
2E23  01AD001A           [1805] loadk      26  692      ; -1262.3919677734
2E27  81AD001B           [1806] loadk      27  694      ; -1256.6950683594
2E2B  C1AD001C           [1807] loadk      28  695      ; 14.864700317383
2E2F  9F000019           [1808] setlist    25  2        ; index 1 to 3
2E33  8101001A           [1809] loadk      26  6        ; 5
2E37  9F000017           [1810] setlist    23  2        ; index 1 to 3
2E3B  0A800118           [1811] newtable   24  3   0    ; array=3, hash=0
2E3F  C5010019           [1812] getglobal  25  7        ; pickup
2E43  C6CD0C19           [1813] gettable   25  25  311  ; "det_grenade"
2E47  0A80011A           [1814] newtable   26  3   0    ; array=3, hash=0
2E4B  41AE001B           [1815] loadk      27  697      ; -1312.5653076172
2E4F  C1AE001C           [1816] loadk      28  699      ; -631.86279296875
2E53  01AF001D           [1817] loadk      29  700      ; 14.874300003052
2E57  9F00001A           [1818] setlist    26  2        ; index 1 to 3
2E5B  8101001B           [1819] loadk      27  6        ; 5
2E5F  9F000018           [1820] setlist    24  2        ; index 1 to 3
2E63  0A800119           [1821] newtable   25  3   0    ; array=3, hash=0
2E67  C501001A           [1822] getglobal  26  7        ; pickup
2E6B  C6490D1A           [1823] gettable   26  26  295  ; "rocket_launcher"
2E6F  0A80011B           [1824] newtable   27  3   0    ; array=3, hash=0
2E73  81AF001C           [1825] loadk      28  702      ; -1735.3708496094
2E77  01B0001D           [1826] loadk      29  704      ; -1728.8214111328
2E7B  41B0001E           [1827] loadk      30  705      ; 14.865599632263
2E7F  9F00001B           [1828] setlist    27  2        ; index 1 to 3
2E83  8101001C           [1829] loadk      28  6        ; 5
2E87  9F000019           [1830] setlist    25  2        ; index 1 to 3
2E8B  0A80011A           [1831] newtable   26  3   0    ; array=3, hash=0
2E8F  C501001B           [1832] getglobal  27  7        ; pickup
2E93  86C00D1B           [1833] gettable   27  27  258  ; "shotgun"
2E97  0A80011C           [1834] newtable   28  3   0    ; array=3, hash=0
2E9B  C1B0001D           [1835] loadk      29  707      ; -1354.6937255859
2E9F  41B1001E           [1836] loadk      30  709      ; -809.41088867188
2EA3  81B1001F           [1837] loadk      31  710      ; 20.893699645996
2EA7  9F00001C           [1838] setlist    28  2        ; index 1 to 3
2EAB  0103001D           [1839] loadk      29  12       ; 10
2EAF  9F00001A           [1840] setlist    26  2        ; index 1 to 3
2EB3  0A80011B           [1841] newtable   27  3   0    ; array=3, hash=0
2EB7  C501001C           [1842] getglobal  28  7        ; pickup
2EBB  C144001D           [1843] loadk      29  275      ; "health"
2EBF  46070E1C           [1844] gettable   28  28  29 
2EC3  0A80011D           [1845] newtable   29  3   0    ; array=3, hash=0
2EC7  01B2001E           [1846] loadk      30  712      ; -935.67657470703
2ECB  41B2001F           [1847] loadk      31  713      ; 1338.0249023438
2ECF  81B20020           [1848] loadk      32  714      ; 11.136300086975
2ED3  9F00001D           [1849] setlist    29  2        ; index 1 to 3
2ED7  8100001E           [1850] loadk      30  2        ; 1
2EDB  9F00001B           [1851] setlist    27  2        ; index 1 to 3
2EDF  0A80011C           [1852] newtable   28  3   0    ; array=3, hash=0
2EE3  C501001D           [1853] getglobal  29  7        ; pickup
2EE7  C144001E           [1854] loadk      30  275      ; "health"
2EEB  86870E1D           [1855] gettable   29  29  30 
2EEF  0A80011E           [1856] newtable   30  3   0    ; array=3, hash=0
2EF3  01B3001F           [1857] loadk      31  716      ; -783.65887451172
2EF7  41B30020           [1858] loadk      32  717      ; 1490.8420410156
2EFB  81B30021           [1859] loadk      33  718      ; 12.238699913025
2EFF  9F00001E           [1860] setlist    30  2        ; index 1 to 3
2F03  8100001F           [1861] loadk      31  2        ; 1
2F07  9F00001C           [1862] setlist    28  2        ; index 1 to 3
2F0B  0A80011D           [1863] newtable   29  3   0    ; array=3, hash=0
2F0F  C501001E           [1864] getglobal  30  7        ; pickup
2F13  C144001F           [1865] loadk      31  275      ; "health"
2F17  C6070F1E           [1866] gettable   30  30  31 
2F1B  0A80011F           [1867] newtable   31  3   0    ; array=3, hash=0
2F1F  01B40020           [1868] loadk      32  720      ; -822.44592285156
2F23  41B40021           [1869] loadk      33  721      ; 1149.0817871094
2F27  81B40022           [1870] loadk      34  722      ; 12.416500091553
2F2B  9F00001F           [1871] setlist    31  2        ; index 1 to 3
2F2F  81000020           [1872] loadk      32  2        ; 1
2F33  9F00001D           [1873] setlist    29  2        ; index 1 to 3
2F37  0A80011E           [1874] newtable   30  3   0    ; array=3, hash=0
2F3B  C501001F           [1875] getglobal  31  7        ; pickup
2F3F  C1440020           [1876] loadk      32  275      ; "health"
2F43  06880F1F           [1877] gettable   31  31  32 
2F47  0A800120           [1878] newtable   32  3   0    ; array=3, hash=0
2F4B  01B50021           [1879] loadk      33  724      ; -594.88159179688
2F4F  41B50022           [1880] loadk      34  725      ; 1353.4747314453
2F53  81B50023           [1881] loadk      35  726      ; 11.772199630737
2F57  9F000020           [1882] setlist    32  2        ; index 1 to 3
2F5B  81000021           [1883] loadk      33  2        ; 1
2F5F  9F00001E           [1884] setlist    30  2        ; index 1 to 3
2F63  0A80011F           [1885] newtable   31  3   0    ; array=3, hash=0
2F67  C5010020           [1886] getglobal  32  7        ; pickup
2F6B  C1440021           [1887] loadk      33  275      ; "health"
2F6F  46081020           [1888] gettable   32  32  33 
2F73  0A800121           [1889] newtable   33  3   0    ; array=3, hash=0
2F77  01B60022           [1890] loadk      34  728      ; -345.33081054688
2F7B  41B60023           [1891] loadk      35  729      ; 1171.2283935547
2F7F  81B60024           [1892] loadk      36  730      ; 11.494700431824
2F83  9F000021           [1893] setlist    33  2        ; index 1 to 3
2F87  81000022           [1894] loadk      34  2        ; 1
2F8B  9F00001F           [1895] setlist    31  2        ; index 1 to 3
2F8F  0A800120           [1896] newtable   32  3   0    ; array=3, hash=0
2F93  C5010021           [1897] getglobal  33  7        ; pickup
2F97  C1440022           [1898] loadk      34  275      ; "health"
2F9B  86881021           [1899] gettable   33  33  34 
2F9F  0A800122           [1900] newtable   34  3   0    ; array=3, hash=0
2FA3  01B70023           [1901] loadk      35  732      ; -852.91851806641
2FA7  41B70024           [1902] loadk      36  733      ; 797.42022705078
2FAB  81B70025           [1903] loadk      37  734      ; 11.089400291443
2FAF  9F000022           [1904] setlist    34  2        ; index 1 to 3
2FB3  81000023           [1905] loadk      35  2        ; 1
2FB7  9F000020           [1906] setlist    32  2        ; index 1 to 3
2FBB  0A800121           [1907] newtable   33  3   0    ; array=3, hash=0
2FBF  C5010022           [1908] getglobal  34  7        ; pickup
2FC3  C1440023           [1909] loadk      35  275      ; "health"
2FC7  C6081122           [1910] gettable   34  34  35 
2FCB  0A800123           [1911] newtable   35  3   0    ; array=3, hash=0
2FCF  01B80024           [1912] loadk      36  736      ; -480.70419311523
2FD3  41B80025           [1913] loadk      37  737      ; 952.58697509766
2FD7  81B80026           [1914] loadk      38  738      ; 14.269200325012
2FDB  9F000023           [1915] setlist    35  2        ; index 1 to 3
2FDF  81000024           [1916] loadk      36  2        ; 1
2FE3  9F000021           [1917] setlist    33  2        ; index 1 to 3
2FE7  DF0F0001           [1918] setlist    1   63       ; index 33 to 64
2FEB  0A800102           [1919] newtable   2   3   0    ; array=3, hash=0
2FEF  C5010003           [1920] getglobal  3   7        ; pickup
2FF3  C1440004           [1921] loadk      4   275      ; "health"
2FF7  06810103           [1922] gettable   3   3   4  
2FFB  0A800104           [1923] newtable   4   3   0    ; array=3, hash=0
2FFF  01B90005           [1924] loadk      5   740      ; -721.05639648438
3003  41B90006           [1925] loadk      6   741      ; 364.49841308594
3007  81B90007           [1926] loadk      7   742      ; 11.100700378418
300B  9F000004           [1927] setlist    4   2        ; index 1 to 3
300F  81000005           [1928] loadk      5   2        ; 1
3013  9F000002           [1929] setlist    2   2        ; index 1 to 3
3017  0A800103           [1930] newtable   3   3   0    ; array=3, hash=0
301B  C5010004           [1931] getglobal  4   7        ; pickup
301F  C1440005           [1932] loadk      5   275      ; "health"
3023  46010204           [1933] gettable   4   4   5  
3027  0A800105           [1934] newtable   5   3   0    ; array=3, hash=0
302B  01BA0006           [1935] loadk      6   744      ; -1092.8365478516
302F  41BA0007           [1936] loadk      7   745      ; 114.19090270996
3033  81BA0008           [1937] loadk      8   746      ; 11.267100334167
3037  9F000005           [1938] setlist    5   2        ; index 1 to 3
303B  81000006           [1939] loadk      6   2        ; 1
303F  9F000003           [1940] setlist    3   2        ; index 1 to 3
3043  0A800104           [1941] newtable   4   3   0    ; array=3, hash=0
3047  C5010005           [1942] getglobal  5   7        ; pickup
304B  C1440006           [1943] loadk      6   275      ; "health"
304F  86810205           [1944] gettable   5   5   6  
3053  0A800106           [1945] newtable   6   3   0    ; array=3, hash=0
3057  01BB0007           [1946] loadk      7   748      ; -935.74768066406
305B  81BB0008           [1947] loadk      8   750      ; -116.33820343018
305F  C1BB0009           [1948] loadk      9   751      ; 6.6479001045227
3063  9F000006           [1949] setlist    6   2        ; index 1 to 3
3067  81000007           [1950] loadk      7   2        ; 1
306B  9F000004           [1951] setlist    4   2        ; index 1 to 3
306F  0A800105           [1952] newtable   5   3   0    ; array=3, hash=0
3073  C5010006           [1953] getglobal  6   7        ; pickup
3077  C1440007           [1954] loadk      7   275      ; "health"
307B  C6010306           [1955] gettable   6   6   7  
307F  0A800107           [1956] newtable   7   3   0    ; array=3, hash=0
3083  41BC0008           [1957] loadk      8   753      ; -1211.2629394531
3087  C1BC0009           [1958] loadk      9   755      ; -460.3996887207
308B  01BD000A           [1959] loadk      10  756      ; 10.990400314331
308F  9F000007           [1960] setlist    7   2        ; index 1 to 3
3093  81000008           [1961] loadk      8   2        ; 1
3097  9F000005           [1962] setlist    5   2        ; index 1 to 3
309B  0A800106           [1963] newtable   6   3   0    ; array=3, hash=0
309F  C5010007           [1964] getglobal  7   7        ; pickup
30A3  C1440008           [1965] loadk      8   275      ; "health"
30A7  06820307           [1966] gettable   7   7   8  
30AB  0A800108           [1967] newtable   8   3   0    ; array=3, hash=0
30AF  81BD0009           [1968] loadk      9   758      ; -1068.5666503906
30B3  01BE000A           [1969] loadk      10  760      ; -630.99322509766
30B7  41BE000B           [1970] loadk      11  761      ; 11.156999588013
30BB  9F000008           [1971] setlist    8   2        ; index 1 to 3
30BF  81000009           [1972] loadk      9   2        ; 1
30C3  9F000006           [1973] setlist    6   2        ; index 1 to 3
30C7  0A800107           [1974] newtable   7   3   0    ; array=3, hash=0
30CB  C5010008           [1975] getglobal  8   7        ; pickup
30CF  C1440009           [1976] loadk      9   275      ; "health"
30D3  46020408           [1977] gettable   8   8   9  
30D7  0A800109           [1978] newtable   9   3   0    ; array=3, hash=0
30DB  C1BE000A           [1979] loadk      10  763      ; -883.86431884766
30DF  41BF000B           [1980] loadk      11  765      ; -402.33340454102
30E3  81BF000C           [1981] loadk      12  766      ; 13.392499923706
30E7  9F000009           [1982] setlist    9   2        ; index 1 to 3
30EB  8100000A           [1983] loadk      10  2        ; 1
30EF  9F000007           [1984] setlist    7   2        ; index 1 to 3
30F3  0A800108           [1985] newtable   8   3   0    ; array=3, hash=0
30F7  C5010009           [1986] getglobal  9   7        ; pickup
30FB  C144000A           [1987] loadk      10  275      ; "health"
30FF  86820409           [1988] gettable   9   9   10 
3103  0A80010A           [1989] newtable   10  3   0    ; array=3, hash=0
3107  01C0000B           [1990] loadk      11  768      ; -842.39837646484
310B  81C0000C           [1991] loadk      12  770      ; -958.21112060547
310F  C1C0000D           [1992] loadk      13  771      ; 11.105899810791
3113  9F00000A           [1993] setlist    10  2        ; index 1 to 3
3117  8100000B           [1994] loadk      11  2        ; 1
311B  9F000008           [1995] setlist    8   2        ; index 1 to 3
311F  0A800109           [1996] newtable   9   3   0    ; array=3, hash=0
3123  C501000A           [1997] getglobal  10  7        ; pickup
3127  C144000B           [1998] loadk      11  275      ; "health"
312B  C602050A           [1999] gettable   10  10  11 
312F  0A80010B           [2000] newtable   11  3   0    ; array=3, hash=0
3133  41C1000C           [2001] loadk      12  773      ; -748.40051269531
3137  C1C1000D           [2002] loadk      13  775      ; -1257.3142089844
313B  01C2000E           [2003] loadk      14  776      ; 11.093799591064
313F  9F00000B           [2004] setlist    11  2        ; index 1 to 3
3143  8100000C           [2005] loadk      12  2        ; 1
3147  9F000009           [2006] setlist    9   2        ; index 1 to 3
314B  0A80010A           [2007] newtable   10  3   0    ; array=3, hash=0
314F  C501000B           [2008] getglobal  11  7        ; pickup
3153  C144000C           [2009] loadk      12  275      ; "health"
3157  0683050B           [2010] gettable   11  11  12 
315B  0A80010C           [2011] newtable   12  3   0    ; array=3, hash=0
315F  81C2000D           [2012] loadk      13  778      ; -984.54772949219
3163  01C3000E           [2013] loadk      14  780      ; -1283.3100585938
3167  41C3000F           [2014] loadk      15  781      ; 28.135299682617
316B  9F00000C           [2015] setlist    12  2        ; index 1 to 3
316F  8100000D           [2016] loadk      13  2        ; 1
3173  9F00000A           [2017] setlist    10  2        ; index 1 to 3
3177  0A80010B           [2018] newtable   11  3   0    ; array=3, hash=0
317B  C501000C           [2019] getglobal  12  7        ; pickup
317F  C144000D           [2020] loadk      13  275      ; "health"
3183  4603060C           [2021] gettable   12  12  13 
3187  0A80010D           [2022] newtable   13  3   0    ; array=3, hash=0
318B  C1C3000E           [2023] loadk      14  783      ; -1158.4897460938
318F  41C4000F           [2024] loadk      15  785      ; -989.93548583984
3193  81C40010           [2025] loadk      16  786      ; 14.866200447083
3197  9F00000D           [2026] setlist    13  2        ; index 1 to 3
319B  8100000E           [2027] loadk      14  2        ; 1
319F  9F00000B           [2028] setlist    11  2        ; index 1 to 3
31A3  0A80010C           [2029] newtable   12  3   0    ; array=3, hash=0
31A7  C501000D           [2030] getglobal  13  7        ; pickup
31AB  C144000E           [2031] loadk      14  275      ; "health"
31AF  8683060D           [2032] gettable   13  13  14 
31B3  0A80010E           [2033] newtable   14  3   0    ; array=3, hash=0
31B7  01C5000F           [2034] loadk      15  788      ; -1435.2156982422
31BB  81C50010           [2035] loadk      16  790      ; -805.29888916016
31BF  C1C50011           [2036] loadk      17  791      ; 14.866800308228
31C3  9F00000E           [2037] setlist    14  2        ; index 1 to 3
31C7  8100000F           [2038] loadk      15  2        ; 1
31CB  9F00000C           [2039] setlist    12  2        ; index 1 to 3
31CF  0A80010D           [2040] newtable   13  3   0    ; array=3, hash=0
31D3  C501000E           [2041] getglobal  14  7        ; pickup
31D7  C144000F           [2042] loadk      15  275      ; "health"
31DB  C603070E           [2043] gettable   14  14  15 
31DF  0A80010F           [2044] newtable   15  3   0    ; array=3, hash=0
31E3  41C60010           [2045] loadk      16  793      ; -1630.5889892578
31E7  C1C60011           [2046] loadk      17  795      ; -639.6796875
31EB  01C70012           [2047] loadk      18  796      ; 14.885000228882
31EF  9F00000F           [2048] setlist    15  2        ; index 1 to 3
31F3  81000010           [2049] loadk      16  2        ; 1
31F7  9F00000D           [2050] setlist    13  2        ; index 1 to 3
31FB  0A80010E           [2051] newtable   14  3   0    ; array=3, hash=0
31FF  C501000F           [2052] getglobal  15  7        ; pickup
3203  C1440010           [2053] loadk      16  275      ; "health"
3207  0684070F           [2054] gettable   15  15  16 
320B  0A800110           [2055] newtable   16  3   0    ; array=3, hash=0
320F  81C70011           [2056] loadk      17  798      ; -1589.8696289063
3213  01C80012           [2057] loadk      18  800      ; -340.8450012207
3217  41C80013           [2058] loadk      19  801      ; 14.862500190735
321B  9F000010           [2059] setlist    16  2        ; index 1 to 3
321F  81000011           [2060] loadk      17  2        ; 1
3223  9F00000E           [2061] setlist    14  2        ; index 1 to 3
3227  0A80010F           [2062] newtable   15  3   0    ; array=3, hash=0
322B  C5010010           [2063] getglobal  16  7        ; pickup
322F  415F0011           [2064] loadk      17  381      ; "armour"
3233  46040810           [2065] gettable   16  16  17 
3237  0A800111           [2066] newtable   17  3   0    ; array=3, hash=0
323B  C1C80012           [2067] loadk      18  803      ; -1085.8861083984
323F  01C90013           [2068] loadk      19  804      ; 1351.0035400391
3243  41C90014           [2069] loadk      20  805      ; 9.5072002410889
3247  9F000011           [2070] setlist    17  2        ; index 1 to 3
324B  81000012           [2071] loadk      18  2        ; 1
324F  9F00000F           [2072] setlist    15  2        ; index 1 to 3
3253  0A800110           [2073] newtable   16  3   0    ; array=3, hash=0
3257  C5010011           [2074] getglobal  17  7        ; pickup
325B  415F0012           [2075] loadk      18  381      ; "armour"
325F  86840811           [2076] gettable   17  17  18 
3263  0A800112           [2077] newtable   18  3   0    ; array=3, hash=0
3267  C1C90013           [2078] loadk      19  807      ; -459.71539306641
326B  01CA0014           [2079] loadk      20  808      ; 1205.6772460938
326F  41CA0015           [2080] loadk      21  809      ; 9.6822004318237
3273  9F000012           [2081] setlist    18  2        ; index 1 to 3
3277  81000013           [2082] loadk      19  2        ; 1
327B  9F000010           [2083] setlist    16  2        ; index 1 to 3
327F  0A800111           [2084] newtable   17  3   0    ; array=3, hash=0
3283  C5010012           [2085] getglobal  18  7        ; pickup
3287  415F0013           [2086] loadk      19  381      ; "armour"
328B  C6040912           [2087] gettable   18  18  19 
328F  0A800113           [2088] newtable   19  3   0    ; array=3, hash=0
3293  C1CA0014           [2089] loadk      20  811      ; -259.0705871582
3297  01CB0015           [2090] loadk      21  812      ; 1434.6746826172
329B  817A0016           [2091] loadk      22  490      ; 11.39999961853
329F  9F000013           [2092] setlist    19  2        ; index 1 to 3
32A3  81000014           [2093] loadk      20  2        ; 1
32A7  9F000011           [2094] setlist    17  2        ; index 1 to 3
32AB  0A800112           [2095] newtable   18  3   0    ; array=3, hash=0
32AF  C5010013           [2096] getglobal  19  7        ; pickup
32B3  415F0014           [2097] loadk      20  381      ; "armour"
32B7  06850913           [2098] gettable   19  19  20 
32BB  0A800114           [2099] newtable   20  3   0    ; array=3, hash=0
32BF  81CB0015           [2100] loadk      21  814      ; -740.05181884766
32C3  C1CB0016           [2101] loadk      22  815      ; 1081.8537597656
32C7  01CC0017           [2102] loadk      23  816      ; 9.7062997817993
32CB  9F000014           [2103] setlist    20  2        ; index 1 to 3
32CF  81000015           [2104] loadk      21  2        ; 1
32D3  9F000012           [2105] setlist    18  2        ; index 1 to 3
32D7  0A800113           [2106] newtable   19  3   0    ; array=3, hash=0
32DB  C5010014           [2107] getglobal  20  7        ; pickup
32DF  415F0015           [2108] loadk      21  381      ; "armour"
32E3  46050A14           [2109] gettable   20  20  21 
32E7  0A800115           [2110] newtable   21  3   0    ; array=3, hash=0
32EB  81CC0016           [2111] loadk      22  818      ; -920.13470458984
32EF  C1CC0017           [2112] loadk      23  819      ; 944.64910888672
32F3  01CD0018           [2113] loadk      24  820      ; 11.08629989624
32F7  9F000015           [2114] setlist    21  2        ; index 1 to 3
32FB  81000016           [2115] loadk      22  2        ; 1
32FF  9F000013           [2116] setlist    19  2        ; index 1 to 3
3303  0A800114           [2117] newtable   20  3   0    ; array=3, hash=0
3307  C5010015           [2118] getglobal  21  7        ; pickup
330B  415F0016           [2119] loadk      22  381      ; "armour"
330F  86850A15           [2120] gettable   21  21  22 
3313  0A800116           [2121] newtable   22  3   0    ; array=3, hash=0
3317  81CD0017           [2122] loadk      23  822      ; -564.1162109375
331B  C1CD0018           [2123] loadk      24  823      ; 700.20269775391
331F  01CE0019           [2124] loadk      25  824      ; 20.632299423218
3323  9F000016           [2125] setlist    22  2        ; index 1 to 3
3327  81000017           [2126] loadk      23  2        ; 1
332B  9F000014           [2127] setlist    20  2        ; index 1 to 3
332F  0A800115           [2128] newtable   21  3   0    ; array=3, hash=0
3333  C5010016           [2129] getglobal  22  7        ; pickup
3337  415F0017           [2130] loadk      23  381      ; "armour"
333B  C6050B16           [2131] gettable   22  22  23 
333F  0A800117           [2132] newtable   23  3   0    ; array=3, hash=0
3343  81CE0018           [2133] loadk      24  826      ; -746.32312011719
3347  C1CE0019           [2134] loadk      25  827      ; 243.98519897461
334B  01CF001A           [2135] loadk      26  828      ; 17.02499961853
334F  9F000017           [2136] setlist    23  2        ; index 1 to 3
3353  81000018           [2137] loadk      24  2        ; 1
3357  9F000015           [2138] setlist    21  2        ; index 1 to 3
335B  0A800116           [2139] newtable   22  3   0    ; array=3, hash=0
335F  C5010017           [2140] getglobal  23  7        ; pickup
3363  415F0018           [2141] loadk      24  381      ; "armour"
3367  06860B17           [2142] gettable   23  23  24 
336B  0A800118           [2143] newtable   24  3   0    ; array=3, hash=0
336F  81CF0019           [2144] loadk      25  830      ; -954.98748779297
3373  C1CF001A           [2145] loadk      26  831      ; 271.83190917969
3377  818A001B           [2146] loadk      27  554      ; 11.266500473022
337B  9F000018           [2147] setlist    24  2        ; index 1 to 3
337F  81000019           [2148] loadk      25  2        ; 1
3383  9F000016           [2149] setlist    22  2        ; index 1 to 3
3387  0A800117           [2150] newtable   23  3   0    ; array=3, hash=0
338B  C5010018           [2151] getglobal  24  7        ; pickup
338F  415F0019           [2152] loadk      25  381      ; "armour"
3393  46060C18           [2153] gettable   24  24  25 
3397  0A800119           [2154] newtable   25  3   0    ; array=3, hash=0
339B  41D0001A           [2155] loadk      26  833      ; -907.28631591797
339F  81D0001B           [2156] loadk      27  834      ; 50.303100585938
33A3  C1D0001C           [2157] loadk      28  835      ; 10.084799766541
33A7  9F000019           [2158] setlist    25  2        ; index 1 to 3
33AB  8100001A           [2159] loadk      26  2        ; 1
33AF  9F000017           [2160] setlist    23  2        ; index 1 to 3
33B3  0A800118           [2161] newtable   24  3   0    ; array=3, hash=0
33B7  C5010019           [2162] getglobal  25  7        ; pickup
33BB  415F001A           [2163] loadk      26  381      ; "armour"
33BF  86860C19           [2164] gettable   25  25  26 
33C3  0A80011A           [2165] newtable   26  3   0    ; array=3, hash=0
33C7  41D1001B           [2166] loadk      27  837      ; -1166.4326171875
33CB  81D1001C           [2167] loadk      28  838      ; 88.992797851563
33CF  C1D1001D           [2168] loadk      29  839      ; 11.130000114441
33D3  9F00001A           [2169] setlist    26  2        ; index 1 to 3
33D7  8100001B           [2170] loadk      27  2        ; 1
33DB  9F000018           [2171] setlist    24  2        ; index 1 to 3
33DF  0A800119           [2172] newtable   25  3   0    ; array=3, hash=0
33E3  C501001A           [2173] getglobal  26  7        ; pickup
33E7  415F001B           [2174] loadk      27  381      ; "armour"
33EB  C6060D1A           [2175] gettable   26  26  27 
33EF  0A80011B           [2176] newtable   27  3   0    ; array=3, hash=0
33F3  41D2001C           [2177] loadk      28  841      ; -1022.3394775391
33F7  C1D2001D           [2178] loadk      29  843      ; -455.16738891602
33FB  01D3001E           [2179] loadk      30  844      ; 17.444799423218
33FF  9F00001B           [2180] setlist    27  2        ; index 1 to 3
3403  8100001C           [2181] loadk      28  2        ; 1
3407  9F000019           [2182] setlist    25  2        ; index 1 to 3
340B  0A80011A           [2183] newtable   26  3   0    ; array=3, hash=0
340F  C501001B           [2184] getglobal  27  7        ; pickup
3413  415F001C           [2185] loadk      28  381      ; "armour"
3417  06870D1B           [2186] gettable   27  27  28 
341B  0A80011C           [2187] newtable   28  3   0    ; array=3, hash=0
341F  81D3001D           [2188] loadk      29  846      ; -1125.7805175781
3423  01D4001E           [2189] loadk      30  848      ; -610.58227539063
3427  41D4001F           [2190] loadk      31  849      ; 26.059999465942
342B  9F00001C           [2191] setlist    28  2        ; index 1 to 3
342F  8100001D           [2192] loadk      29  2        ; 1
3433  9F00001A           [2193] setlist    26  2        ; index 1 to 3
3437  0A80011B           [2194] newtable   27  3   0    ; array=3, hash=0
343B  C501001C           [2195] getglobal  28  7        ; pickup
343F  415F001D           [2196] loadk      29  381      ; "armour"
3443  46070E1C           [2197] gettable   28  28  29 
3447  0A80011D           [2198] newtable   29  3   0    ; array=3, hash=0
344B  C1D4001E           [2199] loadk      30  851      ; -805.01641845703
344F  41D5001F           [2200] loadk      31  853      ; -326.24490356445
3453  C1990020           [2201] loadk      32  615      ; 8.2847995758057
3457  9F00001D           [2202] setlist    29  2        ; index 1 to 3
345B  8100001E           [2203] loadk      30  2        ; 1
345F  9F00001B           [2204] setlist    27  2        ; index 1 to 3
3463  0A80011C           [2205] newtable   28  3   0    ; array=3, hash=0
3467  C501001D           [2206] getglobal  29  7        ; pickup
346B  415F001E           [2207] loadk      30  381      ; "armour"
346F  86870E1D           [2208] gettable   29  29  30 
3473  0A80011E           [2209] newtable   30  3   0    ; array=3, hash=0
3477  C1D5001F           [2210] loadk      31  855      ; -1048.9211425781
347B  41D60020           [2211] loadk      32  857      ; -764.75799560547
347F  81D60021           [2212] loadk      33  858      ; 12.01039981842
3483  9F00001E           [2213] setlist    30  2        ; index 1 to 3
3487  8100001F           [2214] loadk      31  2        ; 1
348B  9F00001C           [2215] setlist    28  2        ; index 1 to 3
348F  0A80011D           [2216] newtable   29  3   0    ; array=3, hash=0
3493  C501001E           [2217] getglobal  30  7        ; pickup
3497  415F001F           [2218] loadk      31  381      ; "armour"
349B  C6070F1E           [2219] gettable   30  30  31 
349F  0A80011F           [2220] newtable   31  3   0    ; array=3, hash=0
34A3  01D70020           [2221] loadk      32  860      ; -884.31158447266
34A7  81D70021           [2222] loadk      33  862      ; -1015.0842895508
34AB  C1D70022           [2223] loadk      34  863      ; 14.376700401306
34AF  9F00001F           [2224] setlist    31  2        ; index 1 to 3
34B3  81000020           [2225] loadk      32  2        ; 1
34B7  9F00001D           [2226] setlist    29  2        ; index 1 to 3
34BB  0A80011E           [2227] newtable   30  3   0    ; array=3, hash=0
34BF  C501001F           [2228] getglobal  31  7        ; pickup
34C3  415F0020           [2229] loadk      32  381      ; "armour"
34C7  06880F1F           [2230] gettable   31  31  32 
34CB  0A800120           [2231] newtable   32  3   0    ; array=3, hash=0
34CF  41D80021           [2232] loadk      33  865      ; -690.48181152344
34D3  C1D80022           [2233] loadk      34  867      ; -1585.0610351563
34D7  01D90023           [2234] loadk      35  868      ; 12.521300315857
34DB  9F000020           [2235] setlist    32  2        ; index 1 to 3
34DF  81000021           [2236] loadk      33  2        ; 1
34E3  9F00001E           [2237] setlist    30  2        ; index 1 to 3
34E7  0A80011F           [2238] newtable   31  3   0    ; array=3, hash=0
34EB  C5010020           [2239] getglobal  32  7        ; pickup
34EF  415F0021           [2240] loadk      33  381      ; "armour"
34F3  46081020           [2241] gettable   32  32  33 
34F7  0A800121           [2242] newtable   33  3   0    ; array=3, hash=0
34FB  81D90022           [2243] loadk      34  870      ; -1382.1281738281
34FF  01DA0023           [2244] loadk      35  872      ; -367.20001220703
3503  41DA0024           [2245] loadk      36  873      ; 14.867600440979
3507  9F000021           [2246] setlist    33  2        ; index 1 to 3
350B  81000022           [2247] loadk      34  2        ; 1
350F  9F00001F           [2248] setlist    31  2        ; index 1 to 3
3513  0A800120           [2249] newtable   32  3   0    ; array=3, hash=0
3517  C5010021           [2250] getglobal  33  7        ; pickup
351B  415F0022           [2251] loadk      34  381      ; "armour"
351F  86881021           [2252] gettable   33  33  34 
3523  0A800122           [2253] newtable   34  3   0    ; array=3, hash=0
3527  C1DA0023           [2254] loadk      35  875      ; -1516.0902099609
352B  41DB0024           [2255] loadk      36  877      ; -810.55181884766
352F  81B10025           [2256] loadk      37  710      ; 20.893699645996
3533  9F000022           [2257] setlist    34  2        ; index 1 to 3
3537  81000023           [2258] loadk      35  2        ; 1
353B  9F000020           [2259] setlist    32  2        ; index 1 to 3
353F  9F170001           [2260] setlist    1   94       ; index 65 to 95
3543  00800000           [2261] move       0   1      
3547  1B000100           [2262] return     0   2      
354B  1B800000           [2263] return     0   1      
                         ** end of function **

                         * code:
354F  03000000           sizecode (3)
3553  22000000           [1] closure    0   0        ; 0 upvalues
3557  1B000100           [2] return     0   2      
355B  1B800000           [3] return     0   1      
                         ** end of function **

355F                     ** end of chunk **
