Pos   Hex Data           Description or Code
------------------------------------------------------------------------
0000                     ** source chunk: SPAWNPOINTDATA.LUA.LC
                         ** global header start **
0000  1B4C7561           header signature: "\27Lua"
0004  50                 version (major:minor hex digits)
0005  01                 endianness (1=little endian)
0006  04                 size of int (bytes)
0007  04                 size of size_t (bytes)
0008  04                 size of Instruction (bytes)
0009  06                 size of OP (bits)
000A  08                 size of A (bits)
000B  09                 size of B (bits)
000C  09                 size of C (bits)
000D  04                 size of number (bytes)
000E  3BAFEF4B           sample number (single)
                         * chunk platform unrecognized
                         ** global header end **
                         
0012                     ** function [0] definition (level 1)
                         ** start of function **
0012  08000000           string size (8)
0016  3D286E6F6E652900   "=(none)"
                         source name: =(none)
001E  00000000           line defined (0)
0022  00                 nups (0)
0023  00                 numparams (0)
0024  00                 is_vararg (0)
0025  02                 maxstacksize (2)
                         * lines:
0026  00000000           sizelineinfo (0)
                         [pc] (line)
                         * locals:
002A  00000000           sizelocvars (0)
                         * upvalues:
002E  00000000           sizeupvalues (0)
                         * constants:
0032  00000000           sizek (0)
                         * functions:
0036  01000000           sizep (1)
                         
003A                     ** function [0] definition (level 2)
                         ** start of function **
003A  00000000           string size (0)
                         source name: (none)
003E  05000000           line defined (5)
0042  00                 nups (0)
0043  00                 numparams (0)
0044  00                 is_vararg (0)
0045  26                 maxstacksize (38)
                         * lines:
0046  00000000           sizelineinfo (0)
                         [pc] (line)
                         * locals:
004A  00000000           sizelocvars (0)
                         * upvalues:
004E  00000000           sizeupvalues (0)
                         * constants:
0052  B4030000           sizek (948)
0056  04                 const type 4
0057  0D000000           string size (13)
005B  47616D654C6F6361+  "GameLoca"
0063  74696F6E00         "tion\0"
                         const [0]: "GameLocation"
0068  03                 const type 3
0069  00000000           const [1]: (0)
006D  03                 const type 3
006E  0000803F           const [2]: (1)
0072  03                 const type 3
0073  00000040           const [3]: (2)
0077  03                 const type 3
0078  00004040           const [4]: (3)
007C  03                 const type 3
007D  00008040           const [5]: (4)
0081  03                 const type 3
0082  0000A040           const [6]: (5)
0086  03                 const type 3
0087  9A59FB43           const [7]: (502.70001220703)
008B  03                 const type 3
008C  CDCC2143           const [8]: (161.80000305176)
0090  03                 const type 3
0091  CDCC21C3           const [9]: (-161.80000305176)
0095  03                 const type 3
0096  33333B41           const [10]: (11.699999809265)
009A  03                 const type 3
009B  0000BE42           const [11]: (95)
009F  03                 const type 3
00A0  CDCCF743           const [12]: (495.60000610352)
00A4  03                 const type 3
00A5  3333A842           const [13]: (84.099998474121)
00A9  03                 const type 3
00AA  3333A8C2           const [14]: (-84.099998474121)
00AE  03                 const type 3
00AF  00002041           const [15]: (10)
00B3  03                 const type 3
00B4  00002A43           const [16]: (170)
00B8  03                 const type 3
00B9  6626E943           const [17]: (466.29998779297)
00BD  03                 const type 3
00BE  CDCC9C41           const [18]: (19.60000038147)
00C2  03                 const type 3
00C3  CDCC9CC1           const [19]: (-19.60000038147)
00C7  03                 const type 3
00C8  33332B41           const [20]: (10.699999809265)
00CC  03                 const type 3
00CD  0080A743           const [21]: (335)
00D1  03                 const type 3
00D2  9A790144           const [22]: (517.90002441406)
00D6  03                 const type 3
00D7  3333BB42           const [23]: (93.599998474121)
00DB  03                 const type 3
00DC  9A993141           const [24]: (11.10000038147)
00E0  03                 const type 3
00E1  0000C242           const [25]: (97)
00E5  03                 const type 3
00E6  0040D843           const [26]: (432.5)
00EA  03                 const type 3
00EB  00008B42           const [27]: (69.5)
00EF  03                 const type 3
00F0  00003041           const [28]: (11)
00F4  03                 const type 3
00F5  00008C43           const [29]: (280)
00F9  03                 const type 3
00FA  CD0C8143           const [30]: (258.10000610352)
00FE  03                 const type 3
00FF  33739343           const [31]: (294.89999389648)
0103  03                 const type 3
0104  33330B41           const [32]: (8.6999998092651)
0108  03                 const type 3
0109  9AD99343           const [33]: (295.70001220703)
010D  03                 const type 3
010E  66668D43           const [34]: (282.79998779297)
0112  03                 const type 3
0113  9A998D41           const [35]: (17.700000762939)
0117  03                 const type 3
0118  00006643           const [36]: (230)
011C  03                 const type 3
011D  6626BE43           const [37]: (380.29998779297)
0121  03                 const type 3
0122  9A197843           const [38]: (248.10000610352)
0126  03                 const type 3
0127  CDCC2C41           const [39]: (10.800000190735)
012B  03                 const type 3
012C  0040D243           const [40]: (420.5)
0130  03                 const type 3
0131  9A198843           const [41]: (272.20001220703)
0135  03                 const type 3
0136  9A993941           const [42]: (11.60000038147)
013A  03                 const type 3
013B  00009B43           const [43]: (310)
013F  03                 const type 3
0140  CDCCEF43           const [44]: (479.60000610352)
0144  03                 const type 3
0145  00004A43           const [45]: (202)
0149  03                 const type 3
014A  CDCC3441           const [46]: (11.300000190735)
014E  03                 const type 3
014F  00005C43           const [47]: (220)
0153  03                 const type 3
0154  33B30744           const [48]: (542.79998779297)
0158  03                 const type 3
0159  3333B743           const [49]: (366.39999389648)
015D  03                 const type 3
015E  66667641           const [50]: (15.39999961853)
0162  03                 const type 3
0163  00009842           const [51]: (76)
0167  03                 const type 3
0168  66A60B44           const [52]: (558.59997558594)
016C  03                 const type 3
016D  33530444           const [53]: (529.29998779297)
0171  03                 const type 3
0172  00004041           const [54]: (12)
0176  03                 const type 3
0177  00000243           const [55]: (130)
017B  03                 const type 3
017C  9A59F243           const [56]: (484.70001220703)
0180  03                 const type 3
0181  0080F743           const [57]: (495)
0185  03                 const type 3
0186  00003841           const [58]: (11.5)
018A  03                 const type 3
018B  0000F042           const [59]: (120)
018F  03                 const type 3
0190  3373C043           const [60]: (384.89999389648)
0194  03                 const type 3
0195  66E6B643           const [61]: (365.79998779297)
0199  03                 const type 3
019A  00007B43           const [62]: (251)
019E  03                 const type 3
019F  3333F043           const [63]: (480.39999389648)
01A3  03                 const type 3
01A4  9A19C943           const [64]: (402.20001220703)
01A8  03                 const type 3
01A9  CD0C9543           const [65]: (298.10000610352)
01AD  03                 const type 3
01AE  33B3DF43           const [66]: (447.39999389648)
01B2  03                 const type 3
01B3  9A992941           const [67]: (10.60000038147)
01B7  03                 const type 3
01B8  9AD99C43           const [68]: (313.70001220703)
01BC  03                 const type 3
01BD  33F3B343           const [69]: (359.89999389648)
01C1  03                 const type 3
01C2  33335341           const [70]: (13.199999809265)
01C6  03                 const type 3
01C7  0000AA43           const [71]: (340)
01CB  03                 const type 3
01CC  33F3AD43           const [72]: (347.89999389648)
01D0  03                 const type 3
01D1  9A790E44           const [73]: (569.90002441406)
01D5  03                 const type 3
01D6  9A992141           const [74]: (10.10000038147)
01DA  03                 const type 3
01DB  00808443           const [75]: (265)
01DF  03                 const type 3
01E0  6666D043           const [76]: (416.79998779297)
01E4  03                 const type 3
01E5  33B32144           const [77]: (646.79998779297)
01E9  03                 const type 3
01EA  33333341           const [78]: (11.199999809265)
01EE  03                 const type 3
01EF  0080B043           const [79]: (353)
01F3  03                 const type 3
01F4  66E6F643           const [80]: (493.79998779297)
01F8  03                 const type 3
01F9  00A03644           const [81]: (730.5)
01FD  03                 const type 3
01FE  66667643           const [82]: (246.39999389648)
0202  03                 const type 3
0203  66A62F44           const [83]: (702.59997558594)
0207  03                 const type 3
0208  66664E41           const [84]: (12.89999961853)
020C  03                 const type 3
020D  0080A843           const [85]: (337)
0211  03                 const type 3
0212  9AB91144           const [86]: (582.90002441406)
0216  03                 const type 3
0217  00603C44           const [87]: (753.5)
021B  03                 const type 3
021C  00005041           const [88]: (13)
0220  03                 const type 3
0221  0000B442           const [89]: (90)
0225  03                 const type 3
0226  9AB91044           const [90]: (578.90002441406)
022A  03                 const type 3
022B  66466B44           const [91]: (941.09997558594)
022F  03                 const type 3
0230  0000EC42           const [92]: (118)
0234  03                 const type 3
0235  9A59D843           const [93]: (432.70001220703)
0239  03                 const type 3
023A  33536E44           const [94]: (953.29998779297)
023E  03                 const type 3
023F  CDCC7441           const [95]: (15.300000190735)
0243  03                 const type 3
0244  00009443           const [96]: (296)
0248  03                 const type 3
0249  9AD98F43           const [97]: (287.70001220703)
024D  03                 const type 3
024E  9A798144           const [98]: (1035.8000488281)
0252  03                 const type 3
0253  66665641           const [99]: (13.39999961853)
0257  03                 const type 3
0258  00809343           const [100]: (295)
025C  03                 const type 3
025D  9A995043           const [101]: (208.60000610352)
0261  03                 const type 3
0262  CD1C9A44           const [102]: (1232.9000244141)
0266  03                 const type 3
0267  33338B41           const [103]: (17.39999961853)
026B  03                 const type 3
026C  00009343           const [104]: (294)
0270  03                 const type 3
0271  66668543           const [105]: (266.79998779297)
0275  03                 const type 3
0276  66F6A144           const [106]: (1295.6999511719)
027A  03                 const type 3
027B  00007A43           const [107]: (250)
027F  03                 const type 3
0280  CD6C0344           const [108]: (525.70001220703)
0284  03                 const type 3
0285  00A09E44           const [109]: (1269)
0289  03                 const type 3
028A  9A998141           const [110]: (16.200000762939)
028E  03                 const type 3
028F  0000FC42           const [111]: (126)
0293  03                 const type 3
0294  33F30744           const [112]: (543.79998779297)
0298  03                 const type 3
0299  CD1C8344           const [113]: (1048.9000244141)
029D  03                 const type 3
029E  33339741           const [114]: (18.89999961853)
02A2  03                 const type 3
02A3  0000BC42           const [115]: (94)
02A7  03                 const type 3
02A8  33B36443           const [116]: (228.69999694824)
02AC  03                 const type 3
02AD  66666D44           const [117]: (949.59997558594)
02B1  03                 const type 3
02B2  6666D641           const [118]: (26.799999237061)
02B6  03                 const type 3
02B7  00003042           const [119]: (44)
02BB  03                 const type 3
02BC  9AD9AE43           const [120]: (349.70001220703)
02C0  03                 const type 3
02C1  9A990142           const [121]: (32.400001525879)
02C5  03                 const type 3
02C6  9A9901C2           const [122]: (-32.400001525879)
02CA  03                 const type 3
02CB  00004842           const [123]: (50)
02CF  03                 const type 3
02D0  33F38243           const [124]: (261.89999389648)
02D4  03                 const type 3
02D5  9A99C541           const [125]: (24.700000762939)
02D9  03                 const type 3
02DA  00007043           const [126]: (240)
02DE  03                 const type 3
02DF  9AD9B543           const [127]: (363.70001220703)
02E3  03                 const type 3
02E4  CD4C1E43           const [128]: (158.30000305176)
02E8  03                 const type 3
02E9  CD4C1EC3           const [129]: (-158.30000305176)
02ED  03                 const type 3
02EE  CDCC8743           const [130]: (271.60000610352)
02F2  03                 const type 3
02F3  CDCC6B43           const [131]: (235.80000305176)
02F7  03                 const type 3
02F8  CDCC6BC3           const [132]: (-235.80000305176)
02FC  03                 const type 3
02FD  66664641           const [133]: (12.39999961853)
0301  03                 const type 3
0302  0000AA42           const [134]: (85)
0306  03                 const type 3
0307  CD4C9443           const [135]: (296.60000610352)
030B  03                 const type 3
030C  66669743           const [136]: (302.79998779297)
0310  03                 const type 3
0311  666697C3           const [137]: (-302.79998779297)
0315  03                 const type 3
0316  66663E41           const [138]: (11.89999961853)
031A  03                 const type 3
031B  00003443           const [139]: (180)
031F  03                 const type 3
0320  33334643           const [140]: (198.19999694824)
0324  03                 const type 3
0325  CDCCF543           const [141]: (491.60000610352)
0329  03                 const type 3
032A  CDCCF5C3           const [142]: (-491.60000610352)
032E  03                 const type 3
032F  00002F43           const [143]: (175)
0333  03                 const type 3
0334  CD4C8843           const [144]: (272.60000610352)
0338  03                 const type 3
0339  66A6DB43           const [145]: (439.29998779297)
033D  03                 const type 3
033E  66A6DBC3           const [146]: (-439.29998779297)
0342  03                 const type 3
0343  66667C43           const [147]: (252.39999389648)
0347  03                 const type 3
0348  9A19F043           const [148]: (480.20001220703)
034C  03                 const type 3
034D  9A19F0C3           const [149]: (-480.20001220703)
0351  03                 const type 3
0352  0000AC42           const [150]: (86)
0356  03                 const type 3
0357  66664943           const [151]: (201.39999389648)
035B  03                 const type 3
035C  CD4CD743           const [152]: (430.60000610352)
0360  03                 const type 3
0361  CD4CD7C3           const [153]: (-430.60000610352)
0365  03                 const type 3
0366  0000E842           const [154]: (116)
036A  03                 const type 3
036B  66E64043           const [155]: (192.89999389648)
036F  03                 const type 3
0370  00200E44           const [156]: (568.5)
0374  03                 const type 3
0375  00200EC4           const [157]: (-568.5)
0379  03                 const type 3
037A  33332341           const [158]: (10.199999809265)
037E  03                 const type 3
037F  0000AF43           const [159]: (350)
0383  03                 const type 3
0384  9A99A142           const [160]: (80.800003051758)
0388  03                 const type 3
0389  CD8CEC43           const [161]: (473.10000610352)
038D  03                 const type 3
038E  CD8CECC3           const [162]: (-473.10000610352)
0392  03                 const type 3
0393  9A995941           const [163]: (13.60000038147)
0397  03                 const type 3
0398  0000A841           const [164]: (21)
039C  03                 const type 3
039D  CDCC6143           const [165]: (225.80000305176)
03A1  03                 const type 3
03A2  33938E44           const [166]: (1140.5999755859)
03A6  03                 const type 3
03A7  33938EC4           const [167]: (-1140.5999755859)
03AB  03                 const type 3
03AC  6666A542           const [168]: (82.699996948242)
03B0  03                 const type 3
03B1  6626C343           const [169]: (390.29998779297)
03B5  03                 const type 3
03B6  9A597744           const [170]: (989.40002441406)
03BA  03                 const type 3
03BB  9A5977C4           const [171]: (-989.40002441406)
03BF  03                 const type 3
03C0  9A997F43           const [172]: (255.60000610352)
03C4  03                 const type 3
03C5  66467244           const [173]: (969.09997558594)
03C9  03                 const type 3
03CA  664672C4           const [174]: (-969.09997558594)
03CE  03                 const type 3
03CF  00002841           const [175]: (10.5)
03D3  03                 const type 3
03D4  CDCCAB43           const [176]: (343.60000610352)
03D8  03                 const type 3
03D9  3373B643           const [177]: (364.89999389648)
03DD  03                 const type 3
03DE  CDAC2D44           const [178]: (694.70001220703)
03E2  03                 const type 3
03E3  CDAC2DC4           const [179]: (-694.70001220703)
03E7  03                 const type 3
03E8  00009441           const [180]: (18.5)
03EC  03                 const type 3
03ED  00005243           const [181]: (210)
03F1  03                 const type 3
03F2  00002D43           const [182]: (173)
03F6  03                 const type 3
03F7  CDEC6544           const [183]: (919.70001220703)
03FB  03                 const type 3
03FC  CDEC65C4           const [184]: (-919.70001220703)
0400  03                 const type 3
0401  00006943           const [185]: (233)
0405  03                 const type 3
0406  0000C842           const [186]: (100)
040A  03                 const type 3
040B  CD8C4A44           const [187]: (810.20001220703)
040F  03                 const type 3
0410  CD8C4AC4           const [188]: (-810.20001220703)
0414  03                 const type 3
0415  66662641           const [189]: (10.39999961853)
0419  03                 const type 3
041A  00006B43           const [190]: (235)
041E  03                 const type 3
041F  33335643           const [191]: (214.19999694824)
0423  03                 const type 3
0424  33734344           const [192]: (781.79998779297)
0428  03                 const type 3
0429  337343C4           const [193]: (-781.79998779297)
042D  03                 const type 3
042E  33334341           const [194]: (12.199999809265)
0432  03                 const type 3
0433  00008242           const [195]: (65)
0437  03                 const type 3
0438  CDCCA943           const [196]: (339.60000610352)
043C  03                 const type 3
043D  CDCC0C44           const [197]: (563.20001220703)
0441  03                 const type 3
0442  CDCC0CC4           const [198]: (-563.20001220703)
0446  03                 const type 3
0447  33F39243           const [199]: (293.89999389648)
044B  03                 const type 3
044C  66A6F443           const [200]: (489.29998779297)
0450  03                 const type 3
0451  66A6F4C3           const [201]: (-489.29998779297)
0455  03                 const type 3
0456  33B35943           const [202]: (217.69999694824)
045A  03                 const type 3
045B  CD4CCA43           const [203]: (404.60000610352)
045F  03                 const type 3
0460  00C0E743           const [204]: (463.5)
0464  03                 const type 3
0465  00C0E7C3           const [205]: (-463.5)
0469  03                 const type 3
046A  0000A543           const [206]: (330)
046E  03                 const type 3
046F  CD0C0644           const [207]: (536.20001220703)
0473  03                 const type 3
0474  CD8CC843           const [208]: (401.10000610352)
0478  03                 const type 3
0479  CD8CC8C3           const [209]: (-401.10000610352)
047D  03                 const type 3
047E  0000E642           const [210]: (115)
0482  03                 const type 3
0483  3373E543           const [211]: (458.89999389648)
0487  03                 const type 3
0488  9A19FF43           const [212]: (510.20001220703)
048C  03                 const type 3
048D  9A19FFC3           const [213]: (-510.20001220703)
0491  03                 const type 3
0492  66662E41           const [214]: (10.89999961853)
0496  03                 const type 3
0497  00002643           const [215]: (166)
049B  03                 const type 3
049C  3333E243           const [216]: (452.39999389648)
04A0  03                 const type 3
04A1  CD6C1444           const [217]: (593.70001220703)
04A5  03                 const type 3
04A6  CD6C14C4           const [218]: (-593.70001220703)
04AA  03                 const type 3
04AB  33F3C743           const [219]: (399.89999389648)
04AF  03                 const type 3
04B0  00402A44           const [220]: (681)
04B4  03                 const type 3
04B5  00402AC4           const [221]: (-681)
04B9  03                 const type 3
04BA  9A99FF42           const [222]: (127.80000305176)
04BE  03                 const type 3
04BF  66C63144           const [223]: (711.09997558594)
04C3  03                 const type 3
04C4  66C631C4           const [224]: (-711.09997558594)
04C8  03                 const type 3
04C9  00808A43           const [225]: (277)
04CD  03                 const type 3
04CE  66663743           const [226]: (183.39999389648)
04D2  03                 const type 3
04D3  00F0BF44           const [227]: (1535.5)
04D7  03                 const type 3
04D8  00F0BFC4           const [228]: (-1535.5)
04DC  03                 const type 3
04DD  00C0B143           const [229]: (355.5)
04E1  03                 const type 3
04E2  9A991843           const [230]: (152.60000610352)
04E6  03                 const type 3
04E7  0030BD44           const [231]: (1513.5)
04EB  03                 const type 3
04EC  0030BDC4           const [232]: (-1513.5)
04F0  03                 const type 3
04F1  9A999141           const [233]: (18.200000762939)
04F5  03                 const type 3
04F6  33B37443           const [234]: (244.69999694824)
04FA  03                 const type 3
04FB  9A998743           const [235]: (271.20001220703)
04FF  03                 const type 3
0500  3303B044           const [236]: (1408.0999755859)
0504  03                 const type 3
0505  3303B0C4           const [237]: (-1408.0999755859)
0509  03                 const type 3
050A  66664F43           const [238]: (207.39999389648)
050E  03                 const type 3
050F  33A3AE44           const [239]: (1397.0999755859)
0513  03                 const type 3
0514  33A3AEC4           const [240]: (-1397.0999755859)
0518  03                 const type 3
0519  33338543           const [241]: (266.39999389648)
051D  03                 const type 3
051E  33336E43           const [242]: (238.19999694824)
0522  03                 const type 3
0523  6616A044           const [243]: (1280.6999511719)
0527  03                 const type 3
0528  6616A0C4           const [244]: (-1280.6999511719)
052C  03                 const type 3
052D  CDCCA142           const [245]: (80.900001525879)
0531  03                 const type 3
0532  9AA9BF44           const [246]: (1533.3000488281)
0536  03                 const type 3
0537  9AA9BFC4           const [247]: (-1533.3000488281)
053B  03                 const type 3
053C  00008743           const [248]: (270)
0540  03                 const type 3
0541  6666BE41           const [249]: (23.799999237061)
0545  03                 const type 3
0546  6666BEC1           const [250]: (-23.799999237061)
054A  03                 const type 3
054B  CD2CBD44           const [251]: (1513.4000244141)
054F  03                 const type 3
0550  CD2CBDC4           const [252]: (-1513.4000244141)
0554  03                 const type 3
0555  9A991742           const [253]: (37.900001525879)
0559  03                 const type 3
055A  3333C642           const [254]: (99.099998474121)
055E  03                 const type 3
055F  3353B844           const [255]: (1474.5999755859)
0563  03                 const type 3
0564  3353B8C4           const [256]: (-1474.5999755859)
0568  03                 const type 3
0569  00805243           const [257]: (210.5)
056D  03                 const type 3
056E  00001D43           const [258]: (157)
0572  03                 const type 3
0573  CDFCB044           const [259]: (1415.9000244141)
0577  03                 const type 3
0578  CDFCB0C4           const [260]: (-1415.9000244141)
057C  03                 const type 3
057D  CDCC8841           const [261]: (17.10000038147)
0581  03                 const type 3
0582  0000A042           const [262]: (80)
0586  03                 const type 3
0587  CDCCDE42           const [263]: (111.40000152588)
058B  03                 const type 3
058C  0040A544           const [264]: (1322)
0590  03                 const type 3
0591  0040A5C4           const [265]: (-1322)
0595  03                 const type 3
0596  CDCCE742           const [266]: (115.90000152588)
059A  03                 const type 3
059B  0000A444           const [267]: (1312)
059F  03                 const type 3
05A0  0000A4C4           const [268]: (-1312)
05A4  03                 const type 3
05A5  CDCC8C40           const [269]: (4.4000000953674)
05A9  03                 const type 3
05AA  33332542           const [270]: (41.299999237061)
05AE  03                 const type 3
05AF  CD3CA444           const [271]: (1313.9000244141)
05B3  03                 const type 3
05B4  CD3CA4C4           const [272]: (-1313.9000244141)
05B8  03                 const type 3
05B9  33338C42           const [273]: (70.099998474121)
05BD  03                 const type 3
05BE  33338CC2           const [274]: (-70.099998474121)
05C2  03                 const type 3
05C3  6656C844           const [275]: (1602.6999511719)
05C7  03                 const type 3
05C8  6656C8C4           const [276]: (-1602.6999511719)
05CC  03                 const type 3
05CD  66668640           const [277]: (4.1999998092651)
05D1  03                 const type 3
05D2  66667242           const [278]: (60.599998474121)
05D6  03                 const type 3
05D7  666672C2           const [279]: (-60.599998474121)
05DB  03                 const type 3
05DC  66A6B244           const [280]: (1429.1999511719)
05E0  03                 const type 3
05E1  66A6B2C4           const [281]: (-1429.1999511719)
05E5  03                 const type 3
05E6  3333FB41           const [282]: (31.39999961853)
05EA  03                 const type 3
05EB  3333FBC1           const [283]: (-31.39999961853)
05EF  03                 const type 3
05F0  CD1CA844           const [284]: (1344.9000244141)
05F4  03                 const type 3
05F5  CD1CA8C4           const [285]: (-1344.9000244141)
05F9  03                 const type 3
05FA  CDCC2441           const [286]: (10.300000190735)
05FE  03                 const type 3
05FF  00008243           const [287]: (260)
0603  03                 const type 3
0604  9A99B642           const [288]: (91.300003051758)
0608  03                 const type 3
0609  9A99B6C2           const [289]: (-91.300003051758)
060D  03                 const type 3
060E  9AB9A544           const [290]: (1325.8000488281)
0612  03                 const type 3
0613  9AB9A5C4           const [291]: (-1325.8000488281)
0617  03                 const type 3
0618  66668F42           const [292]: (71.699996948242)
061C  03                 const type 3
061D  66668FC2           const [293]: (-71.699996948242)
0621  03                 const type 3
0622  00A09A44           const [294]: (1237)
0626  03                 const type 3
0627  00A09AC4           const [295]: (-1237)
062B  03                 const type 3
062C  66E67643           const [296]: (246.89999389648)
0630  03                 const type 3
0631  66E676C3           const [297]: (-246.89999389648)
0635  03                 const type 3
0636  CD1CAA44           const [298]: (1360.9000244141)
063A  03                 const type 3
063B  CD1CAAC4           const [299]: (-1360.9000244141)
063F  03                 const type 3
0640  9A990141           const [300]: (8.1000003814697)
0644  03                 const type 3
0645  9A190F43           const [301]: (143.10000610352)
0649  03                 const type 3
064A  9A190FC3           const [302]: (-143.10000610352)
064E  03                 const type 3
064F  9A89AD44           const [303]: (1388.3000488281)
0653  03                 const type 3
0654  9A89ADC4           const [304]: (-1388.3000488281)
0658  03                 const type 3
0659  9A997940           const [305]: (3.9000000953674)
065D  03                 const type 3
065E  0000DC42           const [306]: (110)
0662  03                 const type 3
0663  9A598243           const [307]: (260.70001220703)
0667  03                 const type 3
0668  9A5982C3           const [308]: (-260.70001220703)
066C  03                 const type 3
066D  CDCC9744           const [309]: (1214.4000244141)
0671  03                 const type 3
0672  CDCC97C4           const [310]: (-1214.4000244141)
0676  03                 const type 3
0677  33B34B43           const [311]: (203.69999694824)
067B  03                 const type 3
067C  33B34BC3           const [312]: (-203.69999694824)
0680  03                 const type 3
0681  CD4C8944           const [313]: (1098.4000244141)
0685  03                 const type 3
0686  CD4C89C4           const [314]: (-1098.4000244141)
068A  03                 const type 3
068B  00006041           const [315]: (14)
068F  03                 const type 3
0690  9A99F542           const [316]: (122.80000305176)
0694  03                 const type 3
0695  9A99F5C2           const [317]: (-122.80000305176)
0699  03                 const type 3
069A  CD1C8544           const [318]: (1064.9000244141)
069E  03                 const type 3
069F  CD1C85C4           const [319]: (-1064.9000244141)
06A3  03                 const type 3
06A4  00006143           const [320]: (225)
06A8  03                 const type 3
06A9  66660443           const [321]: (132.39999389648)
06AD  03                 const type 3
06AE  66268A44           const [322]: (1105.1999511719)
06B2  03                 const type 3
06B3  66268AC4           const [323]: (-1105.1999511719)
06B7  03                 const type 3
06B8  6656AD44           const [324]: (1386.6999511719)
06BC  03                 const type 3
06BD  6656ADC4           const [325]: (-1386.6999511719)
06C1  03                 const type 3
06C2  00009143           const [326]: (290)
06C6  03                 const type 3
06C7  CDECA644           const [327]: (1335.4000244141)
06CB  03                 const type 3
06CC  CDECA6C4           const [328]: (-1335.4000244141)
06D0  03                 const type 3
06D1  CD4C0143           const [329]: (129.30000305176)
06D5  03                 const type 3
06D6  CD4C01C3           const [330]: (-129.30000305176)
06DA  03                 const type 3
06DB  3323AD44           const [331]: (1385.0999755859)
06DF  03                 const type 3
06E0  3323ADC4           const [332]: (-1385.0999755859)
06E4  03                 const type 3
06E5  00008C42           const [333]: (70)
06E9  03                 const type 3
06EA  CDCCE042           const [334]: (112.40000152588)
06EE  03                 const type 3
06EF  CDCCE0C2           const [335]: (-112.40000152588)
06F3  03                 const type 3
06F4  33F37344           const [336]: (975.79998779297)
06F8  03                 const type 3
06F9  33F373C4           const [337]: (-975.79998779297)
06FD  03                 const type 3
06FE  CD4C2743           const [338]: (167.30000305176)
0702  03                 const type 3
0703  CD4C27C3           const [339]: (-167.30000305176)
0707  03                 const type 3
0708  9A195F44           const [340]: (892.40002441406)
070C  03                 const type 3
070D  9A195FC4           const [341]: (-892.40002441406)
0711  03                 const type 3
0712  00808943           const [342]: (275)
0716  03                 const type 3
0717  66665E42           const [343]: (55.599998474121)
071B  03                 const type 3
071C  00408444           const [344]: (1058)
0720  03                 const type 3
0721  004084C4           const [345]: (-1058)
0725  03                 const type 3
0726  6666E640           const [346]: (7.1999998092651)
072A  03                 const type 3
072B  CDEC5E44           const [347]: (891.70001220703)
072F  03                 const type 3
0730  CDEC5EC4           const [348]: (-891.70001220703)
0734  03                 const type 3
0735  00809743           const [349]: (303)
0739  03                 const type 3
073A  33339842           const [350]: (76.099998474121)
073E  03                 const type 3
073F  CD2C8744           const [351]: (1081.4000244141)
0743  03                 const type 3
0744  66668241           const [352]: (16.299999237061)
0748  03                 const type 3
0749  33338341           const [353]: (16.39999961853)
074D  03                 const type 3
074E  333383C1           const [354]: (-16.39999961853)
0752  03                 const type 3
0753  CDAC9644           const [355]: (1205.4000244141)
0757  03                 const type 3
0758  3333AB41           const [356]: (21.39999961853)
075C  03                 const type 3
075D  00004643           const [357]: (198)
0761  03                 const type 3
0762  66660842           const [358]: (34.099998474121)
0766  03                 const type 3
0767  666608C2           const [359]: (-34.099998474121)
076B  03                 const type 3
076C  33638B44           const [360]: (1115.0999755859)
0770  03                 const type 3
0771  00008841           const [361]: (17)
0775  03                 const type 3
0776  00808843           const [362]: (273)
077A  03                 const type 3
077B  9AA98644           const [363]: (1077.3000488281)
077F  03                 const type 3
0780  33336B41           const [364]: (14.699999809265)
0784  03                 const type 3
0785  00004843           const [365]: (200)
0789  03                 const type 3
078A  33337F42           const [366]: (63.799999237061)
078E  03                 const type 3
078F  33337FC2           const [367]: (-63.799999237061)
0793  03                 const type 3
0794  33337F44           const [368]: (1020.799987793)
0798  03                 const type 3
0799  00003843           const [369]: (184)
079D  03                 const type 3
079E  33339242           const [370]: (73.099998474121)
07A2  03                 const type 3
07A3  333392C2           const [371]: (-73.099998474121)
07A7  03                 const type 3
07A8  CD2C6944           const [372]: (932.70001220703)
07AC  03                 const type 3
07AD  CDCCCC3E           const [373]: (0.40000000596046)
07B1  03                 const type 3
07B2  CDCCCCBE           const [374]: (-0.40000000596046)
07B6  03                 const type 3
07B7  CD4C7044           const [375]: (961.20001220703)
07BB  03                 const type 3
07BC  9A998442           const [376]: (66.300003051758)
07C0  03                 const type 3
07C1  9A9984C2           const [377]: (-66.300003051758)
07C5  03                 const type 3
07C6  00805D44           const [378]: (886)
07CA  03                 const type 3
07CB  9A994941           const [379]: (12.60000038147)
07CF  03                 const type 3
07D0  9A9949C1           const [380]: (-12.60000038147)
07D4  03                 const type 3
07D5  CDEC5844           const [381]: (867.70001220703)
07D9  03                 const type 3
07DA  0000A043           const [382]: (320)
07DE  03                 const type 3
07DF  0000B342           const [383]: (89.5)
07E3  03                 const type 3
07E4  33336D44           const [384]: (948.79998779297)
07E8  03                 const type 3
07E9  0080A243           const [385]: (325)
07ED  03                 const type 3
07EE  9A99AC42           const [386]: (86.300003051758)
07F2  03                 const type 3
07F3  00406644           const [387]: (921)
07F7  03                 const type 3
07F8  33337B41           const [388]: (15.699999809265)
07FC  03                 const type 3
07FD  0000A343           const [389]: (326)
0801  03                 const type 3
0802  CDCC4E42           const [390]: (51.700000762939)
0806  03                 const type 3
0807  6666CC42           const [391]: (102.19999694824)
080B  03                 const type 3
080C  33B37943           const [392]: (249.69999694824)
0810  03                 const type 3
0811  9A99AD41           const [393]: (21.700000762939)
0815  03                 const type 3
0816  CD4C1F43           const [394]: (159.30000305176)
081A  03                 const type 3
081B  33334943           const [395]: (201.19999694824)
081F  03                 const type 3
0820  CDCC4441           const [396]: (12.300000190735)
0824  03                 const type 3
0825  00007042           const [397]: (60)
0829  03                 const type 3
082A  CDCCBC40           const [398]: (5.9000000953674)
082E  03                 const type 3
082F  CDCCBCC0           const [399]: (-5.9000000953674)
0833  03                 const type 3
0834  6666B442           const [400]: (90.199996948242)
0838  03                 const type 3
0839  CDCCE441           const [401]: (28.60000038147)
083D  03                 const type 3
083E  0080A643           const [402]: (333)
0842  03                 const type 3
0843  9A990D42           const [403]: (35.400001525879)
0847  03                 const type 3
0848  9A990DC2           const [404]: (-35.400001525879)
084C  03                 const type 3
084D  CDCC1043           const [405]: (144.80000305176)
0851  03                 const type 3
0852  9A99D941           const [406]: (27.200000762939)
0856  03                 const type 3
0857  33330F42           const [407]: (35.799999237061)
085B  03                 const type 3
085C  33330FC2           const [408]: (-35.799999237061)
0860  03                 const type 3
0861  33336F42           const [409]: (59.799999237061)
0865  03                 const type 3
0866  9A99DD41           const [410]: (27.700000762939)
086A  03                 const type 3
086B  66668E42           const [411]: (71.199996948242)
086F  03                 const type 3
0870  6666C640           const [412]: (6.1999998092651)
0874  03                 const type 3
0875  66668C43           const [413]: (280.79998779297)
0879  03                 const type 3
087A  CDCCB441           const [414]: (22.60000038147)
087E  03                 const type 3
087F  66E66243           const [415]: (226.89999389648)
0883  03                 const type 3
0884  9A992043           const [416]: (160.60000610352)
0888  03                 const type 3
0889  CD8CAD43           const [417]: (347.10000610352)
088D  03                 const type 3
088E  CDCC9841           const [418]: (19.10000038147)
0892  03                 const type 3
0893  CDCCD142           const [419]: (104.90000152588)
0897  03                 const type 3
0898  6666D743           const [420]: (430.79998779297)
089C  03                 const type 3
089D  00001843           const [421]: (152)
08A1  03                 const type 3
08A2  9A991343           const [422]: (147.60000610352)
08A6  03                 const type 3
08A7  0000E643           const [423]: (460)
08AB  03                 const type 3
08AC  CDCC5C41           const [424]: (13.800000190735)
08B0  03                 const type 3
08B1  CD4C3C43           const [425]: (188.30000305176)
08B5  03                 const type 3
08B6  33333543           const [426]: (181.19999694824)
08BA  03                 const type 3
08BB  CD4CD543           const [427]: (426.60000610352)
08BF  03                 const type 3
08C0  9A996941           const [428]: (14.60000038147)
08C4  03                 const type 3
08C5  66E63143           const [429]: (177.89999389648)
08C9  03                 const type 3
08CA  CDCC4943           const [430]: (201.80000305176)
08CE  03                 const type 3
08CF  9A599C43           const [431]: (312.70001220703)
08D3  03                 const type 3
08D4  00007841           const [432]: (15.5)
08D8  03                 const type 3
08D9  3333B442           const [433]: (90.099998474121)
08DD  03                 const type 3
08DE  9A995342           const [434]: (52.900001525879)
08E2  03                 const type 3
08E3  3333A243           const [435]: (324.39999389648)
08E7  03                 const type 3
08E8  CDCCA041           const [436]: (20.10000038147)
08EC  03                 const type 3
08ED  CD4C6043           const [437]: (224.30000305176)
08F1  03                 const type 3
08F2  CDCC6442           const [438]: (57.200000762939)
08F6  03                 const type 3
08F7  33336243           const [439]: (226.19999694824)
08FB  03                 const type 3
08FC  9A99A541           const [440]: (20.700000762939)
0900  03                 const type 3
0901  33B3AA43           const [441]: (341.39999389648)
0905  03                 const type 3
0906  0000B542           const [442]: (90.5)
090A  03                 const type 3
090B  33F38A43           const [443]: (277.89999389648)
090F  03                 const type 3
0910  33F3BC43           const [444]: (377.89999389648)
0914  03                 const type 3
0915  33F3BCC3           const [445]: (-377.89999389648)
0919  03                 const type 3
091A  00E00644           const [446]: (539.5)
091E  03                 const type 3
091F  00E006C4           const [447]: (-539.5)
0923  03                 const type 3
0924  9A998941           const [448]: (17.200000762939)
0928  03                 const type 3
0929  33333243           const [449]: (178.19999694824)
092D  03                 const type 3
092E  333332C3           const [450]: (-178.19999694824)
0932  03                 const type 3
0933  CDCCC543           const [451]: (395.60000610352)
0937  03                 const type 3
0938  CDCCC5C3           const [452]: (-395.60000610352)
093C  03                 const type 3
093D  0000DE42           const [453]: (111)
0941  03                 const type 3
0942  33F30244           const [454]: (523.79998779297)
0946  03                 const type 3
0947  33F302C4           const [455]: (-523.79998779297)
094B  03                 const type 3
094C  33F3A843           const [456]: (337.89999389648)
0950  03                 const type 3
0951  33F3A8C3           const [457]: (-337.89999389648)
0955  03                 const type 3
0956  9A190C44           const [458]: (560.40002441406)
095A  03                 const type 3
095B  9A190CC4           const [459]: (-560.40002441406)
095F  03                 const type 3
0960  CD8CFD43           const [460]: (507.10000610352)
0964  03                 const type 3
0965  CD8CFDC3           const [461]: (-507.10000610352)
0969  03                 const type 3
096A  33F33044           const [462]: (707.79998779297)
096E  03                 const type 3
096F  33F330C4           const [463]: (-707.79998779297)
0973  03                 const type 3
0974  CDCCFA43           const [464]: (501.60000610352)
0978  03                 const type 3
0979  CDCCFAC3           const [465]: (-501.60000610352)
097D  03                 const type 3
097E  CD4C7E43           const [466]: (254.30000305176)
0982  03                 const type 3
0983  CD4C7EC3           const [467]: (-254.30000305176)
0987  03                 const type 3
0988  9A999843           const [468]: (305.20001220703)
098C  03                 const type 3
098D  9A9998C3           const [469]: (-305.20001220703)
0991  03                 const type 3
0992  CDCC0E43           const [470]: (142.80000305176)
0996  03                 const type 3
0997  CDCCBB43           const [471]: (375.60000610352)
099B  03                 const type 3
099C  CDCCBBC3           const [472]: (-375.60000610352)
09A0  03                 const type 3
09A1  CD8C8C43           const [473]: (281.10000610352)
09A5  03                 const type 3
09A6  CD8C8CC3           const [474]: (-281.10000610352)
09AA  03                 const type 3
09AB  9A193743           const [475]: (183.10000610352)
09AF  03                 const type 3
09B0  0000DE43           const [476]: (444)
09B4  03                 const type 3
09B5  0000DEC3           const [477]: (-444)
09B9  03                 const type 3
09BA  CDCC9543           const [478]: (299.60000610352)
09BE  03                 const type 3
09BF  CDCC95C3           const [479]: (-299.60000610352)
09C3  03                 const type 3
09C4  00401844           const [480]: (609)
09C8  03                 const type 3
09C9  004018C4           const [481]: (-609)
09CD  03                 const type 3
09CE  3333A443           const [482]: (328.39999389648)
09D2  03                 const type 3
09D3  3333A4C3           const [483]: (-328.39999389648)
09D7  03                 const type 3
09D8  66E64943           const [484]: (201.89999389648)
09DC  03                 const type 3
09DD  33532744           const [485]: (669.29998779297)
09E1  03                 const type 3
09E2  335327C4           const [486]: (-669.29998779297)
09E6  03                 const type 3
09E7  00C0B743           const [487]: (367.5)
09EB  03                 const type 3
09EC  00C0B7C3           const [488]: (-367.5)
09F0  03                 const type 3
09F1  00805443           const [489]: (212.5)
09F5  03                 const type 3
09F6  66E6D843           const [490]: (433.79998779297)
09FA  03                 const type 3
09FB  66E6D8C3           const [491]: (-433.79998779297)
09FF  03                 const type 3
0A00  33F30944           const [492]: (551.79998779297)
0A04  03                 const type 3
0A05  33F309C4           const [493]: (-551.79998779297)
0A09  03                 const type 3
0A0A  CDCC4C41           const [494]: (12.800000190735)
0A0E  03                 const type 3
0A0F  CD0CAE43           const [495]: (348.10000610352)
0A13  03                 const type 3
0A14  CDCCE243           const [496]: (453.60000610352)
0A18  03                 const type 3
0A19  CDCCE2C3           const [497]: (-453.60000610352)
0A1D  03                 const type 3
0A1E  9A190044           const [498]: (512.40002441406)
0A22  03                 const type 3
0A23  9A1900C4           const [499]: (-512.40002441406)
0A27  03                 const type 3
0A28  9A994141           const [500]: (12.10000038147)
0A2C  03                 const type 3
0A2D  6666AD43           const [501]: (346.79998779297)
0A31  03                 const type 3
0A32  66A6CA43           const [502]: (405.29998779297)
0A36  03                 const type 3
0A37  66A6CAC3           const [503]: (-405.29998779297)
0A3B  03                 const type 3
0A3C  CD2C1E44           const [504]: (632.70001220703)
0A40  03                 const type 3
0A41  CD2C1EC4           const [505]: (-632.70001220703)
0A45  03                 const type 3
0A46  CD4CAF43           const [506]: (350.60000610352)
0A4A  03                 const type 3
0A4B  CD4CAFC3           const [507]: (-350.60000610352)
0A4F  03                 const type 3
0A50  33D31D44           const [508]: (631.29998779297)
0A54  03                 const type 3
0A55  33D31DC4           const [509]: (-631.29998779297)
0A59  03                 const type 3
0A5A  CDCC8943           const [510]: (275.60000610352)
0A5E  03                 const type 3
0A5F  CD0C8D43           const [511]: (282.10000610352)
0A63  03                 const type 3
0A64  CD0C8DC3           const [512]: (-282.10000610352)
0A68  03                 const type 3
0A69  9A191044           const [513]: (576.40002441406)
0A6D  03                 const type 3
0A6E  9A1910C4           const [514]: (-576.40002441406)
0A72  03                 const type 3
0A73  CDCC2C40           const [515]: (2.7000000476837)
0A77  03                 const type 3
0A78  0000C040           const [516]: (6)
0A7C  03                 const type 3
0A7D  0000E040           const [517]: (7)
0A81  03                 const type 3
0A82  00000041           const [518]: (8)
0A86  03                 const type 3
0A87  00001041           const [519]: (9)
0A8B  03                 const type 3
0A8C  0080FD43           const [520]: (507)
0A90  03                 const type 3
0A91  0080FDC3           const [521]: (-507)
0A95  03                 const type 3
0A96  9AA98E44           const [522]: (1141.3000488281)
0A9A  03                 const type 3
0A9B  00003543           const [523]: (181)
0A9F  03                 const type 3
0AA0  33330C44           const [524]: (560.79998779297)
0AA4  03                 const type 3
0AA5  33330CC4           const [525]: (-560.79998779297)
0AA9  03                 const type 3
0AAA  33939144           const [526]: (1164.5999755859)
0AAE  03                 const type 3
0AAF  00001743           const [527]: (151)
0AB3  03                 const type 3
0AB4  00204344           const [528]: (780.5)
0AB8  03                 const type 3
0AB9  002043C4           const [529]: (-780.5)
0ABD  03                 const type 3
0ABE  CDCC8B44           const [530]: (1118.4000244141)
0AC2  03                 const type 3
0AC3  00201F44           const [531]: (636.5)
0AC7  03                 const type 3
0AC8  00201FC4           const [532]: (-636.5)
0ACC  03                 const type 3
0ACD  9A796344           const [533]: (909.90002441406)
0AD1  03                 const type 3
0AD2  0000B842           const [534]: (92)
0AD6  03                 const type 3
0AD7  CD0C6C44           const [535]: (944.20001220703)
0ADB  03                 const type 3
0ADC  CD0C6CC4           const [536]: (-944.20001220703)
0AE0  03                 const type 3
0AE1  9AB96144           const [537]: (902.90002441406)
0AE5  03                 const type 3
0AE6  00205244           const [538]: (840.5)
0AEA  03                 const type 3
0AEB  002052C4           const [539]: (-840.5)
0AEF  03                 const type 3
0AF0  9AF9A144           const [540]: (1295.8000488281)
0AF4  03                 const type 3
0AF5  0000D642           const [541]: (107)
0AF9  03                 const type 3
0AFA  CD4CA143           const [542]: (322.60000610352)
0AFE  03                 const type 3
0AFF  CD4CA1C3           const [543]: (-322.60000610352)
0B03  03                 const type 3
0B04  00608744           const [544]: (1083)
0B08  03                 const type 3
0B09  9A991141           const [545]: (9.1000003814697)
0B0D  03                 const type 3
0B0E  0000A041           const [546]: (20)
0B12  03                 const type 3
0B13  3373AD43           const [547]: (346.89999389648)
0B17  03                 const type 3
0B18  3373ADC3           const [548]: (-346.89999389648)
0B1C  03                 const type 3
0B1D  CD7C9244           const [549]: (1171.9000244141)
0B21  03                 const type 3
0B22  66663641           const [550]: (11.39999961853)
0B26  03                 const type 3
0B27  00009C43           const [551]: (312)
0B2B  03                 const type 3
0B2C  00409543           const [552]: (298.5)
0B30  03                 const type 3
0B31  004095C3           const [553]: (-298.5)
0B35  03                 const type 3
0B36  0000A844           const [554]: (1344)
0B3A  03                 const type 3
0B3B  00000C43           const [555]: (140)
0B3F  03                 const type 3
0B40  3333E043           const [556]: (448.39999389648)
0B44  03                 const type 3
0B45  3333E0C3           const [557]: (-448.39999389648)
0B49  03                 const type 3
0B4A  9AA9A244           const [558]: (1301.3000488281)
0B4E  03                 const type 3
0B4F  CDCCCC3D           const [559]: (0.10000000149012)
0B53  03                 const type 3
0B54  CDAC1444           const [560]: (594.70001220703)
0B58  03                 const type 3
0B59  CDAC14C4           const [561]: (-594.70001220703)
0B5D  03                 const type 3
0B5E  9AF9A944           const [562]: (1359.8000488281)
0B62  03                 const type 3
0B63  00403C44           const [563]: (753)
0B67  03                 const type 3
0B68  00403CC4           const [564]: (-753)
0B6C  03                 const type 3
0B6D  CD2C2744           const [565]: (668.70001220703)
0B71  03                 const type 3
0B72  CD2C27C4           const [566]: (-668.70001220703)
0B76  03                 const type 3
0B77  6636AD44           const [567]: (1385.6999511719)
0B7B  03                 const type 3
0B7C  00002442           const [568]: (41)
0B80  03                 const type 3
0B81  CDCC4244           const [569]: (779.20001220703)
0B85  03                 const type 3
0B86  CDCC42C4           const [570]: (-779.20001220703)
0B8A  03                 const type 3
0B8B  6686B244           const [571]: (1428.1999511719)
0B8F  03                 const type 3
0B90  00E04F44           const [572]: (831.5)
0B94  03                 const type 3
0B95  00E04FC4           const [573]: (-831.5)
0B99  03                 const type 3
0B9A  66F6BC44           const [574]: (1511.6999511719)
0B9E  03                 const type 3
0B9F  9AF96444           const [575]: (915.90002441406)
0BA3  03                 const type 3
0BA4  9AF964C4           const [576]: (-915.90002441406)
0BA8  03                 const type 3
0BA9  0080BB44           const [577]: (1500)
0BAD  03                 const type 3
0BAE  9A998541           const [578]: (16.700000762939)
0BB2  03                 const type 3
0BB3  00006243           const [579]: (226)
0BB7  03                 const type 3
0BB8  CD4C5C44           const [580]: (881.20001220703)
0BBC  03                 const type 3
0BBD  CD4C5CC4           const [581]: (-881.20001220703)
0BC1  03                 const type 3
0BC2  CDCCA644           const [582]: (1334.4000244141)
0BC6  03                 const type 3
0BC7  00C08044           const [583]: (1030)
0BCB  03                 const type 3
0BCC  00C080C4           const [584]: (-1030)
0BD0  03                 const type 3
0BD1  9A79A644           const [585]: (1331.8000488281)
0BD5  03                 const type 3
0BD6  9A592244           const [586]: (649.40002441406)
0BDA  03                 const type 3
0BDB  9A5922C4           const [587]: (-649.40002441406)
0BDF  03                 const type 3
0BE0  9A39BB44           const [588]: (1497.8000488281)
0BE4  03                 const type 3
0BE5  9A597344           const [589]: (973.40002441406)
0BE9  03                 const type 3
0BEA  9A5973C4           const [590]: (-973.40002441406)
0BEE  03                 const type 3
0BEF  00009142           const [591]: (72.5)
0BF3  03                 const type 3
0BF4  000091C2           const [592]: (-72.5)
0BF8  03                 const type 3
0BF9  00001643           const [593]: (150)
0BFD  03                 const type 3
0BFE  9A798644           const [594]: (1075.8000488281)
0C02  03                 const type 3
0C03  9A7986C4           const [595]: (-1075.8000488281)
0C07  03                 const type 3
0C08  CD4C0843           const [596]: (136.30000305176)
0C0C  03                 const type 3
0C0D  CD4C08C3           const [597]: (-136.30000305176)
0C11  03                 const type 3
0C12  00605D44           const [598]: (885.5)
0C16  03                 const type 3
0C17  00605DC4           const [599]: (-885.5)
0C1B  03                 const type 3
0C1C  9A193443           const [600]: (180.10000610352)
0C20  03                 const type 3
0C21  CDCC1441           const [601]: (9.3000001907349)
0C25  03                 const type 3
0C26  0000A842           const [602]: (84)
0C2A  03                 const type 3
0C2B  00108344           const [603]: (1048.5)
0C2F  03                 const type 3
0C30  001083C4           const [604]: (-1048.5)
0C34  03                 const type 3
0C35  33739F43           const [605]: (318.89999389648)
0C39  03                 const type 3
0C3A  66666444           const [606]: (913.59997558594)
0C3E  03                 const type 3
0C3F  666664C4           const [607]: (-913.59997558594)
0C43  03                 const type 3
0C44  3373A943           const [608]: (338.89999389648)
0C48  03                 const type 3
0C49  00002C43           const [609]: (172)
0C4D  03                 const type 3
0C4E  00803F44           const [610]: (766)
0C52  03                 const type 3
0C53  00803FC4           const [611]: (-766)
0C57  03                 const type 3
0C58  33B33944           const [612]: (742.79998779297)
0C5C  03                 const type 3
0C5D  33B339C4           const [613]: (-742.79998779297)
0C61  03                 const type 3
0C62  CD0C8543           const [614]: (266.10000610352)
0C66  03                 const type 3
0C67  66666641           const [615]: (14.39999961853)
0C6B  03                 const type 3
0C6C  00008343           const [616]: (262)
0C70  03                 const type 3
0C71  CD6C1B44           const [617]: (621.70001220703)
0C75  03                 const type 3
0C76  CD6C1BC4           const [618]: (-621.70001220703)
0C7A  03                 const type 3
0C7B  00601044           const [619]: (577.5)
0C7F  03                 const type 3
0C80  9A195A44           const [620]: (872.40002441406)
0C84  03                 const type 3
0C85  9A195AC4           const [621]: (-872.40002441406)
0C89  03                 const type 3
0C8A  33F33D44           const [622]: (759.79998779297)
0C8E  03                 const type 3
0C8F  0000B243           const [623]: (356)
0C93  03                 const type 3
0C94  33D30644           const [624]: (539.29998779297)
0C98  03                 const type 3
0C99  33D306C4           const [625]: (-539.29998779297)
0C9D  03                 const type 3
0C9E  9AD95344           const [626]: (847.40002441406)
0CA2  03                 const type 3
0CA3  0000B841           const [627]: (23)
0CA7  03                 const type 3
0CA8  33931944           const [628]: (614.29998779297)
0CAC  03                 const type 3
0CAD  339319C4           const [629]: (-614.29998779297)
0CB1  03                 const type 3
0CB2  66E64844           const [630]: (803.59997558594)
0CB6  03                 const type 3
0CB7  CDCCEC41           const [631]: (29.60000038147)
0CBB  03                 const type 3
0CBC  CD2C2D44           const [632]: (692.70001220703)
0CC0  03                 const type 3
0CC1  CD2C2DC4           const [633]: (-692.70001220703)
0CC5  03                 const type 3
0CC6  9A193044           const [634]: (704.40002441406)
0CCA  03                 const type 3
0CCB  0080A543           const [635]: (331)
0CCF  03                 const type 3
0CD0  66265044           const [636]: (832.59997558594)
0CD4  03                 const type 3
0CD5  662650C4           const [637]: (-832.59997558594)
0CD9  03                 const type 3
0CDA  66C68144           const [638]: (1038.1999511719)
0CDE  03                 const type 3
0CDF  00000843           const [639]: (136)
0CE3  03                 const type 3
0CE4  33F3C043           const [640]: (385.89999389648)
0CE8  03                 const type 3
0CE9  33F3C0C3           const [641]: (-385.89999389648)
0CED  03                 const type 3
0CEE  CD6C8444           const [642]: (1059.4000244141)
0CF2  03                 const type 3
0CF3  9AD99344           const [643]: (1182.8000488281)
0CF7  03                 const type 3
0CF8  9AD993C4           const [644]: (-1182.8000488281)
0CFC  03                 const type 3
0CFD  33131244           const [645]: (584.29998779297)
0D01  03                 const type 3
0D02  331312C4           const [646]: (-584.29998779297)
0D06  03                 const type 3
0D07  9AF98D44           const [647]: (1135.8000488281)
0D0B  03                 const type 3
0D0C  9AF98DC4           const [648]: (-1135.8000488281)
0D10  03                 const type 3
0D11  00A01C44           const [649]: (626.5)
0D15  03                 const type 3
0D16  00A01CC4           const [650]: (-626.5)
0D1A  03                 const type 3
0D1B  3333CF41           const [651]: (25.89999961853)
0D1F  03                 const type 3
0D20  00204C44           const [652]: (816.5)
0D24  03                 const type 3
0D25  00204CC4           const [653]: (-816.5)
0D29  03                 const type 3
0D2A  0040AE43           const [654]: (348.5)
0D2E  03                 const type 3
0D2F  0040AEC3           const [655]: (-348.5)
0D33  03                 const type 3
0D34  9AF96A44           const [656]: (939.90002441406)
0D38  03                 const type 3
0D39  9AF96AC4           const [657]: (-939.90002441406)
0D3D  03                 const type 3
0D3E  3373E843           const [658]: (464.89999389648)
0D42  03                 const type 3
0D43  3373E8C3           const [659]: (-464.89999389648)
0D47  03                 const type 3
0D48  0000E041           const [660]: (28)
0D4C  03                 const type 3
0D4D  9AB97D44           const [661]: (1014.9000244141)
0D51  03                 const type 3
0D52  9AB97DC4           const [662]: (-1014.9000244141)
0D56  03                 const type 3
0D57  9A195D44           const [663]: (884.40002441406)
0D5B  03                 const type 3
0D5C  9A195DC4           const [664]: (-884.40002441406)
0D60  03                 const type 3
0D61  CD8CAA43           const [665]: (341.10000610352)
0D65  03                 const type 3
0D66  CD8CAAC3           const [666]: (-341.10000610352)
0D6A  03                 const type 3
0D6B  66A66944           const [667]: (934.59997558594)
0D6F  03                 const type 3
0D70  66A669C4           const [668]: (-934.59997558594)
0D74  03                 const type 3
0D75  9A196643           const [669]: (230.10000610352)
0D79  03                 const type 3
0D7A  9A1966C3           const [670]: (-230.10000610352)
0D7E  03                 const type 3
0D7F  0000D040           const [671]: (6.5)
0D83  03                 const type 3
0D84  CD4C8244           const [672]: (1042.4000244141)
0D88  03                 const type 3
0D89  CD4C82C4           const [673]: (-1042.4000244141)
0D8D  03                 const type 3
0D8E  9A197243           const [674]: (242.10000610352)
0D92  03                 const type 3
0D93  9A1972C3           const [675]: (-242.10000610352)
0D97  03                 const type 3
0D98  00708E44           const [676]: (1139.5)
0D9C  03                 const type 3
0D9D  00708EC4           const [677]: (-1139.5)
0DA1  03                 const type 3
0DA2  9AD99D43           const [678]: (315.70001220703)
0DA6  03                 const type 3
0DA7  9AD99DC3           const [679]: (-315.70001220703)
0DAB  03                 const type 3
0DAC  0000B443           const [680]: (360)
0DB0  03                 const type 3
0DB1  00909544           const [681]: (1196.5)
0DB5  03                 const type 3
0DB6  009095C4           const [682]: (-1196.5)
0DBA  03                 const type 3
0DBB  0000A643           const [683]: (332)
0DBF  03                 const type 3
0DC0  0000A6C3           const [684]: (-332)
0DC4  03                 const type 3
0DC5  00004C43           const [685]: (204)
0DC9  03                 const type 3
0DCA  66168844           const [686]: (1088.6999511719)
0DCE  03                 const type 3
0DCF  661688C4           const [687]: (-1088.6999511719)
0DD3  03                 const type 3
0DD4  CDCC8041           const [688]: (16.10000038147)
0DD8  03                 const type 3
0DD9  00002243           const [689]: (162)
0DDD  03                 const type 3
0DDE  00608F44           const [690]: (1147)
0DE2  03                 const type 3
0DE3  00608FC4           const [691]: (-1147)
0DE7  03                 const type 3
0DE8  0080E043           const [692]: (449)
0DEC  03                 const type 3
0DED  0080E0C3           const [693]: (-449)
0DF1  03                 const type 3
0DF2  00002143           const [694]: (161)
0DF6  03                 const type 3
0DF7  CD9C8544           const [695]: (1068.9000244141)
0DFB  03                 const type 3
0DFC  CD9C85C4           const [696]: (-1068.9000244141)
0E00  03                 const type 3
0E01  33930644           const [697]: (538.29998779297)
0E05  03                 const type 3
0E06  339306C4           const [698]: (-538.29998779297)
0E0A  03                 const type 3
0E0B  33735A44           const [699]: (873.79998779297)
0E0F  03                 const type 3
0E10  33735AC4           const [700]: (-873.79998779297)
0E14  03                 const type 3
0E15  CD4C0343           const [701]: (131.30000305176)
0E19  03                 const type 3
0E1A  CD4C03C3           const [702]: (-131.30000305176)
0E1E  03                 const type 3
0E1F  CD4C3A44           const [703]: (745.20001220703)
0E23  03                 const type 3
0E24  CD4C3AC4           const [704]: (-745.20001220703)
0E28  03                 const type 3
0E29  66C66244           const [705]: (907.09997558594)
0E2D  03                 const type 3
0E2E  66C662C4           const [706]: (-907.09997558594)
0E32  03                 const type 3
0E33  00004A42           const [707]: (50.5)
0E37  03                 const type 3
0E38  9AA99044           const [708]: (1157.3000488281)
0E3C  03                 const type 3
0E3D  9AA990C4           const [709]: (-1157.3000488281)
0E41  03                 const type 3
0E42  6666DD42           const [710]: (110.69999694824)
0E46  03                 const type 3
0E47  6666DDC2           const [711]: (-110.69999694824)
0E4B  03                 const type 3
0E4C  0000B041           const [712]: (22)
0E50  03                 const type 3
0E51  9A999B44           const [713]: (1244.8000488281)
0E55  03                 const type 3
0E56  9A999BC4           const [714]: (-1244.8000488281)
0E5A  03                 const type 3
0E5B  3333F340           const [715]: (7.5999999046326)
0E5F  03                 const type 3
0E60  33238944           const [716]: (1097.0999755859)
0E64  03                 const type 3
0E65  332389C4           const [717]: (-1097.0999755859)
0E69  03                 const type 3
0E6A  0000D942           const [718]: (108.5)
0E6E  03                 const type 3
0E6F  66A67444           const [719]: (978.59997558594)
0E73  03                 const type 3
0E74  66A674C4           const [720]: (-978.59997558594)
0E78  03                 const type 3
0E79  6666EA42           const [721]: (117.19999694824)
0E7D  03                 const type 3
0E7E  33331341           const [722]: (9.1999998092651)
0E82  03                 const type 3
0E83  0080B243           const [723]: (357)
0E87  03                 const type 3
0E88  9A192F44           const [724]: (700.40002441406)
0E8C  03                 const type 3
0E8D  9A192FC4           const [725]: (-700.40002441406)
0E91  03                 const type 3
0E92  CDDCA044           const [726]: (1286.9000244141)
0E96  03                 const type 3
0E97  CDDCA0C4           const [727]: (-1286.9000244141)
0E9B  03                 const type 3
0E9C  00002042           const [728]: (40)
0EA0  03                 const type 3
0EA1  CD2C3A44           const [729]: (744.70001220703)
0EA5  03                 const type 3
0EA6  CD2C3AC4           const [730]: (-744.70001220703)
0EAA  03                 const type 3
0EAB  00809E44           const [731]: (1268)
0EAF  03                 const type 3
0EB0  00809EC4           const [732]: (-1268)
0EB4  03                 const type 3
0EB5  00202644           const [733]: (664.5)
0EB9  03                 const type 3
0EBA  002026C4           const [734]: (-664.5)
0EBE  03                 const type 3
0EBF  6696AB44           const [735]: (1372.6999511719)
0EC3  03                 const type 3
0EC4  6696ABC4           const [736]: (-1372.6999511719)
0EC8  03                 const type 3
0EC9  0000D041           const [737]: (26)
0ECD  03                 const type 3
0ECE  66263244           const [738]: (712.59997558594)
0ED2  03                 const type 3
0ED3  662632C4           const [739]: (-712.59997558594)
0ED7  03                 const type 3
0ED8  CD7CBB44           const [740]: (1499.9000244141)
0EDC  03                 const type 3
0EDD  CD7CBBC4           const [741]: (-1499.9000244141)
0EE1  03                 const type 3
0EE2  9AF95A44           const [742]: (875.90002441406)
0EE6  03                 const type 3
0EE7  9AF95AC4           const [743]: (-875.90002441406)
0EEB  03                 const type 3
0EEC  9A09B044           const [744]: (1408.3000488281)
0EF0  03                 const type 3
0EF1  9A09B0C4           const [745]: (-1408.3000488281)
0EF5  03                 const type 3
0EF6  00004343           const [746]: (195)
0EFA  03                 const type 3
0EFB  66A65944           const [747]: (870.59997558594)
0EFF  03                 const type 3
0F00  66A659C4           const [748]: (-870.59997558594)
0F04  03                 const type 3
0F05  00C0A544           const [749]: (1326)
0F09  03                 const type 3
0F0A  00C0A5C4           const [750]: (-1326)
0F0E  03                 const type 3
0F0F  00908044           const [751]: (1028.5)
0F13  03                 const type 3
0F14  009080C4           const [752]: (-1028.5)
0F18  03                 const type 3
0F19  6696B544           const [753]: (1452.6999511719)
0F1D  03                 const type 3
0F1E  6696B5C4           const [754]: (-1452.6999511719)
0F22  03                 const type 3
0F23  33337544           const [755]: (980.79998779297)
0F27  03                 const type 3
0F28  333375C4           const [756]: (-980.79998779297)
0F2C  03                 const type 3
0F2D  66D69C44           const [757]: (1254.6999511719)
0F31  03                 const type 3
0F32  66D69CC4           const [758]: (-1254.6999511719)
0F36  03                 const type 3
0F37  00E05144           const [759]: (839.5)
0F3B  03                 const type 3
0F3C  00E051C4           const [760]: (-839.5)
0F40  03                 const type 3
0F41  CD5C9944           const [761]: (1226.9000244141)
0F45  03                 const type 3
0F46  CD5C99C4           const [762]: (-1226.9000244141)
0F4A  03                 const type 3
0F4B  9A995141           const [763]: (13.10000038147)
0F4F  03                 const type 3
0F50  00007842           const [764]: (62)
0F54  03                 const type 3
0F55  33D35244           const [765]: (843.29998779297)
0F59  03                 const type 3
0F5A  33D352C4           const [766]: (-843.29998779297)
0F5E  03                 const type 3
0F5F  66C66F44           const [767]: (959.09997558594)
0F63  03                 const type 3
0F64  66C66FC4           const [768]: (-959.09997558594)
0F68  03                 const type 3
0F69  00E07644           const [769]: (987.5)
0F6D  03                 const type 3
0F6E  00E076C4           const [770]: (-987.5)
0F72  03                 const type 3
0F73  9A798D44           const [771]: (1131.8000488281)
0F77  03                 const type 3
0F78  9A798DC4           const [772]: (-1131.8000488281)
0F7C  03                 const type 3
0F7D  CDCC6C41           const [773]: (14.800000190735)
0F81  03                 const type 3
0F82  9A795C44           const [774]: (881.90002441406)
0F86  03                 const type 3
0F87  9A795CC4           const [775]: (-881.90002441406)
0F8B  03                 const type 3
0F8C  33D37D44           const [776]: (1015.299987793)
0F90  03                 const type 3
0F91  33D37DC4           const [777]: (-1015.299987793)
0F95  03                 const type 3
0F96  00003E43           const [778]: (190)
0F9A  03                 const type 3
0F9B  9A197D44           const [779]: (1012.4000244141)
0F9F  03                 const type 3
0FA0  9A197DC4           const [780]: (-1012.4000244141)
0FA4  03                 const type 3
0FA5  9A995F44           const [781]: (894.40002441406)
0FA9  03                 const type 3
0FAA  9A995FC4           const [782]: (-894.40002441406)
0FAE  03                 const type 3
0FAF  33B35044           const [783]: (834.79998779297)
0FB3  03                 const type 3
0FB4  33B350C4           const [784]: (-834.79998779297)
0FB8  03                 const type 3
0FB9  9A593F44           const [785]: (765.40002441406)
0FBD  03                 const type 3
0FBE  9A593FC4           const [786]: (-765.40002441406)
0FC2  03                 const type 3
0FC3  66569244           const [787]: (1170.6999511719)
0FC7  03                 const type 3
0FC8  665692C4           const [788]: (-1170.6999511719)
0FCC  03                 const type 3
0FCD  33133044           const [789]: (704.29998779297)
0FD1  03                 const type 3
0FD2  331330C4           const [790]: (-704.29998779297)
0FD6  03                 const type 3
0FD7  9A99B541           const [791]: (22.700000762939)
0FDB  03                 const type 3
0FDC  33D35844           const [792]: (867.29998779297)
0FE0  03                 const type 3
0FE1  33D358C4           const [793]: (-867.29998779297)
0FE5  03                 const type 3
0FE6  66662944           const [794]: (677.59997558594)
0FEA  03                 const type 3
0FEB  666629C4           const [795]: (-677.59997558594)
0FEF  03                 const type 3
0FF0  9A796B44           const [796]: (941.90002441406)
0FF4  03                 const type 3
0FF5  9A796BC4           const [797]: (-941.90002441406)
0FF9  03                 const type 3
0FFA  00202C44           const [798]: (688.5)
0FFE  03                 const type 3
0FFF  00202CC4           const [799]: (-688.5)
1003  03                 const type 3
1004  00808544           const [800]: (1068)
1008  03                 const type 3
1009  008085C4           const [801]: (-1068)
100D  03                 const type 3
100E  9A991E44           const [802]: (634.40002441406)
1012  03                 const type 3
1013  9A991EC4           const [803]: (-634.40002441406)
1017  03                 const type 3
1018  E6D68E44           const [804]: (1142.7155761719)
101C  03                 const type 3
101D  E6D68EC4           const [805]: (-1142.7155761719)
1021  03                 const type 3
1022  B0E98744           const [806]: (1087.302734375)
1026  03                 const type 3
1027  B0E987C4           const [807]: (-1087.302734375)
102B  03                 const type 3
102C  54E36D41           const [808]: (14.868000030518)
1030  03                 const type 3
1031  47CB9043           const [809]: (289.58810424805)
1035  03                 const type 3
1036  D2AF9844           const [810]: (1221.4943847656)
103A  03                 const type 3
103B  D2AF98C4           const [811]: (-1221.4943847656)
103F  03                 const type 3
1040  D3B69A44           const [812]: (1237.7132568359)
1044  03                 const type 3
1045  D3B69AC4           const [813]: (-1237.7132568359)
1049  03                 const type 3
104A  1E166B41           const [814]: (14.692899703979)
104E  03                 const type 3
104F  14709B43           const [815]: (310.87561035156)
1053  03                 const type 3
1054  36808F44           const [816]: (1148.0065917969)
1058  03                 const type 3
1059  36808FC4           const [817]: (-1148.0065917969)
105D  03                 const type 3
105E  A6FC9D44           const [818]: (1263.8952636719)
1062  03                 const type 3
1063  A6FC9DC4           const [819]: (-1263.8952636719)
1067  03                 const type 3
1068  2A3A6D41           const [820]: (14.826700210571)
106C  03                 const type 3
106D  3A92A441           const [821]: (20.571399688721)
1071  03                 const type 3
1072  91C3A844           const [822]: (1350.1114501953)
1076  03                 const type 3
1077  91C3A8C4           const [823]: (-1350.1114501953)
107B  03                 const type 3
107C  E92C9944           const [824]: (1225.4034423828)
1080  03                 const type 3
1081  E92C99C4           const [825]: (-1225.4034423828)
1085  03                 const type 3
1086  0E3E9141           const [826]: (18.155300140381)
108A  03                 const type 3
108B  B1A08A43           const [827]: (277.25540161133)
108F  03                 const type 3
1090  D60CDD44           const [828]: (1768.4011230469)
1094  03                 const type 3
1095  D60CDDC4           const [829]: (-1768.4011230469)
1099  03                 const type 3
109A  D81C9544           const [830]: (1192.9013671875)
109E  03                 const type 3
109F  D81C95C4           const [831]: (-1192.9013671875)
10A3  03                 const type 3
10A4  BDE36D41           const [832]: (14.868100166321)
10A8  03                 const type 3
10A9  CB718D43           const [833]: (282.88900756836)
10AD  03                 const type 3
10AE  F485B344           const [834]: (1436.1860351563)
10B2  03                 const type 3
10B3  F485B3C4           const [835]: (-1436.1860351563)
10B7  03                 const type 3
10B8  F7114A44           const [836]: (808.28070068359)
10BC  03                 const type 3
10BD  F7114AC4           const [837]: (-808.28070068359)
10C1  03                 const type 3
10C2  6ADE6D41           const [838]: (14.866800308228)
10C6  03                 const type 3
10C7  EC2FAB40           const [839]: (5.3495998382568)
10CB  03                 const type 3
10CC  A6D2C444           const [840]: (1574.5827636719)
10D0  03                 const type 3
10D1  A6D2C4C4           const [841]: (-1574.5827636719)
10D5  03                 const type 3
10D6  7A929844           const [842]: (1220.5773925781)
10DA  03                 const type 3
10DB  7A9298C4           const [843]: (-1220.5773925781)
10DF  03                 const type 3
10E0  13618F40           const [844]: (4.4805998802185)
10E4  03                 const type 3
10E5  F3EA9444           const [845]: (1191.3421630859)
10E9  03                 const type 3
10EA  F3EA94C4           const [846]: (-1191.3421630859)
10EE  03                 const type 3
10EF  036C5444           const [847]: (849.68768310547)
10F3  03                 const type 3
10F4  036C54C4           const [848]: (-849.68768310547)
10F8  03                 const type 3
10F9  B7D16D41           const [849]: (14.863699913025)
10FD  03                 const type 3
10FE  6134A942           const [850]: (84.60230255127)
1102  03                 const type 3
1103  EFBDC044           const [851]: (1541.9354248047)
1107  03                 const type 3
1108  EFBDC0C4           const [852]: (-1541.9354248047)
110C  03                 const type 3
110D  7B2C2844           const [853]: (672.69500732422)
1111  03                 const type 3
1112  7B2C28C4           const [854]: (-672.69500732422)
1116  03                 const type 3
1117  DDB56D41           const [855]: (14.856900215149)
111B  03                 const type 3
111C  13626C43           const [856]: (236.38310241699)
1120  03                 const type 3
1121  4056D744           const [857]: (1722.6953125)
1125  03                 const type 3
1126  4056D7C4           const [858]: (-1722.6953125)
112A  03                 const type 3
112B  6F98A743           const [859]: (335.19088745117)
112F  03                 const type 3
1130  6F98A7C3           const [860]: (-335.19088745117)
1134  03                 const type 3
1135  3FC66D41           const [861]: (14.860899925232)
1139  03                 const type 3
113A  E8D9A43F           const [862]: (1.2878999710083)
113E  03                 const type 3
113F  CDDCC644           const [863]: (1590.9000244141)
1143  03                 const type 3
1144  CDDCC6C4           const [864]: (-1590.9000244141)
1148  03                 const type 3
1149  66463A44           const [865]: (745.09997558594)
114D  03                 const type 3
114E  66463AC4           const [866]: (-745.09997558594)
1152  03                 const type 3
1153  00E0D344           const [867]: (1695)
1157  03                 const type 3
1158  00E0D3C4           const [868]: (-1695)
115C  03                 const type 3
115D  00A01F44           const [869]: (638.5)
1161  03                 const type 3
1162  00A01FC4           const [870]: (-638.5)
1166  03                 const type 3
1167  CD4C8443           const [871]: (264.60000610352)
116B  03                 const type 3
116C  66E6A944           const [872]: (1359.1999511719)
1170  03                 const type 3
1171  66E6A9C4           const [873]: (-1359.1999511719)
1175  03                 const type 3
1176  33132244           const [874]: (648.29998779297)
117A  03                 const type 3
117B  331322C4           const [875]: (-648.29998779297)
117F  03                 const type 3
1180  33B34743           const [876]: (199.69999694824)
1184  03                 const type 3
1185  9AC9AF44           const [877]: (1406.3000488281)
1189  03                 const type 3
118A  9AC9AFC4           const [878]: (-1406.3000488281)
118E  03                 const type 3
118F  33B3CB43           const [879]: (407.39999389648)
1193  03                 const type 3
1194  33B3CBC3           const [880]: (-407.39999389648)
1198  03                 const type 3
1199  9A69A444           const [881]: (1315.3000488281)
119D  03                 const type 3
119E  9A69A4C4           const [882]: (-1315.3000488281)
11A2  03                 const type 3
11A3  00405844           const [883]: (865)
11A7  03                 const type 3
11A8  004058C4           const [884]: (-865)
11AC  03                 const type 3
11AD  9A99B243           const [885]: (357.20001220703)
11B1  03                 const type 3
11B2  3323C744           const [886]: (1593.0999755859)
11B6  03                 const type 3
11B7  3323C7C4           const [887]: (-1593.0999755859)
11BB  03                 const type 3
11BC  00C06144           const [888]: (903)
11C0  03                 const type 3
11C1  00C061C4           const [889]: (-903)
11C5  03                 const type 3
11C6  9A19B043           const [890]: (352.20001220703)
11CA  03                 const type 3
11CB  CD9CBD44           const [891]: (1516.9000244141)
11CF  03                 const type 3
11D0  CD9CBDC4           const [892]: (-1516.9000244141)
11D4  03                 const type 3
11D5  CD6C7A44           const [893]: (1001.700012207)
11D9  03                 const type 3
11DA  CD6C7AC4           const [894]: (-1001.700012207)
11DE  03                 const type 3
11DF  33339142           const [895]: (72.599998474121)
11E3  03                 const type 3
11E4  0030B244           const [896]: (1425.5)
11E8  03                 const type 3
11E9  0030B2C4           const [897]: (-1425.5)
11ED  03                 const type 3
11EE  00209F44           const [898]: (1273)
11F2  03                 const type 3
11F3  00209FC4           const [899]: (-1273)
11F7  03                 const type 3
11F8  00C0AB43           const [900]: (343.5)
11FC  03                 const type 3
11FD  6686D944           const [901]: (1740.1999511719)
1201  03                 const type 3
1202  6686D9C4           const [902]: (-1740.1999511719)
1206  03                 const type 3
1207  3333C342           const [903]: (97.599998474121)
120B  03                 const type 3
120C  3333C3C2           const [904]: (-97.599998474121)
1210  03                 const type 3
1211  9A198543           const [905]: (266.20001220703)
1215  03                 const type 3
1216  CD4CD344           const [906]: (1690.4000244141)
121A  03                 const type 3
121B  CD4CD3C4           const [907]: (-1690.4000244141)
121F  03                 const type 3
1220  CD4C3E43           const [908]: (190.30000305176)
1224  03                 const type 3
1225  9A09D744           const [909]: (1720.3000488281)
1229  03                 const type 3
122A  9A09D7C4           const [910]: (-1720.3000488281)
122E  03                 const type 3
122F  9A99F742           const [911]: (123.80000305176)
1233  03                 const type 3
1234  9A99F7C2           const [912]: (-123.80000305176)
1238  03                 const type 3
1239  CD4C4B43           const [913]: (203.30000305176)
123D  03                 const type 3
123E  CD7CD644           const [914]: (1715.9000244141)
1242  03                 const type 3
1243  CD7CD6C4           const [915]: (-1715.9000244141)
1247  03                 const type 3
1248  00001C43           const [916]: (156)
124C  03                 const type 3
124D  00001CC3           const [917]: (-156)
1251  03                 const type 3
1252  66268443           const [918]: (264.29998779297)
1256  03                 const type 3
1257  0000CE44           const [919]: (1648)
125B  03                 const type 3
125C  0000CEC4           const [920]: (-1648)
1260  03                 const type 3
1261  66662E43           const [921]: (174.39999389648)
1265  03                 const type 3
1266  66662EC3           const [922]: (-174.39999389648)
126A  03                 const type 3
126B  9A99B242           const [923]: (89.300003051758)
126F  03                 const type 3
1270  9AC9D644           const [924]: (1718.3000488281)
1274  03                 const type 3
1275  9AC9D6C4           const [925]: (-1718.3000488281)
1279  03                 const type 3
127A  66664B43           const [926]: (203.39999389648)
127E  03                 const type 3
127F  66664BC3           const [927]: (-203.39999389648)
1283  03                 const type 3
1284  CD4C3343           const [928]: (179.30000305176)
1288  03                 const type 3
1289  CD0CDD44           const [929]: (1768.4000244141)
128D  03                 const type 3
128E  CD0CDDC4           const [930]: (-1768.4000244141)
1292  03                 const type 3
1293  CDCC8F43           const [931]: (287.60000610352)
1297  03                 const type 3
1298  CDCC8FC3           const [932]: (-287.60000610352)
129C  03                 const type 3
129D  9AC9C744           const [933]: (1598.3000488281)
12A1  03                 const type 3
12A2  9AC9C7C4           const [934]: (-1598.3000488281)
12A6  03                 const type 3
12A7  CDCC8043           const [935]: (257.60000610352)
12AB  03                 const type 3
12AC  CDCC80C3           const [936]: (-257.60000610352)
12B0  03                 const type 3
12B1  6666B642           const [937]: (91.199996948242)
12B5  03                 const type 3
12B6  CDCCCD44           const [938]: (1646.4000244141)
12BA  03                 const type 3
12BB  CDCCCDC4           const [939]: (-1646.4000244141)
12BF  03                 const type 3
12C0  9A196043           const [940]: (224.10000610352)
12C4  03                 const type 3
12C5  9A1960C3           const [941]: (-224.10000610352)
12C9  03                 const type 3
12CA  CDCCAA42           const [942]: (85.400001525879)
12CE  03                 const type 3
12CF  9AC9D044           const [943]: (1670.3000488281)
12D3  03                 const type 3
12D4  9AC9D0C4           const [944]: (-1670.3000488281)
12D8  03                 const type 3
12D9  9A996C43           const [945]: (236.60000610352)
12DD  03                 const type 3
12DE  9A996CC3           const [946]: (-236.60000610352)
12E2  03                 const type 3
12E3  9A993343           const [947]: (179.60000610352)
                         * functions:
12E7  00000000           sizep (0)
                         * code:
12EB  36080000           sizecode (2102)
12EF  0A000000           [0001] newtable   0   0   0    ; array=0, hash=0
12F3  05000001           [0002] getglobal  1   0        ; GameLocation
12F7  99800001           [0003] call       1   1   2  
12FB  D5BE0001           [0004] eq         1   1   251  ; 0, to [6] if false
12FF  D4048000           [0005] jmp        20           ; to [26]
1303  05000001           [0006] getglobal  1   0        ; GameLocation
1307  99800001           [0007] call       1   1   2  
130B  15BF0001           [0008] eq         1   1   252  ; 1, to [10] if false
130F  D4038000           [0009] jmp        16           ; to [26]
1313  05000001           [0010] getglobal  1   0        ; GameLocation
1317  99800001           [0011] call       1   1   2  
131B  55BF0001           [0012] eq         1   1   253  ; 2, to [14] if false
131F  D4028000           [0013] jmp        12           ; to [26]
1323  05000001           [0014] getglobal  1   0        ; GameLocation
1327  99800001           [0015] call       1   1   2  
132B  95BF0001           [0016] eq         1   1   254  ; 3, to [18] if false
132F  D4018000           [0017] jmp        8            ; to [26]
1333  05000001           [0018] getglobal  1   0        ; GameLocation
1337  99800001           [0019] call       1   1   2  
133B  D5BF0001           [0020] eq         1   1   255  ; 4, to [22] if false
133F  D4008000           [0021] jmp        4            ; to [26]
1343  05000001           [0022] getglobal  1   0        ; GameLocation
1347  99800001           [0023] call       1   1   2  
134B  15C00000           [0024] eq         0   1   256  ; 5, to [26] if true
134F  541F8100           [0025] jmp        1150         ; to [1176]
1353  0A001601           [0026] newtable   1   44  0    ; array=128, hash=0
1357  0A800102           [0027] newtable   2   3   0    ; array=3, hash=0
135B  0A800103           [0028] newtable   3   3   0    ; array=3, hash=0
135F  C1010004           [0029] loadk      4   7        ; 502.70001220703
1363  41020005           [0030] loadk      5   9        ; -161.80000305176
1367  81020006           [0031] loadk      6   10       ; 11.699999809265
136B  9F000003           [0032] setlist    3   2        ; index 1 to 3
136F  C1020004           [0033] loadk      4   11       ; 95
1373  41000005           [0034] loadk      5   1        ; 0
1377  9F000002           [0035] setlist    2   2        ; index 1 to 3
137B  0A800103           [0036] newtable   3   3   0    ; array=3, hash=0
137F  0A800104           [0037] newtable   4   3   0    ; array=3, hash=0
1383  01030005           [0038] loadk      5   12       ; 495.60000610352
1387  81030006           [0039] loadk      6   14       ; -84.099998474121
138B  C1030007           [0040] loadk      7   15       ; 10
138F  9F000004           [0041] setlist    4   2        ; index 1 to 3
1393  01040005           [0042] loadk      5   16       ; 170
1397  41000006           [0043] loadk      6   1        ; 0
139B  9F000003           [0044] setlist    3   2        ; index 1 to 3
139F  0A800104           [0045] newtable   4   3   0    ; array=3, hash=0
13A3  0A800105           [0046] newtable   5   3   0    ; array=3, hash=0
13A7  41040006           [0047] loadk      6   17       ; 466.29998779297
13AB  C1040007           [0048] loadk      7   19       ; -19.60000038147
13AF  01050008           [0049] loadk      8   20       ; 10.699999809265
13B3  9F000005           [0050] setlist    5   2        ; index 1 to 3
13B7  41050006           [0051] loadk      6   21       ; 335
13BB  41000007           [0052] loadk      7   1        ; 0
13BF  9F000004           [0053] setlist    4   2        ; index 1 to 3
13C3  0A800105           [0054] newtable   5   3   0    ; array=3, hash=0
13C7  0A800106           [0055] newtable   6   3   0    ; array=3, hash=0
13CB  81050007           [0056] loadk      7   22       ; 517.90002441406
13CF  C1050008           [0057] loadk      8   23       ; 93.599998474121
13D3  01060009           [0058] loadk      9   24       ; 11.10000038147
13D7  9F000006           [0059] setlist    6   2        ; index 1 to 3
13DB  41060007           [0060] loadk      7   25       ; 97
13DF  41000008           [0061] loadk      8   1        ; 0
13E3  9F000005           [0062] setlist    5   2        ; index 1 to 3
13E7  0A800106           [0063] newtable   6   3   0    ; array=3, hash=0
13EB  0A800107           [0064] newtable   7   3   0    ; array=3, hash=0
13EF  81060008           [0065] loadk      8   26       ; 432.5
13F3  C1060009           [0066] loadk      9   27       ; 69.5
13F7  0107000A           [0067] loadk      10  28       ; 11
13FB  9F000007           [0068] setlist    7   2        ; index 1 to 3
13FF  41070008           [0069] loadk      8   29       ; 280
1403  41000009           [0070] loadk      9   1        ; 0
1407  9F000006           [0071] setlist    6   2        ; index 1 to 3
140B  0A800107           [0072] newtable   7   3   0    ; array=3, hash=0
140F  0A800108           [0073] newtable   8   3   0    ; array=3, hash=0
1413  81070009           [0074] loadk      9   30       ; 258.10000610352
1417  C107000A           [0075] loadk      10  31       ; 294.89999389648
141B  0108000B           [0076] loadk      11  32       ; 8.6999998092651
141F  9F000008           [0077] setlist    8   2        ; index 1 to 3
1423  01040009           [0078] loadk      9   16       ; 170
1427  4100000A           [0079] loadk      10  1        ; 0
142B  9F000007           [0080] setlist    7   2        ; index 1 to 3
142F  0A800108           [0081] newtable   8   3   0    ; array=3, hash=0
1433  0A800109           [0082] newtable   9   3   0    ; array=3, hash=0
1437  4108000A           [0083] loadk      10  33       ; 295.70001220703
143B  8108000B           [0084] loadk      11  34       ; 282.79998779297
143F  C108000C           [0085] loadk      12  35       ; 17.700000762939
1443  9F000009           [0086] setlist    9   2        ; index 1 to 3
1447  0109000A           [0087] loadk      10  36       ; 230
144B  4100000B           [0088] loadk      11  1        ; 0
144F  9F000008           [0089] setlist    8   2        ; index 1 to 3
1453  0A800109           [0090] newtable   9   3   0    ; array=3, hash=0
1457  0A80010A           [0091] newtable   10  3   0    ; array=3, hash=0
145B  4109000B           [0092] loadk      11  37       ; 380.29998779297
145F  8109000C           [0093] loadk      12  38       ; 248.10000610352
1463  C109000D           [0094] loadk      13  39       ; 10.800000190735
1467  9F00000A           [0095] setlist    10  2        ; index 1 to 3
146B  0109000B           [0096] loadk      11  36       ; 230
146F  4100000C           [0097] loadk      12  1        ; 0
1473  9F000009           [0098] setlist    9   2        ; index 1 to 3
1477  0A80010A           [0099] newtable   10  3   0    ; array=3, hash=0
147B  0A80010B           [0100] newtable   11  3   0    ; array=3, hash=0
147F  010A000C           [0101] loadk      12  40       ; 420.5
1483  410A000D           [0102] loadk      13  41       ; 272.20001220703
1487  810A000E           [0103] loadk      14  42       ; 11.60000038147
148B  9F00000B           [0104] setlist    11  2        ; index 1 to 3
148F  C10A000C           [0105] loadk      12  43       ; 310
1493  4100000D           [0106] loadk      13  1        ; 0
1497  9F00000A           [0107] setlist    10  2        ; index 1 to 3
149B  0A80010B           [0108] newtable   11  3   0    ; array=3, hash=0
149F  0A80010C           [0109] newtable   12  3   0    ; array=3, hash=0
14A3  010B000D           [0110] loadk      13  44       ; 479.60000610352
14A7  410B000E           [0111] loadk      14  45       ; 202
14AB  810B000F           [0112] loadk      15  46       ; 11.300000190735
14AF  9F00000C           [0113] setlist    12  2        ; index 1 to 3
14B3  C10B000D           [0114] loadk      13  47       ; 220
14B7  4100000E           [0115] loadk      14  1        ; 0
14BB  9F00000B           [0116] setlist    11  2        ; index 1 to 3
14BF  0A80010C           [0117] newtable   12  3   0    ; array=3, hash=0
14C3  0A80010D           [0118] newtable   13  3   0    ; array=3, hash=0
14C7  010C000E           [0119] loadk      14  48       ; 542.79998779297
14CB  410C000F           [0120] loadk      15  49       ; 366.39999389648
14CF  810C0010           [0121] loadk      16  50       ; 15.39999961853
14D3  9F00000D           [0122] setlist    13  2        ; index 1 to 3
14D7  C10C000E           [0123] loadk      14  51       ; 76
14DB  4100000F           [0124] loadk      15  1        ; 0
14DF  9F00000C           [0125] setlist    12  2        ; index 1 to 3
14E3  0A80010D           [0126] newtable   13  3   0    ; array=3, hash=0
14E7  0A80010E           [0127] newtable   14  3   0    ; array=3, hash=0
14EB  010D000F           [0128] loadk      15  52       ; 558.59997558594
14EF  410D0010           [0129] loadk      16  53       ; 529.29998779297
14F3  810D0011           [0130] loadk      17  54       ; 12
14F7  9F00000E           [0131] setlist    14  2        ; index 1 to 3
14FB  C10D000F           [0132] loadk      15  55       ; 130
14FF  41000010           [0133] loadk      16  1        ; 0
1503  9F00000D           [0134] setlist    13  2        ; index 1 to 3
1507  0A80010E           [0135] newtable   14  3   0    ; array=3, hash=0
150B  0A80010F           [0136] newtable   15  3   0    ; array=3, hash=0
150F  010E0010           [0137] loadk      16  56       ; 484.70001220703
1513  410E0011           [0138] loadk      17  57       ; 495
1517  810E0012           [0139] loadk      18  58       ; 11.5
151B  9F00000F           [0140] setlist    15  2        ; index 1 to 3
151F  C10E0010           [0141] loadk      16  59       ; 120
1523  41000011           [0142] loadk      17  1        ; 0
1527  9F00000E           [0143] setlist    14  2        ; index 1 to 3
152B  0A80010F           [0144] newtable   15  3   0    ; array=3, hash=0
152F  0A800110           [0145] newtable   16  3   0    ; array=3, hash=0
1533  010F0011           [0146] loadk      17  60       ; 384.89999389648
1537  410F0012           [0147] loadk      18  61       ; 365.79998779297
153B  01070013           [0148] loadk      19  28       ; 11
153F  9F000010           [0149] setlist    16  2        ; index 1 to 3
1543  810F0011           [0150] loadk      17  62       ; 251
1547  41000012           [0151] loadk      18  1        ; 0
154B  9F00000F           [0152] setlist    15  2        ; index 1 to 3
154F  0A800110           [0153] newtable   16  3   0    ; array=3, hash=0
1553  0A800111           [0154] newtable   17  3   0    ; array=3, hash=0
1557  C10F0012           [0155] loadk      18  63       ; 480.39999389648
155B  01100013           [0156] loadk      19  64       ; 402.20001220703
155F  810A0014           [0157] loadk      20  42       ; 11.60000038147
1563  9F000011           [0158] setlist    17  2        ; index 1 to 3
1567  01040012           [0159] loadk      18  16       ; 170
156B  41000013           [0160] loadk      19  1        ; 0
156F  9F000010           [0161] setlist    16  2        ; index 1 to 3
1573  0A800111           [0162] newtable   17  3   0    ; array=3, hash=0
1577  0A800112           [0163] newtable   18  3   0    ; array=3, hash=0
157B  41100013           [0164] loadk      19  65       ; 298.10000610352
157F  81100014           [0165] loadk      20  66       ; 447.39999389648
1583  C1100015           [0166] loadk      21  67       ; 10.60000038147
1587  9F000012           [0167] setlist    18  2        ; index 1 to 3
158B  01040013           [0168] loadk      19  16       ; 170
158F  41000014           [0169] loadk      20  1        ; 0
1593  9F000011           [0170] setlist    17  2        ; index 1 to 3
1597  0A800112           [0171] newtable   18  3   0    ; array=3, hash=0
159B  0A800113           [0172] newtable   19  3   0    ; array=3, hash=0
159F  01110014           [0173] loadk      20  68       ; 313.70001220703
15A3  41110015           [0174] loadk      21  69       ; 359.89999389648
15A7  81110016           [0175] loadk      22  70       ; 13.199999809265
15AB  9F000013           [0176] setlist    19  2        ; index 1 to 3
15AF  C1110014           [0177] loadk      20  71       ; 340
15B3  41000015           [0178] loadk      21  1        ; 0
15B7  9F000012           [0179] setlist    18  2        ; index 1 to 3
15BB  0A800113           [0180] newtable   19  3   0    ; array=3, hash=0
15BF  0A800114           [0181] newtable   20  3   0    ; array=3, hash=0
15C3  01120015           [0182] loadk      21  72       ; 347.89999389648
15C7  41120016           [0183] loadk      22  73       ; 569.90002441406
15CB  81120017           [0184] loadk      23  74       ; 10.10000038147
15CF  9F000014           [0185] setlist    20  2        ; index 1 to 3
15D3  C1120015           [0186] loadk      21  75       ; 265
15D7  41000016           [0187] loadk      22  1        ; 0
15DB  9F000013           [0188] setlist    19  2        ; index 1 to 3
15DF  0A800114           [0189] newtable   20  3   0    ; array=3, hash=0
15E3  0A800115           [0190] newtable   21  3   0    ; array=3, hash=0
15E7  01130016           [0191] loadk      22  76       ; 416.79998779297
15EB  41130017           [0192] loadk      23  77       ; 646.79998779297
15EF  81130018           [0193] loadk      24  78       ; 11.199999809265
15F3  9F000015           [0194] setlist    21  2        ; index 1 to 3
15F7  C1130016           [0195] loadk      22  79       ; 353
15FB  41000017           [0196] loadk      23  1        ; 0
15FF  9F000014           [0197] setlist    20  2        ; index 1 to 3
1603  0A800115           [0198] newtable   21  3   0    ; array=3, hash=0
1607  0A800116           [0199] newtable   22  3   0    ; array=3, hash=0
160B  01140017           [0200] loadk      23  80       ; 493.79998779297
160F  41140018           [0201] loadk      24  81       ; 730.5
1613  810B0019           [0202] loadk      25  46       ; 11.300000190735
1617  9F000016           [0203] setlist    22  2        ; index 1 to 3
161B  C1130017           [0204] loadk      23  79       ; 353
161F  41000018           [0205] loadk      24  1        ; 0
1623  9F000015           [0206] setlist    21  2        ; index 1 to 3
1627  0A800116           [0207] newtable   22  3   0    ; array=3, hash=0
162B  0A800117           [0208] newtable   23  3   0    ; array=3, hash=0
162F  81140018           [0209] loadk      24  82       ; 246.39999389648
1633  C1140019           [0210] loadk      25  83       ; 702.59997558594
1637  0115001A           [0211] loadk      26  84       ; 12.89999961853
163B  9F000017           [0212] setlist    23  2        ; index 1 to 3
163F  41150018           [0213] loadk      24  85       ; 337
1643  41000019           [0214] loadk      25  1        ; 0
1647  9F000016           [0215] setlist    22  2        ; index 1 to 3
164B  0A800117           [0216] newtable   23  3   0    ; array=3, hash=0
164F  0A800118           [0217] newtable   24  3   0    ; array=3, hash=0
1653  81150019           [0218] loadk      25  86       ; 582.90002441406
1657  C115001A           [0219] loadk      26  87       ; 753.5
165B  0116001B           [0220] loadk      27  88       ; 13
165F  9F000018           [0221] setlist    24  2        ; index 1 to 3
1663  41160019           [0222] loadk      25  89       ; 90
1667  4100001A           [0223] loadk      26  1        ; 0
166B  9F000017           [0224] setlist    23  2        ; index 1 to 3
166F  0A800118           [0225] newtable   24  3   0    ; array=3, hash=0
1673  0A800119           [0226] newtable   25  3   0    ; array=3, hash=0
1677  8116001A           [0227] loadk      26  90       ; 578.90002441406
167B  C116001B           [0228] loadk      27  91       ; 941.09997558594
167F  810C001C           [0229] loadk      28  50       ; 15.39999961853
1683  9F000019           [0230] setlist    25  2        ; index 1 to 3
1687  0117001A           [0231] loadk      26  92       ; 118
168B  4100001B           [0232] loadk      27  1        ; 0
168F  9F000018           [0233] setlist    24  2        ; index 1 to 3
1693  0A800119           [0234] newtable   25  3   0    ; array=3, hash=0
1697  0A80011A           [0235] newtable   26  3   0    ; array=3, hash=0
169B  4117001B           [0236] loadk      27  93       ; 432.70001220703
169F  8117001C           [0237] loadk      28  94       ; 953.29998779297
16A3  C117001D           [0238] loadk      29  95       ; 15.300000190735
16A7  9F00001A           [0239] setlist    26  2        ; index 1 to 3
16AB  0118001B           [0240] loadk      27  96       ; 296
16AF  4100001C           [0241] loadk      28  1        ; 0
16B3  9F000019           [0242] setlist    25  2        ; index 1 to 3
16B7  0A80011A           [0243] newtable   26  3   0    ; array=3, hash=0
16BB  0A80011B           [0244] newtable   27  3   0    ; array=3, hash=0
16BF  4118001C           [0245] loadk      28  97       ; 287.70001220703
16C3  8118001D           [0246] loadk      29  98       ; 1035.8000488281
16C7  C118001E           [0247] loadk      30  99       ; 13.39999961853
16CB  9F00001B           [0248] setlist    27  2        ; index 1 to 3
16CF  0119001C           [0249] loadk      28  100      ; 295
16D3  4100001D           [0250] loadk      29  1        ; 0
16D7  9F00001A           [0251] setlist    26  2        ; index 1 to 3
16DB  0A80011B           [0252] newtable   27  3   0    ; array=3, hash=0
16DF  0A80011C           [0253] newtable   28  3   0    ; array=3, hash=0
16E3  4119001D           [0254] loadk      29  101      ; 208.60000610352
16E7  8119001E           [0255] loadk      30  102      ; 1232.9000244141
16EB  C119001F           [0256] loadk      31  103      ; 17.39999961853
16EF  9F00001C           [0257] setlist    28  2        ; index 1 to 3
16F3  011A001D           [0258] loadk      29  104      ; 294
16F7  4100001E           [0259] loadk      30  1        ; 0
16FB  9F00001B           [0260] setlist    27  2        ; index 1 to 3
16FF  0A80011C           [0261] newtable   28  3   0    ; array=3, hash=0
1703  0A80011D           [0262] newtable   29  3   0    ; array=3, hash=0
1707  411A001E           [0263] loadk      30  105      ; 266.79998779297
170B  811A001F           [0264] loadk      31  106      ; 1295.6999511719
170F  C1190020           [0265] loadk      32  103      ; 17.39999961853
1713  9F00001D           [0266] setlist    29  2        ; index 1 to 3
1717  C11A001E           [0267] loadk      30  107      ; 250
171B  4100001F           [0268] loadk      31  1        ; 0
171F  9F00001C           [0269] setlist    28  2        ; index 1 to 3
1723  0A80011D           [0270] newtable   29  3   0    ; array=3, hash=0
1727  0A80011E           [0271] newtable   30  3   0    ; array=3, hash=0
172B  011B001F           [0272] loadk      31  108      ; 525.70001220703
172F  411B0020           [0273] loadk      32  109      ; 1269
1733  811B0021           [0274] loadk      33  110      ; 16.200000762939
1737  9F00001E           [0275] setlist    30  2        ; index 1 to 3
173B  C11B001F           [0276] loadk      31  111      ; 126
173F  41000020           [0277] loadk      32  1        ; 0
1743  9F00001D           [0278] setlist    29  2        ; index 1 to 3
1747  0A80011E           [0279] newtable   30  3   0    ; array=3, hash=0
174B  0A80011F           [0280] newtable   31  3   0    ; array=3, hash=0
174F  011C0020           [0281] loadk      32  112      ; 543.79998779297
1753  411C0021           [0282] loadk      33  113      ; 1048.9000244141
1757  811C0022           [0283] loadk      34  114      ; 18.89999961853
175B  9F00001F           [0284] setlist    31  2        ; index 1 to 3
175F  C11C0020           [0285] loadk      32  115      ; 94
1763  41000021           [0286] loadk      33  1        ; 0
1767  9F00001E           [0287] setlist    30  2        ; index 1 to 3
176B  0A80011F           [0288] newtable   31  3   0    ; array=3, hash=0
176F  0A800120           [0289] newtable   32  3   0    ; array=3, hash=0
1773  011D0021           [0290] loadk      33  116      ; 228.69999694824
1777  411D0022           [0291] loadk      34  117      ; 949.59997558594
177B  811D0023           [0292] loadk      35  118      ; 26.799999237061
177F  9F000020           [0293] setlist    32  2        ; index 1 to 3
1783  C11D0021           [0294] loadk      33  119      ; 44
1787  41000022           [0295] loadk      34  1        ; 0
178B  9F00001F           [0296] setlist    31  2        ; index 1 to 3
178F  0A800120           [0297] newtable   32  3   0    ; array=3, hash=0
1793  0A800121           [0298] newtable   33  3   0    ; array=3, hash=0
1797  011E0022           [0299] loadk      34  120      ; 349.70001220703
179B  811E0023           [0300] loadk      35  122      ; -32.400001525879
179F  C1100024           [0301] loadk      36  67       ; 10.60000038147
17A3  9F000021           [0302] setlist    33  2        ; index 1 to 3
17A7  C11E0022           [0303] loadk      34  123      ; 50
17AB  41000023           [0304] loadk      35  1        ; 0
17AF  9F000020           [0305] setlist    32  2        ; index 1 to 3
17B3  0A800121           [0306] newtable   33  3   0    ; array=3, hash=0
17B7  0A800122           [0307] newtable   34  3   0    ; array=3, hash=0
17BB  011F0023           [0308] loadk      35  124      ; 261.89999389648
17BF  411F0024           [0309] loadk      36  125      ; 24.700000762939
17C3  81020025           [0310] loadk      37  10       ; 11.699999809265
17C7  9F000022           [0311] setlist    34  2        ; index 1 to 3
17CB  811F0023           [0312] loadk      35  126      ; 240
17CF  41000024           [0313] loadk      36  1        ; 0
17D3  9F000021           [0314] setlist    33  2        ; index 1 to 3
17D7  DF070001           [0315] setlist    1   31       ; index 1 to 32
17DB  0A800102           [0316] newtable   2   3   0    ; array=3, hash=0
17DF  0A800103           [0317] newtable   3   3   0    ; array=3, hash=0
17E3  C11F0004           [0318] loadk      4   127      ; 363.70001220703
17E7  41200005           [0319] loadk      5   129      ; -158.30000305176
17EB  01060006           [0320] loadk      6   24       ; 11.10000038147
17EF  9F000003           [0321] setlist    3   2        ; index 1 to 3
17F3  C1110004           [0322] loadk      4   71       ; 340
17F7  41000005           [0323] loadk      5   1        ; 0
17FB  9F000002           [0324] setlist    2   2        ; index 1 to 3
17FF  0A800103           [0325] newtable   3   3   0    ; array=3, hash=0
1803  0A800104           [0326] newtable   4   3   0    ; array=3, hash=0
1807  81200005           [0327] loadk      5   130      ; 271.60000610352
180B  01210006           [0328] loadk      6   132      ; -235.80000305176
180F  41210007           [0329] loadk      7   133      ; 12.39999961853
1813  9F000004           [0330] setlist    4   2        ; index 1 to 3
1817  81210005           [0331] loadk      5   134      ; 85
181B  41000006           [0332] loadk      6   1        ; 0
181F  9F000003           [0333] setlist    3   2        ; index 1 to 3
1823  0A800104           [0334] newtable   4   3   0    ; array=3, hash=0
1827  0A800105           [0335] newtable   5   3   0    ; array=3, hash=0
182B  C1210006           [0336] loadk      6   135      ; 296.60000610352
182F  41220007           [0337] loadk      7   137      ; -302.79998779297
1833  81220008           [0338] loadk      8   138      ; 11.89999961853
1837  9F000005           [0339] setlist    5   2        ; index 1 to 3
183B  C1220006           [0340] loadk      6   139      ; 180
183F  41000007           [0341] loadk      7   1        ; 0
1843  9F000004           [0342] setlist    4   2        ; index 1 to 3
1847  0A800105           [0343] newtable   5   3   0    ; array=3, hash=0
184B  0A800106           [0344] newtable   6   3   0    ; array=3, hash=0
184F  01230007           [0345] loadk      7   140      ; 198.19999694824
1853  81230008           [0346] loadk      8   142      ; -491.60000610352
1857  810B0009           [0347] loadk      9   46       ; 11.300000190735
185B  9F000006           [0348] setlist    6   2        ; index 1 to 3
185F  C1230007           [0349] loadk      7   143      ; 175
1863  41000008           [0350] loadk      8   1        ; 0
1867  9F000005           [0351] setlist    5   2        ; index 1 to 3
186B  0A800106           [0352] newtable   6   3   0    ; array=3, hash=0
186F  0A800107           [0353] newtable   7   3   0    ; array=3, hash=0
1873  01240008           [0354] loadk      8   144      ; 272.60000610352
1877  81240009           [0355] loadk      9   146      ; -439.29998779297
187B  8112000A           [0356] loadk      10  74       ; 10.10000038147
187F  9F000007           [0357] setlist    7   2        ; index 1 to 3
1883  41160008           [0358] loadk      8   89       ; 90
1887  41000009           [0359] loadk      9   1        ; 0
188B  9F000006           [0360] setlist    6   2        ; index 1 to 3
188F  0A800107           [0361] newtable   7   3   0    ; array=3, hash=0
1893  0A800108           [0362] newtable   8   3   0    ; array=3, hash=0
1897  C1240009           [0363] loadk      9   147      ; 252.39999389648
189B  4125000A           [0364] loadk      10  149      ; -480.20001220703
189F  0116000B           [0365] loadk      11  88       ; 13
18A3  9F000008           [0366] setlist    8   2        ; index 1 to 3
18A7  81250009           [0367] loadk      9   150      ; 86
18AB  4100000A           [0368] loadk      10  1        ; 0
18AF  9F000007           [0369] setlist    7   2        ; index 1 to 3
18B3  0A800108           [0370] newtable   8   3   0    ; array=3, hash=0
18B7  0A800109           [0371] newtable   9   3   0    ; array=3, hash=0
18BB  C125000A           [0372] loadk      10  151      ; 201.39999389648
18BF  4126000B           [0373] loadk      11  153      ; -430.60000610352
18C3  C110000C           [0374] loadk      12  67       ; 10.60000038147
18C7  9F000009           [0375] setlist    9   2        ; index 1 to 3
18CB  8126000A           [0376] loadk      10  154      ; 116
18CF  4100000B           [0377] loadk      11  1        ; 0
18D3  9F000008           [0378] setlist    8   2        ; index 1 to 3
18D7  0A800109           [0379] newtable   9   3   0    ; array=3, hash=0
18DB  0A80010A           [0380] newtable   10  3   0    ; array=3, hash=0
18DF  C126000B           [0381] loadk      11  155      ; 192.89999389648
18E3  4127000C           [0382] loadk      12  157      ; -568.5
18E7  8127000D           [0383] loadk      13  158      ; 10.199999809265
18EB  9F00000A           [0384] setlist    10  2        ; index 1 to 3
18EF  C127000B           [0385] loadk      11  159      ; 350
18F3  4100000C           [0386] loadk      12  1        ; 0
18F7  9F000009           [0387] setlist    9   2        ; index 1 to 3
18FB  0A80010A           [0388] newtable   10  3   0    ; array=3, hash=0
18FF  0A80010B           [0389] newtable   11  3   0    ; array=3, hash=0
1903  0128000C           [0390] loadk      12  160      ; 80.800003051758
1907  8128000D           [0391] loadk      13  162      ; -473.10000610352
190B  C128000E           [0392] loadk      14  163      ; 13.60000038147
190F  9F00000B           [0393] setlist    11  2        ; index 1 to 3
1913  0129000C           [0394] loadk      12  164      ; 21
1917  4100000D           [0395] loadk      13  1        ; 0
191B  9F00000A           [0396] setlist    10  2        ; index 1 to 3
191F  0A80010B           [0397] newtable   11  3   0    ; array=3, hash=0
1923  0A80010C           [0398] newtable   12  3   0    ; array=3, hash=0
1927  4129000D           [0399] loadk      13  165      ; 225.80000305176
192B  C129000E           [0400] loadk      14  167      ; -1140.5999755859
192F  0105000F           [0401] loadk      15  20       ; 10.699999809265
1933  9F00000C           [0402] setlist    12  2        ; index 1 to 3
1937  012A000D           [0403] loadk      13  168      ; 82.699996948242
193B  8100000E           [0404] loadk      14  2        ; 1
193F  9F00000B           [0405] setlist    11  2        ; index 1 to 3
1943  0A80010C           [0406] newtable   12  3   0    ; array=3, hash=0
1947  0A80010D           [0407] newtable   13  3   0    ; array=3, hash=0
194B  412A000E           [0408] loadk      14  169      ; 390.29998779297
194F  C12A000F           [0409] loadk      15  171      ; -989.40002441406
1953  01070010           [0410] loadk      16  28       ; 11
1957  9F00000D           [0411] setlist    13  2        ; index 1 to 3
195B  C10E000E           [0412] loadk      14  59       ; 120
195F  8100000F           [0413] loadk      15  2        ; 1
1963  9F00000C           [0414] setlist    12  2        ; index 1 to 3
1967  0A80010D           [0415] newtable   13  3   0    ; array=3, hash=0
196B  0A80010E           [0416] newtable   14  3   0    ; array=3, hash=0
196F  012B000F           [0417] loadk      15  172      ; 255.60000610352
1973  812B0010           [0418] loadk      16  174      ; -969.09997558594
1977  C12B0011           [0419] loadk      17  175      ; 10.5
197B  9F00000E           [0420] setlist    14  2        ; index 1 to 3
197F  012C000F           [0421] loadk      15  176      ; 343.60000610352
1983  81000010           [0422] loadk      16  2        ; 1
1987  9F00000D           [0423] setlist    13  2        ; index 1 to 3
198B  0A80010E           [0424] newtable   14  3   0    ; array=3, hash=0
198F  0A80010F           [0425] newtable   15  3   0    ; array=3, hash=0
1993  412C0010           [0426] loadk      16  177      ; 364.89999389648
1997  C12C0011           [0427] loadk      17  179      ; -694.70001220703
199B  012D0012           [0428] loadk      18  180      ; 18.5
199F  9F00000F           [0429] setlist    15  2        ; index 1 to 3
19A3  412D0010           [0430] loadk      16  181      ; 210
19A7  81000011           [0431] loadk      17  2        ; 1
19AB  9F00000E           [0432] setlist    14  2        ; index 1 to 3
19AF  0A80010F           [0433] newtable   15  3   0    ; array=3, hash=0
19B3  0A800110           [0434] newtable   16  3   0    ; array=3, hash=0
19B7  812D0011           [0435] loadk      17  182      ; 173
19BB  012E0012           [0436] loadk      18  184      ; -919.70001220703
19BF  41210013           [0437] loadk      19  133      ; 12.39999961853
19C3  9F000010           [0438] setlist    16  2        ; index 1 to 3
19C7  412E0011           [0439] loadk      17  185      ; 233
19CB  81000012           [0440] loadk      18  2        ; 1
19CF  9F00000F           [0441] setlist    15  2        ; index 1 to 3
19D3  0A800110           [0442] newtable   16  3   0    ; array=3, hash=0
19D7  0A800111           [0443] newtable   17  3   0    ; array=3, hash=0
19DB  812E0012           [0444] loadk      18  186      ; 100
19DF  012F0013           [0445] loadk      19  188      ; -810.20001220703
19E3  412F0014           [0446] loadk      20  189      ; 10.39999961853
19E7  9F000011           [0447] setlist    17  2        ; index 1 to 3
19EB  812F0012           [0448] loadk      18  190      ; 235
19EF  81000013           [0449] loadk      19  2        ; 1
19F3  9F000010           [0450] setlist    16  2        ; index 1 to 3
19F7  0A800111           [0451] newtable   17  3   0    ; array=3, hash=0
19FB  0A800112           [0452] newtable   18  3   0    ; array=3, hash=0
19FF  C12F0013           [0453] loadk      19  191      ; 214.19999694824
1A03  41300014           [0454] loadk      20  193      ; -781.79998779297
1A07  81300015           [0455] loadk      21  194      ; 12.199999809265
1A0B  9F000012           [0456] setlist    18  2        ; index 1 to 3
1A0F  C1300013           [0457] loadk      19  195      ; 65
1A13  81000014           [0458] loadk      20  2        ; 1
1A17  9F000011           [0459] setlist    17  2        ; index 1 to 3
1A1B  0A800112           [0460] newtable   18  3   0    ; array=3, hash=0
1A1F  0A800113           [0461] newtable   19  3   0    ; array=3, hash=0
1A23  01310014           [0462] loadk      20  196      ; 339.60000610352
1A27  81310015           [0463] loadk      21  198      ; -563.20001220703
1A2B  C1030016           [0464] loadk      22  15       ; 10
1A2F  9F000013           [0465] setlist    19  2        ; index 1 to 3
1A33  C1110014           [0466] loadk      20  71       ; 340
1A37  81000015           [0467] loadk      21  2        ; 1
1A3B  9F000012           [0468] setlist    18  2        ; index 1 to 3
1A3F  0A800113           [0469] newtable   19  3   0    ; array=3, hash=0
1A43  0A800114           [0470] newtable   20  3   0    ; array=3, hash=0
1A47  C1310015           [0471] loadk      21  199      ; 293.89999389648
1A4B  41320016           [0472] loadk      22  201      ; -489.29998779297
1A4F  C1030017           [0473] loadk      23  15       ; 10
1A53  9F000014           [0474] setlist    20  2        ; index 1 to 3
1A57  81320015           [0475] loadk      21  202      ; 217.69999694824
1A5B  81000016           [0476] loadk      22  2        ; 1
1A5F  9F000013           [0477] setlist    19  2        ; index 1 to 3
1A63  0A800114           [0478] newtable   20  3   0    ; array=3, hash=0
1A67  0A800115           [0479] newtable   21  3   0    ; array=3, hash=0
1A6B  C1320016           [0480] loadk      22  203      ; 404.60000610352
1A6F  41330017           [0481] loadk      23  205      ; -463.5
1A73  81120018           [0482] loadk      24  74       ; 10.10000038147
1A77  9F000015           [0483] setlist    21  2        ; index 1 to 3
1A7B  81330016           [0484] loadk      22  206      ; 330
1A7F  81000017           [0485] loadk      23  2        ; 1
1A83  9F000014           [0486] setlist    20  2        ; index 1 to 3
1A87  0A800115           [0487] newtable   21  3   0    ; array=3, hash=0
1A8B  0A800116           [0488] newtable   22  3   0    ; array=3, hash=0
1A8F  C1330017           [0489] loadk      23  207      ; 536.20001220703
1A93  41340018           [0490] loadk      24  209      ; -401.10000610352
1A97  01070019           [0491] loadk      25  28       ; 11
1A9B  9F000016           [0492] setlist    22  2        ; index 1 to 3
1A9F  81340017           [0493] loadk      23  210      ; 115
1AA3  81000018           [0494] loadk      24  2        ; 1
1AA7  9F000015           [0495] setlist    21  2        ; index 1 to 3
1AAB  0A800116           [0496] newtable   22  3   0    ; array=3, hash=0
1AAF  0A800117           [0497] newtable   23  3   0    ; array=3, hash=0
1AB3  C1340018           [0498] loadk      24  211      ; 458.89999389648
1AB7  41350019           [0499] loadk      25  213      ; -510.20001220703
1ABB  8135001A           [0500] loadk      26  214      ; 10.89999961853
1ABF  9F000017           [0501] setlist    23  2        ; index 1 to 3
1AC3  C1350018           [0502] loadk      24  215      ; 166
1AC7  81000019           [0503] loadk      25  2        ; 1
1ACB  9F000016           [0504] setlist    22  2        ; index 1 to 3
1ACF  0A800117           [0505] newtable   23  3   0    ; array=3, hash=0
1AD3  0A800118           [0506] newtable   24  3   0    ; array=3, hash=0
1AD7  01360019           [0507] loadk      25  216      ; 452.39999389648
1ADB  8136001A           [0508] loadk      26  218      ; -593.70001220703
1ADF  810D001B           [0509] loadk      27  54       ; 12
1AE3  9F000018           [0510] setlist    24  2        ; index 1 to 3
1AE7  811F0019           [0511] loadk      25  126      ; 240
1AEB  8100001A           [0512] loadk      26  2        ; 1
1AEF  9F000017           [0513] setlist    23  2        ; index 1 to 3
1AF3  0A800118           [0514] newtable   24  3   0    ; array=3, hash=0
1AF7  0A800119           [0515] newtable   25  3   0    ; array=3, hash=0
1AFB  C136001A           [0516] loadk      26  219      ; 399.89999389648
1AFF  4137001B           [0517] loadk      27  221      ; -681
1B03  0107001C           [0518] loadk      28  28       ; 11
1B07  9F000019           [0519] setlist    25  2        ; index 1 to 3
1B0B  C11A001A           [0520] loadk      26  107      ; 250
1B0F  8100001B           [0521] loadk      27  2        ; 1
1B13  9F000018           [0522] setlist    24  2        ; index 1 to 3
1B17  0A800119           [0523] newtable   25  3   0    ; array=3, hash=0
1B1B  0A80011A           [0524] newtable   26  3   0    ; array=3, hash=0
1B1F  8137001B           [0525] loadk      27  222      ; 127.80000305176
1B23  0138001C           [0526] loadk      28  224      ; -711.09997558594
1B27  C109001D           [0527] loadk      29  39       ; 10.800000190735
1B2B  9F00001A           [0528] setlist    26  2        ; index 1 to 3
1B2F  4138001B           [0529] loadk      27  225      ; 277
1B33  8100001C           [0530] loadk      28  2        ; 1
1B37  9F000019           [0531] setlist    25  2        ; index 1 to 3
1B3B  0A80011A           [0532] newtable   26  3   0    ; array=3, hash=0
1B3F  0A80011B           [0533] newtable   27  3   0    ; array=3, hash=0
1B43  8138001C           [0534] loadk      28  226      ; 183.39999389648
1B47  0139001D           [0535] loadk      29  228      ; -1535.5
1B4B  C109001E           [0536] loadk      30  39       ; 10.800000190735
1B4F  9F00001B           [0537] setlist    27  2        ; index 1 to 3
1B53  4139001C           [0538] loadk      28  229      ; 355.5
1B57  C100001D           [0539] loadk      29  3        ; 2
1B5B  9F00001A           [0540] setlist    26  2        ; index 1 to 3
1B5F  0A80011B           [0541] newtable   27  3   0    ; array=3, hash=0
1B63  0A80011C           [0542] newtable   28  3   0    ; array=3, hash=0
1B67  8139001D           [0543] loadk      29  230      ; 152.60000610352
1B6B  013A001E           [0544] loadk      30  232      ; -1513.5
1B6F  413A001F           [0545] loadk      31  233      ; 18.200000762939
1B73  9F00001C           [0546] setlist    28  2        ; index 1 to 3
1B77  813A001D           [0547] loadk      29  234      ; 244.69999694824
1B7B  C100001E           [0548] loadk      30  3        ; 2
1B7F  9F00001B           [0549] setlist    27  2        ; index 1 to 3
1B83  0A80011C           [0550] newtable   28  3   0    ; array=3, hash=0
1B87  0A80011D           [0551] newtable   29  3   0    ; array=3, hash=0
1B8B  C13A001E           [0552] loadk      30  235      ; 271.20001220703
1B8F  413B001F           [0553] loadk      31  237      ; -1408.0999755859
1B93  01070020           [0554] loadk      32  28       ; 11
1B97  9F00001D           [0555] setlist    29  2        ; index 1 to 3
1B9B  C122001E           [0556] loadk      30  139      ; 180
1B9F  C100001F           [0557] loadk      31  3        ; 2
1BA3  9F00001C           [0558] setlist    28  2        ; index 1 to 3
1BA7  0A80011D           [0559] newtable   29  3   0    ; array=3, hash=0
1BAB  0A80011E           [0560] newtable   30  3   0    ; array=3, hash=0
1BAF  813B001F           [0561] loadk      31  238      ; 207.39999389648
1BB3  013C0020           [0562] loadk      32  240      ; -1397.0999755859
1BB7  810D0021           [0563] loadk      33  54       ; 12
1BBB  9F00001E           [0564] setlist    30  2        ; index 1 to 3
1BBF  413C001F           [0565] loadk      31  241      ; 266.39999389648
1BC3  C1000020           [0566] loadk      32  3        ; 2
1BC7  9F00001D           [0567] setlist    29  2        ; index 1 to 3
1BCB  0A80011E           [0568] newtable   30  3   0    ; array=3, hash=0
1BCF  0A80011F           [0569] newtable   31  3   0    ; array=3, hash=0
1BD3  813C0020           [0570] loadk      32  242      ; 238.19999694824
1BD7  013D0021           [0571] loadk      33  244      ; -1280.6999511719
1BDB  01070022           [0572] loadk      34  28       ; 11
1BDF  9F00001F           [0573] setlist    31  2        ; index 1 to 3
1BE3  C11A0020           [0574] loadk      32  107      ; 250
1BE7  C1000021           [0575] loadk      33  3        ; 2
1BEB  9F00001E           [0576] setlist    30  2        ; index 1 to 3
1BEF  0A80011F           [0577] newtable   31  3   0    ; array=3, hash=0
1BF3  0A800120           [0578] newtable   32  3   0    ; array=3, hash=0
1BF7  413D0021           [0579] loadk      33  245      ; 80.900001525879
1BFB  C13D0022           [0580] loadk      34  247      ; -1533.3000488281
1BFF  810E0023           [0581] loadk      35  58       ; 11.5
1C03  9F000020           [0582] setlist    32  2        ; index 1 to 3
1C07  013E0021           [0583] loadk      33  248      ; 270
1C0B  C1000022           [0584] loadk      34  3        ; 2
1C0F  9F00001F           [0585] setlist    31  2        ; index 1 to 3
1C13  0A800120           [0586] newtable   32  3   0    ; array=3, hash=0
1C17  0A800121           [0587] newtable   33  3   0    ; array=3, hash=0
1C1B  813E0022           [0588] loadk      34  250      ; -23.799999237061
1C1F  013F0023           [0589] loadk      35  252      ; -1513.4000244141
1C23  412F0024           [0590] loadk      36  189      ; 10.39999961853
1C27  9F000021           [0591] setlist    33  2        ; index 1 to 3
1C2B  413F0022           [0592] loadk      34  253      ; 37.900001525879
1C2F  C1000023           [0593] loadk      35  3        ; 2
1C33  9F000020           [0594] setlist    32  2        ; index 1 to 3
1C37  0A800121           [0595] newtable   33  3   0    ; array=3, hash=0
1C3B  0A800122           [0596] newtable   34  3   0    ; array=3, hash=0
1C3F  813F0023           [0597] loadk      35  254      ; 99.099998474121
1C43  01400024           [0598] loadk      36  256      ; -1474.5999755859
1C47  412F0025           [0599] loadk      37  189      ; 10.39999961853
1C4B  9F000022           [0600] setlist    34  2        ; index 1 to 3
1C4F  41400023           [0601] loadk      35  257      ; 210.5
1C53  C1000024           [0602] loadk      36  3        ; 2
1C57  9F000021           [0603] setlist    33  2        ; index 1 to 3
1C5B  DF0F0001           [0604] setlist    1   63       ; index 33 to 64
1C5F  0A800102           [0605] newtable   2   3   0    ; array=3, hash=0
1C63  0A800103           [0606] newtable   3   3   0    ; array=3, hash=0
1C67  81400004           [0607] loadk      4   258      ; 157
1C6B  01410005           [0608] loadk      5   260      ; -1415.9000244141
1C6F  41410006           [0609] loadk      6   261      ; 17.10000038147
1C73  9F000003           [0610] setlist    3   2        ; index 1 to 3
1C77  81410004           [0611] loadk      4   262      ; 80
1C7B  C1000005           [0612] loadk      5   3        ; 2
1C7F  9F000002           [0613] setlist    2   2        ; index 1 to 3
1C83  0A800103           [0614] newtable   3   3   0    ; array=3, hash=0
1C87  0A800104           [0615] newtable   4   3   0    ; array=3, hash=0
1C8B  C1410005           [0616] loadk      5   263      ; 111.40000152588
1C8F  41420006           [0617] loadk      6   265      ; -1322
1C93  412F0007           [0618] loadk      7   189      ; 10.39999961853
1C97  9F000004           [0619] setlist    4   2        ; index 1 to 3
1C9B  C1300005           [0620] loadk      5   195      ; 65
1C9F  C1000006           [0621] loadk      6   3        ; 2
1CA3  9F000003           [0622] setlist    3   2        ; index 1 to 3
1CA7  0A800104           [0623] newtable   4   3   0    ; array=3, hash=0
1CAB  0A800105           [0624] newtable   5   3   0    ; array=3, hash=0
1CAF  81420006           [0625] loadk      6   266      ; 115.90000152588
1CB3  01430007           [0626] loadk      7   268      ; -1312
1CB7  41430008           [0627] loadk      8   269      ; 4.4000000953674
1CBB  9F000005           [0628] setlist    5   2        ; index 1 to 3
1CBF  41000006           [0629] loadk      6   1        ; 0
1CC3  C1000007           [0630] loadk      7   3        ; 2
1CC7  9F000004           [0631] setlist    4   2        ; index 1 to 3
1CCB  0A800105           [0632] newtable   5   3   0    ; array=3, hash=0
1CCF  0A800106           [0633] newtable   6   3   0    ; array=3, hash=0
1CD3  81430007           [0634] loadk      7   270      ; 41.299999237061
1CD7  01440008           [0635] loadk      8   272      ; -1313.9000244141
1CDB  412F0009           [0636] loadk      9   189      ; 10.39999961853
1CDF  9F000006           [0637] setlist    6   2        ; index 1 to 3
1CE3  C1120007           [0638] loadk      7   75       ; 265
1CE7  C1000008           [0639] loadk      8   3        ; 2
1CEB  9F000005           [0640] setlist    5   2        ; index 1 to 3
1CEF  0A800106           [0641] newtable   6   3   0    ; array=3, hash=0
1CF3  0A800107           [0642] newtable   7   3   0    ; array=3, hash=0
1CF7  81440008           [0643] loadk      8   274      ; -70.099998474121
1CFB  01450009           [0644] loadk      9   276      ; -1602.6999511719
1CFF  8130000A           [0645] loadk      10  194      ; 12.199999809265
1D03  9F000007           [0646] setlist    7   2        ; index 1 to 3
1D07  41450008           [0647] loadk      8   277      ; 4.1999998092651
1D0B  C1000009           [0648] loadk      9   3        ; 2
1D0F  9F000006           [0649] setlist    6   2        ; index 1 to 3
1D13  0A800107           [0650] newtable   7   3   0    ; array=3, hash=0
1D17  0A800108           [0651] newtable   8   3   0    ; array=3, hash=0
1D1B  C1450009           [0652] loadk      9   279      ; -60.599998474121
1D1F  4146000A           [0653] loadk      10  281      ; -1429.1999511719
1D23  0107000B           [0654] loadk      11  28       ; 11
1D27  9F000008           [0655] setlist    8   2        ; index 1 to 3
1D2B  C11A0009           [0656] loadk      9   107      ; 250
1D2F  C100000A           [0657] loadk      10  3        ; 2
1D33  9F000007           [0658] setlist    7   2        ; index 1 to 3
1D37  0A800108           [0659] newtable   8   3   0    ; array=3, hash=0
1D3B  0A800109           [0660] newtable   9   3   0    ; array=3, hash=0
1D3F  C146000A           [0661] loadk      10  283      ; -31.39999961853
1D43  4147000B           [0662] loadk      11  285      ; -1344.9000244141
1D47  8147000C           [0663] loadk      12  286      ; 10.300000190735
1D4B  9F000009           [0664] setlist    9   2        ; index 1 to 3
1D4F  C147000A           [0665] loadk      10  287      ; 260
1D53  C100000B           [0666] loadk      11  3        ; 2
1D57  9F000008           [0667] setlist    8   2        ; index 1 to 3
1D5B  0A800109           [0668] newtable   9   3   0    ; array=3, hash=0
1D5F  0A80010A           [0669] newtable   10  3   0    ; array=3, hash=0
1D63  4148000B           [0670] loadk      11  289      ; -91.300003051758
1D67  C148000C           [0671] loadk      12  291      ; -1325.8000488281
1D6B  412F000D           [0672] loadk      13  189      ; 10.39999961853
1D6F  9F00000A           [0673] setlist    10  2        ; index 1 to 3
1D73  C147000B           [0674] loadk      11  287      ; 260
1D77  C100000C           [0675] loadk      12  3        ; 2
1D7B  9F000009           [0676] setlist    9   2        ; index 1 to 3
1D7F  0A80010A           [0677] newtable   10  3   0    ; array=3, hash=0
1D83  0A80010B           [0678] newtable   11  3   0    ; array=3, hash=0
1D87  4149000C           [0679] loadk      12  293      ; -71.699996948242
1D8B  C149000D           [0680] loadk      13  295      ; -1237
1D8F  0105000E           [0681] loadk      14  20       ; 10.699999809265
1D93  9F00000B           [0682] setlist    11  2        ; index 1 to 3
1D97  C122000C           [0683] loadk      12  139      ; 180
1D9B  C100000D           [0684] loadk      13  3        ; 2
1D9F  9F00000A           [0685] setlist    10  2        ; index 1 to 3
1DA3  0A80010B           [0686] newtable   11  3   0    ; array=3, hash=0
1DA7  0A80010C           [0687] newtable   12  3   0    ; array=3, hash=0
1DAB  414A000D           [0688] loadk      13  297      ; -246.89999389648
1DAF  C14A000E           [0689] loadk      14  299      ; -1360.9000244141
1DB3  014B000F           [0690] loadk      15  300      ; 8.1000003814697
1DB7  9F00000C           [0691] setlist    12  2        ; index 1 to 3
1DBB  013E000D           [0692] loadk      13  248      ; 270
1DBF  C100000E           [0693] loadk      14  3        ; 2
1DC3  9F00000B           [0694] setlist    11  2        ; index 1 to 3
1DC7  0A80010C           [0695] newtable   12  3   0    ; array=3, hash=0
1DCB  0A80010D           [0696] newtable   13  3   0    ; array=3, hash=0
1DCF  814B000E           [0697] loadk      14  302      ; -143.10000610352
1DD3  014C000F           [0698] loadk      15  304      ; -1388.3000488281
1DD7  414C0010           [0699] loadk      16  305      ; 3.9000000953674
1DDB  9F00000D           [0700] setlist    13  2        ; index 1 to 3
1DDF  814C000E           [0701] loadk      14  306      ; 110
1DE3  C100000F           [0702] loadk      15  3        ; 2
1DE7  9F00000C           [0703] setlist    12  2        ; index 1 to 3
1DEB  0A80010D           [0704] newtable   13  3   0    ; array=3, hash=0
1DEF  0A80010E           [0705] newtable   14  3   0    ; array=3, hash=0
1DF3  014D000F           [0706] loadk      15  308      ; -260.70001220703
1DF7  814D0010           [0707] loadk      16  310      ; -1214.4000244141
1DFB  014B0011           [0708] loadk      17  300      ; 8.1000003814697
1DFF  9F00000E           [0709] setlist    14  2        ; index 1 to 3
1E03  C10A000F           [0710] loadk      15  43       ; 310
1E07  C1000010           [0711] loadk      16  3        ; 2
1E0B  9F00000D           [0712] setlist    13  2        ; index 1 to 3
1E0F  0A80010E           [0713] newtable   14  3   0    ; array=3, hash=0
1E13  0A80010F           [0714] newtable   15  3   0    ; array=3, hash=0
1E17  014E0010           [0715] loadk      16  312      ; -203.69999694824
1E1B  814E0011           [0716] loadk      17  314      ; -1098.4000244141
1E1F  C14E0012           [0717] loadk      18  315      ; 14
1E23  9F00000F           [0718] setlist    15  2        ; index 1 to 3
1E27  812F0010           [0719] loadk      16  190      ; 235
1E2B  C1000011           [0720] loadk      17  3        ; 2
1E2F  9F00000E           [0721] setlist    14  2        ; index 1 to 3
1E33  0A80010F           [0722] newtable   15  3   0    ; array=3, hash=0
1E37  0A800110           [0723] newtable   16  3   0    ; array=3, hash=0
1E3B  414F0011           [0724] loadk      17  317      ; -122.80000305176
1E3F  C14F0012           [0725] loadk      18  319      ; -1064.9000244141
1E43  C14E0013           [0726] loadk      19  315      ; 14
1E47  9F000010           [0727] setlist    16  2        ; index 1 to 3
1E4B  01500011           [0728] loadk      17  320      ; 225
1E4F  C1000012           [0729] loadk      18  3        ; 2
1E53  9F00000F           [0730] setlist    15  2        ; index 1 to 3
1E57  0A800110           [0731] newtable   16  3   0    ; array=3, hash=0
1E5B  0A800111           [0732] newtable   17  3   0    ; array=3, hash=0
1E5F  41500012           [0733] loadk      18  321      ; 132.39999389648
1E63  C1500013           [0734] loadk      19  323      ; -1105.1999511719
1E67  412F0014           [0735] loadk      20  189      ; 10.39999961853
1E6B  9F000011           [0736] setlist    17  2        ; index 1 to 3
1E6F  812F0012           [0737] loadk      18  190      ; 235
1E73  C1000013           [0738] loadk      19  3        ; 2
1E77  9F000010           [0739] setlist    16  2        ; index 1 to 3
1E7B  0A800111           [0740] newtable   17  3   0    ; array=3, hash=0
1E7F  0A800112           [0741] newtable   18  3   0    ; array=3, hash=0
1E83  81120013           [0742] loadk      19  74       ; 10.10000038147
1E87  41510014           [0743] loadk      20  325      ; -1386.6999511719
1E8B  412F0015           [0744] loadk      21  189      ; 10.39999961853
1E8F  9F000012           [0745] setlist    18  2        ; index 1 to 3
1E93  81510013           [0746] loadk      19  326      ; 290
1E97  C1000014           [0747] loadk      20  3        ; 2
1E9B  9F000011           [0748] setlist    17  2        ; index 1 to 3
1E9F  0A800112           [0749] newtable   18  3   0    ; array=3, hash=0
1EA3  0A800113           [0750] newtable   19  3   0    ; array=3, hash=0
1EA7  C1190014           [0751] loadk      20  103      ; 17.39999961853
1EAB  01520015           [0752] loadk      21  328      ; -1335.4000244141
1EAF  412F0016           [0753] loadk      22  189      ; 10.39999961853
1EB3  9F000013           [0754] setlist    19  2        ; index 1 to 3
1EB7  C1220014           [0755] loadk      20  139      ; 180
1EBB  C1000015           [0756] loadk      21  3        ; 2
1EBF  9F000012           [0757] setlist    18  2        ; index 1 to 3
1EC3  0A800113           [0758] newtable   19  3   0    ; array=3, hash=0
1EC7  0A800114           [0759] newtable   20  3   0    ; array=3, hash=0
1ECB  81520015           [0760] loadk      21  330      ; -129.30000305176
1ECF  01530016           [0761] loadk      22  332      ; -1385.0999755859
1ED3  412F0017           [0762] loadk      23  189      ; 10.39999961853
1ED7  9F000014           [0763] setlist    20  2        ; index 1 to 3
1EDB  41530015           [0764] loadk      21  333      ; 70
1EDF  C1000016           [0765] loadk      22  3        ; 2
1EE3  9F000013           [0766] setlist    19  2        ; index 1 to 3
1EE7  0A800114           [0767] newtable   20  3   0    ; array=3, hash=0
1EEB  0A800115           [0768] newtable   21  3   0    ; array=3, hash=0
1EEF  C1530016           [0769] loadk      22  335      ; -112.40000152588
1EF3  41540017           [0770] loadk      23  337      ; -975.79998779297
1EF7  412F0018           [0771] loadk      24  189      ; 10.39999961853
1EFB  9F000015           [0772] setlist    21  2        ; index 1 to 3
1EFF  41050016           [0773] loadk      22  21       ; 335
1F03  C1000017           [0774] loadk      23  3        ; 2
1F07  9F000014           [0775] setlist    20  2        ; index 1 to 3
1F0B  0A800115           [0776] newtable   21  3   0    ; array=3, hash=0
1F0F  0A800116           [0777] newtable   22  3   0    ; array=3, hash=0
1F13  C1540017           [0778] loadk      23  339      ; -167.30000305176
1F17  41550018           [0779] loadk      24  341      ; -892.40002441406
1F1B  412F0019           [0780] loadk      25  189      ; 10.39999961853
1F1F  9F000016           [0781] setlist    22  2        ; index 1 to 3
1F23  81550017           [0782] loadk      23  342      ; 275
1F27  C1000018           [0783] loadk      24  3        ; 2
1F2B  9F000015           [0784] setlist    21  2        ; index 1 to 3
1F2F  0A800116           [0785] newtable   22  3   0    ; array=3, hash=0
1F33  0A800117           [0786] newtable   23  3   0    ; array=3, hash=0
1F37  C1550018           [0787] loadk      24  343      ; 55.599998474121
1F3B  41560019           [0788] loadk      25  345      ; -1058
1F3F  412F001A           [0789] loadk      26  189      ; 10.39999961853
1F43  9F000017           [0790] setlist    23  2        ; index 1 to 3
1F47  C1110018           [0791] loadk      24  71       ; 340
1F4B  C1000019           [0792] loadk      25  3        ; 2
1F4F  9F000016           [0793] setlist    22  2        ; index 1 to 3
1F53  0A800117           [0794] newtable   23  3   0    ; array=3, hash=0
1F57  0A800118           [0795] newtable   24  3   0    ; array=3, hash=0
1F5B  81560019           [0796] loadk      25  346      ; 7.1999998092651
1F5F  0157001A           [0797] loadk      26  348      ; -891.70001220703
1F63  0105001B           [0798] loadk      27  20       ; 10.699999809265
1F67  9F000018           [0799] setlist    24  2        ; index 1 to 3
1F6B  41570019           [0800] loadk      25  349      ; 303
1F6F  C100001A           [0801] loadk      26  3        ; 2
1F73  9F000017           [0802] setlist    23  2        ; index 1 to 3
1F77  0A800118           [0803] newtable   24  3   0    ; array=3, hash=0
1F7B  0A800119           [0804] newtable   25  3   0    ; array=3, hash=0
1F7F  8157001A           [0805] loadk      26  350      ; 76.099998474121
1F83  C157001B           [0806] loadk      27  351      ; 1081.4000244141
1F87  0158001C           [0807] loadk      28  352      ; 16.299999237061
1F8B  9F000019           [0808] setlist    25  2        ; index 1 to 3
1F8F  C122001A           [0809] loadk      26  139      ; 180
1F93  0101001B           [0810] loadk      27  4        ; 3
1F97  9F000018           [0811] setlist    24  2        ; index 1 to 3
1F9B  0A800119           [0812] newtable   25  3   0    ; array=3, hash=0
1F9F  0A80011A           [0813] newtable   26  3   0    ; array=3, hash=0
1FA3  8158001B           [0814] loadk      27  354      ; -16.39999961853
1FA7  C158001C           [0815] loadk      28  355      ; 1205.4000244141
1FAB  0159001D           [0816] loadk      29  356      ; 21.39999961853
1FAF  9F00001A           [0817] setlist    26  2        ; index 1 to 3
1FB3  4159001B           [0818] loadk      27  357      ; 198
1FB7  0101001C           [0819] loadk      28  4        ; 3
1FBB  9F000019           [0820] setlist    25  2        ; index 1 to 3
1FBF  0A80011A           [0821] newtable   26  3   0    ; array=3, hash=0
1FC3  0A80011B           [0822] newtable   27  3   0    ; array=3, hash=0
1FC7  C159001C           [0823] loadk      28  359      ; -34.099998474121
1FCB  015A001D           [0824] loadk      29  360      ; 1115.0999755859
1FCF  415A001E           [0825] loadk      30  361      ; 17
1FD3  9F00001B           [0826] setlist    27  2        ; index 1 to 3
1FD7  815A001C           [0827] loadk      28  362      ; 273
1FDB  0101001D           [0828] loadk      29  4        ; 3
1FDF  9F00001A           [0829] setlist    26  2        ; index 1 to 3
1FE3  0A80011B           [0830] newtable   27  3   0    ; array=3, hash=0
1FE7  0A80011C           [0831] newtable   28  3   0    ; array=3, hash=0
1FEB  C12B001D           [0832] loadk      29  175      ; 10.5
1FEF  C15A001E           [0833] loadk      30  363      ; 1077.3000488281
1FF3  015B001F           [0834] loadk      31  364      ; 14.699999809265
1FF7  9F00001C           [0835] setlist    28  2        ; index 1 to 3
1FFB  415B001D           [0836] loadk      29  365      ; 200
1FFF  0101001E           [0837] loadk      30  4        ; 3
2003  9F00001B           [0838] setlist    27  2        ; index 1 to 3
2007  0A80011C           [0839] newtable   28  3   0    ; array=3, hash=0
200B  0A80011D           [0840] newtable   29  3   0    ; array=3, hash=0
200F  C15B001E           [0841] loadk      30  367      ; -63.799999237061
2013  015C001F           [0842] loadk      31  368      ; 1020.799987793
2017  81350020           [0843] loadk      32  214      ; 10.89999961853
201B  9F00001D           [0844] setlist    29  2        ; index 1 to 3
201F  415C001E           [0845] loadk      30  369      ; 184
2023  0101001F           [0846] loadk      31  4        ; 3
2027  9F00001C           [0847] setlist    28  2        ; index 1 to 3
202B  0A80011D           [0848] newtable   29  3   0    ; array=3, hash=0
202F  0A80011E           [0849] newtable   30  3   0    ; array=3, hash=0
2033  C15C001F           [0850] loadk      31  371      ; -73.099998474121
2037  015D0020           [0851] loadk      32  372      ; 932.70001220703
203B  81350021           [0852] loadk      33  214      ; 10.89999961853
203F  9F00001E           [0853] setlist    30  2        ; index 1 to 3
2043  013E001F           [0854] loadk      31  248      ; 270
2047  01010020           [0855] loadk      32  4        ; 3
204B  9F00001D           [0856] setlist    29  2        ; index 1 to 3
204F  0A80011E           [0857] newtable   30  3   0    ; array=3, hash=0
2053  0A80011F           [0858] newtable   31  3   0    ; array=3, hash=0
2057  815D0020           [0859] loadk      32  374      ; -0.40000000596046
205B  C15D0021           [0860] loadk      33  375      ; 961.20001220703
205F  81350022           [0861] loadk      34  214      ; 10.89999961853
2063  9F00001F           [0862] setlist    31  2        ; index 1 to 3
2067  41070020           [0863] loadk      32  29       ; 280
206B  01010021           [0864] loadk      33  4        ; 3
206F  9F00001E           [0865] setlist    30  2        ; index 1 to 3
2073  0A80011F           [0866] newtable   31  3   0    ; array=3, hash=0
2077  0A800120           [0867] newtable   32  3   0    ; array=3, hash=0
207B  415E0021           [0868] loadk      33  377      ; -66.300003051758
207F  815E0022           [0869] loadk      34  378      ; 886
2083  81350023           [0870] loadk      35  214      ; 10.89999961853
2087  9F000020           [0871] setlist    32  2        ; index 1 to 3
208B  41070021           [0872] loadk      33  29       ; 280
208F  01010022           [0873] loadk      34  4        ; 3
2093  9F00001F           [0874] setlist    31  2        ; index 1 to 3
2097  0A800120           [0875] newtable   32  3   0    ; array=3, hash=0
209B  0A800121           [0876] newtable   33  3   0    ; array=3, hash=0
209F  015F0022           [0877] loadk      34  380      ; -12.60000038147
20A3  415F0023           [0878] loadk      35  381      ; 867.70001220703
20A7  01050024           [0879] loadk      36  20       ; 10.699999809265
20AB  9F000021           [0880] setlist    33  2        ; index 1 to 3
20AF  815F0022           [0881] loadk      34  382      ; 320
20B3  01010023           [0882] loadk      35  4        ; 3
20B7  9F000020           [0883] setlist    32  2        ; index 1 to 3
20BB  0A800121           [0884] newtable   33  3   0    ; array=3, hash=0
20BF  0A800122           [0885] newtable   34  3   0    ; array=3, hash=0
20C3  C15F0023           [0886] loadk      35  383      ; 89.5
20C7  01600024           [0887] loadk      36  384      ; 948.79998779297
20CB  01050025           [0888] loadk      37  20       ; 10.699999809265
20CF  9F000022           [0889] setlist    34  2        ; index 1 to 3
20D3  41600023           [0890] loadk      35  385      ; 325
20D7  01010024           [0891] loadk      36  4        ; 3
20DB  9F000021           [0892] setlist    33  2        ; index 1 to 3
20DF  DF170001           [0893] setlist    1   95       ; index 65 to 96
20E3  0A800102           [0894] newtable   2   3   0    ; array=3, hash=0
20E7  0A800103           [0895] newtable   3   3   0    ; array=3, hash=0
20EB  81600004           [0896] loadk      4   386      ; 86.300003051758
20EF  C1600005           [0897] loadk      5   387      ; 921
20F3  01610006           [0898] loadk      6   388      ; 15.699999809265
20F7  9F000003           [0899] setlist    3   2        ; index 1 to 3
20FB  41610004           [0900] loadk      4   389      ; 326
20FF  01010005           [0901] loadk      5   4        ; 3
2103  9F000002           [0902] setlist    2   2        ; index 1 to 3
2107  0A800103           [0903] newtable   3   3   0    ; array=3, hash=0
210B  0A800104           [0904] newtable   4   3   0    ; array=3, hash=0
210F  81610005           [0905] loadk      5   390      ; 51.700000762939
2113  C1160006           [0906] loadk      6   91       ; 941.09997558594
2117  81350007           [0907] loadk      7   214      ; 10.89999961853
211B  9F000004           [0908] setlist    4   2        ; index 1 to 3
211F  41160005           [0909] loadk      5   89       ; 90
2123  01010006           [0910] loadk      6   4        ; 3
2127  9F000003           [0911] setlist    3   2        ; index 1 to 3
212B  0A800104           [0912] newtable   4   3   0    ; array=3, hash=0
212F  0A800105           [0913] newtable   5   3   0    ; array=3, hash=0
2133  C1610006           [0914] loadk      6   391      ; 102.19999694824
2137  01620007           [0915] loadk      7   392      ; 249.69999694824
213B  41620008           [0916] loadk      8   393      ; 21.700000762939
213F  9F000005           [0917] setlist    5   2        ; index 1 to 3
2143  811F0006           [0918] loadk      6   126      ; 240
2147  41010007           [0919] loadk      7   5        ; 4
214B  9F000004           [0920] setlist    4   2        ; index 1 to 3
214F  0A800105           [0921] newtable   5   3   0    ; array=3, hash=0
2153  0A800106           [0922] newtable   6   3   0    ; array=3, hash=0
2157  81620007           [0923] loadk      7   394      ; 159.30000305176
215B  C1620008           [0924] loadk      8   395      ; 201.19999694824
215F  01630009           [0925] loadk      9   396      ; 12.300000190735
2163  9F000006           [0926] setlist    6   2        ; index 1 to 3
2167  41630007           [0927] loadk      7   397      ; 60
216B  41010008           [0928] loadk      8   5        ; 4
216F  9F000005           [0929] setlist    5   2        ; index 1 to 3
2173  0A800106           [0930] newtable   6   3   0    ; array=3, hash=0
2177  0A800107           [0931] newtable   7   3   0    ; array=3, hash=0
217B  C1630008           [0932] loadk      8   399      ; -5.9000000953674
217F  01640009           [0933] loadk      9   400      ; 90.199996948242
2183  4164000A           [0934] loadk      10  401      ; 28.60000038147
2187  9F000007           [0935] setlist    7   2        ; index 1 to 3
218B  81640008           [0936] loadk      8   402      ; 333
218F  41010009           [0937] loadk      9   5        ; 4
2193  9F000006           [0938] setlist    6   2        ; index 1 to 3
2197  0A800107           [0939] newtable   7   3   0    ; array=3, hash=0
219B  0A800108           [0940] newtable   8   3   0    ; array=3, hash=0
219F  01650009           [0941] loadk      9   404      ; -35.400001525879
21A3  4165000A           [0942] loadk      10  405      ; 144.80000305176
21A7  8165000B           [0943] loadk      11  406      ; 27.200000762939
21AB  9F000008           [0944] setlist    8   2        ; index 1 to 3
21AF  01180009           [0945] loadk      9   96       ; 296
21B3  4101000A           [0946] loadk      10  5        ; 4
21B7  9F000007           [0947] setlist    7   2        ; index 1 to 3
21BB  0A800108           [0948] newtable   8   3   0    ; array=3, hash=0
21BF  0A800109           [0949] newtable   9   3   0    ; array=3, hash=0
21C3  0166000A           [0950] loadk      10  408      ; -35.799999237061
21C7  4166000B           [0951] loadk      11  409      ; 59.799999237061
21CB  8166000C           [0952] loadk      12  410      ; 27.700000762939
21CF  9F000009           [0953] setlist    9   2        ; index 1 to 3
21D3  C166000A           [0954] loadk      10  411      ; 71.199996948242
21D7  4101000B           [0955] loadk      11  5        ; 4
21DB  9F000008           [0956] setlist    8   2        ; index 1 to 3
21DF  0A800109           [0957] newtable   9   3   0    ; array=3, hash=0
21E3  0A80010A           [0958] newtable   10  3   0    ; array=3, hash=0
21E7  0167000B           [0959] loadk      11  412      ; 6.1999998092651
21EB  4167000C           [0960] loadk      12  413      ; 280.79998779297
21EF  8167000D           [0961] loadk      13  414      ; 22.60000038147
21F3  9F00000A           [0962] setlist    10  2        ; index 1 to 3
21F7  C167000B           [0963] loadk      11  415      ; 226.89999389648
21FB  4101000C           [0964] loadk      12  5        ; 4
21FF  9F000009           [0965] setlist    9   2        ; index 1 to 3
2203  0A80010A           [0966] newtable   10  3   0    ; array=3, hash=0
2207  0A80010B           [0967] newtable   11  3   0    ; array=3, hash=0
220B  0168000C           [0968] loadk      12  416      ; 160.60000610352
220F  4168000D           [0969] loadk      13  417      ; 347.10000610352
2213  8168000E           [0970] loadk      14  418      ; 19.10000038147
2217  9F00000B           [0971] setlist    11  2        ; index 1 to 3
221B  4106000C           [0972] loadk      12  25       ; 97
221F  4101000D           [0973] loadk      13  5        ; 4
2223  9F00000A           [0974] setlist    10  2        ; index 1 to 3
2227  0A80010B           [0975] newtable   11  3   0    ; array=3, hash=0
222B  0A80010C           [0976] newtable   12  3   0    ; array=3, hash=0
222F  C168000D           [0977] loadk      13  419      ; 104.90000152588
2233  0169000E           [0978] loadk      14  420      ; 430.79998779297
2237  C119000F           [0979] loadk      15  103      ; 17.39999961853
223B  9F00000C           [0980] setlist    12  2        ; index 1 to 3
223F  4169000D           [0981] loadk      13  421      ; 152
2243  4101000E           [0982] loadk      14  5        ; 4
2247  9F00000B           [0983] setlist    11  2        ; index 1 to 3
224B  0A80010C           [0984] newtable   12  3   0    ; array=3, hash=0
224F  0A80010D           [0985] newtable   13  3   0    ; array=3, hash=0
2253  8169000E           [0986] loadk      14  422      ; 147.60000610352
2257  C169000F           [0987] loadk      15  423      ; 460
225B  016A0010           [0988] loadk      16  424      ; 13.800000190735
225F  9F00000D           [0989] setlist    13  2        ; index 1 to 3
2263  416A000E           [0990] loadk      14  425      ; 188.30000305176
2267  4101000F           [0991] loadk      15  5        ; 4
226B  9F00000C           [0992] setlist    12  2        ; index 1 to 3
226F  0A80010D           [0993] newtable   13  3   0    ; array=3, hash=0
2273  0A80010E           [0994] newtable   14  3   0    ; array=3, hash=0
2277  816A000F           [0995] loadk      15  426      ; 181.19999694824
227B  C16A0010           [0996] loadk      16  427      ; 426.60000610352
227F  016B0011           [0997] loadk      17  428      ; 14.60000038147
2283  9F00000E           [0998] setlist    14  2        ; index 1 to 3
2287  416B000F           [0999] loadk      15  429      ; 177.89999389648
228B  41010010           [1000] loadk      16  5        ; 4
228F  9F00000D           [1001] setlist    13  2        ; index 1 to 3
2293  0A80010E           [1002] newtable   14  3   0    ; array=3, hash=0
2297  0A80010F           [1003] newtable   15  3   0    ; array=3, hash=0
229B  816B0010           [1004] loadk      16  430      ; 201.80000305176
229F  C16B0011           [1005] loadk      17  431      ; 312.70001220703
22A3  016C0012           [1006] loadk      18  432      ; 15.5
22A7  9F00000F           [1007] setlist    15  2        ; index 1 to 3
22AB  416C0010           [1008] loadk      16  433      ; 90.099998474121
22AF  41010011           [1009] loadk      17  5        ; 4
22B3  9F00000E           [1010] setlist    14  2        ; index 1 to 3
22B7  0A80010F           [1011] newtable   15  3   0    ; array=3, hash=0
22BB  0A800110           [1012] newtable   16  3   0    ; array=3, hash=0
22BF  816C0011           [1013] loadk      17  434      ; 52.900001525879
22C3  C16C0012           [1014] loadk      18  435      ; 324.39999389648
22C7  016D0013           [1015] loadk      19  436      ; 20.10000038147
22CB  9F000010           [1016] setlist    16  2        ; index 1 to 3
22CF  416D0011           [1017] loadk      17  437      ; 224.30000305176
22D3  41010012           [1018] loadk      18  5        ; 4
22D7  9F00000F           [1019] setlist    15  2        ; index 1 to 3
22DB  0A800110           [1020] newtable   16  3   0    ; array=3, hash=0
22DF  0A800111           [1021] newtable   17  3   0    ; array=3, hash=0
22E3  816D0012           [1022] loadk      18  438      ; 57.200000762939
22E7  C16D0013           [1023] loadk      19  439      ; 226.19999694824
22EB  016E0014           [1024] loadk      20  440      ; 20.700000762939
22EF  9F000011           [1025] setlist    17  2        ; index 1 to 3
22F3  416E0012           [1026] loadk      18  441      ; 341.39999389648
22F7  41010013           [1027] loadk      19  5        ; 4
22FB  9F000010           [1028] setlist    16  2        ; index 1 to 3
22FF  0A800111           [1029] newtable   17  3   0    ; array=3, hash=0
2303  0A800112           [1030] newtable   18  3   0    ; array=3, hash=0
2307  816E0013           [1031] loadk      19  442      ; 90.5
230B  C16E0014           [1032] loadk      20  443      ; 277.89999389648
230F  41620015           [1033] loadk      21  393      ; 21.700000762939
2313  9F000012           [1034] setlist    18  2        ; index 1 to 3
2317  C1620013           [1035] loadk      19  395      ; 201.19999694824
231B  41010014           [1036] loadk      20  5        ; 4
231F  9F000011           [1037] setlist    17  2        ; index 1 to 3
2323  0A800112           [1038] newtable   18  3   0    ; array=3, hash=0
2327  0A800113           [1039] newtable   19  3   0    ; array=3, hash=0
232B  416F0014           [1040] loadk      20  445      ; -377.89999389648
232F  C16F0015           [1041] loadk      21  447      ; -539.5
2333  01700016           [1042] loadk      22  448      ; 17.200000762939
2337  9F000013           [1043] setlist    19  2        ; index 1 to 3
233B  01180014           [1044] loadk      20  96       ; 296
233F  81010015           [1045] loadk      21  6        ; 5
2343  9F000012           [1046] setlist    18  2        ; index 1 to 3
2347  0A800113           [1047] newtable   19  3   0    ; array=3, hash=0
234B  0A800114           [1048] newtable   20  3   0    ; array=3, hash=0
234F  81700015           [1049] loadk      21  450      ; -178.19999694824
2353  01710016           [1050] loadk      22  452      ; -395.60000610352
2357  C12B0017           [1051] loadk      23  175      ; 10.5
235B  9F000014           [1052] setlist    20  2        ; index 1 to 3
235F  41710015           [1053] loadk      21  453      ; 111
2363  81010016           [1054] loadk      22  6        ; 5
2367  9F000013           [1055] setlist    19  2        ; index 1 to 3
236B  0A800114           [1056] newtable   20  3   0    ; array=3, hash=0
236F  0A800115           [1057] newtable   21  3   0    ; array=3, hash=0
2373  C1710016           [1058] loadk      22  455      ; -523.79998779297
2377  41720017           [1059] loadk      23  457      ; -337.89999389648
237B  81130018           [1060] loadk      24  78       ; 11.199999809265
237F  9F000015           [1061] setlist    21  2        ; index 1 to 3
2383  C1220016           [1062] loadk      22  139      ; 180
2387  81010017           [1063] loadk      23  6        ; 5
238B  9F000014           [1064] setlist    20  2        ; index 1 to 3
238F  0A800115           [1065] newtable   21  3   0    ; array=3, hash=0
2393  0A800116           [1066] newtable   22  3   0    ; array=3, hash=0
2397  C1720017           [1067] loadk      23  459      ; -560.40002441406
239B  41730018           [1068] loadk      24  461      ; -507.10000610352
239F  01060019           [1069] loadk      25  24       ; 11.10000038147
23A3  9F000016           [1070] setlist    22  2        ; index 1 to 3
23A7  01010017           [1071] loadk      23  4        ; 3
23AB  81010018           [1072] loadk      24  6        ; 5
23AF  9F000015           [1073] setlist    21  2        ; index 1 to 3
23B3  0A800116           [1074] newtable   22  3   0    ; array=3, hash=0
23B7  0A800117           [1075] newtable   23  3   0    ; array=3, hash=0
23BB  C1730018           [1076] loadk      24  463      ; -707.79998779297
23BF  41740019           [1077] loadk      25  465      ; -501.60000610352
23C3  8113001A           [1078] loadk      26  78       ; 11.199999809265
23C7  9F000017           [1079] setlist    23  2        ; index 1 to 3
23CB  41070018           [1080] loadk      24  29       ; 280
23CF  81010019           [1081] loadk      25  6        ; 5
23D3  9F000016           [1082] setlist    22  2        ; index 1 to 3
23D7  0A800117           [1083] newtable   23  3   0    ; array=3, hash=0
23DB  0A800118           [1084] newtable   24  3   0    ; array=3, hash=0
23DF  C1740019           [1085] loadk      25  467      ; -254.30000305176
23E3  4175001A           [1086] loadk      26  469      ; -305.20001220703
23E7  8147001B           [1087] loadk      27  286      ; 10.300000190735
23EB  9F000018           [1088] setlist    24  2        ; index 1 to 3
23EF  81750019           [1089] loadk      25  470      ; 142.80000305176
23F3  8101001A           [1090] loadk      26  6        ; 5
23F7  9F000017           [1091] setlist    23  2        ; index 1 to 3
23FB  0A800118           [1092] newtable   24  3   0    ; array=3, hash=0
23FF  0A800119           [1093] newtable   25  3   0    ; array=3, hash=0
2403  0176001A           [1094] loadk      26  472      ; -375.60000610352
2407  8176001B           [1095] loadk      27  474      ; -281.10000610352
240B  C110001C           [1096] loadk      28  67       ; 10.60000038147
240F  9F000019           [1097] setlist    25  2        ; index 1 to 3
2413  C176001A           [1098] loadk      26  475      ; 183.10000610352
2417  8101001B           [1099] loadk      27  6        ; 5
241B  9F000018           [1100] setlist    24  2        ; index 1 to 3
241F  0A800119           [1101] newtable   25  3   0    ; array=3, hash=0
2423  0A80011A           [1102] newtable   26  3   0    ; array=3, hash=0
2427  4177001B           [1103] loadk      27  477      ; -444
242B  C177001C           [1104] loadk      28  479      ; -299.60000610352
242F  8113001D           [1105] loadk      29  78       ; 11.199999809265
2433  9F00001A           [1106] setlist    26  2        ; index 1 to 3
2437  C176001B           [1107] loadk      27  475      ; 183.10000610352
243B  8101001C           [1108] loadk      28  6        ; 5
243F  9F000019           [1109] setlist    25  2        ; index 1 to 3
2443  0A80011A           [1110] newtable   26  3   0    ; array=3, hash=0
2447  0A80011B           [1111] newtable   27  3   0    ; array=3, hash=0
244B  4178001C           [1112] loadk      28  481      ; -609
244F  C178001D           [1113] loadk      29  483      ; -328.39999389648
2453  8113001E           [1114] loadk      30  78       ; 11.199999809265
2457  9F00001B           [1115] setlist    27  2        ; index 1 to 3
245B  0179001C           [1116] loadk      28  484      ; 201.89999389648
245F  8101001D           [1117] loadk      29  6        ; 5
2463  9F00001A           [1118] setlist    26  2        ; index 1 to 3
2467  0A80011B           [1119] newtable   27  3   0    ; array=3, hash=0
246B  0A80011C           [1120] newtable   28  3   0    ; array=3, hash=0
246F  8179001D           [1121] loadk      29  486      ; -669.29998779297
2473  017A001E           [1122] loadk      30  488      ; -367.5
2477  8135001F           [1123] loadk      31  214      ; 10.89999961853
247B  9F00001C           [1124] setlist    28  2        ; index 1 to 3
247F  417A001D           [1125] loadk      29  489      ; 212.5
2483  8101001E           [1126] loadk      30  6        ; 5
2487  9F00001B           [1127] setlist    27  2        ; index 1 to 3
248B  0A80011C           [1128] newtable   28  3   0    ; array=3, hash=0
248F  0A80011D           [1129] newtable   29  3   0    ; array=3, hash=0
2493  C17A001E           [1130] loadk      30  491      ; -433.79998779297
2497  417B001F           [1131] loadk      31  493      ; -551.79998779297
249B  817B0020           [1132] loadk      32  494      ; 12.800000190735
249F  9F00001D           [1133] setlist    29  2        ; index 1 to 3
24A3  C17B001E           [1134] loadk      30  495      ; 348.10000610352
24A7  8101001F           [1135] loadk      31  6        ; 5
24AB  9F00001C           [1136] setlist    28  2        ; index 1 to 3
24AF  0A80011D           [1137] newtable   29  3   0    ; array=3, hash=0
24B3  0A80011E           [1138] newtable   30  3   0    ; array=3, hash=0
24B7  417C001F           [1139] loadk      31  497      ; -453.60000610352
24BB  C17C0020           [1140] loadk      32  499      ; -512.40002441406
24BF  017D0021           [1141] loadk      33  500      ; 12.10000038147
24C3  9F00001E           [1142] setlist    30  2        ; index 1 to 3
24C7  417D001F           [1143] loadk      31  501      ; 346.79998779297
24CB  81010020           [1144] loadk      32  6        ; 5
24CF  9F00001D           [1145] setlist    29  2        ; index 1 to 3
24D3  0A80011E           [1146] newtable   30  3   0    ; array=3, hash=0
24D7  0A80011F           [1147] newtable   31  3   0    ; array=3, hash=0
24DB  C17D0020           [1148] loadk      32  503      ; -405.29998779297
24DF  417E0021           [1149] loadk      33  505      ; -632.70001220703
24E3  412F0022           [1150] loadk      34  189      ; 10.39999961853
24E7  9F00001F           [1151] setlist    31  2        ; index 1 to 3
24EB  01240020           [1152] loadk      32  144      ; 272.60000610352
24EF  81010021           [1153] loadk      33  6        ; 5
24F3  9F00001E           [1154] setlist    30  2        ; index 1 to 3
24F7  0A80011F           [1155] newtable   31  3   0    ; array=3, hash=0
24FB  0A800120           [1156] newtable   32  3   0    ; array=3, hash=0
24FF  C17E0021           [1157] loadk      33  507      ; -350.60000610352
2503  417F0022           [1158] loadk      34  509      ; -631.29998779297
2507  412F0023           [1159] loadk      35  189      ; 10.39999961853
250B  9F000020           [1160] setlist    32  2        ; index 1 to 3
250F  817F0021           [1161] loadk      33  510      ; 275.60000610352
2513  81010022           [1162] loadk      34  6        ; 5
2517  9F00001F           [1163] setlist    31  2        ; index 1 to 3
251B  0A800120           [1164] newtable   32  3   0    ; array=3, hash=0
251F  0A800121           [1165] newtable   33  3   0    ; array=3, hash=0
2523  01800022           [1166] loadk      34  512      ; -282.10000610352
2527  81800023           [1167] loadk      35  514      ; -576.40002441406
252B  817B0024           [1168] loadk      36  494      ; 12.800000190735
252F  9F000021           [1169] setlist    33  2        ; index 1 to 3
2533  C1800022           [1170] loadk      34  515      ; 2.7000000476837
2537  81010023           [1171] loadk      35  6        ; 5
253B  9F000020           [1172] setlist    32  2        ; index 1 to 3
253F  9F1F0001           [1173] setlist    1   126      ; index 97 to 127
2543  00800000           [1174] move       0   1      
2547  14E78000           [1175] jmp        925          ; to [2101]
254B  05000001           [1176] getglobal  1   0        ; GameLocation
254F  99800001           [1177] call       1   1   2  
2553  01810002           [1178] loadk      2   516      ; 6
2557  95800001           [1179] eq         1   1   2    ; to [1181] if false
255B  94058000           [1180] jmp        23           ; to [1204]
255F  05000001           [1181] getglobal  1   0        ; GameLocation
2563  99800001           [1182] call       1   1   2  
2567  41810002           [1183] loadk      2   517      ; 7
256B  95800001           [1184] eq         1   1   2    ; to [1186] if false
256F  54048000           [1185] jmp        18           ; to [1204]
2573  05000001           [1186] getglobal  1   0        ; GameLocation
2577  99800001           [1187] call       1   1   2  
257B  81810002           [1188] loadk      2   518      ; 8
257F  95800001           [1189] eq         1   1   2    ; to [1191] if false
2583  14038000           [1190] jmp        13           ; to [1204]
2587  05000001           [1191] getglobal  1   0        ; GameLocation
258B  99800001           [1192] call       1   1   2  
258F  C1810002           [1193] loadk      2   519      ; 9
2593  95800001           [1194] eq         1   1   2    ; to [1196] if false
2597  D4018000           [1195] jmp        8            ; to [1204]
259B  05000001           [1196] getglobal  1   0        ; GameLocation
259F  99800001           [1197] call       1   1   2  
25A3  55C20001           [1198] eq         1   1   265  ; 10, to [1200] if false
25A7  D4008000           [1199] jmp        4            ; to [1204]
25AB  05000001           [1200] getglobal  1   0        ; GameLocation
25AF  99800001           [1201] call       1   1   2  
25B3  95C50000           [1202] eq         0   1   278  ; 11, to [1204] if true
25B7  14E08000           [1203] jmp        897          ; to [2101]
25BB  0A801301           [1204] newtable   1   39  0    ; array=112, hash=0
25BF  0A800102           [1205] newtable   2   3   0    ; array=3, hash=0
25C3  0A800103           [1206] newtable   3   3   0    ; array=3, hash=0
25C7  41820004           [1207] loadk      4   521      ; -507
25CB  81820005           [1208] loadk      5   522      ; 1141.3000488281
25CF  01070006           [1209] loadk      6   28       ; 11
25D3  9F000003           [1210] setlist    3   2        ; index 1 to 3
25D7  C1820004           [1211] loadk      4   523      ; 181
25DB  01810005           [1212] loadk      5   516      ; 6
25DF  9F000002           [1213] setlist    2   2        ; index 1 to 3
25E3  0A800103           [1214] newtable   3   3   0    ; array=3, hash=0
25E7  0A800104           [1215] newtable   4   3   0    ; array=3, hash=0
25EB  41830005           [1216] loadk      5   525      ; -560.79998779297
25EF  81830006           [1217] loadk      6   526      ; 1164.5999755859
25F3  810B0007           [1218] loadk      7   46       ; 11.300000190735
25F7  9F000004           [1219] setlist    4   2        ; index 1 to 3
25FB  C1830005           [1220] loadk      5   527      ; 151
25FF  01810006           [1221] loadk      6   516      ; 6
2603  9F000003           [1222] setlist    3   2        ; index 1 to 3
2607  0A800104           [1223] newtable   4   3   0    ; array=3, hash=0
260B  0A800105           [1224] newtable   5   3   0    ; array=3, hash=0
260F  41840006           [1225] loadk      6   529      ; -780.5
2613  81840007           [1226] loadk      7   530      ; 1118.4000244141
2617  413A0008           [1227] loadk      8   233      ; 18.200000762939
261B  9F000005           [1228] setlist    5   2        ; index 1 to 3
261F  01010006           [1229] loadk      6   4        ; 3
2623  01810007           [1230] loadk      7   516      ; 6
2627  9F000004           [1231] setlist    4   2        ; index 1 to 3
262B  0A800105           [1232] newtable   5   3   0    ; array=3, hash=0
262F  0A800106           [1233] newtable   6   3   0    ; array=3, hash=0
2633  01850007           [1234] loadk      7   532      ; -636.5
2637  41850008           [1235] loadk      8   533      ; 909.90002441406
263B  01070009           [1236] loadk      9   28       ; 11
263F  9F000006           [1237] setlist    6   2        ; index 1 to 3
2643  81850007           [1238] loadk      7   534      ; 92
2647  01810008           [1239] loadk      8   516      ; 6
264B  9F000005           [1240] setlist    5   2        ; index 1 to 3
264F  0A800106           [1241] newtable   6   3   0    ; array=3, hash=0
2653  0A800107           [1242] newtable   7   3   0    ; array=3, hash=0
2657  01860008           [1243] loadk      8   536      ; -944.20001220703
265B  41860009           [1244] loadk      9   537      ; 902.90002441406
265F  0107000A           [1245] loadk      10  28       ; 11
2663  9F000007           [1246] setlist    7   2        ; index 1 to 3
2667  013E0008           [1247] loadk      8   248      ; 270
266B  01810009           [1248] loadk      9   516      ; 6
266F  9F000006           [1249] setlist    6   2        ; index 1 to 3
2673  0A800107           [1250] newtable   7   3   0    ; array=3, hash=0
2677  0A800108           [1251] newtable   8   3   0    ; array=3, hash=0
267B  C1860009           [1252] loadk      9   539      ; -840.5
267F  0187000A           [1253] loadk      10  540      ; 1295.8000488281
2683  810E000B           [1254] loadk      11  58       ; 11.5
2687  9F000008           [1255] setlist    8   2        ; index 1 to 3
268B  41870009           [1256] loadk      9   541      ; 107
268F  0181000A           [1257] loadk      10  516      ; 6
2693  9F000007           [1258] setlist    7   2        ; index 1 to 3
2697  0A800108           [1259] newtable   8   3   0    ; array=3, hash=0
269B  0A800109           [1260] newtable   9   3   0    ; array=3, hash=0
269F  C187000A           [1261] loadk      10  543      ; -322.60000610352
26A3  0188000B           [1262] loadk      11  544      ; 1083
26A7  4188000C           [1263] loadk      12  545      ; 9.1000003814697
26AB  9F000009           [1264] setlist    9   2        ; index 1 to 3
26AF  8188000A           [1265] loadk      10  546      ; 20
26B3  0181000B           [1266] loadk      11  516      ; 6
26B7  9F000008           [1267] setlist    8   2        ; index 1 to 3
26BB  0A800109           [1268] newtable   9   3   0    ; array=3, hash=0
26BF  0A80010A           [1269] newtable   10  3   0    ; array=3, hash=0
26C3  0189000B           [1270] loadk      11  548      ; -346.89999389648
26C7  4189000C           [1271] loadk      12  549      ; 1171.9000244141
26CB  8189000D           [1272] loadk      13  550      ; 11.39999961853
26CF  9F00000A           [1273] setlist    10  2        ; index 1 to 3
26D3  C189000B           [1274] loadk      11  551      ; 312
26D7  0181000C           [1275] loadk      12  516      ; 6
26DB  9F000009           [1276] setlist    9   2        ; index 1 to 3
26DF  0A80010A           [1277] newtable   10  3   0    ; array=3, hash=0
26E3  0A80010B           [1278] newtable   11  3   0    ; array=3, hash=0
26E7  418A000C           [1279] loadk      12  553      ; -298.5
26EB  818A000D           [1280] loadk      13  554      ; 1344
26EF  8189000E           [1281] loadk      14  550      ; 11.39999961853
26F3  9F00000B           [1282] setlist    11  2        ; index 1 to 3
26F7  C18A000C           [1283] loadk      12  555      ; 140
26FB  0181000D           [1284] loadk      13  516      ; 6
26FF  9F00000A           [1285] setlist    10  2        ; index 1 to 3
2703  0A80010B           [1286] newtable   11  3   0    ; array=3, hash=0
2707  0A80010C           [1287] newtable   12  3   0    ; array=3, hash=0
270B  418B000D           [1288] loadk      13  557      ; -448.39999389648
270F  818B000E           [1289] loadk      14  558      ; 1301.3000488281
2713  8135000F           [1290] loadk      15  214      ; 10.89999961853
2717  9F00000C           [1291] setlist    12  2        ; index 1 to 3
271B  C18B000D           [1292] loadk      13  559      ; 0.10000000149012
271F  0181000E           [1293] loadk      14  516      ; 6
2723  9F00000B           [1294] setlist    11  2        ; index 1 to 3
2727  0A80010C           [1295] newtable   12  3   0    ; array=3, hash=0
272B  0A80010D           [1296] newtable   13  3   0    ; array=3, hash=0
272F  418C000E           [1297] loadk      14  561      ; -594.70001220703
2733  818C000F           [1298] loadk      15  562      ; 1359.8000488281
2737  81020010           [1299] loadk      16  10       ; 11.699999809265
273B  9F00000D           [1300] setlist    13  2        ; index 1 to 3
273F  415C000E           [1301] loadk      14  369      ; 184
2743  0181000F           [1302] loadk      15  516      ; 6
2747  9F00000C           [1303] setlist    12  2        ; index 1 to 3
274B  0A80010D           [1304] newtable   13  3   0    ; array=3, hash=0
274F  0A80010E           [1305] newtable   14  3   0    ; array=3, hash=0
2753  018D000F           [1306] loadk      15  564      ; -753
2757  01870010           [1307] loadk      16  540      ; 1295.8000488281
275B  810A0011           [1308] loadk      17  42       ; 11.60000038147
275F  9F00000E           [1309] setlist    14  2        ; index 1 to 3
2763  8188000F           [1310] loadk      15  546      ; 20
2767  01810010           [1311] loadk      16  516      ; 6
276B  9F00000D           [1312] setlist    13  2        ; index 1 to 3
276F  0A80010E           [1313] newtable   14  3   0    ; array=3, hash=0
2773  0A80010F           [1314] newtable   15  3   0    ; array=3, hash=0
2777  818D0010           [1315] loadk      16  566      ; -668.70001220703
277B  C18D0011           [1316] loadk      17  567      ; 1385.6999511719
277F  81220012           [1317] loadk      18  138      ; 11.89999961853
2783  9F00000F           [1318] setlist    15  2        ; index 1 to 3
2787  018E0010           [1319] loadk      16  568      ; 41
278B  01810011           [1320] loadk      17  516      ; 6
278F  9F00000E           [1321] setlist    14  2        ; index 1 to 3
2793  0A80010F           [1322] newtable   15  3   0    ; array=3, hash=0
2797  0A800110           [1323] newtable   16  3   0    ; array=3, hash=0
279B  818E0011           [1324] loadk      17  570      ; -779.20001220703
279F  C18E0012           [1325] loadk      18  571      ; 1428.1999511719
27A3  81220013           [1326] loadk      19  138      ; 11.89999961853
27A7  9F000010           [1327] setlist    16  2        ; index 1 to 3
27AB  C1220011           [1328] loadk      17  139      ; 180
27AF  01810012           [1329] loadk      18  516      ; 6
27B3  9F00000F           [1330] setlist    15  2        ; index 1 to 3
27B7  0A800110           [1331] newtable   16  3   0    ; array=3, hash=0
27BB  0A800111           [1332] newtable   17  3   0    ; array=3, hash=0
27BF  418F0012           [1333] loadk      18  573      ; -831.5
27C3  818F0013           [1334] loadk      19  574      ; 1511.6999511719
27C7  81300014           [1335] loadk      20  194      ; 12.199999809265
27CB  9F000011           [1336] setlist    17  2        ; index 1 to 3
27CF  C1220012           [1337] loadk      18  139      ; 180
27D3  01810013           [1338] loadk      19  516      ; 6
27D7  9F000010           [1339] setlist    16  2        ; index 1 to 3
27DB  0A800111           [1340] newtable   17  3   0    ; array=3, hash=0
27DF  0A800112           [1341] newtable   18  3   0    ; array=3, hash=0
27E3  01900013           [1342] loadk      19  576      ; -915.90002441406
27E7  41900014           [1343] loadk      20  577      ; 1500
27EB  81900015           [1344] loadk      21  578      ; 16.700000762939
27EF  9F000012           [1345] setlist    18  2        ; index 1 to 3
27F3  C1900013           [1346] loadk      19  579      ; 226
27F7  01810014           [1347] loadk      20  516      ; 6
27FB  9F000011           [1348] setlist    17  2        ; index 1 to 3
27FF  0A800112           [1349] newtable   18  3   0    ; array=3, hash=0
2803  0A800113           [1350] newtable   19  3   0    ; array=3, hash=0
2807  41910014           [1351] loadk      20  581      ; -881.20001220703
280B  81910015           [1352] loadk      21  582      ; 1334.4000244141
280F  81890016           [1353] loadk      22  550      ; 11.39999961853
2813  9F000013           [1354] setlist    19  2        ; index 1 to 3
2817  415B0014           [1355] loadk      20  365      ; 200
281B  01810015           [1356] loadk      21  516      ; 6
281F  9F000012           [1357] setlist    18  2        ; index 1 to 3
2823  0A800113           [1358] newtable   19  3   0    ; array=3, hash=0
2827  0A800114           [1359] newtable   20  3   0    ; array=3, hash=0
282B  01920015           [1360] loadk      21  584      ; -1030
282F  41920016           [1361] loadk      22  585      ; 1331.8000488281
2833  01080017           [1362] loadk      23  32       ; 8.6999998092651
2837  9F000014           [1363] setlist    20  2        ; index 1 to 3
283B  41070015           [1364] loadk      21  29       ; 280
283F  01810016           [1365] loadk      22  516      ; 6
2843  9F000013           [1366] setlist    19  2        ; index 1 to 3
2847  0A800114           [1367] newtable   20  3   0    ; array=3, hash=0
284B  0A800115           [1368] newtable   21  3   0    ; array=3, hash=0
284F  C1920016           [1369] loadk      22  587      ; -649.40002441406
2853  01930017           [1370] loadk      23  588      ; 1497.8000488281
2857  810D0018           [1371] loadk      24  54       ; 12
285B  9F000015           [1372] setlist    21  2        ; index 1 to 3
285F  81340016           [1373] loadk      22  210      ; 115
2863  01810017           [1374] loadk      23  516      ; 6
2867  9F000014           [1375] setlist    20  2        ; index 1 to 3
286B  0A800115           [1376] newtable   21  3   0    ; array=3, hash=0
286F  0A800116           [1377] newtable   22  3   0    ; array=3, hash=0
2873  81930017           [1378] loadk      23  590      ; -973.40002441406
2877  01940018           [1379] loadk      24  592      ; -72.5
287B  01050019           [1380] loadk      25  20       ; 10.699999809265
287F  9F000016           [1381] setlist    22  2        ; index 1 to 3
2883  41940017           [1382] loadk      23  593      ; 150
2887  41810018           [1383] loadk      24  517      ; 7
288B  9F000015           [1384] setlist    21  2        ; index 1 to 3
288F  0A800116           [1385] newtable   22  3   0    ; array=3, hash=0
2893  0A800117           [1386] newtable   23  3   0    ; array=3, hash=0
2897  C1940018           [1387] loadk      24  595      ; -1075.8000488281
289B  41950019           [1388] loadk      25  597      ; -136.30000305176
289F  810B001A           [1389] loadk      26  46       ; 11.300000190735
28A3  9F000017           [1390] setlist    23  2        ; index 1 to 3
28A7  815F0018           [1391] loadk      24  382      ; 320
28AB  41810019           [1392] loadk      25  517      ; 7
28AF  9F000016           [1393] setlist    22  2        ; index 1 to 3
28B3  0A800117           [1394] newtable   23  3   0    ; array=3, hash=0
28B7  0A800118           [1395] newtable   24  3   0    ; array=3, hash=0
28BB  C1950019           [1396] loadk      25  599      ; -885.5
28BF  0196001A           [1397] loadk      26  600      ; 180.10000610352
28C3  4196001B           [1398] loadk      27  601      ; 9.3000001907349
28C7  9F000018           [1399] setlist    24  2        ; index 1 to 3
28CB  81960019           [1400] loadk      25  602      ; 84
28CF  4181001A           [1401] loadk      26  517      ; 7
28D3  9F000017           [1402] setlist    23  2        ; index 1 to 3
28D7  0A800118           [1403] newtable   24  3   0    ; array=3, hash=0
28DB  0A800119           [1404] newtable   25  3   0    ; array=3, hash=0
28DF  0197001A           [1405] loadk      26  604      ; -1048.5
28E3  4197001B           [1406] loadk      27  605      ; 318.89999389648
28E7  8113001C           [1407] loadk      28  78       ; 11.199999809265
28EB  9F000019           [1408] setlist    25  2        ; index 1 to 3
28EF  013E001A           [1409] loadk      26  248      ; 270
28F3  4181001B           [1410] loadk      27  517      ; 7
28F7  9F000018           [1411] setlist    24  2        ; index 1 to 3
28FB  0A800119           [1412] newtable   25  3   0    ; array=3, hash=0
28FF  0A80011A           [1413] newtable   26  3   0    ; array=3, hash=0
2903  C197001B           [1414] loadk      27  607      ; -913.59997558594
2907  0198001C           [1415] loadk      28  608      ; 338.89999389648
290B  8113001D           [1416] loadk      29  78       ; 11.199999809265
290F  9F00001A           [1417] setlist    26  2        ; index 1 to 3
2913  4198001B           [1418] loadk      27  609      ; 172
2917  4181001C           [1419] loadk      28  517      ; 7
291B  9F000019           [1420] setlist    25  2        ; index 1 to 3
291F  0A80011A           [1421] newtable   26  3   0    ; array=3, hash=0
2923  0A80011B           [1422] newtable   27  3   0    ; array=3, hash=0
2927  C198001C           [1423] loadk      28  611      ; -766
292B  C10D001D           [1424] loadk      29  55       ; 130
292F  0107001E           [1425] loadk      30  28       ; 11
2933  9F00001B           [1426] setlist    27  2        ; index 1 to 3
2937  4159001C           [1427] loadk      28  357      ; 198
293B  4181001D           [1428] loadk      29  517      ; 7
293F  9F00001A           [1429] setlist    26  2        ; index 1 to 3
2943  0A80011B           [1430] newtable   27  3   0    ; array=3, hash=0
2947  0A80011C           [1431] newtable   28  3   0    ; array=3, hash=0
294B  4199001D           [1432] loadk      29  613      ; -742.79998779297
294F  8199001E           [1433] loadk      30  614      ; 266.10000610352
2953  C199001F           [1434] loadk      31  615      ; 14.39999961853
2957  9F00001C           [1435] setlist    28  2        ; index 1 to 3
295B  019A001D           [1436] loadk      29  616      ; 262
295F  4181001E           [1437] loadk      30  517      ; 7
2963  9F00001B           [1438] setlist    27  2        ; index 1 to 3
2967  0A80011C           [1439] newtable   28  3   0    ; array=3, hash=0
296B  0A80011D           [1440] newtable   29  3   0    ; array=3, hash=0
296F  819A001E           [1441] loadk      30  618      ; -621.70001220703
2973  C19A001F           [1442] loadk      31  619      ; 577.5
2977  01070020           [1443] loadk      32  28       ; 11
297B  9F00001D           [1444] setlist    29  2        ; index 1 to 3
297F  C10E001E           [1445] loadk      30  59       ; 120
2983  4181001F           [1446] loadk      31  517      ; 7
2987  9F00001C           [1447] setlist    28  2        ; index 1 to 3
298B  0A80011D           [1448] newtable   29  3   0    ; array=3, hash=0
298F  0A80011E           [1449] newtable   30  3   0    ; array=3, hash=0
2993  419B001F           [1450] loadk      31  621      ; -872.40002441406
2997  819B0020           [1451] loadk      32  622      ; 759.79998779297
299B  01070021           [1452] loadk      33  28       ; 11
299F  9F00001E           [1453] setlist    30  2        ; index 1 to 3
29A3  C19B001F           [1454] loadk      31  623      ; 356
29A7  41810020           [1455] loadk      32  517      ; 7
29AB  9F00001D           [1456] setlist    29  2        ; index 1 to 3
29AF  0A80011E           [1457] newtable   30  3   0    ; array=3, hash=0
29B3  0A80011F           [1458] newtable   31  3   0    ; array=3, hash=0
29B7  419C0020           [1459] loadk      32  625      ; -539.29998779297
29BB  819C0021           [1460] loadk      33  626      ; 847.40002441406
29BF  C19C0022           [1461] loadk      34  627      ; 23
29C3  9F00001F           [1462] setlist    31  2        ; index 1 to 3
29C7  41070020           [1463] loadk      32  29       ; 280
29CB  41810021           [1464] loadk      33  517      ; 7
29CF  9F00001E           [1465] setlist    30  2        ; index 1 to 3
29D3  0A80011F           [1466] newtable   31  3   0    ; array=3, hash=0
29D7  0A800120           [1467] newtable   32  3   0    ; array=3, hash=0
29DB  419D0021           [1468] loadk      33  629      ; -614.29998779297
29DF  819D0022           [1469] loadk      34  630      ; 803.59997558594
29E3  C19D0023           [1470] loadk      35  631      ; 29.60000038147
29E7  9F000020           [1471] setlist    32  2        ; index 1 to 3
29EB  C1220021           [1472] loadk      33  139      ; 180
29EF  41810022           [1473] loadk      34  517      ; 7
29F3  9F00001F           [1474] setlist    31  2        ; index 1 to 3
29F7  0A800120           [1475] newtable   32  3   0    ; array=3, hash=0
29FB  0A800121           [1476] newtable   33  3   0    ; array=3, hash=0
29FF  419E0022           [1477] loadk      34  633      ; -692.70001220703
2A03  819E0023           [1478] loadk      35  634      ; 704.40002441406
2A07  017D0024           [1479] loadk      36  500      ; 12.10000038147
2A0B  9F000021           [1480] setlist    33  2        ; index 1 to 3
2A0F  C19E0022           [1481] loadk      34  635      ; 331
2A13  41810023           [1482] loadk      35  517      ; 7
2A17  9F000020           [1483] setlist    32  2        ; index 1 to 3
2A1B  0A800121           [1484] newtable   33  3   0    ; array=3, hash=0
2A1F  0A800122           [1485] newtable   34  3   0    ; array=3, hash=0
2A23  419F0023           [1486] loadk      35  637      ; -832.59997558594
2A27  819F0024           [1487] loadk      36  638      ; 1038.1999511719
2A2B  01610025           [1488] loadk      37  388      ; 15.699999809265
2A2F  9F000022           [1489] setlist    34  2        ; index 1 to 3
2A33  C19F0023           [1490] loadk      35  639      ; 136
2A37  41810024           [1491] loadk      36  517      ; 7
2A3B  9F000021           [1492] setlist    33  2        ; index 1 to 3
2A3F  DF070001           [1493] setlist    1   31       ; index 1 to 32
2A43  0A800102           [1494] newtable   2   3   0    ; array=3, hash=0
2A47  0A800103           [1495] newtable   3   3   0    ; array=3, hash=0
2A4B  41A00004           [1496] loadk      4   641      ; -385.89999389648
2A4F  81A00005           [1497] loadk      5   642      ; 1059.4000244141
2A53  01160006           [1498] loadk      6   88       ; 13
2A57  9F000003           [1499] setlist    3   2        ; index 1 to 3
2A5B  C1820004           [1500] loadk      4   523      ; 181
2A5F  41810005           [1501] loadk      5   517      ; 7
2A63  9F000002           [1502] setlist    2   2        ; index 1 to 3
2A67  0A800103           [1503] newtable   3   3   0    ; array=3, hash=0
2A6B  0A800104           [1504] newtable   4   3   0    ; array=3, hash=0
2A6F  01A10005           [1505] loadk      5   644      ; -1182.8000488281
2A73  81A10006           [1506] loadk      6   646      ; -584.29998779297
2A77  810E0007           [1507] loadk      7   58       ; 11.5
2A7B  9F000004           [1508] setlist    4   2        ; index 1 to 3
2A7F  412D0005           [1509] loadk      5   181      ; 210
2A83  81810006           [1510] loadk      6   518      ; 8
2A87  9F000003           [1511] setlist    3   2        ; index 1 to 3
2A8B  0A800104           [1512] newtable   4   3   0    ; array=3, hash=0
2A8F  0A800105           [1513] newtable   5   3   0    ; array=3, hash=0
2A93  01A20006           [1514] loadk      6   648      ; -1135.8000488281
2A97  81A20007           [1515] loadk      7   650      ; -626.5
2A9B  C1A20008           [1516] loadk      8   651      ; 25.89999961853
2A9F  9F000005           [1517] setlist    5   2        ; index 1 to 3
2AA3  C19C0006           [1518] loadk      6   627      ; 23
2AA7  81810007           [1519] loadk      7   518      ; 8
2AAB  9F000004           [1520] setlist    4   2        ; index 1 to 3
2AAF  0A800105           [1521] newtable   5   3   0    ; array=3, hash=0
2AB3  0A800106           [1522] newtable   6   3   0    ; array=3, hash=0
2AB7  41A30007           [1523] loadk      7   653      ; -816.5
2ABB  C1A30008           [1524] loadk      8   655      ; -348.5
2ABF  01070009           [1525] loadk      9   28       ; 11
2AC3  9F000006           [1526] setlist    6   2        ; index 1 to 3
2AC7  41160007           [1527] loadk      7   89       ; 90
2ACB  81810008           [1528] loadk      8   518      ; 8
2ACF  9F000005           [1529] setlist    5   2        ; index 1 to 3
2AD3  0A800106           [1530] newtable   6   3   0    ; array=3, hash=0
2AD7  0A800107           [1531] newtable   7   3   0    ; array=3, hash=0
2ADB  41A40008           [1532] loadk      8   657      ; -939.90002441406
2ADF  C1A40009           [1533] loadk      9   659      ; -464.89999389648
2AE3  8135000A           [1534] loadk      10  214      ; 10.89999961853
2AE7  9F000007           [1535] setlist    7   2        ; index 1 to 3
2AEB  01A50008           [1536] loadk      8   660      ; 28
2AEF  81810009           [1537] loadk      9   518      ; 8
2AF3  9F000006           [1538] setlist    6   2        ; index 1 to 3
2AF7  0A800107           [1539] newtable   7   3   0    ; array=3, hash=0
2AFB  0A800108           [1540] newtable   8   3   0    ; array=3, hash=0
2AFF  81A50009           [1541] loadk      9   662      ; -1014.9000244141
2B03  C17C000A           [1542] loadk      10  499      ; -512.40002441406
2B07  810B000B           [1543] loadk      11  46       ; 11.300000190735
2B0B  9F000008           [1544] setlist    8   2        ; index 1 to 3
2B0F  41070009           [1545] loadk      9   29       ; 280
2B13  8181000A           [1546] loadk      10  518      ; 8
2B17  9F000007           [1547] setlist    7   2        ; index 1 to 3
2B1B  0A800108           [1548] newtable   8   3   0    ; array=3, hash=0
2B1F  0A800109           [1549] newtable   9   3   0    ; array=3, hash=0
2B23  01A6000A           [1550] loadk      10  664      ; -884.40002441406
2B27  81A6000B           [1551] loadk      11  666      ; -341.10000610352
2B2B  0106000C           [1552] loadk      12  24       ; 11.10000038147
2B2F  9F000009           [1553] setlist    9   2        ; index 1 to 3
2B33  013E000A           [1554] loadk      10  248      ; 270
2B37  8181000B           [1555] loadk      11  518      ; 8
2B3B  9F000008           [1556] setlist    8   2        ; index 1 to 3
2B3F  0A800109           [1557] newtable   9   3   0    ; array=3, hash=0
2B43  0A80010A           [1558] newtable   10  3   0    ; array=3, hash=0
2B47  01A7000B           [1559] loadk      11  668      ; -934.59997558594
2B4B  81A7000C           [1560] loadk      12  670      ; -230.10000610352
2B4F  C1A7000D           [1561] loadk      13  671      ; 6.5
2B53  9F00000A           [1562] setlist    10  2        ; index 1 to 3
2B57  C122000B           [1563] loadk      11  139      ; 180
2B5B  8181000C           [1564] loadk      12  518      ; 8
2B5F  9F000009           [1565] setlist    9   2        ; index 1 to 3
2B63  0A80010A           [1566] newtable   10  3   0    ; array=3, hash=0
2B67  0A80010B           [1567] newtable   11  3   0    ; array=3, hash=0
2B6B  41A8000C           [1568] loadk      12  673      ; -1042.4000244141
2B6F  C1A8000D           [1569] loadk      13  675      ; -242.10000610352
2B73  8189000E           [1570] loadk      14  550      ; 11.39999961853
2B77  9F00000B           [1571] setlist    11  2        ; index 1 to 3
2B7B  415B000C           [1572] loadk      12  365      ; 200
2B7F  8181000D           [1573] loadk      13  518      ; 8
2B83  9F00000A           [1574] setlist    10  2        ; index 1 to 3
2B87  0A80010B           [1575] newtable   11  3   0    ; array=3, hash=0
2B8B  0A80010C           [1576] newtable   12  3   0    ; array=3, hash=0
2B8F  41A9000D           [1577] loadk      13  677      ; -1139.5
2B93  C1A9000E           [1578] loadk      14  679      ; -315.70001220703
2B97  8135000F           [1579] loadk      15  214      ; 10.89999961853
2B9B  9F00000C           [1580] setlist    12  2        ; index 1 to 3
2B9F  01AA000D           [1581] loadk      13  680      ; 360
2BA3  8181000E           [1582] loadk      14  518      ; 8
2BA7  9F00000B           [1583] setlist    11  2        ; index 1 to 3
2BAB  0A80010C           [1584] newtable   12  3   0    ; array=3, hash=0
2BAF  0A80010D           [1585] newtable   13  3   0    ; array=3, hash=0
2BB3  81AA000E           [1586] loadk      14  682      ; -1196.5
2BB7  01AB000F           [1587] loadk      15  684      ; -332
2BBB  81350010           [1588] loadk      16  214      ; 10.89999961853
2BBF  9F00000D           [1589] setlist    13  2        ; index 1 to 3
2BC3  41AB000E           [1590] loadk      14  685      ; 204
2BC7  8181000F           [1591] loadk      15  518      ; 8
2BCB  9F00000C           [1592] setlist    12  2        ; index 1 to 3
2BCF  0A80010D           [1593] newtable   13  3   0    ; array=3, hash=0
2BD3  0A80010E           [1594] newtable   14  3   0    ; array=3, hash=0
2BD7  C1AB000F           [1595] loadk      15  687      ; -1088.6999511719
2BDB  017A0010           [1596] loadk      16  488      ; -367.5
2BDF  01AC0011           [1597] loadk      17  688      ; 16.10000038147
2BE3  9F00000E           [1598] setlist    14  2        ; index 1 to 3
2BE7  41AC000F           [1599] loadk      15  689      ; 162
2BEB  81810010           [1600] loadk      16  518      ; 8
2BEF  9F00000D           [1601] setlist    13  2        ; index 1 to 3
2BF3  0A80010E           [1602] newtable   14  3   0    ; array=3, hash=0
2BF7  0A80010F           [1603] newtable   15  3   0    ; array=3, hash=0
2BFB  C1AC0010           [1604] loadk      16  691      ; -1147
2BFF  41AD0011           [1605] loadk      17  693      ; -449
2C03  81350012           [1606] loadk      18  214      ; 10.89999961853
2C07  9F00000F           [1607] setlist    15  2        ; index 1 to 3
2C0B  81AD0010           [1608] loadk      16  694      ; 161
2C0F  81810011           [1609] loadk      17  518      ; 8
2C13  9F00000E           [1610] setlist    14  2        ; index 1 to 3
2C17  0A80010F           [1611] newtable   15  3   0    ; array=3, hash=0
2C1B  0A800110           [1612] newtable   16  3   0    ; array=3, hash=0
2C1F  01AE0011           [1613] loadk      17  696      ; -1068.9000244141
2C23  81AE0012           [1614] loadk      18  698      ; -538.29998779297
2C27  01060013           [1615] loadk      19  24       ; 11.10000038147
2C2B  9F000010           [1616] setlist    16  2        ; index 1 to 3
2C2F  C19C0011           [1617] loadk      17  627      ; 23
2C33  81810012           [1618] loadk      18  518      ; 8
2C37  9F00000F           [1619] setlist    15  2        ; index 1 to 3
2C3B  0A800110           [1620] newtable   16  3   0    ; array=3, hash=0
2C3F  0A800111           [1621] newtable   17  3   0    ; array=3, hash=0
2C43  01AF0012           [1622] loadk      18  700      ; -873.79998779297
2C47  81AF0013           [1623] loadk      19  702      ; -131.30000305176
2C4B  01070014           [1624] loadk      20  28       ; 11
2C4F  9F000011           [1625] setlist    17  2        ; index 1 to 3
2C53  C1890012           [1626] loadk      18  551      ; 312
2C57  81810013           [1627] loadk      19  518      ; 8
2C5B  9F000010           [1628] setlist    16  2        ; index 1 to 3
2C5F  0A800111           [1629] newtable   17  3   0    ; array=3, hash=0
2C63  0A800112           [1630] newtable   18  3   0    ; array=3, hash=0
2C67  01B00013           [1631] loadk      19  704      ; -745.20001220703
2C6B  01010014           [1632] loadk      20  4        ; 3
2C6F  01070015           [1633] loadk      21  28       ; 11
2C73  9F000012           [1634] setlist    18  2        ; index 1 to 3
2C77  81410013           [1635] loadk      19  262      ; 80
2C7B  81810014           [1636] loadk      20  518      ; 8
2C7F  9F000011           [1637] setlist    17  2        ; index 1 to 3
2C83  0A800112           [1638] newtable   18  3   0    ; array=3, hash=0
2C87  0A800113           [1639] newtable   19  3   0    ; array=3, hash=0
2C8B  81B00014           [1640] loadk      20  706      ; -907.09997558594
2C8F  C1B00015           [1641] loadk      21  707      ; 50.5
2C93  81120016           [1642] loadk      22  74       ; 10.10000038147
2C97  9F000013           [1643] setlist    19  2        ; index 1 to 3
2C9B  019A0014           [1644] loadk      20  616      ; 262
2C9F  81810015           [1645] loadk      21  518      ; 8
2CA3  9F000012           [1646] setlist    18  2        ; index 1 to 3
2CA7  0A800113           [1647] newtable   19  3   0    ; array=3, hash=0
2CAB  0A800114           [1648] newtable   20  3   0    ; array=3, hash=0
2CAF  41B10015           [1649] loadk      21  709      ; -1157.3000488281
2CB3  C1B10016           [1650] loadk      22  711      ; -110.69999694824
2CB7  81890017           [1651] loadk      23  550      ; 11.39999961853
2CBB  9F000014           [1652] setlist    20  2        ; index 1 to 3
2CBF  01B20015           [1653] loadk      21  712      ; 22
2CC3  81810016           [1654] loadk      22  518      ; 8
2CC7  9F000013           [1655] setlist    19  2        ; index 1 to 3
2CCB  0A800114           [1656] newtable   20  3   0    ; array=3, hash=0
2CCF  0A800115           [1657] newtable   21  3   0    ; array=3, hash=0
2CD3  81B20016           [1658] loadk      22  714      ; -1244.8000488281
2CD7  C1B20017           [1659] loadk      23  715      ; 7.5999999046326
2CDB  81890018           [1660] loadk      24  550      ; 11.39999961853
2CDF  9F000015           [1661] setlist    21  2        ; index 1 to 3
2CE3  013E0016           [1662] loadk      22  248      ; 270
2CE7  81810017           [1663] loadk      23  518      ; 8
2CEB  9F000014           [1664] setlist    20  2        ; index 1 to 3
2CEF  0A800115           [1665] newtable   21  3   0    ; array=3, hash=0
2CF3  0A800116           [1666] newtable   22  3   0    ; array=3, hash=0
2CF7  41B30017           [1667] loadk      23  717      ; -1097.0999755859
2CFB  81B30018           [1668] loadk      24  718      ; 108.5
2CFF  81130019           [1669] loadk      25  78       ; 11.199999809265
2D03  9F000016           [1670] setlist    22  2        ; index 1 to 3
2D07  013E0017           [1671] loadk      23  248      ; 270
2D0B  81810018           [1672] loadk      24  518      ; 8
2D0F  9F000015           [1673] setlist    21  2        ; index 1 to 3
2D13  0A800116           [1674] newtable   22  3   0    ; array=3, hash=0
2D17  0A800117           [1675] newtable   23  3   0    ; array=3, hash=0
2D1B  01B40018           [1676] loadk      24  720      ; -978.59997558594
2D1F  41B40019           [1677] loadk      25  721      ; 117.19999694824
2D23  81B4001A           [1678] loadk      26  722      ; 9.1999998092651
2D27  9F000017           [1679] setlist    23  2        ; index 1 to 3
2D2B  C1B40018           [1680] loadk      24  723      ; 357
2D2F  81810019           [1681] loadk      25  518      ; 8
2D33  9F000016           [1682] setlist    22  2        ; index 1 to 3
2D37  0A800117           [1683] newtable   23  3   0    ; array=3, hash=0
2D3B  0A800118           [1684] newtable   24  3   0    ; array=3, hash=0
2D3F  41B50019           [1685] loadk      25  725      ; -700.40002441406
2D43  C1B5001A           [1686] loadk      26  727      ; -1286.9000244141
2D47  0107001B           [1687] loadk      27  28       ; 11
2D4B  9F000018           [1688] setlist    24  2        ; index 1 to 3
2D4F  01B60019           [1689] loadk      25  728      ; 40
2D53  C181001A           [1690] loadk      26  519      ; 9
2D57  9F000017           [1691] setlist    23  2        ; index 1 to 3
2D5B  0A800118           [1692] newtable   24  3   0    ; array=3, hash=0
2D5F  0A800119           [1693] newtable   25  3   0    ; array=3, hash=0
2D63  81B6001A           [1694] loadk      26  730      ; -744.70001220703
2D67  01B7001B           [1695] loadk      27  732      ; -1268
2D6B  0107001C           [1696] loadk      28  28       ; 11
2D6F  9F000019           [1697] setlist    25  2        ; index 1 to 3
2D73  8188001A           [1698] loadk      26  546      ; 20
2D77  C181001B           [1699] loadk      27  519      ; 9
2D7B  9F000018           [1700] setlist    24  2        ; index 1 to 3
2D7F  0A800119           [1701] newtable   25  3   0    ; array=3, hash=0
2D83  0A80011A           [1702] newtable   26  3   0    ; array=3, hash=0
2D87  81B7001B           [1703] loadk      27  734      ; -664.5
2D8B  01B8001C           [1704] loadk      28  736      ; -1372.6999511719
2D8F  0107001D           [1705] loadk      29  28       ; 11
2D93  9F00001A           [1706] setlist    26  2        ; index 1 to 3
2D97  41B8001B           [1707] loadk      27  737      ; 26
2D9B  C181001C           [1708] loadk      28  519      ; 9
2D9F  9F000019           [1709] setlist    25  2        ; index 1 to 3
2DA3  0A80011A           [1710] newtable   26  3   0    ; array=3, hash=0
2DA7  0A80011B           [1711] newtable   27  3   0    ; array=3, hash=0
2DAB  C1B8001C           [1712] loadk      28  739      ; -712.59997558594
2DAF  41B9001D           [1713] loadk      29  741      ; -1499.9000244141
2DB3  8189001E           [1714] loadk      30  550      ; 11.39999961853
2DB7  9F00001B           [1715] setlist    27  2        ; index 1 to 3
2DBB  8188001C           [1716] loadk      28  546      ; 20
2DBF  C181001D           [1717] loadk      29  519      ; 9
2DC3  9F00001A           [1718] setlist    26  2        ; index 1 to 3
2DC7  0A80011B           [1719] newtable   27  3   0    ; array=3, hash=0
2DCB  0A80011C           [1720] newtable   28  3   0    ; array=3, hash=0
2DCF  C1B9001D           [1721] loadk      29  743      ; -875.90002441406
2DD3  41BA001E           [1722] loadk      30  745      ; -1408.3000488281
2DD7  810A001F           [1723] loadk      31  42       ; 11.60000038147
2DDB  9F00001C           [1724] setlist    28  2        ; index 1 to 3
2DDF  81BA001D           [1725] loadk      29  746      ; 195
2DE3  C181001E           [1726] loadk      30  519      ; 9
2DE7  9F00001B           [1727] setlist    27  2        ; index 1 to 3
2DEB  0A80011C           [1728] newtable   28  3   0    ; array=3, hash=0
2DEF  0A80011D           [1729] newtable   29  3   0    ; array=3, hash=0
2DF3  01BB001E           [1730] loadk      30  748      ; -870.59997558594
2DF7  81BB001F           [1731] loadk      31  750      ; -1326
2DFB  810E0020           [1732] loadk      32  58       ; 11.5
2DFF  9F00001D           [1733] setlist    29  2        ; index 1 to 3
2E03  815F001E           [1734] loadk      30  382      ; 320
2E07  C181001F           [1735] loadk      31  519      ; 9
2E0B  9F00001C           [1736] setlist    28  2        ; index 1 to 3
2E0F  0A80011D           [1737] newtable   29  3   0    ; array=3, hash=0
2E13  0A80011E           [1738] newtable   30  3   0    ; array=3, hash=0
2E17  01BC001F           [1739] loadk      31  752      ; -1028.5
2E1B  81BC0020           [1740] loadk      32  754      ; -1452.6999511719
2E1F  81020021           [1741] loadk      33  10       ; 11.699999809265
2E23  9F00001E           [1742] setlist    30  2        ; index 1 to 3
2E27  4161001F           [1743] loadk      31  389      ; 326
2E2B  C1810020           [1744] loadk      32  519      ; 9
2E2F  9F00001D           [1745] setlist    29  2        ; index 1 to 3
2E33  0A80011E           [1746] newtable   30  3   0    ; array=3, hash=0
2E37  0A80011F           [1747] newtable   31  3   0    ; array=3, hash=0
2E3B  01BD0020           [1748] loadk      32  756      ; -980.79998779297
2E3F  81BD0021           [1749] loadk      33  758      ; -1254.6999511719
2E43  810B0022           [1750] loadk      34  46       ; 11.300000190735
2E47  9F00001F           [1751] setlist    31  2        ; index 1 to 3
2E4B  C11A0020           [1752] loadk      32  107      ; 250
2E4F  C1810021           [1753] loadk      33  519      ; 9
2E53  9F00001E           [1754] setlist    30  2        ; index 1 to 3
2E57  0A80011F           [1755] newtable   31  3   0    ; array=3, hash=0
2E5B  0A800120           [1756] newtable   32  3   0    ; array=3, hash=0
2E5F  01BE0021           [1757] loadk      33  760      ; -839.5
2E63  81BE0022           [1758] loadk      34  762      ; -1226.9000244141
2E67  C1BE0023           [1759] loadk      35  763      ; 13.10000038147
2E6B  9F000020           [1760] setlist    32  2        ; index 1 to 3
2E6F  01BF0021           [1761] loadk      33  764      ; 62
2E73  C1810022           [1762] loadk      34  519      ; 9
2E77  9F00001F           [1763] setlist    31  2        ; index 1 to 3
2E7B  0A800120           [1764] newtable   32  3   0    ; array=3, hash=0
2E7F  0A800121           [1765] newtable   33  3   0    ; array=3, hash=0
2E83  81BF0022           [1766] loadk      34  766      ; -843.29998779297
2E87  01C00023           [1767] loadk      35  768      ; -959.09997558594
2E8B  01060024           [1768] loadk      36  24       ; 11.10000038147
2E8F  9F000021           [1769] setlist    33  2        ; index 1 to 3
2E93  81510022           [1770] loadk      34  326      ; 290
2E97  C1810023           [1771] loadk      35  519      ; 9
2E9B  9F000020           [1772] setlist    32  2        ; index 1 to 3
2E9F  0A800121           [1773] newtable   33  3   0    ; array=3, hash=0
2EA3  0A800122           [1774] newtable   34  3   0    ; array=3, hash=0
2EA7  81C00023           [1775] loadk      35  770      ; -987.5
2EAB  01C10024           [1776] loadk      36  772      ; -1131.8000488281
2EAF  41C10025           [1777] loadk      37  773      ; 14.800000190735
2EB3  9F000022           [1778] setlist    34  2        ; index 1 to 3
2EB7  01810023           [1779] loadk      35  516      ; 6
2EBB  C1810024           [1780] loadk      36  519      ; 9
2EBF  9F000021           [1781] setlist    33  2        ; index 1 to 3
2EC3  DF0F0001           [1782] setlist    1   63       ; index 33 to 64
2EC7  0A800102           [1783] newtable   2   3   0    ; array=3, hash=0
2ECB  0A800103           [1784] newtable   3   3   0    ; array=3, hash=0
2ECF  C1C10004           [1785] loadk      4   775      ; -881.90002441406
2ED3  41C20005           [1786] loadk      5   777      ; -1015.299987793
2ED7  41C10006           [1787] loadk      6   773      ; 14.800000190735
2EDB  9F000003           [1788] setlist    3   2        ; index 1 to 3
2EDF  81C20004           [1789] loadk      4   778      ; 190
2EE3  C1810005           [1790] loadk      5   519      ; 9
2EE7  9F000002           [1791] setlist    2   2        ; index 1 to 3
2EEB  0A800103           [1792] newtable   3   3   0    ; array=3, hash=0
2EEF  0A800104           [1793] newtable   4   3   0    ; array=3, hash=0
2EF3  01C30005           [1794] loadk      5   780      ; -1012.4000244141
2EF7  81C30006           [1795] loadk      6   782      ; -894.40002441406
2EFB  817B0007           [1796] loadk      7   494      ; 12.800000190735
2EFF  9F000004           [1797] setlist    4   2        ; index 1 to 3
2F03  C10E0005           [1798] loadk      5   59       ; 120
2F07  C1810006           [1799] loadk      6   519      ; 9
2F0B  9F000003           [1800] setlist    3   2        ; index 1 to 3
2F0F  0A800104           [1801] newtable   4   3   0    ; array=3, hash=0
2F13  0A800105           [1802] newtable   5   3   0    ; array=3, hash=0
2F17  01C40006           [1803] loadk      6   784      ; -834.79998779297
2F1B  81C40007           [1804] loadk      7   786      ; -765.40002441406
2F1F  01060008           [1805] loadk      8   24       ; 11.10000038147
2F23  9F000005           [1806] setlist    5   2        ; index 1 to 3
2F27  81550006           [1807] loadk      6   342      ; 275
2F2B  C1810007           [1808] loadk      7   519      ; 9
2F2F  9F000004           [1809] setlist    4   2        ; index 1 to 3
2F33  0A800105           [1810] newtable   5   3   0    ; array=3, hash=0
2F37  0A800106           [1811] newtable   6   3   0    ; array=3, hash=0
2F3B  01C50007           [1812] loadk      7   788      ; -1170.6999511719
2F3F  81C50008           [1813] loadk      8   790      ; -704.29998779297
2F43  C1C50009           [1814] loadk      9   791      ; 22.700000762939
2F47  9F000006           [1815] setlist    6   2        ; index 1 to 3
2F4B  81550007           [1816] loadk      7   342      ; 275
2F4F  C1810008           [1817] loadk      8   519      ; 9
2F53  9F000005           [1818] setlist    5   2        ; index 1 to 3
2F57  0A800106           [1819] newtable   6   3   0    ; array=3, hash=0
2F5B  0A800107           [1820] newtable   7   3   0    ; array=3, hash=0
2F5F  41C60008           [1821] loadk      8   793      ; -867.29998779297
2F63  C1C60009           [1822] loadk      9   795      ; -677.59997558594
2F67  8113000A           [1823] loadk      10  78       ; 11.199999809265
2F6B  9F000007           [1824] setlist    7   2        ; index 1 to 3
2F6F  41050008           [1825] loadk      8   21       ; 335
2F73  C1810009           [1826] loadk      9   519      ; 9
2F77  9F000006           [1827] setlist    6   2        ; index 1 to 3
2F7B  0A800107           [1828] newtable   7   3   0    ; array=3, hash=0
2F7F  0A800108           [1829] newtable   8   3   0    ; array=3, hash=0
2F83  41C70009           [1830] loadk      9   797      ; -941.90002441406
2F87  C1C7000A           [1831] loadk      10  799      ; -688.5
2F8B  8189000B           [1832] loadk      11  550      ; 11.39999961853
2F8F  9F000008           [1833] setlist    8   2        ; index 1 to 3
2F93  01810009           [1834] loadk      9   516      ; 6
2F97  C181000A           [1835] loadk      10  519      ; 9
2F9B  9F000007           [1836] setlist    7   2        ; index 1 to 3
2F9F  0A800108           [1837] newtable   8   3   0    ; array=3, hash=0
2FA3  0A800109           [1838] newtable   9   3   0    ; array=3, hash=0
2FA7  41C8000A           [1839] loadk      10  801      ; -1068
2FAB  C1C8000B           [1840] loadk      11  803      ; -634.40002441406
2FAF  8113000C           [1841] loadk      12  78       ; 11.199999809265
2FB3  9F000009           [1842] setlist    9   2        ; index 1 to 3
2FB7  0181000A           [1843] loadk      10  516      ; 6
2FBB  C181000B           [1844] loadk      11  519      ; 9
2FBF  9F000008           [1845] setlist    8   2        ; index 1 to 3
2FC3  0A800109           [1846] newtable   9   3   0    ; array=3, hash=0
2FC7  0A80010A           [1847] newtable   10  3   0    ; array=3, hash=0
2FCB  41C9000B           [1848] loadk      11  805      ; -1142.7155761719
2FCF  C1C9000C           [1849] loadk      12  807      ; -1087.302734375
2FD3  01CA000D           [1850] loadk      13  808      ; 14.868000030518
2FD7  9F00000A           [1851] setlist    10  2        ; index 1 to 3
2FDB  41CA000B           [1852] loadk      11  809      ; 289.58810424805
2FDF  C103000C           [1853] loadk      12  15       ; 10
2FE3  9F000009           [1854] setlist    9   2        ; index 1 to 3
2FE7  0A80010A           [1855] newtable   10  3   0    ; array=3, hash=0
2FEB  0A80010B           [1856] newtable   11  3   0    ; array=3, hash=0
2FEF  C1CA000C           [1857] loadk      12  811      ; -1221.4943847656
2FF3  41CB000D           [1858] loadk      13  813      ; -1237.7132568359
2FF7  81CB000E           [1859] loadk      14  814      ; 14.692899703979
2FFB  9F00000B           [1860] setlist    11  2        ; index 1 to 3
2FFF  C1CB000C           [1861] loadk      12  815      ; 310.87561035156
3003  C103000D           [1862] loadk      13  15       ; 10
3007  9F00000A           [1863] setlist    10  2        ; index 1 to 3
300B  0A80010B           [1864] newtable   11  3   0    ; array=3, hash=0
300F  0A80010C           [1865] newtable   12  3   0    ; array=3, hash=0
3013  41CC000D           [1866] loadk      13  817      ; -1148.0065917969
3017  C1CC000E           [1867] loadk      14  819      ; -1263.8952636719
301B  01CD000F           [1868] loadk      15  820      ; 14.826700210571
301F  9F00000C           [1869] setlist    12  2        ; index 1 to 3
3023  41CD000D           [1870] loadk      13  821      ; 20.571399688721
3027  C103000E           [1871] loadk      14  15       ; 10
302B  9F00000B           [1872] setlist    11  2        ; index 1 to 3
302F  0A80010C           [1873] newtable   12  3   0    ; array=3, hash=0
3033  0A80010D           [1874] newtable   13  3   0    ; array=3, hash=0
3037  C1CD000E           [1875] loadk      14  823      ; -1350.1114501953
303B  41CE000F           [1876] loadk      15  825      ; -1225.4034423828
303F  81CE0010           [1877] loadk      16  826      ; 18.155300140381
3043  9F00000D           [1878] setlist    13  2        ; index 1 to 3
3047  C1CE000E           [1879] loadk      14  827      ; 277.25540161133
304B  C103000F           [1880] loadk      15  15       ; 10
304F  9F00000C           [1881] setlist    12  2        ; index 1 to 3
3053  0A80010D           [1882] newtable   13  3   0    ; array=3, hash=0
3057  0A80010E           [1883] newtable   14  3   0    ; array=3, hash=0
305B  41CF000F           [1884] loadk      15  829      ; -1768.4011230469
305F  C1CF0010           [1885] loadk      16  831      ; -1192.9013671875
3063  01D00011           [1886] loadk      17  832      ; 14.868100166321
3067  9F00000E           [1887] setlist    14  2        ; index 1 to 3
306B  41D0000F           [1888] loadk      15  833      ; 282.88900756836
306F  C1030010           [1889] loadk      16  15       ; 10
3073  9F00000D           [1890] setlist    13  2        ; index 1 to 3
3077  0A80010E           [1891] newtable   14  3   0    ; array=3, hash=0
307B  0A80010F           [1892] newtable   15  3   0    ; array=3, hash=0
307F  C1D00010           [1893] loadk      16  835      ; -1436.1860351563
3083  41D10011           [1894] loadk      17  837      ; -808.28070068359
3087  81D10012           [1895] loadk      18  838      ; 14.866800308228
308B  9F00000F           [1896] setlist    15  2        ; index 1 to 3
308F  C1D10010           [1897] loadk      16  839      ; 5.3495998382568
3093  C1030011           [1898] loadk      17  15       ; 10
3097  9F00000E           [1899] setlist    14  2        ; index 1 to 3
309B  0A80010F           [1900] newtable   15  3   0    ; array=3, hash=0
309F  0A800110           [1901] newtable   16  3   0    ; array=3, hash=0
30A3  41D20011           [1902] loadk      17  841      ; -1574.5827636719
30A7  C1D20012           [1903] loadk      18  843      ; -1220.5773925781
30AB  01D00013           [1904] loadk      19  832      ; 14.868100166321
30AF  9F000010           [1905] setlist    16  2        ; index 1 to 3
30B3  01D30011           [1906] loadk      17  844      ; 4.4805998802185
30B7  C1030012           [1907] loadk      18  15       ; 10
30BB  9F00000F           [1908] setlist    15  2        ; index 1 to 3
30BF  0A800110           [1909] newtable   16  3   0    ; array=3, hash=0
30C3  0A800111           [1910] newtable   17  3   0    ; array=3, hash=0
30C7  81D30012           [1911] loadk      18  846      ; -1191.3421630859
30CB  01D40013           [1912] loadk      19  848      ; -849.68768310547
30CF  41D40014           [1913] loadk      20  849      ; 14.863699913025
30D3  9F000011           [1914] setlist    17  2        ; index 1 to 3
30D7  81D40012           [1915] loadk      18  850      ; 84.60230255127
30DB  C1030013           [1916] loadk      19  15       ; 10
30DF  9F000010           [1917] setlist    16  2        ; index 1 to 3
30E3  0A800111           [1918] newtable   17  3   0    ; array=3, hash=0
30E7  0A800112           [1919] newtable   18  3   0    ; array=3, hash=0
30EB  01D50013           [1920] loadk      19  852      ; -1541.9354248047
30EF  81D50014           [1921] loadk      20  854      ; -672.69500732422
30F3  C1D50015           [1922] loadk      21  855      ; 14.856900215149
30F7  9F000012           [1923] setlist    18  2        ; index 1 to 3
30FB  01D60013           [1924] loadk      19  856      ; 236.38310241699
30FF  C1030014           [1925] loadk      20  15       ; 10
3103  9F000011           [1926] setlist    17  2        ; index 1 to 3
3107  0A800112           [1927] newtable   18  3   0    ; array=3, hash=0
310B  0A800113           [1928] newtable   19  3   0    ; array=3, hash=0
310F  81D60014           [1929] loadk      20  858      ; -1722.6953125
3113  01D70015           [1930] loadk      21  860      ; -335.19088745117
3117  41D70016           [1931] loadk      22  861      ; 14.860899925232
311B  9F000013           [1932] setlist    19  2        ; index 1 to 3
311F  81D70014           [1933] loadk      20  862      ; 1.2878999710083
3123  C1030015           [1934] loadk      21  15       ; 10
3127  9F000012           [1935] setlist    18  2        ; index 1 to 3
312B  0A800113           [1936] newtable   19  3   0    ; array=3, hash=0
312F  0A800114           [1937] newtable   20  3   0    ; array=3, hash=0
3133  01D80015           [1938] loadk      21  864      ; -1590.9000244141
3137  81D80016           [1939] loadk      22  866      ; -745.09997558594
313B  41C10017           [1940] loadk      23  773      ; 14.800000190735
313F  9F000014           [1941] setlist    20  2        ; index 1 to 3
3143  81080015           [1942] loadk      21  34       ; 282.79998779297
3147  C1030016           [1943] loadk      22  15       ; 10
314B  9F000013           [1944] setlist    19  2        ; index 1 to 3
314F  0A800114           [1945] newtable   20  3   0    ; array=3, hash=0
3153  0A800115           [1946] newtable   21  3   0    ; array=3, hash=0
3157  01D90016           [1947] loadk      22  868      ; -1695
315B  81D90017           [1948] loadk      23  870      ; -638.5
315F  41C10018           [1949] loadk      24  773      ; 14.800000190735
3163  9F000015           [1950] setlist    21  2        ; index 1 to 3
3167  C1D90016           [1951] loadk      22  871      ; 264.60000610352
316B  C1030017           [1952] loadk      23  15       ; 10
316F  9F000014           [1953] setlist    20  2        ; index 1 to 3
3173  0A800115           [1954] newtable   21  3   0    ; array=3, hash=0
3177  0A800116           [1955] newtable   22  3   0    ; array=3, hash=0
317B  41DA0017           [1956] loadk      23  873      ; -1359.1999511719
317F  C1DA0018           [1957] loadk      24  875      ; -648.29998779297
3183  41C10019           [1958] loadk      25  773      ; 14.800000190735
3187  9F000016           [1959] setlist    22  2        ; index 1 to 3
318B  01DB0017           [1960] loadk      23  876      ; 199.69999694824
318F  C1030018           [1961] loadk      24  15       ; 10
3193  9F000015           [1962] setlist    21  2        ; index 1 to 3
3197  0A800116           [1963] newtable   22  3   0    ; array=3, hash=0
319B  0A800117           [1964] newtable   23  3   0    ; array=3, hash=0
319F  81DB0018           [1965] loadk      24  878      ; -1406.3000488281
31A3  01DC0019           [1966] loadk      25  880      ; -407.39999389648
31A7  41C1001A           [1967] loadk      26  773      ; 14.800000190735
31AB  9F000017           [1968] setlist    23  2        ; index 1 to 3
31AF  01040018           [1969] loadk      24  16       ; 170
31B3  C1030019           [1970] loadk      25  15       ; 10
31B7  9F000016           [1971] setlist    22  2        ; index 1 to 3
31BB  0A800117           [1972] newtable   23  3   0    ; array=3, hash=0
31BF  0A800118           [1973] newtable   24  3   0    ; array=3, hash=0
31C3  81DC0019           [1974] loadk      25  882      ; -1315.3000488281
31C7  01DD001A           [1975] loadk      26  884      ; -865
31CB  41C1001B           [1976] loadk      27  773      ; 14.800000190735
31CF  9F000018           [1977] setlist    24  2        ; index 1 to 3
31D3  41DD0019           [1978] loadk      25  885      ; 357.20001220703
31D7  C103001A           [1979] loadk      26  15       ; 10
31DB  9F000017           [1980] setlist    23  2        ; index 1 to 3
31DF  0A800118           [1981] newtable   24  3   0    ; array=3, hash=0
31E3  0A800119           [1982] newtable   25  3   0    ; array=3, hash=0
31E7  C1DD001A           [1983] loadk      26  887      ; -1593.0999755859
31EB  41DE001B           [1984] loadk      27  889      ; -903
31EF  41C1001C           [1985] loadk      28  773      ; 14.800000190735
31F3  9F000019           [1986] setlist    25  2        ; index 1 to 3
31F7  81DE001A           [1987] loadk      26  890      ; 352.20001220703
31FB  C103001B           [1988] loadk      27  15       ; 10
31FF  9F000018           [1989] setlist    24  2        ; index 1 to 3
3203  0A800119           [1990] newtable   25  3   0    ; array=3, hash=0
3207  0A80011A           [1991] newtable   26  3   0    ; array=3, hash=0
320B  01DF001B           [1992] loadk      27  892      ; -1516.9000244141
320F  81DF001C           [1993] loadk      28  894      ; -1001.700012207
3213  41C1001D           [1994] loadk      29  773      ; 14.800000190735
3217  9F00001A           [1995] setlist    26  2        ; index 1 to 3
321B  C1DF001B           [1996] loadk      27  895      ; 72.599998474121
321F  C103001C           [1997] loadk      28  15       ; 10
3223  9F000019           [1998] setlist    25  2        ; index 1 to 3
3227  0A80011A           [1999] newtable   26  3   0    ; array=3, hash=0
322B  0A80011B           [2000] newtable   27  3   0    ; array=3, hash=0
322F  41E0001C           [2001] loadk      28  897      ; -1425.5
3233  C1E0001D           [2002] loadk      29  899      ; -1273
3237  41C1001E           [2003] loadk      30  773      ; 14.800000190735
323B  9F00001B           [2004] setlist    27  2        ; index 1 to 3
323F  01E1001C           [2005] loadk      28  900      ; 343.5
3243  C103001D           [2006] loadk      29  15       ; 10
3247  9F00001A           [2007] setlist    26  2        ; index 1 to 3
324B  0A80011B           [2008] newtable   27  3   0    ; array=3, hash=0
324F  0A80011C           [2009] newtable   28  3   0    ; array=3, hash=0
3253  81E1001D           [2010] loadk      29  902      ; -1740.1999511719
3257  01E2001E           [2011] loadk      30  904      ; -97.599998474121
325B  41C1001F           [2012] loadk      31  773      ; 14.800000190735
325F  9F00001C           [2013] setlist    28  2        ; index 1 to 3
3263  41E2001D           [2014] loadk      29  905      ; 266.20001220703
3267  0107001E           [2015] loadk      30  28       ; 11
326B  9F00001B           [2016] setlist    27  2        ; index 1 to 3
326F  0A80011C           [2017] newtable   28  3   0    ; array=3, hash=0
3273  0A80011D           [2018] newtable   29  3   0    ; array=3, hash=0
3277  C1E2001E           [2019] loadk      30  907      ; -1690.4000244141
327B  414F001F           [2020] loadk      31  317      ; -122.80000305176
327F  016B0020           [2021] loadk      32  428      ; 14.60000038147
3283  9F00001D           [2022] setlist    29  2        ; index 1 to 3
3287  01E3001E           [2023] loadk      30  908      ; 190.30000305176
328B  0107001F           [2024] loadk      31  28       ; 11
328F  9F00001C           [2025] setlist    28  2        ; index 1 to 3
3293  0A80011D           [2026] newtable   29  3   0    ; array=3, hash=0
3297  0A80011E           [2027] newtable   30  3   0    ; array=3, hash=0
329B  81E3001F           [2028] loadk      31  910      ; -1720.3000488281
329F  01E40020           [2029] loadk      32  912      ; -123.80000305176
32A3  016B0021           [2030] loadk      33  428      ; 14.60000038147
32A7  9F00001E           [2031] setlist    30  2        ; index 1 to 3
32AB  41E4001F           [2032] loadk      31  913      ; 203.30000305176
32AF  01070020           [2033] loadk      32  28       ; 11
32B3  9F00001D           [2034] setlist    29  2        ; index 1 to 3
32B7  0A80011E           [2035] newtable   30  3   0    ; array=3, hash=0
32BB  0A80011F           [2036] newtable   31  3   0    ; array=3, hash=0
32BF  C1E40020           [2037] loadk      32  915      ; -1715.9000244141
32C3  41E50021           [2038] loadk      33  917      ; -156
32C7  016B0022           [2039] loadk      34  428      ; 14.60000038147
32CB  9F00001F           [2040] setlist    31  2        ; index 1 to 3
32CF  81E50020           [2041] loadk      32  918      ; 264.29998779297
32D3  01070021           [2042] loadk      33  28       ; 11
32D7  9F00001E           [2043] setlist    30  2        ; index 1 to 3
32DB  0A80011F           [2044] newtable   31  3   0    ; array=3, hash=0
32DF  0A800120           [2045] newtable   32  3   0    ; array=3, hash=0
32E3  01E60021           [2046] loadk      33  920      ; -1648
32E7  81E60022           [2047] loadk      34  922      ; -174.39999389648
32EB  016B0023           [2048] loadk      35  428      ; 14.60000038147
32EF  9F000020           [2049] setlist    32  2        ; index 1 to 3
32F3  C1E60021           [2050] loadk      33  923      ; 89.300003051758
32F7  01070022           [2051] loadk      34  28       ; 11
32FB  9F00001F           [2052] setlist    31  2        ; index 1 to 3
32FF  0A800120           [2053] newtable   32  3   0    ; array=3, hash=0
3303  0A800121           [2054] newtable   33  3   0    ; array=3, hash=0
3307  41E70022           [2055] loadk      34  925      ; -1718.3000488281
330B  C1E70023           [2056] loadk      35  927      ; -203.39999389648
330F  016B0024           [2057] loadk      36  428      ; 14.60000038147
3313  9F000021           [2058] setlist    33  2        ; index 1 to 3
3317  01E80022           [2059] loadk      34  928      ; 179.30000305176
331B  01070023           [2060] loadk      35  28       ; 11
331F  9F000020           [2061] setlist    32  2        ; index 1 to 3
3323  0A800121           [2062] newtable   33  3   0    ; array=3, hash=0
3327  0A800122           [2063] newtable   34  3   0    ; array=3, hash=0
332B  81E80023           [2064] loadk      35  930      ; -1768.4000244141
332F  01E90024           [2065] loadk      36  932      ; -287.60000610352
3333  015B0025           [2066] loadk      37  364      ; 14.699999809265
3337  9F000022           [2067] setlist    34  2        ; index 1 to 3
333B  C1120023           [2068] loadk      35  75       ; 265
333F  01070024           [2069] loadk      36  28       ; 11
3343  9F000021           [2070] setlist    33  2        ; index 1 to 3
3347  DF170001           [2071] setlist    1   95       ; index 65 to 96
334B  0A800102           [2072] newtable   2   3   0    ; array=3, hash=0
334F  0A800103           [2073] newtable   3   3   0    ; array=3, hash=0
3353  81E90004           [2074] loadk      4   934      ; -1598.3000488281
3357  01EA0005           [2075] loadk      5   936      ; -257.60000610352
335B  016B0006           [2076] loadk      6   428      ; 14.60000038147
335F  9F000003           [2077] setlist    3   2        ; index 1 to 3
3363  41EA0004           [2078] loadk      4   937      ; 91.199996948242
3367  01070005           [2079] loadk      5   28       ; 11
336B  9F000002           [2080] setlist    2   2        ; index 1 to 3
336F  0A800103           [2081] newtable   3   3   0    ; array=3, hash=0
3373  0A800104           [2082] newtable   4   3   0    ; array=3, hash=0
3377  C1EA0005           [2083] loadk      5   939      ; -1646.4000244141
337B  41EB0006           [2084] loadk      6   941      ; -224.10000610352
337F  016B0007           [2085] loadk      7   428      ; 14.60000038147
3383  9F000004           [2086] setlist    4   2        ; index 1 to 3
3387  81EB0005           [2087] loadk      5   942      ; 85.400001525879
338B  01070006           [2088] loadk      6   28       ; 11
338F  9F000003           [2089] setlist    3   2        ; index 1 to 3
3393  0A800104           [2090] newtable   4   3   0    ; array=3, hash=0
3397  0A800105           [2091] newtable   5   3   0    ; array=3, hash=0
339B  01EC0006           [2092] loadk      6   944      ; -1670.3000488281
339F  81EC0007           [2093] loadk      7   946      ; -236.60000610352
33A3  016B0008           [2094] loadk      8   428      ; 14.60000038147
33A7  9F000005           [2095] setlist    5   2        ; index 1 to 3
33AB  C1EC0006           [2096] loadk      6   947      ; 179.60000610352
33AF  01070007           [2097] loadk      7   28       ; 11
33B3  9F000004           [2098] setlist    4   2        ; index 1 to 3
33B7  9F180001           [2099] setlist    1   98       ; index 97 to 99
33BB  00800000           [2100] move       0   1      
33BF  1B000100           [2101] return     0   2      
33C3  1B800000           [2102] return     0   1      
                         ** end of function **

                         * code:
33C7  03000000           sizecode (3)
33CB  22000000           [1] closure    0   0        ; 0 upvalues
33CF  1B000100           [2] return     0   2      
33D3  1B800000           [3] return     0   1      
                         ** end of function **

33D7                     ** end of chunk **
